Workbook
Name ____ELE1: #REF!
Name ____EPE1: #REF!
Name ____VTL04: #REF!
Name ___CAF4: #REF!
Name ___ELE1: #REF!
Name ___EPE1: #REF!
Name ___PV42: #REF!
Name ___PV44: #REF!
Name ___SKY1: #REF!
Name ___SKY2: #REF!
Name ___VTL01: #REF!
Name ___VTL02: #REF!
Name ___VTL03: #REF!
Name ___VTL05: #REF!
Name ___VTL06: #REF!
Name ___VTL07: #REF!
Name ___VTL08: #REF!
Name ___VTL09: #REF!
Name __CAF4: #REF!
Name __ELE1: #REF!
Name __ELE1: #REF!
Name __EPE1: #REF!
Name __EPE1: #REF!
Name __PV42: #REF!
Name __PV44: #REF!
Name __SKY1: #REF!
Name __SKY2: #REF!
Name __VTL01: #REF!
Name __VTL02: #REF!
Name __VTL03: #REF!
Name __VTL04: #REF!
Name __VTL05: #REF!
Name __VTL06: #REF!
Name __VTL07: #REF!
Name __VTL08: #REF!
Name __VTL09: #REF!
Name _1Excel_BuiltIn_Print_Area_4_1_1: #REF!
Name _C: #REF!
Name _CAF4: '[9]Base de Dados'!$H$33
Name _D: #REF!
Name _ELE1: #REF!
Name _ELE1: #REF!
Name _EPE1: #REF!
Name _EPE1: #REF!
Name _P: #REF!
Name _PV42: '[9]Base de Dados'!$H$29
Name _PV44: '[9]Base de Dados'!$H$30
Name _SKY1: '[9]Base de Dados'!$H$36
Name _SKY2: '[9]Base de Dados'!$H$35
Name _VTL01: [9]Plan1!$Y$8
Name _VTL02: [9]Plan1!$Y$13
Name _VTL03: [9]Plan1!$Y$21
Name _VTL04: [12]VT!#REF!
Name _VTL04: [12]VT!#REF!
Name _VTL05: [9]Plan1!$Y$26
Name _VTL06: [9]Plan1!$Y$31
Name _VTL07: [9]Plan1!$Y$35
Name _VTL08: [9]Plan1!$Y$38
Name _VTL09: [9]Plan1!$Y$41
Name A: #REF!

Sheet AEO
L2: Nº SI / Nº AEO
F3: AUTORIZAÇÃO DE EXECUÇÃO DE OBRAS - AEO
B7: AUTOMAÇÃO
B9: DISTRIBUIDORA
B10: EQUATORIAL GOIÁS
B12: Contrato: | C12: Linha: | D12: Empreiteira: | H12: Valor Original: | J12: Valor Adicional: | L12: Valor Total Autorizado:
B13: 4600027637 | C13: =VLOOKUP(B13,Contratos!E:H,4,0) -> 30 | D13: =VLOOKUP(B13,Contratos!E:G,3,0) -> ENERGY SYSTEN CONSTRUCOES E MANUTEN | H13: =SUMPRODUCT('Lista de Serviços & Medição'!F:F,'Lista de Serviços & Medição'!H:H) -> 6848.94 | J13: =SUMPRODUCT('Lista de Serviços & Medição'!G:G,'Lista de Serviços & Medição'!H:H) -> 0 | L13: =H13+J13 -> 6848.94
B15: IDENTIFICAÇÃO DO PROJETO: | G15: SUBESTAÇÃO: | J15: PEP / ORDEM:
B16: =VLOOKUP(J16,CN43N!C:D,2,0) -> EQTL-GO>SE BJE>69KV>AMP POTENCIA | G16: =VLOOKUP(J16,Portifólio!F:I,4,0) -> SE BOM JARDIM | J16: GO-2530208AMP0.F
B18: ESCOPO MACRO DA OBRA:
B20: =VLOOKUP(J16,Portifólio!F:J,5,0) -> 1,00 x SUBST. DE TRANSFORMADOR DE FORÇA + 1,00 x TRANSFORMADOR DE FORÇA 34,5/13,8kV 5,0/6,3MVA - YNYN0D1 + 1,00 x BARRAMENTO DUPLO OU BPT 13,8kV + 1,00 x ENTRADA DE LINHA 13,8kV c/ DJ
B26: AUTORIZAMOS EXECUTAR OS SERVIÇOS CONSTANTES NESTA AUTORIZAÇÃO, DENTRO DAS NORMAS BEM COMO DE ACORDO COM AS DEMAIS CONDIÇÕES ESTABELECIDAS NO CONTRATO DE EMPREITADAS EM VIGOR E RECOMENDAÇÕES EM ANEXO AO CONTRATO
B28: Prazo de Execução
B29: Início Autorizado: | C29: 46134 | G29: Liberação comissionamento esperado: | H29: 46135 | K29: Término Autorizado: | L29: 46137
B34: GUSTAVO DE JESUS OLIVEIRA | I34: =VLOOKUP(B13,Contratos!E:L,8,0) -> GIOVANNI CENDES FINOTTI
B35: =VLOOKUP(B34,Contratos!J:K,2,0) -> G52901707 | I35: =VLOOKUP(I34,Contratos!L:M,2,0) -> 027.157.771-16
B36: RESPONSÁVEL EQUATORIAL | I36: =D13 -> ENERGY SYSTEN CONSTRUCOES E MANUTEN

Sheet Lista de Serviços & Medição
E3: LISTA DE SERVIÇOS E PLANILHA DE MEDIÇÃO | I3: MEDIÇÃO | J3: Medição nº 01 | L3: Medição nº 02 | N3: Medição nº 03 | P3: Medição nº 04 | R3: Medição nº 05 | T3: Medição nº 06 | V3: Medição nº 07 | X3: Medição nº 08 | Z3: Medição nº 09 | AB3: Medição nº 10 | AD3: Medição nº 11 | AF3: Medição nº 12 | AH3: Medição nº 13 | AJ3: Medição nº 14 | AL3: Medição nº 15 | AN3: Medição nº 16 | AP3: Medição nº 17 | AR3: Medição nº 18 | AT3: Medição nº 19 | AV3: Medição nº 20
I4: Mês
I5: RC ODI
I6: RC CIV
I7: RC ODD
J8: VALORES DESTA MEDIÇÃO | L8: VALORES DESTA MEDIÇÃO | N8: VALORES DESTA MEDIÇÃO | P8: VALORES DESTA MEDIÇÃO | R8: VALORES DESTA MEDIÇÃO | T8: VALORES DESTA MEDIÇÃO | V8: VALORES DESTA MEDIÇÃO | X8: VALORES DESTA MEDIÇÃO | Z8: VALORES DESTA MEDIÇÃO | AB8: VALORES DESTA MEDIÇÃO | AD8: VALORES DESTA MEDIÇÃO | AF8: VALORES DESTA MEDIÇÃO | AH8: VALORES DESTA MEDIÇÃO | AJ8: VALORES DESTA MEDIÇÃO | AL8: VALORES DESTA MEDIÇÃO | AN8: VALORES DESTA MEDIÇÃO | AP8: VALORES DESTA MEDIÇÃO | AR8: VALORES DESTA MEDIÇÃO | AT8: VALORES DESTA MEDIÇÃO | AV8: VALORES DESTA MEDIÇÃO | AX8: TOTAIS ACUMULADOS | AZ8: SALDO A FATURAR | BA8: SALDO A FATURAR
B9: CÓDIGO SAP | C9: LINHA | D9: DESCRIMINAÇÃO DOS SERVICOS | E9: UNID. | F9: QUANT. PREVISTA ORIGINAL | G9: QUANT. ADICIONAL | H9: PREÇO UNITÁRIO | I9: R$ TOTAL
J11: QUANT. | K11: VALOR | L11: QUANT. | M11: VALOR | N11: QUANT. | O11: VALOR | P11: QUANT. | Q11: VALOR | R11: QUANT. | S11: VALOR | T11: QUANT. | U11: VALOR | V11: QUANT. | W11: VALOR | X11: QUANT. | Y11: VALOR | Z11: QUANT. | AA11: VALOR | AB11: QUANT. | AC11: VALOR | AD11: QUANT. | AE11: VALOR | AF11: QUANT. | AG11: VALOR | AH11: QUANT. | AI11: VALOR | AJ11: QUANT. | AK11: VALOR | AL11: QUANT. | AM11: VALOR | AN11: QUANT. | AO11: VALOR | AP11: QUANT. | AQ11: VALOR | AR11: QUANT. | AS11: VALOR | AT11: QUANT. | AU11: VALOR | AV11: QUANT. | AW11: VALOR | AX11: QUANT. | AY11: TOTAL | AZ11: QUANT. | BA11: TOTAL
D12: SERVIÇOS PRELIMINARES - MOBILIZAÇÃO & DESMOBILIZAÇÃO (FATOR "M") | I12: =SUBTOTAL(9,I13:I86) -> 0 | K12: =SUBTOTAL(9,K13:K86) -> 0 | M12: =SUBTOTAL(9,M13:M86) -> 0 | O12: =SUBTOTAL(9,O13:O86) -> 0 | Q12: =SUBTOTAL(9,Q13:Q86) -> 0 | S12: =SUBTOTAL(9,S13:S86) -> 0 | U12: =SUBTOTAL(9,U13:U86) -> 0 | W12: =SUBTOTAL(9,W13:W86) -> 0 | Y12: =SUBTOTAL(9,Y13:Y86) -> 0 | AA12: =SUBTOTAL(9,AA13:AA86) -> 0 | AC12: =SUBTOTAL(9,AC13:AC86) -> 0 | AE12: =SUBTOTAL(9,AE13:AE86) -> 0 | AG12: =SUBTOTAL(9,AG13:AG86) -> 0 | AI12: =SUBTOTAL(9,AI13:AI86) -> 0 | AK12: =SUBTOTAL(9,AK13:AK86) -> 0 | AM12: =SUBTOTAL(9,AM13:AM86) -> 0 | AO12: =SUBTOTAL(9,AO13:AO86) -> 0 | AQ12: =SUBTOTAL(9,AQ13:AQ86) -> 0 | AS12: =SUBTOTAL(9,AS13:AS86) -> 0 | AU12: =SUBTOTAL(9,AU13:AU86) -> 0 | AW12: =SUBTOTAL(9,AW13:AW86) -> 0 | AY12: =SUBTOTAL(9,AY13:AY86) -> 0 | BA12: =SUBTOTAL(9,BA13:BA86) -> 0
B13: 5045500013 | C13: =IFERROR(IF(B13,VLOOKUP((AEO!$B$13&AEO!$C$13&B13&E13),MSRV5!A:F,6,0),""),"N/A") -> 10 | D13: MOB / DESMOBILIZACAO LD DE 0 A 50KM LD | E13: =IF(B13,VLOOKUP(B13,MSRV5!B:D,3,0),"") -> KM | H13: =IFERROR(IF(B13,VLOOKUP((AEO!$B$13&AEO!$C$13&B13&E13),MSRV5!A:E,5,0),""),0) -> 615.33 | I13: =(F13+G13)*H13 -> 0 | K13: =J13*$H13 -> 0 | M13: =L13*$H13 -> 0 | O13: =N13*$H13 -> 0 | Q13: =P13*$H13 -> 0 | S13: =R13*$H13 -> 0 | U13: =T13*$H13 -> 0 | W13: =V13*$H13 -> 0 | Y13: =X13*$H13 -> 0 | AA13: =Z13*$H13 -> 0 | AC13: =AB13*$H13 -> 0 | AE13: =AD13*$H13 -> 0 | AG13: =AF13*$H13 -> 0 | AI13: =AH13*$H13 -> 0 | AK13: =AJ13*$H13 -> 0 | AM13: =AL13*$H13 -> 0 | AO13: =AN13*$H13 -> 0 | AQ13: =AP13*$H13 -> 0 | AS13: =AR13*$H13 -> 0 | AU13: =AT13*$H13 -> 0 | AW13: =AV13*$H13 -> 0 | AX13: =SUM(AV13,AT13,AR13,AP13,AN13,AL13,AJ13,AH13,AF13,AD13,AB13,Z13,X13,V13,T13,R13,P13,N13,L13,J13) -> 0 | AY13: =SUM(AW13,AU13,AS13,AQ13,AO13,AM13,AK13,AI13,AG13,AE13,AC13,AA13,Y13,W13,U13,S13,Q13,O13,M13,K13) -> 0 | AZ13: =(F13+G13)-AX13 -> 0 | BA13: =I13-AY13 -> 0
B14: 5045500014 | C14: =IFERROR(IF(B14,VLOOKUP((AEO!$B$13&AEO!$C$13&B14&E14),MSRV5!A:F,6,0),""),"N/A") -> 20 | D14: MOB / DESMOBILIZACAO LD DE 51 A 200KM LD | E14: =IF(B14,VLOOKUP(B14,MSRV5!B:D,3,0),"") -> KM | H14: =IFERROR(IF(B14,VLOOKUP((AEO!$B$13&AEO!$C$13&B14&E14),MSRV5!A:E,5,0),""),0) -> 672.31 | I14: =(F14+G14)*H14 -> 0 | K14: =J14*$H14 -> 0 | M14: =L14*$H14 -> 0 | O14: =N14*$H14 -> 0 | Q14: =P14*$H14 -> 0 | S14: =R14*$H14 -> 0 | U14: =T14*$H14 -> 0 | W14: =V14*$H14 -> 0 | Y14: =X14*$H14 -> 0 | AA14: =Z14*$H14 -> 0 | AC14: =AB14*$H14 -> 0 | AE14: =AD14*$H14 -> 0 | AG14: =AF14*$H14 -> 0 | AI14: =AH14*$H14 -> 0 | AK14: =AJ14*$H14 -> 0 | AM14: =AL14*$H14 -> 0 | AO14: =AN14*$H14 -> 0 | AQ14: =AP14*$H14 -> 0 | AS14: =AR14*$H14 -> 0 | AU14: =AT14*$H14 -> 0 | AW14: =AV14*$H14 -> 0 | AX14: =SUM(AV14,AT14,AR14,AP14,AN14,AL14,AJ14,AH14,AF14,AD14,AB14,Z14,X14,V14,T14,R14,P14,N14,L14,J14) -> 0 | AY14: =SUM(AW14,AU14,AS14,AQ14,AO14,AM14,AK14,AI14,AG14,AE14,AC14,AA14,Y14,W14,U14,S14,Q14,O14,M14,K14) -> 0 | AZ14: =(F14+G14)-AX14 -> 0 | BA14: =I14-AY14 -> 0
B15: 5045500015 | C15: =IFERROR(IF(B15,VLOOKUP((AEO!$B$13&AEO!$C$13&B15&E15),MSRV5!A:F,6,0),""),"N/A") -> 30 | D15: MOB/ DESMOBILIZACAO LD ACIMA DE 600KM LD | E15: =IF(B15,VLOOKUP(B15,MSRV5!B:D,3,0),"") -> KM | H15: =IFERROR(IF(B15,VLOOKUP((AEO!$B$13&AEO!$C$13&B15&E15),MSRV5!A:E,5,0),""),0) -> 216.59 | I15: =(F15+G15)*H15 -> 0 | K15: =J15*$H15 -> 0 | M15: =L15*$H15 -> 0 | O15: =N15*$H15 -> 0 | Q15: =P15*$H15 -> 0 | S15: =R15*$H15 -> 0 | U15: =T15*$H15 -> 0 | W15: =V15*$H15 -> 0 | Y15: =X15*$H15 -> 0 | AA15: =Z15*$H15 -> 0 | AC15: =AB15*$H15 -> 0 | AE15: =AD15*$H15 -> 0 | AG15: =AF15*$H15 -> 0 | AI15: =AH15*$H15 -> 0 | AK15: =AJ15*$H15 -> 0 | AM15: =AL15*$H15 -> 0 | AO15: =AN15*$H15 -> 0 | AQ15: =AP15*$H15 -> 0 | AS15: =AR15*$H15 -> 0 | AU15: =AT15*$H15 -> 0 | AW15: =AV15*$H15 -> 0 | AX15: =SUM(AV15,AT15,AR15,AP15,AN15,AL15,AJ15,AH15,AF15,AD15,AB15,Z15,X15,V15,T15,R15,P15,N15,L15,J15) -> 0 | AY15: =SUM(AW15,AU15,AS15,AQ15,AO15,AM15,AK15,AI15,AG15,AE15,AC15,AA15,Y15,W15,U15,S15,Q15,O15,M15,K15) -> 0 | AZ15: =(F15+G15)-AX15 -> 0 | BA15: =I15-AY15 -> 0
B16: 5045500016 | C16: =IFERROR(IF(B16,VLOOKUP((AEO!$B$13&AEO!$C$13&B16&E16),MSRV5!A:F,6,0),""),"N/A") -> 40 | D16: MOB/ DESMOBILIZACAO LD DE 201 A 400KM LD | E16: =IF(B16,VLOOKUP(B16,MSRV5!B:D,3,0),"") -> KM | H16: =IFERROR(IF(B16,VLOOKUP((AEO!$B$13&AEO!$C$13&B16&E16),MSRV5!A:E,5,0),""),0) -> 383.96 | I16: =(F16+G16)*H16 -> 0 | K16: =J16*$H16 -> 0 | M16: =L16*$H16 -> 0 | O16: =N16*$H16 -> 0 | Q16: =P16*$H16 -> 0 | S16: =R16*$H16 -> 0 | U16: =T16*$H16 -> 0 | W16: =V16*$H16 -> 0 | Y16: =X16*$H16 -> 0 | AA16: =Z16*$H16 -> 0 | AC16: =AB16*$H16 -> 0 | AE16: =AD16*$H16 -> 0 | AG16: =AF16*$H16 -> 0 | AI16: =AH16*$H16 -> 0 | AK16: =AJ16*$H16 -> 0 | AM16: =AL16*$H16 -> 0 | AO16: =AN16*$H16 -> 0 | AQ16: =AP16*$H16 -> 0 | AS16: =AR16*$H16 -> 0 | AU16: =AT16*$H16 -> 0 | AW16: =AV16*$H16 -> 0 | AX16: =SUM(AV16,AT16,AR16,AP16,AN16,AL16,AJ16,AH16,AF16,AD16,AB16,Z16,X16,V16,T16,R16,P16,N16,L16,J16) -> 0 | AY16: =SUM(AW16,AU16,AS16,AQ16,AO16,AM16,AK16,AI16,AG16,AE16,AC16,AA16,Y16,W16,U16,S16,Q16,O16,M16,K16) -> 0 | AZ16: =(F16+G16)-AX16 -> 0 | BA16: =I16-AY16 -> 0
B17: 5045500019 | C17: =IFERROR(IF(B17,VLOOKUP((AEO!$B$13&AEO!$C$13&B17&E17),MSRV5!A:F,6,0),""),"N/A") -> 50 | D17: DESMOBIL 0 A 200KM EQP 5H RESIT OHM LD | E17: =IF(B17,VLOOKUP(B17,MSRV5!B:D,3,0),"") -> CDA | H17: =IFERROR(IF(B17,VLOOKUP((AEO!$B$13&AEO!$C$13&B17&E17),MSRV5!A:E,5,0),""),0) -> 135.37 | I17: =(F17+G17)*H17 -> 0 | K17: =J17*$H17 -> 0 | M17: =L17*$H17 -> 0 | O17: =N17*$H17 -> 0 | Q17: =P17*$H17 -> 0 | S17: =R17*$H17 -> 0 | U17: =T17*$H17 -> 0 | W17: =V17*$H17 -> 0 | Y17: =X17*$H17 -> 0 | AA17: =Z17*$H17 -> 0 | AC17: =AB17*$H17 -> 0 | AE17: =AD17*$H17 -> 0 | AG17: =AF17*$H17 -> 0 | AI17: =AH17*$H17 -> 0 | AK17: =AJ17*$H17 -> 0 | AM17: =AL17*$H17 -> 0 | AO17: =AN17*$H17 -> 0 | AQ17: =AP17*$H17 -> 0 | AS17: =AR17*$H17 -> 0 | AU17: =AT17*$H17 -> 0 | AW17: =AV17*$H17 -> 0 | AX17: =SUM(AV17,AT17,AR17,AP17,AN17,AL17,AJ17,AH17,AF17,AD17,AB17,Z17,X17,V17,T17,R17,P17,N17,L17,J17) -> 0 | AY17: =SUM(AW17,AU17,AS17,AQ17,AO17,AM17,AK17,AI17,AG17,AE17,AC17,AA17,Y17,W17,U17,S17,Q17,O17,M17,K17) -> 0 | AZ17: =(F17+G17)-AX17 -> 0 | BA17: =I17-AY17 -> 0
B18: 5045500020 | C18: =IFERROR(IF(B18,VLOOKUP((AEO!$B$13&AEO!$C$13&B18&E18),MSRV5!A:F,6,0),""),"N/A") -> 60 | D18: DESMOBIL 0 A 200KM EQP 5H SERV TEC LD | E18: =IF(B18,VLOOKUP(B18,MSRV5!B:D,3,0),"") -> CDA | H18: =IFERROR(IF(B18,VLOOKUP((AEO!$B$13&AEO!$C$13&B18&E18),MSRV5!A:E,5,0),""),0) -> 172.29 | I18: =(F18+G18)*H18 -> 0 | K18: =J18*$H18 -> 0 | M18: =L18*$H18 -> 0 | O18: =N18*$H18 -> 0 | Q18: =P18*$H18 -> 0 | S18: =R18*$H18 -> 0 | U18: =T18*$H18 -> 0 | W18: =V18*$H18 -> 0 | Y18: =X18*$H18 -> 0 | AA18: =Z18*$H18 -> 0 | AC18: =AB18*$H18 -> 0 | AE18: =AD18*$H18 -> 0 | AG18: =AF18*$H18 -> 0 | AI18: =AH18*$H18 -> 0 | AK18: =AJ18*$H18 -> 0 | AM18: =AL18*$H18 -> 0 | AO18: =AN18*$H18 -> 0 | AQ18: =AP18*$H18 -> 0 | AS18: =AR18*$H18 -> 0 | AU18: =AT18*$H18 -> 0 | AW18: =AV18*$H18 -> 0 | AX18: =SUM(AV18,AT18,AR18,AP18,AN18,AL18,AJ18,AH18,AF18,AD18,AB18,Z18,X18,V18,T18,R18,P18,N18,L18,J18) -> 0 | AY18: =SUM(AW18,AU18,AS18,AQ18,AO18,AM18,AK18,AI18,AG18,AE18,AC18,AA18,Y18,W18,U18,S18,Q18,O18,M18,K18) -> 0 | AZ18: =(F18+G18)-AX18 -> 0 | BA18: =I18-AY18 -> 0
B19: 5045500021 | C19: =IFERROR(IF(B19,VLOOKUP((AEO!$B$13&AEO!$C$13&B19&E19),MSRV5!A:F,6,0),""),"N/A") -> 70 | D19: DESMOBIL 201 A 400KM EQP 5H RESIT OHM LD | E19: =IF(B19,VLOOKUP(B19,MSRV5!B:D,3,0),"") -> CDA | H19: =IFERROR(IF(B19,VLOOKUP((AEO!$B$13&AEO!$C$13&B19&E19),MSRV5!A:E,5,0),""),0) -> 209.23 | I19: =(F19+G19)*H19 -> 0 | K19: =J19*$H19 -> 0 | M19: =L19*$H19 -> 0 | O19: =N19*$H19 -> 0 | Q19: =P19*$H19 -> 0 | S19: =R19*$H19 -> 0 | U19: =T19*$H19 -> 0 | W19: =V19*$H19 -> 0 | Y19: =X19*$H19 -> 0 | AA19: =Z19*$H19 -> 0 | AC19: =AB19*$H19 -> 0 | AE19: =AD19*$H19 -> 0 | AG19: =AF19*$H19 -> 0 | AI19: =AH19*$H19 -> 0 | AK19: =AJ19*$H19 -> 0 | AM19: =AL19*$H19 -> 0 | AO19: =AN19*$H19 -> 0 | AQ19: =AP19*$H19 -> 0 | AS19: =AR19*$H19 -> 0 | AU19: =AT19*$H19 -> 0 | AW19: =AV19*$H19 -> 0 | AX19: =SUM(AV19,AT19,AR19,AP19,AN19,AL19,AJ19,AH19,AF19,AD19,AB19,Z19,X19,V19,T19,R19,P19,N19,L19,J19) -> 0 | AY19: =SUM(AW19,AU19,AS19,AQ19,AO19,AM19,AK19,AI19,AG19,AE19,AC19,AA19,Y19,W19,U19,S19,Q19,O19,M19,K19) -> 0 | AZ19: =(F19+G19)-AX19 -> 0 | BA19: =I19-AY19 -> 0
B20: 5045500022 | C20: =IFERROR(IF(B20,VLOOKUP((AEO!$B$13&AEO!$C$13&B20&E20),MSRV5!A:F,6,0),""),"N/A") -> 80 | D20: DESMOBIL 201 A 400KM EQP 5H SERV TEC LD | E20: =IF(B20,VLOOKUP(B20,MSRV5!B:D,3,0),"") -> CDA | H20: =IFERROR(IF(B20,VLOOKUP((AEO!$B$13&AEO!$C$13&B20&E20),MSRV5!A:E,5,0),""),0) -> 19.7 | I20: =(F20+G20)*H20 -> 0 | K20: =J20*$H20 -> 0 | M20: =L20*$H20 -> 0 | O20: =N20*$H20 -> 0 | Q20: =P20*$H20 -> 0 | S20: =R20*$H20 -> 0 | U20: =T20*$H20 -> 0 | W20: =V20*$H20 -> 0 | Y20: =X20*$H20 -> 0 | AA20: =Z20*$H20 -> 0 | AC20: =AB20*$H20 -> 0 | AE20: =AD20*$H20 -> 0 | AG20: =AF20*$H20 -> 0 | AI20: =AH20*$H20 -> 0 | AK20: =AJ20*$H20 -> 0 | AM20: =AL20*$H20 -> 0 | AO20: =AN20*$H20 -> 0 | AQ20: =AP20*$H20 -> 0 | AS20: =AR20*$H20 -> 0 | AU20: =AT20*$H20 -> 0 | AW20: =AV20*$H20 -> 0 | AX20: =SUM(AV20,AT20,AR20,AP20,AN20,AL20,AJ20,AH20,AF20,AD20,AB20,Z20,X20,V20,T20,R20,P20,N20,L20,J20) -> 0 | AY20: =SUM(AW20,AU20,AS20,AQ20,AO20,AM20,AK20,AI20,AG20,AE20,AC20,AA20,Y20,W20,U20,S20,Q20,O20,M20,K20) -> 0 | AZ20: =(F20+G20)-AX20 -> 0 | BA20: =I20-AY20 -> 0
B21: 5045500023 | C21: =IFERROR(IF(B21,VLOOKUP((AEO!$B$13&AEO!$C$13&B21&E21),MSRV5!A:F,6,0),""),"N/A") -> 90 | D21: DESMOBIL 401 A 600KM EQP 5H RESIT OHM LD | E21: =IF(B21,VLOOKUP(B21,MSRV5!B:D,3,0),"") -> CDA | H21: =IFERROR(IF(B21,VLOOKUP((AEO!$B$13&AEO!$C$13&B21&E21),MSRV5!A:E,5,0),""),0) -> 295.35 | I21: =(F21+G21)*H21 -> 0 | K21: =J21*$H21 -> 0 | M21: =L21*$H21 -> 0 | O21: =N21*$H21 -> 0 | Q21: =P21*$H21 -> 0 | S21: =R21*$H21 -> 0 | U21: =T21*$H21 -> 0 | W21: =V21*$H21 -> 0 | Y21: =X21*$H21 -> 0 | AA21: =Z21*$H21 -> 0 | AC21: =AB21*$H21 -> 0 | AE21: =AD21*$H21 -> 0 | AG21: =AF21*$H21 -> 0 | AI21: =AH21*$H21 -> 0 | AK21: =AJ21*$H21 -> 0 | AM21: =AL21*$H21 -> 0 | AO21: =AN21*$H21 -> 0 | AQ21: =AP21*$H21 -> 0 | AS21: =AR21*$H21 -> 0 | AU21: =AT21*$H21 -> 0 | AW21: =AV21*$H21 -> 0 | AX21: =SUM(AV21,AT21,AR21,AP21,AN21,AL21,AJ21,AH21,AF21,AD21,AB21,Z21,X21,V21,T21,R21,P21,N21,L21,J21) -> 0 | AY21: =SUM(AW21,AU21,AS21,AQ21,AO21,AM21,AK21,AI21,AG21,AE21,AC21,AA21,Y21,W21,U21,S21,Q21,O21,M21,K21) -> 0 | AZ21: =(F21+G21)-AX21 -> 0 | BA21: =I21-AY21 -> 0
B22: 5045500024 | C22: =IFERROR(IF(B22,VLOOKUP((AEO!$B$13&AEO!$C$13&B22&E22),MSRV5!A:F,6,0),""),"N/A") -> 100 | D22: DESMOBIL 401 A 600KM EQP 5H SERV TEC LD | E22: =IF(B22,VLOOKUP(B22,MSRV5!B:D,3,0),"") -> CDA | H22: =IFERROR(IF(B22,VLOOKUP((AEO!$B$13&AEO!$C$13&B22&E22),MSRV5!A:E,5,0),""),0) -> 295.35 | I22: =(F22+G22)*H22 -> 0 | K22: =J22*$H22 -> 0 | M22: =L22*$H22 -> 0 | O22: =N22*$H22 -> 0 | Q22: =P22*$H22 -> 0 | S22: =R22*$H22 -> 0 | U22: =T22*$H22 -> 0 | W22: =V22*$H22 -> 0 | Y22: =X22*$H22 -> 0 | AA22: =Z22*$H22 -> 0 | AC22: =AB22*$H22 -> 0 | AE22: =AD22*$H22 -> 0 | AG22: =AF22*$H22 -> 0 | AI22: =AH22*$H22 -> 0 | AK22: =AJ22*$H22 -> 0 | AM22: =AL22*$H22 -> 0 | AO22: =AN22*$H22 -> 0 | AQ22: =AP22*$H22 -> 0 | AS22: =AR22*$H22 -> 0 | AU22: =AT22*$H22 -> 0 | AW22: =AV22*$H22 -> 0 | AX22: =SUM(AV22,AT22,AR22,AP22,AN22,AL22,AJ22,AH22,AF22,AD22,AB22,Z22,X22,V22,T22,R22,P22,N22,L22,J22) -> 0 | AY22: =SUM(AW22,AU22,AS22,AQ22,AO22,AM22,AK22,AI22,AG22,AE22,AC22,AA22,Y22,W22,U22,S22,Q22,O22,M22,K22) -> 0 | AZ22: =(F22+G22)-AX22 -> 0 | BA22: =I22-AY22 -> 0
B23: 5045500030 | C23: =IFERROR(IF(B23,VLOOKUP((AEO!$B$13&AEO!$C$13&B23&E23),MSRV5!A:F,6,0),""),"N/A") -> 110 | D23: DESMOBILIZAR 201 A 400KM EQP 5H SOND LD | E23: =IF(B23,VLOOKUP(B23,MSRV5!B:D,3,0),"") -> CDA | H23: =IFERROR(IF(B23,VLOOKUP((AEO!$B$13&AEO!$C$13&B23&E23),MSRV5!A:E,5,0),""),0) -> 315.04 | I23: =(F23+G23)*H23 -> 0 | K23: =J23*$H23 -> 0 | M23: =L23*$H23 -> 0 | O23: =N23*$H23 -> 0 | Q23: =P23*$H23 -> 0 | S23: =R23*$H23 -> 0 | U23: =T23*$H23 -> 0 | W23: =V23*$H23 -> 0 | Y23: =X23*$H23 -> 0 | AA23: =Z23*$H23 -> 0 | AC23: =AB23*$H23 -> 0 | AE23: =AD23*$H23 -> 0 | AG23: =AF23*$H23 -> 0 | AI23: =AH23*$H23 -> 0 | AK23: =AJ23*$H23 -> 0 | AM23: =AL23*$H23 -> 0 | AO23: =AN23*$H23 -> 0 | AQ23: =AP23*$H23 -> 0 | AS23: =AR23*$H23 -> 0 | AU23: =AT23*$H23 -> 0 | AW23: =AV23*$H23 -> 0 | AX23: =SUM(AV23,AT23,AR23,AP23,AN23,AL23,AJ23,AH23,AF23,AD23,AB23,Z23,X23,V23,T23,R23,P23,N23,L23,J23) -> 0 | AY23: =SUM(AW23,AU23,AS23,AQ23,AO23,AM23,AK23,AI23,AG23,AE23,AC23,AA23,Y23,W23,U23,S23,Q23,O23,M23,K23) -> 0 | AZ23: =(F23+G23)-AX23 -> 0 | BA23: =I23-AY23 -> 0
B24: 5045500031 | C24: =IFERROR(IF(B24,VLOOKUP((AEO!$B$13&AEO!$C$13&B24&E24),MSRV5!A:F,6,0),""),"N/A") -> 120 | D24: DESMOBILIZAR 201 A 400KM EQP 5H TOPOG LD | E24: =IF(B24,VLOOKUP(B24,MSRV5!B:D,3,0),"") -> CDA | H24: =IFERROR(IF(B24,VLOOKUP((AEO!$B$13&AEO!$C$13&B24&E24),MSRV5!A:E,5,0),""),0) -> 2707.41 | I24: =(F24+G24)*H24 -> 0 | K24: =J24*$H24 -> 0 | M24: =L24*$H24 -> 0 | O24: =N24*$H24 -> 0 | Q24: =P24*$H24 -> 0 | S24: =R24*$H24 -> 0 | U24: =T24*$H24 -> 0 | W24: =V24*$H24 -> 0 | Y24: =X24*$H24 -> 0 | AA24: =Z24*$H24 -> 0 | AC24: =AB24*$H24 -> 0 | AE24: =AD24*$H24 -> 0 | AG24: =AF24*$H24 -> 0 | AI24: =AH24*$H24 -> 0 | AK24: =AJ24*$H24 -> 0 | AM24: =AL24*$H24 -> 0 | AO24: =AN24*$H24 -> 0 | AQ24: =AP24*$H24 -> 0 | AS24: =AR24*$H24 -> 0 | AU24: =AT24*$H24 -> 0 | AW24: =AV24*$H24 -> 0 | AX24: =SUM(AV24,AT24,AR24,AP24,AN24,AL24,AJ24,AH24,AF24,AD24,AB24,Z24,X24,V24,T24,R24,P24,N24,L24,J24) -> 0 | AY24: =SUM(AW24,AU24,AS24,AQ24,AO24,AM24,AK24,AI24,AG24,AE24,AC24,AA24,Y24,W24,U24,S24,Q24,O24,M24,K24) -> 0 | AZ24: =(F24+G24)-AX24 -> 0 | BA24: =I24-AY24 -> 0
... B49: 5056000041 | C49: =IFERROR(IF(B49,VLOOKUP((AEO!$B$13&AEO!$C$13&B49&E49),MSRV5!A:F,6,0),""),"N/A") -> 370 | D49: DESMOB EQUIPE E MAQ. DE 201KM A 400KM | E49: =IF(B49,VLOOKUP(B49,MSRV5!B:D,3,0),"") -> KM | H49: =IFERROR(IF(B49,VLOOKUP((AEO!$B$13&AEO!$C$13&B49&E49),MSRV5!A:E,5,0),""),0) -> 16.2 | I49: =(F49+G49)*H49 -> 0 | K49: =J49*$H49 -> 0 | M49: =L49*$H49 -> 0 | O49: =N49*$H49 -> 0 | Q49: =P49*$H49 -> 0 | S49: =R49*$H49 -> 0 | U49: =T49*$H49 -> 0 | W49: =V49*$H49 -> 0 | Y49: =X49*$H49 -> 0 | AA49: =Z49*$H49 -> 0 | AC49: =AB49*$H49 -> 0 | AE49: =AD49*$H49 -> 0 | AG49: =AF49*$H49 -> 0 | AI49: =AH49*$H49 -> 0 | AK49: =AJ49*$H49 -> 0 | AM49: =AL49*$H49 -> 0 | AO49: =AN49*$H49 -> 0 | AQ49: =AP49*$H49 -> 0 | AS49: =AR49*$H49 -> 0 | AU49: =AT49*$H49 -> 0 | AW49: =AV49*$H49 -> 0 | AX49: =SUM(AV49,AT49,AR49,AP49,AN49,AL49,AJ49,AH49,AF49,AD49,AB49,Z49,X49,V49,T49,R49,P49,N49,L49,J49) -> 0 | AY49: =SUM(AW49,AU49,AS49,AQ49,AO49,AM49,AK49,AI49,AG49,AE49,AC49,AA49,Y49,W49,U49,S49,Q49,O49,M49,K49) -> 0 | AZ49: =(F49+G49)-AX49 -> 0 | BA49: =I49-AY49 -> 0
B50: 5056000043 | C50: =IFERROR(IF(B50,VLOOKUP((AEO!$B$13&AEO!$C$13&B50&E50),MSRV5!A:F,6,0),""),"N/A") -> 410 | D50: DESMOB. S. PEQ. PORTE, DUR. MÁX. DE 30 D | E50: =IF(B50,VLOOKUP(B50,MSRV5!B:D,3,0),"") -> UA | H50: =IFERROR(IF(B50,VLOOKUP((AEO!$B$13&AEO!$C$13&B50&E50),MSRV5!A:E,5,0),""),0) -> 3120.52 | I50: =(F50+G50)*H50 -> 0 | J50: 0 | K50: =J50*$H50 -> 0 | M50: =L50*$H50 -> 0 | O50: =N50*$H50 -> 0 | Q50: =P50*$H50 -> 0 | S50: =R50*$H50 -> 0 | U50: =T50*$H50 -> 0 | W50: =V50*$H50 -> 0 | Y50: =X50*$H50 -> 0 | AA50: =Z50*$H50 -> 0 | AC50: =AB50*$H50 -> 0 | AE50: =AD50*$H50 -> 0 | AG50: =AF50*$H50 -> 0 | AI50: =AH50*$H50 -> 0 | AK50: =AJ50*$H50 -> 0 | AM50: =AL50*$H50 -> 0 | AO50: =AN50*$H50 -> 0 | AQ50: =AP50*$H50 -> 0 | AS50: =AR50*$H50 -> 0 | AU50: =AT50*$H50 -> 0 | AW50: =AV50*$H50 -> 0 | AX50: =SUM(AV50,AT50,AR50,AP50,AN50,AL50,AJ50,AH50,AF50,AD50,AB50,Z50,X50,V50,T50,R50,P50,N50,L50,J50) -> 0 | AY50: =SUM(AW50,AU50,AS50,AQ50,AO50,AM50,AK50,AI50,AG50,AE50,AC50,AA50,Y50,W50,U50,S50,Q50,O50,M50,K50) -> 0 | AZ50: =(F50+G50)-AX50 -> 0 | BA50: =I50-AY50 -> 0
B51: 5056000044 | C51: =IFERROR(IF(B51,VLOOKUP((AEO!$B$13&AEO!$C$13&B51&E51),MSRV5!A:F,6,0),""),"N/A") -> 390 | D51: DESMOB. SERV. GRANDE PORTE DUR. >120 D | E51: =IF(B51,VLOOKUP(B51,MSRV5!B:D,3,0),"") -> UA | H51: =IFERROR(IF(B51,VLOOKUP((AEO!$B$13&AEO!$C$13&B51&E51),MSRV5!A:E,5,0),""),0) -> 11859.55 | I51: =(F51+G51)*H51 -> 0 | K51: =J51*$H51 -> 0 | M51: =L51*$H51 -> 0 | O51: =N51*$H51 -> 0 | Q51: =P51*$H51 -> 0 | S51: =R51*$H51 -> 0 | U51: =T51*$H51 -> 0 | W51: =V51*$H51 -> 0 | Y51: =X51*$H51 -> 0 | AA51: =Z51*$H51 -> 0 | AC51: =AB51*$H51 -> 0 | AE51: =AD51*$H51 -> 0 | AG51: =AF51*$H51 -> 0 | AI51: =AH51*$H51 -> 0 | AK51: =AJ51*$H51 -> 0 | AM51: =AL51*$H51 -> 0 | AO51: =AN51*$H51 -> 0 | AQ51: =AP51*$H51 -> 0 | AS51: =AR51*$H51 -> 0 | AU51: =AT51*$H51 -> 0 | AW51: =AV51*$H51 -> 0 | AX51: =SUM(AV51,AT51,AR51,AP51,AN51,AL51,AJ51,AH51,AF51,AD51,AB51,Z51,X51,V51,T51,R51,P51,N51,L51,J51) -> 0 | AY51: =SUM(AW51,AU51,AS51,AQ51,AO51,AM51,AK51,AI51,AG51,AE51,AC51,AA51,Y51,W51,U51,S51,Q51,O51,M51,K51) -> 0 | AZ51: =(F51+G51)-AX51 -> 0 | BA51: =I51-AY51 -> 0
B52: 5056000045 | C52: =IFERROR(IF(B52,VLOOKUP((AEO!$B$13&AEO!$C$13&B52&E52),MSRV5!A:F,6,0),""),"N/A") -> 400 | D52: DESMOB. SER. MÉD. PORTE DUR. >60 E <120D | E52: =IF(B52,VLOOKUP(B52,MSRV5!B:D,3,0),"") -> UA | H52: =IFERROR(IF(B52,VLOOKUP((AEO!$B$13&AEO!$C$13&B52&E52),MSRV5!A:E,5,0),""),0) -> 6085.41 | I52: =(F52+G52)*H52 -> 0 | K52: =J52*$H52 -> 0 | M52: =L52*$H52 -> 0 | O52: =N52*$H52 -> 0 | Q52: =P52*$H52 -> 0 | S52: =R52*$H52 -> 0 | U52: =T52*$H52 -> 0 | W52: =V52*$H52 -> 0 | Y52: =X52*$H52 -> 0 | AA52: =Z52*$H52 -> 0 | AC52: =AB52*$H52 -> 0 | AE52: =AD52*$H52 -> 0 | AG52: =AF52*$H52 -> 0 | AI52: =AH52*$H52 -> 0 | AK52: =AJ52*$H52 -> 0 | AM52: =AL52*$H52 -> 0 | AO52: =AN52*$H52 -> 0 | AQ52: =AP52*$H52 -> 0 | AS52: =AR52*$H52 -> 0 | AU52: =AT52*$H52 -> 0 | AW52: =AV52*$H52 -> 0 | AX52: =SUM(AV52,AT52,AR52,AP52,AN52,AL52,AJ52,AH52,AF52,AD52,AB52,Z52,X52,V52,T52,R52,P52,N52,L52,J52) -> 0 | AY52: =SUM(AW52,AU52,AS52,AQ52,AO52,AM52,AK52,AI52,AG52,AE52,AC52,AA52,Y52,W52,U52,S52,Q52,O52,M52,K52) -> 0 | AZ52: =(F52+G52)-AX52 -> 0 | BA52: =I52-AY52 -> 0
B53: 5056000046 | C53: =IFERROR(IF(B53,VLOOKUP((AEO!$B$13&AEO!$C$13&B53&E53),MSRV5!A:F,6,0),""),"N/A") -> 380 | D53: DESMOB. SERV. PEQ. PORTE, DUR. MÁX. 60D | E53: =IF(B53,VLOOKUP(B53,MSRV5!B:D,3,0),"") -> UA | H53: =IFERROR(IF(B53,VLOOKUP((AEO!$B$13&AEO!$C$13&B53&E53),MSRV5!A:E,5,0),""),0) -> 2561.67 | I53: =(F53+G53)*H53 -> 0 | K53: =J53*$H53 -> 0 | M53: =L53*$H53 -> 0 | O53: =N53*$H53 -> 0 | Q53: =P53*$H53 -> 0 | S53: =R53*$H53 -> 0 | U53: =T53*$H53 -> 0 | W53: =V53*$H53 -> 0 | Y53: =X53*$H53 -> 0 | AA53: =Z53*$H53 -> 0 | AC53: =AB53*$H53 -> 0 | AE53: =AD53*$H53 -> 0 | AG53: =AF53*$H53 -> 0 | AI53: =AH53*$H53 -> 0 | AK53: =AJ53*$H53 -> 0 | AM53: =AL53*$H53 -> 0 | AO53: =AN53*$H53 -> 0 | AQ53: =AP53*$H53 -> 0 | AS53: =AR53*$H53 -> 0 | AU53: =AT53*$H53 -> 0 | AW53: =AV53*$H53 -> 0 | AX53: =SUM(AV53,AT53,AR53,AP53,AN53,AL53,AJ53,AH53,AF53,AD53,AB53,Z53,X53,V53,T53,R53,P53,N53,L53,J53) -> 0 | AY53: =SUM(AW53,AU53,AS53,AQ53,AO53,AM53,AK53,AI53,AG53,AE53,AC53,AA53,Y53,W53,U53,S53,Q53,O53,M53,K53) -> 0 | AZ53: =(F53+G53)-AX53 -> 0 | BA53: =I53-AY53 -> 0
B54: 5056000059 | C54: =IFERROR(IF(B54,VLOOKUP((AEO!$B$13&AEO!$C$13&B54&E54),MSRV5!A:F,6,0),""),"N/A") -> 450 | D54: MOBIL. SER. PEQ. PORTE, DUR. MÁX. DE 30D | E54: =IF(B54,VLOOKUP(B54,MSRV5!B:D,3,0),"") -> UA | H54: =IFERROR(IF(B54,VLOOKUP((AEO!$B$13&AEO!$C$13&B54&E54),MSRV5!A:E,5,0),""),0) -> 10757.98 | I54: =(F54+G54)*H54 -> 0 | K54: =J54*$H54 -> 0 | M54: =L54*$H54 -> 0 | O54: =N54*$H54 -> 0 | Q54: =P54*$H54 -> 0 | S54: =R54*$H54 -> 0 | U54: =T54*$H54 -> 0 | W54: =V54*$H54 -> 0 | Y54: =X54*$H54 -> 0 | AA54: =Z54*$H54 -> 0 | AC54: =AB54*$H54 -> 0 | AE54: =AD54*$H54 -> 0 | AG54: =AF54*$H54 -> 0 | AI54: =AH54*$H54 -> 0 | AK54: =AJ54*$H54 -> 0 | AM54: =AL54*$H54 -> 0 | AO54: =AN54*$H54 -> 0 | AQ54: =AP54*$H54 -> 0 | AS54: =AR54*$H54 -> 0 | AU54: =AT54*$H54 -> 0 | AW54: =AV54*$H54 -> 0 | AX54: =SUM(AV54,AT54,AR54,AP54,AN54,AL54,AJ54,AH54,AF54,AD54,AB54,Z54,X54,V54,T54,R54,P54,N54,L54,J54) -> 0 | AY54: =SUM(AW54,AU54,AS54,AQ54,AO54,AM54,AK54,AI54,AG54,AE54,AC54,AA54,Y54,W54,U54,S54,Q54,O54,M54,K54) -> 0 | AZ54: =(F54+G54)-AX54 -> 0 | BA54: =I54-AY54 -> 0
B55: 5056000060 | C55: =IFERROR(IF(B55,VLOOKUP((AEO!$B$13&AEO!$C$13&B55&E55),MSRV5!A:F,6,0),""),"N/A") -> 430 | D55: MOBILIZAR SERV. GRANDE PORTE DUR. >120 D | E55: =IF(B55,VLOOKUP(B55,MSRV5!B:D,3,0),"") -> UA | H55: =IFERROR(IF(B55,VLOOKUP((AEO!$B$13&AEO!$C$13&B55&E55),MSRV5!A:E,5,0),""),0) -> 29675.46 | I55: =(F55+G55)*H55 -> 0 | K55: =J55*$H55 -> 0 | M55: =L55*$H55 -> 0 | O55: =N55*$H55 -> 0 | Q55: =P55*$H55 -> 0 | S55: =R55*$H55 -> 0 | U55: =T55*$H55 -> 0 | W55: =V55*$H55 -> 0 | Y55: =X55*$H55 -> 0 | AA55: =Z55*$H55 -> 0 | AC55: =AB55*$H55 -> 0 | AE55: =AD55*$H55 -> 0 | AG55: =AF55*$H55 -> 0 | AI55: =AH55*$H55 -> 0 | AK55: =AJ55*$H55 -> 0 | AM55: =AL55*$H55 -> 0 | AO55: =AN55*$H55 -> 0 | AQ55: =AP55*$H55 -> 0 | AS55: =AR55*$H55 -> 0 | AU55: =AT55*$H55 -> 0 | AW55: =AV55*$H55 -> 0 | AX55: =SUM(AV55,AT55,AR55,AP55,AN55,AL55,AJ55,AH55,AF55,AD55,AB55,Z55,X55,V55,T55,R55,P55,N55,L55,J55) -> 0 | AY55: =SUM(AW55,AU55,AS55,AQ55,AO55,AM55,AK55,AI55,AG55,AE55,AC55,AA55,Y55,W55,U55,S55,Q55,O55,M55,K55) -> 0 | AZ55: =(F55+G55)-AX55 -> 0 | BA55: =I55-AY55 -> 0
B56: 5056000061 | C56: =IFERROR(IF(B56,VLOOKUP((AEO!$B$13&AEO!$C$13&B56&E56),MSRV5!A:F,6,0),""),"N/A") -> 440 | D56: MOBIL. SERV. MÉD. PORTE DUR. >60 E <120D | E56: =IF(B56,VLOOKUP(B56,MSRV5!B:D,3,0),"") -> UA | H56: =IFERROR(IF(B56,VLOOKUP((AEO!$B$13&AEO!$C$13&B56&E56),MSRV5!A:E,5,0),""),0) -> 17041.68 | I56: =(F56+G56)*H56 -> 0 | K56: =J56*$H56 -> 0 | M56: =L56*$H56 -> 0 | O56: =N56*$H56 -> 0 | Q56: =P56*$H56 -> 0 | S56: =R56*$H56 -> 0 | U56: =T56*$H56 -> 0 | W56: =V56*$H56 -> 0 | Y56: =X56*$H56 -> 0 | AA56: =Z56*$H56 -> 0 | AC56: =AB56*$H56 -> 0 | AE56: =AD56*$H56 -> 0 | AG56: =AF56*$H56 -> 0 | AI56: =AH56*$H56 -> 0 | AK56: =AJ56*$H56 -> 0 | AM56: =AL56*$H56 -> 0 | AO56: =AN56*$H56 -> 0 | AQ56: =AP56*$H56 -> 0 | AS56: =AR56*$H56 -> 0 | AU56: =AT56*$H56 -> 0 | AW56: =AV56*$H56 -> 0 | AX56: =SUM(AV56,AT56,AR56,AP56,AN56,AL56,AJ56,AH56,AF56,AD56,AB56,Z56,X56,V56,T56,R56,P56,N56,L56,J56) -> 0 | AY56: =SUM(AW56,AU56,AS56,AQ56,AO56,AM56,AK56,AI56,AG56,AE56,AC56,AA56,Y56,W56,U56,S56,Q56,O56,M56,K56) -> 0 | AZ56: =(F56+G56)-AX56 -> 0 | BA56: =I56-AY56 -> 0
B57: 5056000062 | C57: =IFERROR(IF(B57,VLOOKUP((AEO!$B$13&AEO!$C$13&B57&E57),MSRV5!A:F,6,0),""),"N/A") -> 420 | D57: MOBILIZ. SER. PEQ. PORTE, DUR. MÁX. 60D | E57: =IF(B57,VLOOKUP(B57,MSRV5!B:D,3,0),"") -> UA | H57: =IFERROR(IF(B57,VLOOKUP((AEO!$B$13&AEO!$C$13&B57&E57),MSRV5!A:E,5,0),""),0) -> 8717.23 | I57: =(F57+G57)*H57 -> 0 | K57: =J57*$H57 -> 0 | M57: =L57*$H57 -> 0 | O57: =N57*$H57 -> 0 | Q57: =P57*$H57 -> 0 | S57: =R57*$H57 -> 0 | U57: =T57*$H57 -> 0 | W57: =V57*$H57 -> 0 | Y57: =X57*$H57 -> 0 | AA57: =Z57*$H57 -> 0 | AC57: =AB57*$H57 -> 0 | AE57: =AD57*$H57 -> 0 | AG57: =AF57*$H57 -> 0 | AI57: =AH57*$H57 -> 0 | AK57: =AJ57*$H57 -> 0 | AM57: =AL57*$H57 -> 0 | AO57: =AN57*$H57 -> 0 | AQ57: =AP57*$H57 -> 0 | AS57: =AR57*$H57 -> 0 | AU57: =AT57*$H57 -> 0 | AW57: =AV57*$H57 -> 0 | AX57: =SUM(AV57,AT57,AR57,AP57,AN57,AL57,AJ57,AH57,AF57,AD57,AB57,Z57,X57,V57,T57,R57,P57,N57,L57,J57) -> 0 | AY57: =SUM(AW57,AU57,AS57,AQ57,AO57,AM57,AK57,AI57,AG57,AE57,AC57,AA57,Y57,W57,U57,S57,Q57,O57,M57,K57) -> 0 | AZ57: =(F57+G57)-AX57 -> 0 | BA57: =I57-AY57 -> 0
B58: 5500300165 | C58: =IFERROR(IF(B58,VLOOKUP((AEO!$B$13&AEO!$C$13&B58&E58),MSRV5!A:F,6,0),""),"N/A") -> 460 | D58: LOCAÇÃO, MARCAÇÃO E ACOMPANHAM. DA OBRA | E58: =IF(B58,VLOOKUP(B58,MSRV5!B:D,3,0),"") -> UN | H58: =IFERROR(IF(B58,VLOOKUP((AEO!$B$13&AEO!$C$13&B58&E58),MSRV5!A:E,5,0),""),0) -> 14269.75 | I58: =(F58+G58)*H58 -> 0 | K58: =J58*$H58 -> 0 | M58: =L58*$H58 -> 0 | O58: =N58*$H58 -> 0 | Q58: =P58*$H58 -> 0 | S58: =R58*$H58 -> 0 | U58: =T58*$H58 -> 0 | W58: =V58*$H58 -> 0 | Y58: =X58*$H58 -> 0 | AA58: =Z58*$H58 -> 0 | AC58: =AB58*$H58 -> 0 | AE58: =AD58*$H58 -> 0 | AG58: =AF58*$H58 -> 0 | AI58: =AH58*$H58 -> 0 | AK58: =AJ58*$H58 -> 0 | AM58: =AL58*$H58 -> 0 | AO58: =AN58*$H58 -> 0 | AQ58: =AP58*$H58 -> 0 | AS58: =AR58*$H58 -> 0 | AU58: =AT58*$H58 -> 0 | AW58: =AV58*$H58 -> 0 | AX58: =SUM(AV58,AT58,AR58,AP58,AN58,AL58,AJ58,AH58,AF58,AD58,AB58,Z58,X58,V58,T58,R58,P58,N58,L58,J58) -> 0 | AY58: =SUM(AW58,AU58,AS58,AQ58,AO58,AM58,AK58,AI58,AG58,AE58,AC58,AA58,Y58,W58,U58,S58,Q58,O58,M58,K58) -> 0 | AZ58: =(F58+G58)-AX58 -> 0 | BA58: =I58-AY58 -> 0
B59: 5053000017 | C59: =IFERROR(IF(B59,VLOOKUP((AEO!$B$13&AEO!$C$13&B59&E59),MSRV5!A:F,6,0),""),"N/A") -> 470 | D59: LIGAÇÃO PROVISÓRIA DE LUZ E FORÇA P/ SE | E59: =IF(B59,VLOOKUP(B59,MSRV5!B:D,3,0),"") -> UN | H59: =IFERROR(IF(B59,VLOOKUP((AEO!$B$13&AEO!$C$13&B59&E59),MSRV5!A:E,5,0),""),0) -> 5181.45 | I59: =(F59+G59)*H59 -> 0 | K59: =J59*$H59 -> 0 | M59: =L59*$H59 -> 0 | O59: =N59*$H59 -> 0 | Q59: =P59*$H59 -> 0 | S59: =R59*$H59 -> 0 | U59: =T59*$H59 -> 0 | W59: =V59*$H59 -> 0 | Y59: =X59*$H59 -> 0 | AA59: =Z59*$H59 -> 0 | AC59: =AB59*$H59 -> 0 | AE59: =AD59*$H59 -> 0 | AG59: =AF59*$H59 -> 0 | AI59: =AH59*$H59 -> 0 | AK59: =AJ59*$H59 -> 0 | AM59: =AL59*$H59 -> 0 | AO59: =AN59*$H59 -> 0 | AQ59: =AP59*$H59 -> 0 | AS59: =AR59*$H59 -> 0 | AU59: =AT59*$H59 -> 0 | AW59: =AV59*$H59 -> 0 | AX59: =SUM(AV59,AT59,AR59,AP59,AN59,AL59,AJ59,AH59,AF59,AD59,AB59,Z59,X59,V59,T59,R59,P59,N59,L59,J59) -> 0 | AY59: =SUM(AW59,AU59,AS59,AQ59,AO59,AM59,AK59,AI59,AG59,AE59,AC59,AA59,Y59,W59,U59,S59,Q59,O59,M59,K59) -> 0 | AZ59: =(F59+G59)-AX59 -> 0 | BA59: =I59-AY59 -> 0
B60: 5500300057 | C60: =IFERROR(IF(B60,VLOOKUP((AEO!$B$13&AEO!$C$13&B60&E60),MSRV5!A:F,6,0),""),"N/A") -> 480 | D60: INSTALAÇÕES PROVIS. DE ENERGIA ELÉTRICA | E60: =IF(B60,VLOOKUP(B60,MSRV5!B:D,3,0),"") -> MES | H60: =IFERROR(IF(B60,VLOOKUP((AEO!$B$13&AEO!$C$13&B60&E60),MSRV5!A:E,5,0),""),0) -> 6383.68 | I60: =(F60+G60)*H60 -> 0 | K60: =J60*$H60 -> 0 | M60: =L60*$H60 -> 0 | O60: =N60*$H60 -> 0 | Q60: =P60*$H60 -> 0 | S60: =R60*$H60 -> 0 | U60: =T60*$H60 -> 0 | W60: =V60*$H60 -> 0 | Y60: =X60*$H60 -> 0 | AA60: =Z60*$H60 -> 0 | AC60: =AB60*$H60 -> 0 | AE60: =AD60*$H60 -> 0 | AG60: =AF60*$H60 -> 0 | AI60: =AH60*$H60 -> 0 | AK60: =AJ60*$H60 -> 0 | AM60: =AL60*$H60 -> 0 | AO60: =AN60*$H60 -> 0 | AQ60: =AP60*$H60 -> 0 | AS60: =AR60*$H60 -> 0 | AU60: =AT60*$H60 -> 0 | AW60: =AV60*$H60 -> 0 | AX60: =SUM(AV60,AT60,AR60,AP60,AN60,AL60,AJ60,AH60,AF60,AD60,AB60,Z60,X60,V60,T60,R60,P60,N60,L60,J60) -> 0 | AY60: =SUM(AW60,AU60,AS60,AQ60,AO60,AM60,AK60,AI60,AG60,AE60,AC60,AA60,Y60,W60,U60,S60,Q60,O60,M60,K60) -> 0 | AZ60: =(F60+G60)-AX60 -> 0 | BA60: =I60-AY60 -> 0
B61: 5500400469 | C61: =IFERROR(IF(B61,VLOOKUP((AEO!$B$13&AEO!$C$13&B61&E61),MSRV5!A:F,6,0),""),"N/A") -> 490 | D61: TELA TAPUME (ISOLAMENTO/SINALIZAÇÃO) | E61: =IF(B61,VLOOKUP(B61,MSRV5!B:D,3,0),"") -> M | H61: =IFERROR(IF(B61,VLOOKUP((AEO!$B$13&AEO!$C$13&B61&E61),MSRV5!A:E,5,0),""),0) -> 20.09 | I61: =(F61+G61)*H61 -> 0 | K61: =J61*$H61 -> 0 | M61: =L61*$H61 -> 0 | O61: =N61*$H61 -> 0 | Q61: =P61*$H61 -> 0 | S61: =R61*$H61 -> 0 | U61: =T61*$H61 -> 0 | W61: =V61*$H61 -> 0 | Y61: =X61*$H61 -> 0 | AA61: =Z61*$H61 -> 0 | AC61: =AB61*$H61 -> 0 | AE61: =AD61*$H61 -> 0 | AG61: =AF61*$H61 -> 0 | AI61: =AH61*$H61 -> 0 | AK61: =AJ61*$H61 -> 0 | AM61: =AL61*$H61 -> 0 | AO61: =AN61*$H61 -> 0 | AQ61: =AP61*$H61 -> 0 | AS61: =AR61*$H61 -> 0 | AU61: =AT61*$H61 -> 0 | AW61: =AV61*$H61 -> 0 | AX61: =SUM(AV61,AT61,AR61,AP61,AN61,AL61,AJ61,AH61,AF61,AD61,AB61,Z61,X61,V61,T61,R61,P61,N61,L61,J61) -> 0 | AY61: =SUM(AW61,AU61,AS61,AQ61,AO61,AM61,AK61,AI61,AG61,AE61,AC61,AA61,Y61,W61,U61,S61,Q61,O61,M61,K61) -> 0 | AZ61: =(F61+G61)-AX61 -> 0 | BA61: =I61-AY61 -> 0
B62: 5056000008 | C62: =IFERROR(IF(B62,VLOOKUP((AEO!$B$13&AEO!$C$13&B62&E62),MSRV5!A:F,6,0),""),"N/A") -> 500 | D62: LIMPEZA GERAL DA OBRA (CIVIL) | E62: =IF(B62,VLOOKUP(B62,MSRV5!B:D,3,0),"") -> UN | H62: =IFERROR(IF(B62,VLOOKUP((AEO!$B$13&AEO!$C$13&B62&E62),MSRV5!A:E,5,0),""),0) -> 1356.17 | I62: =(F62+G62)*H62 -> 0 | K62: =J62*$H62 -> 0 | M62: =L62*$H62 -> 0 | O62: =N62*$H62 -> 0 | Q62: =P62*$H62 -> 0 | S62: =R62*$H62 -> 0 | U62: =T62*$H62 -> 0 | W62: =V62*$H62 -> 0 | Y62: =X62*$H62 -> 0 | AA62: =Z62*$H62 -> 0 | AC62: =AB62*$H62 -> 0 | AE62: =AD62*$H62 -> 0 | AG62: =AF62*$H62 -> 0 | AI62: =AH62*$H62 -> 0 | AK62: =AJ62*$H62 -> 0 | AM62: =AL62*$H62 -> 0 | AO62: =AN62*$H62 -> 0 | AQ62: =AP62*$H62 -> 0 | AS62: =AR62*$H62 -> 0 | AU62: =AT62*$H62 -> 0 | AW62: =AV62*$H62 -> 0 | AX62: =SUM(AV62,AT62,AR62,AP62,AN62,AL62,AJ62,AH62,AF62,AD62,AB62,Z62,X62,V62,T62,R62,P62,N62,L62,J62) -> 0 | AY62: =SUM(AW62,AU62,AS62,AQ62,AO62,AM62,AK62,AI62,AG62,AE62,AC62,AA62,Y62,W62,U62,S62,Q62,O62,M62,K62) -> 0 | AZ62: =(F62+G62)-AX62 -> 0 | BA62: =I62-AY62 -> 0
... B81: 5500400603 | C81: =IFERROR(IF(B81,VLOOKUP((AEO!$B$13&AEO!$C$13&B81&E81),MSRV5!A:F,6,0),""),"N/A") -> 690 | D81: TRANSPORTE DOS CONTAINER | E81: =IF(B81,VLOOKUP(B81,MSRV5!B:D,3,0),"") -> UN | H81: =IFERROR(IF(B81,VLOOKUP((AEO!$B$13&AEO!$C$13&B81&E81),MSRV5!A:E,5,0),""),0) -> 3461.5 | I81: =(F81+G81)*H81 -> 0 | K81: =J81*$H81 -> 0 | M81: =L81*$H81 -> 0 | O81: =N81*$H81 -> 0 | Q81: =P81*$H81 -> 0 | S81: =R81*$H81 -> 0 | U81: =T81*$H81 -> 0 | W81: =V81*$H81 -> 0 | Y81: =X81*$H81 -> 0 | AA81: =Z81*$H81 -> 0 | AC81: =AB81*$H81 -> 0 | AE81: =AD81*$H81 -> 0 | AG81: =AF81*$H81 -> 0 | AI81: =AH81*$H81 -> 0 | AK81: =AJ81*$H81 -> 0 | AM81: =AL81*$H81 -> 0 | AO81: =AN81*$H81 -> 0 | AQ81: =AP81*$H81 -> 0 | AS81: =AR81*$H81 -> 0 | AU81: =AT81*$H81 -> 0 | AW81: =AV81*$H81 -> 0 | AX81: =SUM(AV81,AT81,AR81,AP81,AN81,AL81,AJ81,AH81,AF81,AD81,AB81,Z81,X81,V81,T81,R81,P81,N81,L81,J81) -> 0 | AY81: =SUM(AW81,AU81,AS81,AQ81,AO81,AM81,AK81,AI81,AG81,AE81,AC81,AA81,Y81,W81,U81,S81,Q81,O81,M81,K81) -> 0 | AZ81: =(F81+G81)-AX81 -> 0 | BA81: =I81-AY81 -> 0
B82: 5500000461 | C82: =IFERROR(IF(B82,VLOOKUP((AEO!$B$13&AEO!$C$13&B82&E82),MSRV5!A:F,6,0),""),"N/A") -> 700 | D82: AÇÕES DE SEGURANÇA | E82: =IF(B82,VLOOKUP(B82,MSRV5!B:D,3,0),"") -> UN | F82: 0 | H82: =IFERROR(IF(B82,VLOOKUP((AEO!$B$13&AEO!$C$13&B82&E82),MSRV5!A:E,5,0),""),0) -> 8990.29 | I82: =(F82+G82)*H82 -> 0 | K82: =J82*$H82 -> 0 | M82: =L82*$H82 -> 0 | O82: =N82*$H82 -> 0 | Q82: =P82*$H82 -> 0 | S82: =R82*$H82 -> 0 | U82: =T82*$H82 -> 0 | W82: =V82*$H82 -> 0 | Y82: =X82*$H82 -> 0 | AA82: =Z82*$H82 -> 0 | AC82: =AB82*$H82 -> 0 | AE82: =AD82*$H82 -> 0 | AG82: =AF82*$H82 -> 0 | AI82: =AH82*$H82 -> 0 | AK82: =AJ82*$H82 -> 0 | AM82: =AL82*$H82 -> 0 | AO82: =AN82*$H82 -> 0 | AQ82: =AP82*$H82 -> 0 | AS82: =AR82*$H82 -> 0 | AU82: =AT82*$H82 -> 0 | AW82: =AV82*$H82 -> 0 | AX82: =SUM(AV82,AT82,AR82,AP82,AN82,AL82,AJ82,AH82,AF82,AD82,AB82,Z82,X82,V82,T82,R82,P82,N82,L82,J82) -> 0 | AY82: =SUM(AW82,AU82,AS82,AQ82,AO82,AM82,AK82,AI82,AG82,AE82,AC82,AA82,Y82,W82,U82,S82,Q82,O82,M82,K82) -> 0 | AZ82: =(F82+G82)-AX82 -> 0 | BA82: =I82-AY82 -> 0
B83: 5261000001 | C83: =IFERROR(IF(B83,VLOOKUP((AEO!$B$13&AEO!$C$13&B83&E83),MSRV5!A:F,6,0),""),"N/A") -> 7130 | D83: AÇÕES AMBIENTAIS | E83: =IF(B83,VLOOKUP(B83,MSRV5!B:D,3,0),"") -> UN | H83: =IFERROR(IF(B83,VLOOKUP((AEO!$B$13&AEO!$C$13&B83&E83),MSRV5!A:E,5,0),""),0) -> 50693.91 | I83: =(F83+G83)*H83 -> 0 | K83: =J83*$H83 -> 0 | M83: =L83*$H83 -> 0 | O83: =N83*$H83 -> 0 | Q83: =P83*$H83 -> 0 | S83: =R83*$H83 -> 0 | U83: =T83*$H83 -> 0 | W83: =V83*$H83 -> 0 | Y83: =X83*$H83 -> 0 | AA83: =Z83*$H83 -> 0 | AC83: =AB83*$H83 -> 0 | AE83: =AD83*$H83 -> 0 | AG83: =AF83*$H83 -> 0 | AI83: =AH83*$H83 -> 0 | AK83: =AJ83*$H83 -> 0 | AM83: =AL83*$H83 -> 0 | AO83: =AN83*$H83 -> 0 | AQ83: =AP83*$H83 -> 0 | AS83: =AR83*$H83 -> 0 | AU83: =AT83*$H83 -> 0 | AW83: =AV83*$H83 -> 0 | AX83: =SUM(AV83,AT83,AR83,AP83,AN83,AL83,AJ83,AH83,AF83,AD83,AB83,Z83,X83,V83,T83,R83,P83,N83,L83,J83) -> 0 | AY83: =SUM(AW83,AU83,AS83,AQ83,AO83,AM83,AK83,AI83,AG83,AE83,AC83,AA83,Y83,W83,U83,S83,Q83,O83,M83,K83) -> 0 | AZ83: =(F83+G83)-AX83 -> 0 | BA83: =I83-AY83 -> 0
B84: 5500000955 | C84: =IFERROR(IF(B84,VLOOKUP((AEO!$B$13&AEO!$C$13&B84&E84),MSRV5!A:F,6,0),""),"N/A") -> 720 | D84: BARRAÇÃO REFEITÓRIO 6X6m | E84: =IF(B84,VLOOKUP(B84,MSRV5!B:D,3,0),"") -> UN | H84: =IFERROR(IF(B84,VLOOKUP((AEO!$B$13&AEO!$C$13&B84&E84),MSRV5!A:E,5,0),""),0) -> 7212.04 | I84: =(F84+G84)*H84 -> 0 | K84: =J84*$H84 -> 0 | M84: =L84*$H84 -> 0 | O84: =N84*$H84 -> 0 | Q84: =P84*$H84 -> 0 | S84: =R84*$H84 -> 0 | U84: =T84*$H84 -> 0 | W84: =V84*$H84 -> 0 | Y84: =X84*$H84 -> 0 | AA84: =Z84*$H84 -> 0 | AC84: =AB84*$H84 -> 0 | AE84: =AD84*$H84 -> 0 | AG84: =AF84*$H84 -> 0 | AI84: =AH84*$H84 -> 0 | AK84: =AJ84*$H84 -> 0 | AM84: =AL84*$H84 -> 0 | AO84: =AN84*$H84 -> 0 | AQ84: =AP84*$H84 -> 0 | AS84: =AR84*$H84 -> 0 | AU84: =AT84*$H84 -> 0 | AW84: =AV84*$H84 -> 0 | AX84: =SUM(AV84,AT84,AR84,AP84,AN84,AL84,AJ84,AH84,AF84,AD84,AB84,Z84,X84,V84,T84,R84,P84,N84,L84,J84) -> 0 | AY84: =SUM(AW84,AU84,AS84,AQ84,AO84,AM84,AK84,AI84,AG84,AE84,AC84,AA84,Y84,W84,U84,S84,Q84,O84,M84,K84) -> 0 | AZ84: =(F84+G84)-AX84 -> 0 | BA84: =I84-AY84 -> 0
B85: 5500300116 | C85: =IFERROR(IF(B85,VLOOKUP((AEO!$B$13&AEO!$C$13&B85&E85),MSRV5!A:F,6,0),""),"N/A") -> 730 | D85: LIMPEZA DURANTE E NO FINAL DA OBRA | E85: =IF(B85,VLOOKUP(B85,MSRV5!B:D,3,0),"") -> MES | H85: =IFERROR(IF(B85,VLOOKUP((AEO!$B$13&AEO!$C$13&B85&E85),MSRV5!A:E,5,0),""),0) -> 2454.59 | I85: =(F85+G85)*H85 -> 0 | J85: 0 | K85: =J85*$H85 -> 0 | M85: =L85*$H85 -> 0 | O85: =N85*$H85 -> 0 | Q85: =P85*$H85 -> 0 | S85: =R85*$H85 -> 0 | U85: =T85*$H85 -> 0 | W85: =V85*$H85 -> 0 | Y85: =X85*$H85 -> 0 | AA85: =Z85*$H85 -> 0 | AC85: =AB85*$H85 -> 0 | AE85: =AD85*$H85 -> 0 | AG85: =AF85*$H85 -> 0 | AI85: =AH85*$H85 -> 0 | AK85: =AJ85*$H85 -> 0 | AM85: =AL85*$H85 -> 0 | AO85: =AN85*$H85 -> 0 | AQ85: =AP85*$H85 -> 0 | AS85: =AR85*$H85 -> 0 | AU85: =AT85*$H85 -> 0 | AW85: =AV85*$H85 -> 0 | AX85: =SUM(AV85,AT85,AR85,AP85,AN85,AL85,AJ85,AH85,AF85,AD85,AB85,Z85,X85,V85,T85,R85,P85,N85,L85,J85) -> 0 | AY85: =SUM(AW85,AU85,AS85,AQ85,AO85,AM85,AK85,AI85,AG85,AE85,AC85,AA85,Y85,W85,U85,S85,Q85,O85,M85,K85) -> 0 | AZ85: =(F85+G85)-AX85 -> 0 | BA85: =I85-AY85 -> 0
B86: 5500300221 | C86: =IFERROR(IF(B86,VLOOKUP((AEO!$B$13&AEO!$C$13&B86&E86),MSRV5!A:F,6,0),""),"N/A") -> 740 | D86: MÃO DE OBRA DE ADMINISTRAÇÃO LOCAL | E86: =IF(B86,VLOOKUP(B86,MSRV5!B:D,3,0),"") -> UN | H86: =IFERROR(IF(B86,VLOOKUP((AEO!$B$13&AEO!$C$13&B86&E86),MSRV5!A:E,5,0),""),0) -> 1 | I86: =(F86+G86)*H86 -> 0 | K86: =J86*$H86 -> 0 | M86: =L86*$H86 -> 0 | O86: =N86*$H86 -> 0 | Q86: =P86*$H86 -> 0 | S86: =R86*$H86 -> 0 | U86: =T86*$H86 -> 0 | W86: =V86*$H86 -> 0 | Y86: =X86*$H86 -> 0 | AA86: =Z86*$H86 -> 0 | AC86: =AB86*$H86 -> 0 | AE86: =AD86*$H86 -> 0 | AG86: =AF86*$H86 -> 0 | AI86: =AH86*$H86 -> 0 | AK86: =AJ86*$H86 -> 0 | AM86: =AL86*$H86 -> 0 | AO86: =AN86*$H86 -> 0 | AQ86: =AP86*$H86 -> 0 | AS86: =AR86*$H86 -> 0 | AU86: =AT86*$H86 -> 0 | AW86: =AV86*$H86 -> 0 | AX86: =SUM(AV86,AT86,AR86,AP86,AN86,AL86,AJ86,AH86,AF86,AD86,AB86,Z86,X86,V86,T86,R86,P86,N86,L86,J86) -> 0 | AY86: =SUM(AW86,AU86,AS86,AQ86,AO86,AM86,AK86,AI86,AG86,AE86,AC86,AA86,Y86,W86,U86,S86,Q86,O86,M86,K86) -> 0 | AZ86: =(F86+G86)-AX86 -> 0 | BA86: =I86-AY86 -> 0
C87: =IFERROR(IF(B87,VLOOKUP((AEO!$B$13&AEO!$C$13&B87&E87),MSRV5!A:F,6,0),""),"N/A") | D87: SERVIÇOS PRELIMINARES - TRANSPORTE (FATOR "T") | E87: =IF(B87,VLOOKUP(B87,MSRV5!B:D,3,0),"") | H87: =IFERROR(IF(B87,VLOOKUP((AEO!$B$13&AEO!$C$13&B87&E87),MSRV5!A:E,5,0),""),0) | I87: =SUBTOTAL(9,I88:I100) -> 0 | K87: =SUBTOTAL(9,K88:K100) -> 0 | M87: =SUBTOTAL(9,M88:M100) -> 0 | O87: =SUBTOTAL(9,O88:O100) -> 0 | Q87: =SUBTOTAL(9,Q88:Q100) -> 0 | S87: =SUBTOTAL(9,S88:S100) -> 0 | U87: =SUBTOTAL(9,U88:U100) -> 0 | W87: =SUBTOTAL(9,W88:W100) -> 0 | Y87: =SUBTOTAL(9,Y88:Y100) -> 0 | AA87: =SUBTOTAL(9,AA88:AA100) -> 0 | AC87: =SUBTOTAL(9,AC88:AC100) -> 0 | AE87: =SUBTOTAL(9,AE88:AE100) -> 0 | AG87: =SUBTOTAL(9,AG88:AG100) -> 0 | AI87: =SUBTOTAL(9,AI88:AI100) -> 0 | AK87: =SUBTOTAL(9,AK88:AK100) -> 0 | AM87: =SUBTOTAL(9,AM88:AM100) -> 0 | AO87: =SUBTOTAL(9,AO88:AO100) -> 0 | AQ87: =SUBTOTAL(9,AQ88:AQ100) -> 0 | AS87: =SUBTOTAL(9,AS88:AS100) -> 0 | AU87: =SUBTOTAL(9,AU88:AU100) -> 0 | AW87: =SUBTOTAL(9,AW88:AW100) -> 0 | AY87: =SUBTOTAL(9,AY88:AY100) -> 0 | BA87: =SUBTOTAL(9,BA88:BA100) -> 0
B88: 5500400604 | C88: =IFERROR(IF(B88,VLOOKUP((AEO!$B$13&AEO!$C$13&B88&E88),MSRV5!A:F,6,0),""),"N/A") -> N/A | D88: TRANSPORTE E ESPALHAMENTO | E88: =IF(B88,VLOOKUP(B88,MSRV5!B:D,3,0),"") -> #N/A | H88: =IFERROR(IF(B88,VLOOKUP((AEO!$B$13&AEO!$C$13&B88&E88),MSRV5!A:E,5,0),""),0) -> 0 | I88: =(F88+G88)*H88 -> 0 | K88: =J88*$H88 -> 0 | M88: =L88*$H88 -> 0 | O88: =N88*$H88 -> 0 | Q88: =P88*$H88 -> 0 | S88: =R88*$H88 -> 0 | U88: =T88*$H88 -> 0 | W88: =V88*$H88 -> 0 | Y88: =X88*$H88 -> 0 | AA88: =Z88*$H88 -> 0 | AC88: =AB88*$H88 -> 0 | AE88: =AD88*$H88 -> 0 | AG88: =AF88*$H88 -> 0 | AI88: =AH88*$H88 -> 0 | AK88: =AJ88*$H88 -> 0 | AM88: =AL88*$H88 -> 0 | AO88: =AN88*$H88 -> 0 | AQ88: =AP88*$H88 -> 0 | AS88: =AR88*$H88 -> 0 | AU88: =AT88*$H88 -> 0 | AW88: =AV88*$H88 -> 0 | AX88: =SUM(AV88,AT88,AR88,AP88,AN88,AL88,AJ88,AH88,AF88,AD88,AB88,Z88,X88,V88,T88,R88,P88,N88,L88,J88) -> 0 | AY88: =SUM(AW88,AU88,AS88,AQ88,AO88,AM88,AK88,AI88,AG88,AE88,AC88,AA88,Y88,W88,U88,S88,Q88,O88,M88,K88) -> 0 | AZ88: =(F88+G88)-AX88 -> 0 | BA88: =I88-AY88 -> 0
B89: 5500400605 | C89: =IFERROR(IF(B89,VLOOKUP((AEO!$B$13&AEO!$C$13&B89&E89),MSRV5!A:F,6,0),""),"N/A") -> 750 | D89: TRANSPORTE DAS ESCAVAÇÕES PARA LOCAL ADEQUADO | E89: =IF(B89,VLOOKUP(B89,MSRV5!B:D,3,0),"") -> KM | H89: =IFERROR(IF(B89,VLOOKUP((AEO!$B$13&AEO!$C$13&B89&E89),MSRV5!A:E,5,0),""),0) -> 42.3 | I89: =(F89+G89)*H89 -> 0 | K89: =J89*$H89 -> 0 | M89: =L89*$H89 -> 0 | O89: =N89*$H89 -> 0 | Q89: =P89*$H89 -> 0 | S89: =R89*$H89 -> 0 | U89: =T89*$H89 -> 0 | W89: =V89*$H89 -> 0 | Y89: =X89*$H89 -> 0 | AA89: =Z89*$H89 -> 0 | AC89: =AB89*$H89 -> 0 | AE89: =AD89*$H89 -> 0 | AG89: =AF89*$H89 -> 0 | AI89: =AH89*$H89 -> 0 | AK89: =AJ89*$H89 -> 0 | AM89: =AL89*$H89 -> 0 | AO89: =AN89*$H89 -> 0 | AQ89: =AP89*$H89 -> 0 | AS89: =AR89*$H89 -> 0 | AU89: =AT89*$H89 -> 0 | AW89: =AV89*$H89 -> 0 | AX89: =SUM(AV89,AT89,AR89,AP89,AN89,AL89,AJ89,AH89,AF89,AD89,AB89,Z89,X89,V89,T89,R89,P89,N89,L89,J89) -> 0 | AY89: =SUM(AW89,AU89,AS89,AQ89,AO89,AM89,AK89,AI89,AG89,AE89,AC89,AA89,Y89,W89,U89,S89,Q89,O89,M89,K89) -> 0 | AZ89: =(F89+G89)-AX89 -> 0 | BA89: =I89-AY89 -> 0
B90: 5500400589 | C90: =IFERROR(IF(B90,VLOOKUP((AEO!$B$13&AEO!$C$13&B90&E90),MSRV5!A:F,6,0),""),"N/A") -> 760 | D90: TRANSPORTE/REMOÇÃO DO MATERIAL PROVENIENTE DAS ESCAVAÇÕES PARA FORA DO PÁTIO | E90: =IF(B90,VLOOKUP(B90,MSRV5!B:D,3,0),"") -> M3 | H90: =IFERROR(IF(B90,VLOOKUP((AEO!$B$13&AEO!$C$13&B90&E90),MSRV5!A:E,5,0),""),0) -> 104.23 | I90: =(F90+G90)*H90 -> 0 | K90: =J90*$H90 -> 0 | M90: =L90*$H90 -> 0 | O90: =N90*$H90 -> 0 | Q90: =P90*$H90 -> 0 | S90: =R90*$H90 -> 0 | U90: =T90*$H90 -> 0 | W90: =V90*$H90 -> 0 | Y90: =X90*$H90 -> 0 | AA90: =Z90*$H90 -> 0 | AC90: =AB90*$H90 -> 0 | AE90: =AD90*$H90 -> 0 | AG90: =AF90*$H90 -> 0 | AI90: =AH90*$H90 -> 0 | AK90: =AJ90*$H90 -> 0 | AM90: =AL90*$H90 -> 0 | AO90: =AN90*$H90 -> 0 | AQ90: =AP90*$H90 -> 0 | AS90: =AR90*$H90 -> 0 | AU90: =AT90*$H90 -> 0 | AW90: =AV90*$H90 -> 0 | AX90: =SUM(AV90,AT90,AR90,AP90,AN90,AL90,AJ90,AH90,AF90,AD90,AB90,Z90,X90,V90,T90,R90,P90,N90,L90,J90) -> 0 | AY90: =SUM(AW90,AU90,AS90,AQ90,AO90,AM90,AK90,AI90,AG90,AE90,AC90,AA90,Y90,W90,U90,S90,Q90,O90,M90,K90) -> 0 | AZ90: =(F90+G90)-AX90 -> 0 | BA90: =I90-AY90 -> 0
B91: 5500200419 | C91: =IFERROR(IF(B91,VLOOKUP((AEO!$B$13&AEO!$C$13&B91&E91),MSRV5!A:F,6,0),""),"N/A") -> 770 | D91: TRANSPORTE E ESPALHAMENTO ATÉ 200 M | E91: =IF(B91,VLOOKUP(B91,MSRV5!B:D,3,0),"") -> M3 | H91: =IFERROR(IF(B91,VLOOKUP((AEO!$B$13&AEO!$C$13&B91&E91),MSRV5!A:E,5,0),""),0) -> 3.22 | I91: =(F91+G91)*H91 -> 0 | K91: =J91*$H91 -> 0 | M91: =L91*$H91 -> 0 | O91: =N91*$H91 -> 0 | Q91: =P91*$H91 -> 0 | S91: =R91*$H91 -> 0 | U91: =T91*$H91 -> 0 | W91: =V91*$H91 -> 0 | Y91: =X91*$H91 -> 0 | AA91: =Z91*$H91 -> 0 | AC91: =AB91*$H91 -> 0 | AE91: =AD91*$H91 -> 0 | AG91: =AF91*$H91 -> 0 | AI91: =AH91*$H91 -> 0 | AK91: =AJ91*$H91 -> 0 | AM91: =AL91*$H91 -> 0 | AO91: =AN91*$H91 -> 0 | AQ91: =AP91*$H91 -> 0 | AS91: =AR91*$H91 -> 0 | AU91: =AT91*$H91 -> 0 | AW91: =AV91*$H91 -> 0 | AX91: =SUM(AV91,AT91,AR91,AP91,AN91,AL91,AJ91,AH91,AF91,AD91,AB91,Z91,X91,V91,T91,R91,P91,N91,L91,J91) -> 0 | AY91: =SUM(AW91,AU91,AS91,AQ91,AO91,AM91,AK91,AI91,AG91,AE91,AC91,AA91,Y91,W91,U91,S91,Q91,O91,M91,K91) -> 0 | AZ91: =(F91+G91)-AX91 -> 0 | BA91: =I91-AY91 -> 0
B92: 5500400607 | C92: =IFERROR(IF(B92,VLOOKUP((AEO!$B$13&AEO!$C$13&B92&E92),MSRV5!A:F,6,0),""),"N/A") -> 780 | D92: TRANSPORTE DE POSTE DE AT EM DISTÂNCIA ATÉ 70KM | E92: =IF(B92,VLOOKUP(B92,MSRV5!B:D,3,0),"") -> UN | H92: =IFERROR(IF(B92,VLOOKUP((AEO!$B$13&AEO!$C$13&B92&E92),MSRV5!A:E,5,0),""),0) -> 28.2 | I92: =(F92+G92)*H92 -> 0 | K92: =J92*$H92 -> 0 | M92: =L92*$H92 -> 0 | O92: =N92*$H92 -> 0 | Q92: =P92*$H92 -> 0 | S92: =R92*$H92 -> 0 | U92: =T92*$H92 -> 0 | W92: =V92*$H92 -> 0 | Y92: =X92*$H92 -> 0 | AA92: =Z92*$H92 -> 0 | AC92: =AB92*$H92 -> 0 | AE92: =AD92*$H92 -> 0 | AG92: =AF92*$H92 -> 0 | AI92: =AH92*$H92 -> 0 | AK92: =AJ92*$H92 -> 0 | AM92: =AL92*$H92 -> 0 | AO92: =AN92*$H92 -> 0 | AQ92: =AP92*$H92 -> 0 | AS92: =AR92*$H92 -> 0 | AU92: =AT92*$H92 -> 0 | AW92: =AV92*$H92 -> 0 | AX92: =SUM(AV92,AT92,AR92,AP92,AN92,AL92,AJ92,AH92,AF92,AD92,AB92,Z92,X92,V92,T92,R92,P92,N92,L92,J92) -> 0 | AY92: =SUM(AW92,AU92,AS92,AQ92,AO92,AM92,AK92,AI92,AG92,AE92,AC92,AA92,Y92,W92,U92,S92,Q92,O92,M92,K92) -> 0 | AZ92: =(F92+G92)-AX92 -> 0 | BA92: =I92-AY92 -> 0
B93: 5500400606 | C93: =IFERROR(IF(B93,VLOOKUP((AEO!$B$13&AEO!$C$13&B93&E93),MSRV5!A:F,6,0),""),"N/A") -> 790 | D93: TRANSPORTE DE POSTE DE AT EM DISTÂNCIA SUPERIOR A 70KM | E93: =IF(B93,VLOOKUP(B93,MSRV5!B:D,3,0),"") -> KM | H93: =IFERROR(IF(B93,VLOOKUP((AEO!$B$13&AEO!$C$13&B93&E93),MSRV5!A:E,5,0),""),0) -> 20.37 | I93: =(F93+G93)*H93 -> 0 | K93: =J93*$H93 -> 0 | M93: =L93*$H93 -> 0 | O93: =N93*$H93 -> 0 | Q93: =P93*$H93 -> 0 | S93: =R93*$H93 -> 0 | U93: =T93*$H93 -> 0 | W93: =V93*$H93 -> 0 | Y93: =X93*$H93 -> 0 | AA93: =Z93*$H93 -> 0 | AC93: =AB93*$H93 -> 0 | AE93: =AD93*$H93 -> 0 | AG93: =AF93*$H93 -> 0 | AI93: =AH93*$H93 -> 0 | AK93: =AJ93*$H93 -> 0 | AM93: =AL93*$H93 -> 0 | AO93: =AN93*$H93 -> 0 | AQ93: =AP93*$H93 -> 0 | AS93: =AR93*$H93 -> 0 | AU93: =AT93*$H93 -> 0 | AW93: =AV93*$H93 -> 0 | AX93: =SUM(AV93,AT93,AR93,AP93,AN93,AL93,AJ93,AH93,AF93,AD93,AB93,Z93,X93,V93,T93,R93,P93,N93,L93,J93) -> 0 | AY93: =SUM(AW93,AU93,AS93,AQ93,AO93,AM93,AK93,AI93,AG93,AE93,AC93,AA93,Y93,W93,U93,S93,Q93,O93,M93,K93) -> 0 | AZ93: =(F93+G93)-AX93 -> 0 | BA93: =I93-AY93 -> 0
B94: 5500400600 | C94: =IFERROR(IF(B94,VLOOKUP((AEO!$B$13&AEO!$C$13&B94&E94),MSRV5!A:F,6,0),""),"N/A") -> 800 | D94: TRANSPORTE DE EQUIPAMENTOS MENORES - LT | E94: =IF(B94,VLOOKUP(B94,MSRV5!B:D,3,0),"") -> KM | H94: =IFERROR(IF(B94,VLOOKUP((AEO!$B$13&AEO!$C$13&B94&E94),MSRV5!A:E,5,0),""),0) -> 3.13 | I94: =(F94+G94)*H94 -> 0 | K94: =J94*$H94 -> 0 | M94: =L94*$H94 -> 0 | O94: =N94*$H94 -> 0 | Q94: =P94*$H94 -> 0 | S94: =R94*$H94 -> 0 | U94: =T94*$H94 -> 0 | W94: =V94*$H94 -> 0 | Y94: =X94*$H94 -> 0 | AA94: =Z94*$H94 -> 0 | AC94: =AB94*$H94 -> 0 | AE94: =AD94*$H94 -> 0 | AG94: =AF94*$H94 -> 0 | AI94: =AH94*$H94 -> 0 | AK94: =AJ94*$H94 -> 0 | AM94: =AL94*$H94 -> 0 | AO94: =AN94*$H94 -> 0 | AQ94: =AP94*$H94 -> 0 | AS94: =AR94*$H94 -> 0 | AU94: =AT94*$H94 -> 0 | AW94: =AV94*$H94 -> 0 | AX94: =SUM(AV94,AT94,AR94,AP94,AN94,AL94,AJ94,AH94,AF94,AD94,AB94,Z94,X94,V94,T94,R94,P94,N94,L94,J94) -> 0 | AY94: =SUM(AW94,AU94,AS94,AQ94,AO94,AM94,AK94,AI94,AG94,AE94,AC94,AA94,Y94,W94,U94,S94,Q94,O94,M94,K94) -> 0 | AZ94: =(F94+G94)-AX94 -> 0 | BA94: =I94-AY94 -> 0
B95: 5056000068 | C95: =IFERROR(IF(B95,VLOOKUP((AEO!$B$13&AEO!$C$13&B95&E95),MSRV5!A:F,6,0),""),"N/A") -> 810 | D95: S. FRETE/TRANSP. EQUIP./MAT. DMT>800KM. | E95: =IF(B95,VLOOKUP(B95,MSRV5!B:D,3,0),"") -> KM | H95: =IFERROR(IF(B95,VLOOKUP((AEO!$B$13&AEO!$C$13&B95&E95),MSRV5!A:E,5,0),""),0) -> 11.93 | I95: =(F95+G95)*H95 -> 0 | K95: =J95*$H95 -> 0 | M95: =L95*$H95 -> 0 | O95: =N95*$H95 -> 0 | Q95: =P95*$H95 -> 0 | S95: =R95*$H95 -> 0 | U95: =T95*$H95 -> 0 | W95: =V95*$H95 -> 0 | Y95: =X95*$H95 -> 0 | AA95: =Z95*$H95 -> 0 | AC95: =AB95*$H95 -> 0 | AE95: =AD95*$H95 -> 0 | AG95: =AF95*$H95 -> 0 | AI95: =AH95*$H95 -> 0 | AK95: =AJ95*$H95 -> 0 | AM95: =AL95*$H95 -> 0 | AO95: =AN95*$H95 -> 0 | AQ95: =AP95*$H95 -> 0 | AS95: =AR95*$H95 -> 0 | AU95: =AT95*$H95 -> 0 | AW95: =AV95*$H95 -> 0 | AX95: =SUM(AV95,AT95,AR95,AP95,AN95,AL95,AJ95,AH95,AF95,AD95,AB95,Z95,X95,V95,T95,R95,P95,N95,L95,J95) -> 0 | AY95: =SUM(AW95,AU95,AS95,AQ95,AO95,AM95,AK95,AI95,AG95,AE95,AC95,AA95,Y95,W95,U95,S95,Q95,O95,M95,K95) -> 0 | AZ95: =(F95+G95)-AX95 -> 0 | BA95: =I95-AY95 -> 0
B96: 5056000069 | C96: =IFERROR(IF(B96,VLOOKUP((AEO!$B$13&AEO!$C$13&B96&E96),MSRV5!A:F,6,0),""),"N/A") -> 820 | D96: S. FRETE/TRANS. EQ./MAT. 401<DMT<800KM. | E96: =IF(B96,VLOOKUP(B96,MSRV5!B:D,3,0),"") -> KM | H96: =IFERROR(IF(B96,VLOOKUP((AEO!$B$13&AEO!$C$13&B96&E96),MSRV5!A:E,5,0),""),0) -> 15.63 | I96: =(F96+G96)*H96 -> 0 | K96: =J96*$H96 -> 0 | M96: =L96*$H96 -> 0 | O96: =N96*$H96 -> 0 | Q96: =P96*$H96 -> 0 | S96: =R96*$H96 -> 0 | U96: =T96*$H96 -> 0 | W96: =V96*$H96 -> 0 | Y96: =X96*$H96 -> 0 | AA96: =Z96*$H96 -> 0 | AC96: =AB96*$H96 -> 0 | AE96: =AD96*$H96 -> 0 | AG96: =AF96*$H96 -> 0 | AI96: =AH96*$H96 -> 0 | AK96: =AJ96*$H96 -> 0 | AM96: =AL96*$H96 -> 0 | AO96: =AN96*$H96 -> 0 | AQ96: =AP96*$H96 -> 0 | AS96: =AR96*$H96 -> 0 | AU96: =AT96*$H96 -> 0 | AW96: =AV96*$H96 -> 0 | AX96: =SUM(AV96,AT96,AR96,AP96,AN96,AL96,AJ96,AH96,AF96,AD96,AB96,Z96,X96,V96,T96,R96,P96,N96,L96,J96) -> 0 | AY96: =SUM(AW96,AU96,AS96,AQ96,AO96,AM96,AK96,AI96,AG96,AE96,AC96,AA96,Y96,W96,U96,S96,Q96,O96,M96,K96) -> 0 | AZ96: =(F96+G96)-AX96 -> 0 | BA96: =I96-AY96 -> 0
B97: 5500300849 | C97: =IFERROR(IF(B97,VLOOKUP((AEO!$B$13&AEO!$C$13&B97&E97),MSRV5!A:F,6,0),""),"N/A") -> 830 | D97: S. FRETE/TRAN. EQ. /MAT. 201<DMT<400KM. | E97: =IF(B97,VLOOKUP(B97,MSRV5!B:D,3,0),"") -> KM | F97: 0 | H97: =IFERROR(IF(B97,VLOOKUP((AEO!$B$13&AEO!$C$13&B97&E97),MSRV5!A:E,5,0),""),0) -> 12.13 | I97: =(F97+G97)*H97 -> 0 | J97: 0 | K97: =J97*$H97 -> 0 | M97: =L97*$H97 -> 0 | O97: =N97*$H97 -> 0 | Q97: =P97*$H97 -> 0 | S97: =R97*$H97 -> 0 | U97: =T97*$H97 -> 0 | W97: =V97*$H97 -> 0 | Y97: =X97*$H97 -> 0 | AA97: =Z97*$H97 -> 0 | AC97: =AB97*$H97 -> 0 | AE97: =AD97*$H97 -> 0 | AG97: =AF97*$H97 -> 0 | AI97: =AH97*$H97 -> 0 | AK97: =AJ97*$H97 -> 0 | AM97: =AL97*$H97 -> 0 | AO97: =AN97*$H97 -> 0 | AQ97: =AP97*$H97 -> 0 | AS97: =AR97*$H97 -> 0 | AU97: =AT97*$H97 -> 0 | AW97: =AV97*$H97 -> 0 | AX97: =SUM(AV97,AT97,AR97,AP97,AN97,AL97,AJ97,AH97,AF97,AD97,AB97,Z97,X97,V97,T97,R97,P97,N97,L97,J97) -> 0 | AY97: =SUM(AW97,AU97,AS97,AQ97,AO97,AM97,AK97,AI97,AG97,AE97,AC97,AA97,Y97,W97,U97,S97,Q97,O97,M97,K97) -> 0 | AZ97: =(F97+G97)-AX97 -> 0 | BA97: =I97-AY97 -> 0
B98: 5056000071 | C98: =IFERROR(IF(B98,VLOOKUP((AEO!$B$13&AEO!$C$13&B98&E98),MSRV5!A:F,6,0),""),"N/A") -> 840 | D98: S. FRET./TRA. EQUIP./MAT. P/ OBR. CAPIT. | E98: =IF(B98,VLOOKUP(B98,MSRV5!B:D,3,0),"") -> UN | H98: =IFERROR(IF(B98,VLOOKUP((AEO!$B$13&AEO!$C$13&B98&E98),MSRV5!A:E,5,0),""),0) -> 2366.35 | I98: =(F98+G98)*H98 -> 0 | K98: =J98*$H98 -> 0 | M98: =L98*$H98 -> 0 | O98: =N98*$H98 -> 0 | Q98: =P98*$H98 -> 0 | S98: =R98*$H98 -> 0 | U98: =T98*$H98 -> 0 | W98: =V98*$H98 -> 0 | Y98: =X98*$H98 -> 0 | AA98: =Z98*$H98 -> 0 | AC98: =AB98*$H98 -> 0 | AE98: =AD98*$H98 -> 0 | AG98: =AF98*$H98 -> 0 | AI98: =AH98*$H98 -> 0 | AK98: =AJ98*$H98 -> 0 | AM98: =AL98*$H98 -> 0 | AO98: =AN98*$H98 -> 0 | AQ98: =AP98*$H98 -> 0 | AS98: =AR98*$H98 -> 0 | AU98: =AT98*$H98 -> 0 | AW98: =AV98*$H98 -> 0 | AX98: =SUM(AV98,AT98,AR98,AP98,AN98,AL98,AJ98,AH98,AF98,AD98,AB98,Z98,X98,V98,T98,R98,P98,N98,L98,J98) -> 0 | AY98: =SUM(AW98,AU98,AS98,AQ98,AO98,AM98,AK98,AI98,AG98,AE98,AC98,AA98,Y98,W98,U98,S98,Q98,O98,M98,K98) -> 0 | AZ98: =(F98+G98)-AX98 -> 0 | BA98: =I98-AY98 -> 0
B99: 5500300850 | C99: =IFERROR(IF(B99,VLOOKUP((AEO!$B$13&AEO!$C$13&B99&E99),MSRV5!A:F,6,0),""),"N/A") -> 850 | D99: S. FRETE/TRANSP. EQUIP./MAT. DMT<200KM. | E99: =IF(B99,VLOOKUP(B99,MSRV5!B:D,3,0),"") -> UN | H99: =IFERROR(IF(B99,VLOOKUP((AEO!$B$13&AEO!$C$13&B99&E99),MSRV5!A:E,5,0),""),0) -> 30.76 | I99: =(F99+G99)*H99 -> 0 | K99: =J99*$H99 -> 0 | M99: =L99*$H99 -> 0 | O99: =N99*$H99 -> 0 | Q99: =P99*$H99 -> 0 | S99: =R99*$H99 -> 0 | U99: =T99*$H99 -> 0 | W99: =V99*$H99 -> 0 | Y99: =X99*$H99 -> 0 | AA99: =Z99*$H99 -> 0 | AC99: =AB99*$H99 -> 0 | AE99: =AD99*$H99 -> 0 | AG99: =AF99*$H99 -> 0 | AI99: =AH99*$H99 -> 0 | AK99: =AJ99*$H99 -> 0 | AM99: =AL99*$H99 -> 0 | AO99: =AN99*$H99 -> 0 | AQ99: =AP99*$H99 -> 0 | AS99: =AR99*$H99 -> 0 | AU99: =AT99*$H99 -> 0 | AW99: =AV99*$H99 -> 0 | AX99: =SUM(AV99,AT99,AR99,AP99,AN99,AL99,AJ99,AH99,AF99,AD99,AB99,Z99,X99,V99,T99,R99,P99,N99,L99,J99) -> 0 | AY99: =SUM(AW99,AU99,AS99,AQ99,AO99,AM99,AK99,AI99,AG99,AE99,AC99,AA99,Y99,W99,U99,S99,Q99,O99,M99,K99) -> 0 | AZ99: =(F99+G99)-AX99 -> 0 | BA99: =I99-AY99 -> 0
B100: 5500400583 | C100: =IFERROR(IF(B100,VLOOKUP((AEO!$B$13&AEO!$C$13&B100&E100),MSRV5!A:F,6,0),""),"N/A") -> 860 | D100: TRANSP. DE EQUIPAM. E/OU MATERIAIS - SE | E100: =IF(B100,VLOOKUP(B100,MSRV5!B:D,3,0),"") -> KM | H100: =IFERROR(IF(B100,VLOOKUP((AEO!$B$13&AEO!$C$13&B100&E100),MSRV5!A:E,5,0),""),0) -> 9.46 | I100: =(F100+G100)*H100 -> 0 | K100: =J100*$H100 -> 0 | M100: =L100*$H100 -> 0 | O100: =N100*$H100 -> 0 | Q100: =P100*$H100 -> 0 | S100: =R100*$H100 -> 0 | U100: =T100*$H100 -> 0 | W100: =V100*$H100 -> 0 | Y100: =X100*$H100 -> 0 | AA100: =Z100*$H100 -> 0 | AC100: =AB100*$H100 -> 0 | AE100: =AD100*$H100 -> 0 | AG100: =AF100*$H100 -> 0 | AI100: =AH100*$H100 -> 0 | AK100: =AJ100*$H100 -> 0 | AM100: =AL100*$H100 -> 0 | AO100: =AN100*$H100 -> 0 | AQ100: =AP100*$H100 -> 0 | AS100: =AR100*$H100 -> 0 | AU100: =AT100*$H100 -> 0 | AW100: =AV100*$H100 -> 0 | AX100: =SUM(AV100,AT100,AR100,AP100,AN100,AL100,AJ100,AH100,AF100,AD100,AB100,Z100,X100,V100,T100,R100,P100,N100,L100,J100) -> 0 | AY100: =SUM(AW100,AU100,AS100,AQ100,AO100,AM100,AK100,AI100,AG100,AE100,AC100,AA100,Y100,W100,U100,S100,Q100,O100,M100,K100) -> 0 | AZ100: =(F100+G100)-AX100 -> 0 | BA100: =I100-AY100 -> 0
C101: =IFERROR(IF(B101,VLOOKUP((AEO!$B$13&AEO!$C$13&B101&E101),MSRV5!A:F,6,0),""),"N/A") | D101: CENTRO MODULAR DE INFRA-ESTRUTURA GERAL - OBRAS CIVIS (FATOR "C") | E101: =IF(B101,VLOOKUP(B101,MSRV5!B:D,3,0),"") | H101: =IFERROR(IF(B101,VLOOKUP((AEO!$B$13&AEO!$C$13&B101&E101),MSRV5!A:E,5,0),""),0) | I101: =SUBTOTAL(9,I102:I482) -> 0 | K101: =SUBTOTAL(9,K102:K482) -> 0 | M101: =SUBTOTAL(9,M102:M482) -> 0 | O101: =SUBTOTAL(9,O102:O482) -> 0 | Q101: =SUBTOTAL(9,Q102:Q482) -> 0 | S101: =SUBTOTAL(9,S102:S482) -> 0 | U101: =SUBTOTAL(9,U102:U482) -> 0 | W101: =SUBTOTAL(9,W102:W482) -> 0 | Y101: =SUBTOTAL(9,Y102:Y482) -> 0 | AA101: =SUBTOTAL(9,AA102:AA482) -> 0 | AC101: =SUBTOTAL(9,AC102:AC482) -> 0 | AE101: =SUBTOTAL(9,AE102:AE482) -> 0 | AG101: =SUBTOTAL(9,AG102:AG482) -> 0 | AI101: =SUBTOTAL(9,AI102:AI482) -> 0 | AK101: =SUBTOTAL(9,AK102:AK482) -> 0 | AM101: =SUBTOTAL(9,AM102:AM482) -> 0 | AO101: =SUBTOTAL(9,AO102:AO482) -> 0 | AQ101: =SUBTOTAL(9,AQ102:AQ482) -> 0 | AS101: =SUBTOTAL(9,AS102:AS482) -> 0 | AU101: =SUBTOTAL(9,AU102:AU482) -> 0 | AW101: =SUBTOTAL(9,AW102:AW482) -> 0 | AY101: =SUBTOTAL(9,AY102:AY482) -> 0 | BA101: =SUBTOTAL(9,BA102:BA482) -> 0
B102: 5057100003 | C102: =IFERROR(IF(B102,VLOOKUP((AEO!$B$13&AEO!$C$13&B102&E102),MSRV5!A:F,6,0),""),"N/A") -> 870 | D102: EXECUTAR LEVANTAMENTO PLANIALTIMETRICO | E102: =IF(B102,VLOOKUP(B102,MSRV5!B:D,3,0),"") -> M2 | H102: =IFERROR(IF(B102,VLOOKUP((AEO!$B$13&AEO!$C$13&B102&E102),MSRV5!A:E,5,0),""),0) -> 3.15 | I102: =(F102+G102)*H102 -> 0 | K102: =J102*$H102 -> 0 | M102: =L102*$H102 -> 0 | O102: =N102*$H102 -> 0 | Q102: =P102*$H102 -> 0 | S102: =R102*$H102 -> 0 | U102: =T102*$H102 -> 0 | W102: =V102*$H102 -> 0 | Y102: =X102*$H102 -> 0 | AA102: =Z102*$H102 -> 0 | AC102: =AB102*$H102 -> 0 | AE102: =AD102*$H102 -> 0 | AG102: =AF102*$H102 -> 0 | AI102: =AH102*$H102 -> 0 | AK102: =AJ102*$H102 -> 0 | AM102: =AL102*$H102 -> 0 | AO102: =AN102*$H102 -> 0 | AQ102: =AP102*$H102 -> 0 | AS102: =AR102*$H102 -> 0 | AU102: =AT102*$H102 -> 0 | AW102: =AV102*$H102 -> 0 | AX102: =SUM(AV102,AT102,AR102,AP102,AN102,AL102,AJ102,AH102,AF102,AD102,AB102,Z102,X102,V102,T102,R102,P102,N102,L102,J102) -> 0 | AY102: =SUM(AW102,AU102,AS102,AQ102,AO102,AM102,AK102,AI102,AG102,AE102,AC102,AA102,Y102,W102,U102,S102,Q102,O102,M102,K102) -> 0 | AZ102: =(F102+G102)-AX102 -> 0 | BA102: =I102-AY102 -> 0
B103: 5500300115 | C103: =IFERROR(IF(B103,VLOOKUP((AEO!$B$13&AEO!$C$13&B103&E103),MSRV5!A:F,6,0),""),"N/A") -> 880 | D103: LIMPEZA DO TERRENO / REMOÇÃO | E103: =IF(B103,VLOOKUP(B103,MSRV5!B:D,3,0),"") -> M3 | H103: =IFERROR(IF(B103,VLOOKUP((AEO!$B$13&AEO!$C$13&B103&E103),MSRV5!A:E,5,0),""),0) -> 163.69 | I103: =(F103+G103)*H103 -> 0 | K103: =J103*$H103 -> 0 | M103: =L103*$H103 -> 0 | O103: =N103*$H103 -> 0 | Q103: =P103*$H103 -> 0 | S103: =R103*$H103 -> 0 | U103: =T103*$H103 -> 0 | W103: =V103*$H103 -> 0 | Y103: =X103*$H103 -> 0 | AA103: =Z103*$H103 -> 0 | AC103: =AB103*$H103 -> 0 | AE103: =AD103*$H103 -> 0 | AG103: =AF103*$H103 -> 0 | AI103: =AH103*$H103 -> 0 | AK103: =AJ103*$H103 -> 0 | AM103: =AL103*$H103 -> 0 | AO103: =AN103*$H103 -> 0 | AQ103: =AP103*$H103 -> 0 | AS103: =AR103*$H103 -> 0 | AU103: =AT103*$H103 -> 0 | AW103: =AV103*$H103 -> 0 | AX103: =SUM(AV103,AT103,AR103,AP103,AN103,AL103,AJ103,AH103,AF103,AD103,AB103,Z103,X103,V103,T103,R103,P103,N103,L103,J103) -> 0 | AY103: =SUM(AW103,AU103,AS103,AQ103,AO103,AM103,AK103,AI103,AG103,AE103,AC103,AA103,Y103,W103,U103,S103,Q103,O103,M103,K103) -> 0 | AZ103: =(F103+G103)-AX103 -> 0 | BA103: =I103-AY103 -> 0
B104: 5050100016 | C104: =IFERROR(IF(B104,VLOOKUP((AEO!$B$13&AEO!$C$13&B104&E104),MSRV5!A:F,6,0),""),"N/A") -> 890 | D104: EXECUTAR LIMPEZA MANUAL DE TERRENO | E104: =IF(B104,VLOOKUP(B104,MSRV5!B:D,3,0),"") -> M2 | H104: =IFERROR(IF(B104,VLOOKUP((AEO!$B$13&AEO!$C$13&B104&E104),MSRV5!A:E,5,0),""),0) -> 6.43 | I104: =(F104+G104)*H104 -> 0 | K104: =J104*$H104 -> 0 | M104: =L104*$H104 -> 0 | O104: =N104*$H104 -> 0 | Q104: =P104*$H104 -> 0 | S104: =R104*$H104 -> 0 | U104: =T104*$H104 -> 0 | W104: =V104*$H104 -> 0 | Y104: =X104*$H104 -> 0 | AA104: =Z104*$H104 -> 0 | AC104: =AB104*$H104 -> 0 | AE104: =AD104*$H104 -> 0 | AG104: =AF104*$H104 -> 0 | AI104: =AH104*$H104 -> 0 | AK104: =AJ104*$H104 -> 0 | AM104: =AL104*$H104 -> 0 | AO104: =AN104*$H104 -> 0 | AQ104: =AP104*$H104 -> 0 | AS104: =AR104*$H104 -> 0 | AU104: =AT104*$H104 -> 0 | AW104: =AV104*$H104 -> 0 | AX104: =SUM(AV104,AT104,AR104,AP104,AN104,AL104,AJ104,AH104,AF104,AD104,AB104,Z104,X104,V104,T104,R104,P104,N104,L104,J104) -> 0 | AY104: =SUM(AW104,AU104,AS104,AQ104,AO104,AM104,AK104,AI104,AG104,AE104,AC104,AA104,Y104,W104,U104,S104,Q104,O104,M104,K104) -> 0 | AZ104: =(F104+G104)-AX104 -> 0 | BA104: =I104-AY104 -> 0
B105: 5050100017 | C105: =IFERROR(IF(B105,VLOOKUP((AEO!$B$13&AEO!$C$13&B105&E105),MSRV5!A:F,6,0),""),"N/A") -> 900 | D105: EXECUTAR LIMPEZA MECANIZADA DE TERRENO | E105: =IF(B105,VLOOKUP(B105,MSRV5!B:D,3,0),"") -> M2 | H105: =IFERROR(IF(B105,VLOOKUP((AEO!$B$13&AEO!$C$13&B105&E105),MSRV5!A:E,5,0),""),0) -> 8.44 | I105: =(F105+G105)*H105 -> 0 | K105: =J105*$H105 -> 0 | M105: =L105*$H105 -> 0 | O105: =N105*$H105 -> 0 | Q105: =P105*$H105 -> 0 | S105: =R105*$H105 -> 0 | U105: =T105*$H105 -> 0 | W105: =V105*$H105 -> 0 | Y105: =X105*$H105 -> 0 | AA105: =Z105*$H105 -> 0 | AC105: =AB105*$H105 -> 0 | AE105: =AD105*$H105 -> 0 | AG105: =AF105*$H105 -> 0 | AI105: =AH105*$H105 -> 0 | AK105: =AJ105*$H105 -> 0 | AM105: =AL105*$H105 -> 0 | AO105: =AN105*$H105 -> 0 | AQ105: =AP105*$H105 -> 0 | AS105: =AR105*$H105 -> 0 | AU105: =AT105*$H105 -> 0 | AW105: =AV105*$H105 -> 0 | AX105: =SUM(AV105,AT105,AR105,AP105,AN105,AL105,AJ105,AH105,AF105,AD105,AB105,Z105,X105,V105,T105,R105,P105,N105,L105,J105) -> 0 | AY105: =SUM(AW105,AU105,AS105,AQ105,AO105,AM105,AK105,AI105,AG105,AE105,AC105,AA105,Y105,W105,U105,S105,Q105,O105,M105,K105) -> 0 | AZ105: =(F105+G105)-AX105 -> 0 | BA105: =I105-AY105 -> 0
B106: 5050100018 | C106: =IFERROR(IF(B106,VLOOKUP((AEO!$B$13&AEO!$C$13&B106&E106),MSRV5!A:F,6,0),""),"N/A") -> 910 | D106: EXECUTAR LOCAÇÃO DE OBRA DE SUBESTAÇÃO | E106: =IF(B106,VLOOKUP(B106,MSRV5!B:D,3,0),"") -> M2 | H106: =IFERROR(IF(B106,VLOOKUP((AEO!$B$13&AEO!$C$13&B106&E106),MSRV5!A:E,5,0),""),0) -> 22.4 | I106: =(F106+G106)*H106 -> 0 | K106: =J106*$H106 -> 0 | M106: =L106*$H106 -> 0 | O106: =N106*$H106 -> 0 | Q106: =P106*$H106 -> 0 | S106: =R106*$H106 -> 0 | U106: =T106*$H106 -> 0 | W106: =V106*$H106 -> 0 | Y106: =X106*$H106 -> 0 | AA106: =Z106*$H106 -> 0 | AC106: =AB106*$H106 -> 0 | AE106: =AD106*$H106 -> 0 | AG106: =AF106*$H106 -> 0 | AI106: =AH106*$H106 -> 0 | AK106: =AJ106*$H106 -> 0 | AM106: =AL106*$H106 -> 0 | AO106: =AN106*$H106 -> 0 | AQ106: =AP106*$H106 -> 0 | AS106: =AR106*$H106 -> 0 | AU106: =AT106*$H106 -> 0 | AW106: =AV106*$H106 -> 0 | AX106: =SUM(AV106,AT106,AR106,AP106,AN106,AL106,AJ106,AH106,AF106,AD106,AB106,Z106,X106,V106,T106,R106,P106,N106,L106,J106) -> 0 | AY106: =SUM(AW106,AU106,AS106,AQ106,AO106,AM106,AK106,AI106,AG106,AE106,AC106,AA106,Y106,W106,U106,S106,Q106,O106,M106,K106) -> 0 | AZ106: =(F106+G106)-AX106 -> 0 | BA106: =I106-AY106 -> 0
B107: 5500200404 | C107: =IFERROR(IF(B107,VLOOKUP((AEO!$B$13&AEO!$C$13&B107&E107),MSRV5!A:F,6,0),""),"N/A") -> 920 | D107: ESCAV. C/ MARTELETE ROMPEDOR EM ROCHA | E107: =IF(B107,VLOOKUP(B107,MSRV5!B:D,3,0),"") -> M3 | H107: =IFERROR(IF(B107,VLOOKUP((AEO!$B$13&AEO!$C$13&B107&E107),MSRV5!A:E,5,0),""),0) -> 568.77 | I107: =(F107+G107)*H107 -> 0 | K107: =J107*$H107 -> 0 | M107: =L107*$H107 -> 0 | O107: =N107*$H107 -> 0 | Q107: =P107*$H107 -> 0 | S107: =R107*$H107 -> 0 | U107: =T107*$H107 -> 0 | W107: =V107*$H107 -> 0 | Y107: =X107*$H107 -> 0 | AA107: =Z107*$H107 -> 0 | AC107: =AB107*$H107 -> 0 | AE107: =AD107*$H107 -> 0 | AG107: =AF107*$H107 -> 0 | AI107: =AH107*$H107 -> 0 | AK107: =AJ107*$H107 -> 0 | AM107: =AL107*$H107 -> 0 | AO107: =AN107*$H107 -> 0 | AQ107: =AP107*$H107 -> 0 | AS107: =AR107*$H107 -> 0 | AU107: =AT107*$H107 -> 0 | AW107: =AV107*$H107 -> 0 | AX107: =SUM(AV107,AT107,AR107,AP107,AN107,AL107,AJ107,AH107,AF107,AD107,AB107,Z107,X107,V107,T107,R107,P107,N107,L107,J107) -> 0 | AY107: =SUM(AW107,AU107,AS107,AQ107,AO107,AM107,AK107,AI107,AG107,AE107,AC107,AA107,Y107,W107,U107,S107,Q107,O107,M107,K107) -> 0 | AZ107: =(F107+G107)-AX107 -> 0 | BA107: =I107-AY107 -> 0
B108: 5500000903 | C108: =IFERROR(IF(B108,VLOOKUP((AEO!$B$13&AEO!$C$13&B108&E108),MSRV5!A:F,6,0),""),"N/A") -> 930 | D108: AQUISIÇÃO DE CASCALHO PARA ATERRO | E108: =IF(B108,VLOOKUP(B108,MSRV5!B:D,3,0),"") -> M3 | H108: =IFERROR(IF(B108,VLOOKUP((AEO!$B$13&AEO!$C$13&B108&E108),MSRV5!A:E,5,0),""),0) -> 213.72 | I108: =(F108+G108)*H108 -> 0 | K108: =J108*$H108 -> 0 | M108: =L108*$H108 -> 0 | O108: =N108*$H108 -> 0 | Q108: =P108*$H108 -> 0 | S108: =R108*$H108 -> 0 | U108: =T108*$H108 -> 0 | W108: =V108*$H108 -> 0 | Y108: =X108*$H108 -> 0 | AA108: =Z108*$H108 -> 0 | AC108: =AB108*$H108 -> 0 | AE108: =AD108*$H108 -> 0 | AG108: =AF108*$H108 -> 0 | AI108: =AH108*$H108 -> 0 | AK108: =AJ108*$H108 -> 0 | AM108: =AL108*$H108 -> 0 | AO108: =AN108*$H108 -> 0 | AQ108: =AP108*$H108 -> 0 | AS108: =AR108*$H108 -> 0 | AU108: =AT108*$H108 -> 0 | AW108: =AV108*$H108 -> 0 | AX108: =SUM(AV108,AT108,AR108,AP108,AN108,AL108,AJ108,AH108,AF108,AD108,AB108,Z108,X108,V108,T108,R108,P108,N108,L108,J108) -> 0 | AY108: =SUM(AW108,AU108,AS108,AQ108,AO108,AM108,AK108,AI108,AG108,AE108,AC108,AA108,Y108,W108,U108,S108,Q108,O108,M108,K108) -> 0 | AZ108: =(F108+G108)-AX108 -> 0 | BA108: =I108-AY108 -> 0
B109: 5500200407 | C109: =IFERROR(IF(B109,VLOOKUP((AEO!$B$13&AEO!$C$13&B109&E109),MSRV5!A:F,6,0),""),"N/A") -> 940 | D109: ESCAVAÇÃO DE MATERIAL DE 1ª CATEGORIA | E109: =IF(B109,VLOOKUP(B109,MSRV5!B:D,3,0),"") -> M3 | H109: =IFERROR(IF(B109,VLOOKUP((AEO!$B$13&AEO!$C$13&B109&E109),MSRV5!A:E,5,0),""),0) -> 10.91 | I109: =(F109+G109)*H109 -> 0 | K109: =J109*$H109 -> 0 | M109: =L109*$H109 -> 0 | O109: =N109*$H109 -> 0 | Q109: =P109*$H109 -> 0 | S109: =R109*$H109 -> 0 | U109: =T109*$H109 -> 0 | W109: =V109*$H109 -> 0 | Y109: =X109*$H109 -> 0 | AA109: =Z109*$H109 -> 0 | AC109: =AB109*$H109 -> 0 | AE109: =AD109*$H109 -> 0 | AG109: =AF109*$H109 -> 0 | AI109: =AH109*$H109 -> 0 | AK109: =AJ109*$H109 -> 0 | AM109: =AL109*$H109 -> 0 | AO109: =AN109*$H109 -> 0 | AQ109: =AP109*$H109 -> 0 | AS109: =AR109*$H109 -> 0 | AU109: =AT109*$H109 -> 0 | AW109: =AV109*$H109 -> 0 | AX109: =SUM(AV109,AT109,AR109,AP109,AN109,AL109,AJ109,AH109,AF109,AD109,AB109,Z109,X109,V109,T109,R109,P109,N109,L109,J109) -> 0 | AY109: =SUM(AW109,AU109,AS109,AQ109,AO109,AM109,AK109,AI109,AG109,AE109,AC109,AA109,Y109,W109,U109,S109,Q109,O109,M109,K109) -> 0 | AZ109: =(F109+G109)-AX109 -> 0 | BA109: =I109-AY109 -> 0
B110: 5050100013 | C110: =IFERROR(IF(B110,VLOOKUP((AEO!$B$13&AEO!$C$13&B110&E110),MSRV5!A:F,6,0),""),"N/A") -> 950 | D110: EXECUTAR CORTE MECANIZADO (1ª CATEGORIA) | E110: =IF(B110,VLOOKUP(B110,MSRV5!B:D,3,0),"") -> M3 | H110: =IFERROR(IF(B110,VLOOKUP((AEO!$B$13&AEO!$C$13&B110&E110),MSRV5!A:E,5,0),""),0) -> 141.79 | I110: =(F110+G110)*H110 -> 0 | K110: =J110*$H110 -> 0 | M110: =L110*$H110 -> 0 | O110: =N110*$H110 -> 0 | Q110: =P110*$H110 -> 0 | S110: =R110*$H110 -> 0 | U110: =T110*$H110 -> 0 | W110: =V110*$H110 -> 0 | Y110: =X110*$H110 -> 0 | AA110: =Z110*$H110 -> 0 | AC110: =AB110*$H110 -> 0 | AE110: =AD110*$H110 -> 0 | AG110: =AF110*$H110 -> 0 | AI110: =AH110*$H110 -> 0 | AK110: =AJ110*$H110 -> 0 | AM110: =AL110*$H110 -> 0 | AO110: =AN110*$H110 -> 0 | AQ110: =AP110*$H110 -> 0 | AS110: =AR110*$H110 -> 0 | AU110: =AT110*$H110 -> 0 | AW110: =AV110*$H110 -> 0 | AX110: =SUM(AV110,AT110,AR110,AP110,AN110,AL110,AJ110,AH110,AF110,AD110,AB110,Z110,X110,V110,T110,R110,P110,N110,L110,J110) -> 0 | AY110: =SUM(AW110,AU110,AS110,AQ110,AO110,AM110,AK110,AI110,AG110,AE110,AC110,AA110,Y110,W110,U110,S110,Q110,O110,M110,K110) -> 0 | AZ110: =(F110+G110)-AX110 -> 0 | BA110: =I110-AY110 -> 0
B111: 5500200408 | C111: =IFERROR(IF(B111,VLOOKUP((AEO!$B$13&AEO!$C$13&B111&E111),MSRV5!A:F,6,0),""),"N/A") -> 960 | D111: ESCAVAÇÃO DE MATERIAL DE 2ª CATEGORIA | E111: =IF(B111,VLOOKUP(B111,MSRV5!B:D,3,0),"") -> M3 | H111: =IFERROR(IF(B111,VLOOKUP((AEO!$B$13&AEO!$C$13&B111&E111),MSRV5!A:E,5,0),""),0) -> 18.19 | I111: =(F111+G111)*H111 -> 0 | K111: =J111*$H111 -> 0 | M111: =L111*$H111 -> 0 | O111: =N111*$H111 -> 0 | Q111: =P111*$H111 -> 0 | S111: =R111*$H111 -> 0 | U111: =T111*$H111 -> 0 | W111: =V111*$H111 -> 0 | Y111: =X111*$H111 -> 0 | AA111: =Z111*$H111 -> 0 | AC111: =AB111*$H111 -> 0 | AE111: =AD111*$H111 -> 0 | AG111: =AF111*$H111 -> 0 | AI111: =AH111*$H111 -> 0 | AK111: =AJ111*$H111 -> 0 | AM111: =AL111*$H111 -> 0 | AO111: =AN111*$H111 -> 0 | AQ111: =AP111*$H111 -> 0 | AS111: =AR111*$H111 -> 0 | AU111: =AT111*$H111 -> 0 | AW111: =AV111*$H111 -> 0 | AX111: =SUM(AV111,AT111,AR111,AP111,AN111,AL111,AJ111,AH111,AF111,AD111,AB111,Z111,X111,V111,T111,R111,P111,N111,L111,J111) -> 0 | AY111: =SUM(AW111,AU111,AS111,AQ111,AO111,AM111,AK111,AI111,AG111,AE111,AC111,AA111,Y111,W111,U111,S111,Q111,O111,M111,K111) -> 0 | AZ111: =(F111+G111)-AX111 -> 0 | BA111: =I111-AY111 -> 0
B112: 5050100014 | C112: =IFERROR(IF(B112,VLOOKUP((AEO!$B$13&AEO!$C$13&B112&E112),MSRV5!A:F,6,0),""),"N/A") -> 970 | D112: EXECUTAR CORTE MECANIZADO (3ª CATEGORIA) | E112: =IF(B112,VLOOKUP(B112,MSRV5!B:D,3,0),"") -> M3 | H112: =IFERROR(IF(B112,VLOOKUP((AEO!$B$13&AEO!$C$13&B112&E112),MSRV5!A:E,5,0),""),0) -> 77.61 | I112: =(F112+G112)*H112 -> 0 | K112: =J112*$H112 -> 0 | M112: =L112*$H112 -> 0 | O112: =N112*$H112 -> 0 | Q112: =P112*$H112 -> 0 | S112: =R112*$H112 -> 0 | U112: =T112*$H112 -> 0 | W112: =V112*$H112 -> 0 | Y112: =X112*$H112 -> 0 | AA112: =Z112*$H112 -> 0 | AC112: =AB112*$H112 -> 0 | AE112: =AD112*$H112 -> 0 | AG112: =AF112*$H112 -> 0 | AI112: =AH112*$H112 -> 0 | AK112: =AJ112*$H112 -> 0 | AM112: =AL112*$H112 -> 0 | AO112: =AN112*$H112 -> 0 | AQ112: =AP112*$H112 -> 0 | AS112: =AR112*$H112 -> 0 | AU112: =AT112*$H112 -> 0 | AW112: =AV112*$H112 -> 0 | AX112: =SUM(AV112,AT112,AR112,AP112,AN112,AL112,AJ112,AH112,AF112,AD112,AB112,Z112,X112,V112,T112,R112,P112,N112,L112,J112) -> 0 | AY112: =SUM(AW112,AU112,AS112,AQ112,AO112,AM112,AK112,AI112,AG112,AE112,AC112,AA112,Y112,W112,U112,S112,Q112,O112,M112,K112) -> 0 | AZ112: =(F112+G112)-AX112 -> 0 | BA112: =I112-AY112 -> 0
B113: 5050100011 | C113: =IFERROR(IF(B113,VLOOKUP((AEO!$B$13&AEO!$C$13&B113&E113),MSRV5!A:F,6,0),""),"N/A") -> 980 | D113: EXECUTAR ATERRO MECANIZADO (JAZIDA) | E113: =IF(B113,VLOOKUP(B113,MSRV5!B:D,3,0),"") -> M3 | H113: =IFERROR(IF(B113,VLOOKUP((AEO!$B$13&AEO!$C$13&B113&E113),MSRV5!A:E,5,0),""),0) -> 248.16 | I113: =(F113+G113)*H113 -> 0 | K113: =J113*$H113 -> 0 | M113: =L113*$H113 -> 0 | O113: =N113*$H113 -> 0 | Q113: =P113*$H113 -> 0 | S113: =R113*$H113 -> 0 | U113: =T113*$H113 -> 0 | W113: =V113*$H113 -> 0 | Y113: =X113*$H113 -> 0 | AA113: =Z113*$H113 -> 0 | AC113: =AB113*$H113 -> 0 | AE113: =AD113*$H113 -> 0 | AG113: =AF113*$H113 -> 0 | AI113: =AH113*$H113 -> 0 | AK113: =AJ113*$H113 -> 0 | AM113: =AL113*$H113 -> 0 | AO113: =AN113*$H113 -> 0 | AQ113: =AP113*$H113 -> 0 | AS113: =AR113*$H113 -> 0 | AU113: =AT113*$H113 -> 0 | AW113: =AV113*$H113 -> 0 | AX113: =SUM(AV113,AT113,AR113,AP113,AN113,AL113,AJ113,AH113,AF113,AD113,AB113,Z113,X113,V113,T113,R113,P113,N113,L113,J113) -> 0 | AY113: =SUM(AW113,AU113,AS113,AQ113,AO113,AM113,AK113,AI113,AG113,AE113,AC113,AA113,Y113,W113,U113,S113,Q113,O113,M113,K113) -> 0 | AZ113: =(F113+G113)-AX113 -> 0 | BA113: =I113-AY113 -> 0
... B482: 5500300455 | C482: =IFERROR(IF(B482,VLOOKUP((AEO!$B$13&AEO!$C$13&B482&E482),MSRV5!A:F,6,0),""),"N/A") -> 4400 | D482: PINTURA MURO COM NOME DA SUBESTAÇÃO (INCLUINDO REBOCO) | E482: =IF(B482,VLOOKUP(B482,MSRV5!B:D,3,0),"") -> M2 | H482: =IFERROR(IF(B482,VLOOKUP((AEO!$B$13&AEO!$C$13&B482&E482),MSRV5!A:E,5,0),""),0) -> 545.71 | I482: =(F482+G482)*H482 -> 0 | K482: =J482*$H482 -> 0 | M482: =L482*$H482 -> 0 | O482: =N482*$H482 -> 0 | Q482: =P482*$H482 -> 0 | S482: =R482*$H482 -> 0 | U482: =T482*$H482 -> 0 | W482: =V482*$H482 -> 0 | Y482: =X482*$H482 -> 0 | AA482: =Z482*$H482 -> 0 | AC482: =AB482*$H482 -> 0 | AE482: =AD482*$H482 -> 0 | AG482: =AF482*$H482 -> 0 | AI482: =AH482*$H482 -> 0 | AK482: =AJ482*$H482 -> 0 | AM482: =AL482*$H482 -> 0 | AO482: =AN482*$H482 -> 0 | AQ482: =AP482*$H482 -> 0 | AS482: =AR482*$H482 -> 0 | AU482: =AT482*$H482 -> 0 | AW482: =AV482*$H482 -> 0 | AX482: =SUM(AV482,AT482,AR482,AP482,AN482,AL482,AJ482,AH482,AF482,AD482,AB482,Z482,X482,V482,T482,R482,P482,N482,L482,J482) -> 0 | AY482: =SUM(AW482,AU482,AS482,AQ482,AO482,AM482,AK482,AI482,AG482,AE482,AC482,AA482,Y482,W482,U482,S482,Q482,O482,M482,K482) -> 0 | AZ482: =(F482+G482)-AX482 -> 0 | BA482: =I482-AY482 -> 0
C483: =IFERROR(IF(B483,VLOOKUP((AEO!$B$13&AEO!$C$13&B483&E483),MSRV5!A:F,6,0),""),"N/A") | D483: SERVIÇOS ELETROMECÂNICOS (FATOR "EM") | E483: =IF(B483,VLOOKUP(B483,MSRV5!B:D,3,0),"") | H483: =IFERROR(IF(B483,VLOOKUP((AEO!$B$13&AEO!$C$13&B483&E483),MSRV5!A:E,5,0),""),0) | I483: =SUBTOTAL(9,I484:I627) -> 0 | K483: =SUBTOTAL(9,K484:K627) -> 0 | M483: =SUBTOTAL(9,M484:M627) -> 0 | O483: =SUBTOTAL(9,O484:O627) -> 0 | Q483: =SUBTOTAL(9,Q484:Q627) -> 0 | S483: =SUBTOTAL(9,S484:S627) -> 0 | U483: =SUBTOTAL(9,U484:U627) -> 0 | W483: =SUBTOTAL(9,W484:W627) -> 0 | Y483: =SUBTOTAL(9,Y484:Y627) -> 0 | AA483: =SUBTOTAL(9,AA484:AA627) -> 0 | AC483: =SUBTOTAL(9,AC484:AC627) -> 0 | AE483: =SUBTOTAL(9,AE484:AE627) -> 0 | AG483: =SUBTOTAL(9,AG484:AG627) -> 0 | AI483: =SUBTOTAL(9,AI484:AI627) -> 0 | AK483: =SUBTOTAL(9,AK484:AK627) -> 0 | AM483: =SUBTOTAL(9,AM484:AM627) -> 0 | AO483: =SUBTOTAL(9,AO484:AO627) -> 0 | AQ483: =SUBTOTAL(9,AQ484:AQ627) -> 0 | AS483: =SUBTOTAL(9,AS484:AS627) -> 0 | AU483: =SUBTOTAL(9,AU484:AU627) -> 0 | AW483: =SUBTOTAL(9,AW484:AW627) -> 0 | AY483: =SUBTOTAL(9,AY484:AY627) -> 0 | BA483: =SUBTOTAL(9,BA484:BA627) -> 0
B484: 5500300349 | C484: =IFERROR(IF(B484,VLOOKUP((AEO!$B$13&AEO!$C$13&B484&E484),MSRV5!A:F,6,0),""),"N/A") -> 4410 | D484: MONT. SUPORTE METÁLICO PARA MUFLAS 15 KV | E484: =IF(B484,VLOOKUP(B484,MSRV5!B:D,3,0),"") -> UN | H484: =IFERROR(IF(B484,VLOOKUP((AEO!$B$13&AEO!$C$13&B484&E484),MSRV5!A:E,5,0),""),0) -> 1100.01 | I484: =(F484+G484)*H484 -> 0 | K484: =J484*$H484 -> 0 | M484: =L484*$H484 -> 0 | O484: =N484*$H484 -> 0 | Q484: =P484*$H484 -> 0 | S484: =R484*$H484 -> 0 | U484: =T484*$H484 -> 0 | W484: =V484*$H484 -> 0 | Y484: =X484*$H484 -> 0 | AA484: =Z484*$H484 -> 0 | AC484: =AB484*$H484 -> 0 | AE484: =AD484*$H484 -> 0 | AG484: =AF484*$H484 -> 0 | AI484: =AH484*$H484 -> 0 | AK484: =AJ484*$H484 -> 0 | AM484: =AL484*$H484 -> 0 | AO484: =AN484*$H484 -> 0 | AQ484: =AP484*$H484 -> 0 | AS484: =AR484*$H484 -> 0 | AU484: =AT484*$H484 -> 0 | AW484: =AV484*$H484 -> 0 | AX484: =SUM(AV484,AT484,AR484,AP484,AN484,AL484,AJ484,AH484,AF484,AD484,AB484,Z484,X484,V484,T484,R484,P484,N484,L484,J484) -> 0 | AY484: =SUM(AW484,AU484,AS484,AQ484,AO484,AM484,AK484,AI484,AG484,AE484,AC484,AA484,Y484,W484,U484,S484,Q484,O484,M484,K484) -> 0 | AZ484: =(F484+G484)-AX484 -> 0 | BA484: =I484-AY484 -> 0
B485: 5500300350 | C485: =IFERROR(IF(B485,VLOOKUP((AEO!$B$13&AEO!$C$13&B485&E485),MSRV5!A:F,6,0),""),"N/A") -> 4420 | D485: MONT. SUPORTE METÁLICO PARA TC | E485: =IF(B485,VLOOKUP(B485,MSRV5!B:D,3,0),"") -> UN | H485: =IFERROR(IF(B485,VLOOKUP((AEO!$B$13&AEO!$C$13&B485&E485),MSRV5!A:E,5,0),""),0) -> 1100.01 | I485: =(F485+G485)*H485 -> 0 | K485: =J485*$H485 -> 0 | M485: =L485*$H485 -> 0 | O485: =N485*$H485 -> 0 | Q485: =P485*$H485 -> 0 | S485: =R485*$H485 -> 0 | U485: =T485*$H485 -> 0 | W485: =V485*$H485 -> 0 | Y485: =X485*$H485 -> 0 | AA485: =Z485*$H485 -> 0 | AC485: =AB485*$H485 -> 0 | AE485: =AD485*$H485 -> 0 | AG485: =AF485*$H485 -> 0 | AI485: =AH485*$H485 -> 0 | AK485: =AJ485*$H485 -> 0 | AM485: =AL485*$H485 -> 0 | AO485: =AN485*$H485 -> 0 | AQ485: =AP485*$H485 -> 0 | AS485: =AR485*$H485 -> 0 | AU485: =AT485*$H485 -> 0 | AW485: =AV485*$H485 -> 0 | AX485: =SUM(AV485,AT485,AR485,AP485,AN485,AL485,AJ485,AH485,AF485,AD485,AB485,Z485,X485,V485,T485,R485,P485,N485,L485,J485) -> 0 | AY485: =SUM(AW485,AU485,AS485,AQ485,AO485,AM485,AK485,AI485,AG485,AE485,AC485,AA485,Y485,W485,U485,S485,Q485,O485,M485,K485) -> 0 | AZ485: =(F485+G485)-AX485 -> 0 | BA485: =I485-AY485 -> 0
B486: 5500300045 | C486: =IFERROR(IF(B486,VLOOKUP((AEO!$B$13&AEO!$C$13&B486&E486),MSRV5!A:F,6,0),""),"N/A") -> 4430 | D486: MONT. POSTE DE CONCRETO, DE 14 A 23 M, | E486: =IF(B486,VLOOKUP(B486,MSRV5!B:D,3,0),"") -> UN | H486: =IFERROR(IF(B486,VLOOKUP((AEO!$B$13&AEO!$C$13&B486&E486),MSRV5!A:E,5,0),""),0) -> 7769.66 | I486: =(F486+G486)*H486 -> 0 | K486: =J486*$H486 -> 0 | M486: =L486*$H486 -> 0 | O486: =N486*$H486 -> 0 | Q486: =P486*$H486 -> 0 | S486: =R486*$H486 -> 0 | U486: =T486*$H486 -> 0 | W486: =V486*$H486 -> 0 | Y486: =X486*$H486 -> 0 | AA486: =Z486*$H486 -> 0 | AC486: =AB486*$H486 -> 0 | AE486: =AD486*$H486 -> 0 | AG486: =AF486*$H486 -> 0 | AI486: =AH486*$H486 -> 0 | AK486: =AJ486*$H486 -> 0 | AM486: =AL486*$H486 -> 0 | AO486: =AN486*$H486 -> 0 | AQ486: =AP486*$H486 -> 0 | AS486: =AR486*$H486 -> 0 | AU486: =AT486*$H486 -> 0 | AW486: =AV486*$H486 -> 0 | AX486: =SUM(AV486,AT486,AR486,AP486,AN486,AL486,AJ486,AH486,AF486,AD486,AB486,Z486,X486,V486,T486,R486,P486,N486,L486,J486) -> 0 | AY486: =SUM(AW486,AU486,AS486,AQ486,AO486,AM486,AK486,AI486,AG486,AE486,AC486,AA486,Y486,W486,U486,S486,Q486,O486,M486,K486) -> 0 | AZ486: =(F486+G486)-AX486 -> 0 | BA486: =I486-AY486 -> 0
B487: 5500300044 | C487: =IFERROR(IF(B487,VLOOKUP((AEO!$B$13&AEO!$C$13&B487&E487),MSRV5!A:F,6,0),""),"N/A") -> 4440 | D487: MONT. POSTE DE CONCRETO, DE 10 A 14 M, | E487: =IF(B487,VLOOKUP(B487,MSRV5!B:D,3,0),"") -> UN | H487: =IFERROR(IF(B487,VLOOKUP((AEO!$B$13&AEO!$C$13&B487&E487),MSRV5!A:E,5,0),""),0) -> 3501.19 | I487: =(F487+G487)*H487 -> 0 | K487: =J487*$H487 -> 0 | M487: =L487*$H487 -> 0 | O487: =N487*$H487 -> 0 | Q487: =P487*$H487 -> 0 | S487: =R487*$H487 -> 0 | U487: =T487*$H487 -> 0 | W487: =V487*$H487 -> 0 | Y487: =X487*$H487 -> 0 | AA487: =Z487*$H487 -> 0 | AC487: =AB487*$H487 -> 0 | AE487: =AD487*$H487 -> 0 | AG487: =AF487*$H487 -> 0 | AI487: =AH487*$H487 -> 0 | AK487: =AJ487*$H487 -> 0 | AM487: =AL487*$H487 -> 0 | AO487: =AN487*$H487 -> 0 | AQ487: =AP487*$H487 -> 0 | AS487: =AR487*$H487 -> 0 | AU487: =AT487*$H487 -> 0 | AW487: =AV487*$H487 -> 0 | AX487: =SUM(AV487,AT487,AR487,AP487,AN487,AL487,AJ487,AH487,AF487,AD487,AB487,Z487,X487,V487,T487,R487,P487,N487,L487,J487) -> 0 | AY487: =SUM(AW487,AU487,AS487,AQ487,AO487,AM487,AK487,AI487,AG487,AE487,AC487,AA487,Y487,W487,U487,S487,Q487,O487,M487,K487) -> 0 | AZ487: =(F487+G487)-AX487 -> 0 | BA487: =I487-AY487 -> 0
B488: 5500300358 | C488: =IFERROR(IF(B488,VLOOKUP((AEO!$B$13&AEO!$C$13&B488&E488),MSRV5!A:F,6,0),""),"N/A") -> 4450 | D488: MONT. COLUNA E VIGA METÁLICA TRELIÇADA, | E488: =IF(B488,VLOOKUP(B488,MSRV5!B:D,3,0),"") -> KG | H488: =IFERROR(IF(B488,VLOOKUP((AEO!$B$13&AEO!$C$13&B488&E488),MSRV5!A:E,5,0),""),0) -> 8.65 | I488: =(F488+G488)*H488 -> 0 | K488: =J488*$H488 -> 0 | M488: =L488*$H488 -> 0 | O488: =N488*$H488 -> 0 | Q488: =P488*$H488 -> 0 | S488: =R488*$H488 -> 0 | U488: =T488*$H488 -> 0 | W488: =V488*$H488 -> 0 | Y488: =X488*$H488 -> 0 | AA488: =Z488*$H488 -> 0 | AC488: =AB488*$H488 -> 0 | AE488: =AD488*$H488 -> 0 | AG488: =AF488*$H488 -> 0 | AI488: =AH488*$H488 -> 0 | AK488: =AJ488*$H488 -> 0 | AM488: =AL488*$H488 -> 0 | AO488: =AN488*$H488 -> 0 | AQ488: =AP488*$H488 -> 0 | AS488: =AR488*$H488 -> 0 | AU488: =AT488*$H488 -> 0 | AW488: =AV488*$H488 -> 0 | AX488: =SUM(AV488,AT488,AR488,AP488,AN488,AL488,AJ488,AH488,AF488,AD488,AB488,Z488,X488,V488,T488,R488,P488,N488,L488,J488) -> 0 | AY488: =SUM(AW488,AU488,AS488,AQ488,AO488,AM488,AK488,AI488,AG488,AE488,AC488,AA488,Y488,W488,U488,S488,Q488,O488,M488,K488) -> 0 | AZ488: =(F488+G488)-AX488 -> 0 | BA488: =I488-AY488 -> 0
B489: 5500300015 | C489: =IFERROR(IF(B489,VLOOKUP((AEO!$B$13&AEO!$C$13&B489&E489),MSRV5!A:F,6,0),""),"N/A") -> 4460 | D489: MONT. VIGA DE CONCRETO, DE 10 A 14 M TIPO "DT", | E489: =IF(B489,VLOOKUP(B489,MSRV5!B:D,3,0),"") -> UN | H489: =IFERROR(IF(B489,VLOOKUP((AEO!$B$13&AEO!$C$13&B489&E489),MSRV5!A:E,5,0),""),0) -> 3826.99 | I489: =(F489+G489)*H489 -> 0 | K489: =J489*$H489 -> 0 | M489: =L489*$H489 -> 0 | O489: =N489*$H489 -> 0 | Q489: =P489*$H489 -> 0 | S489: =R489*$H489 -> 0 | U489: =T489*$H489 -> 0 | W489: =V489*$H489 -> 0 | Y489: =X489*$H489 -> 0 | AA489: =Z489*$H489 -> 0 | AC489: =AB489*$H489 -> 0 | AE489: =AD489*$H489 -> 0 | AG489: =AF489*$H489 -> 0 | AI489: =AH489*$H489 -> 0 | AK489: =AJ489*$H489 -> 0 | AM489: =AL489*$H489 -> 0 | AO489: =AN489*$H489 -> 0 | AQ489: =AP489*$H489 -> 0 | AS489: =AR489*$H489 -> 0 | AU489: =AT489*$H489 -> 0 | AW489: =AV489*$H489 -> 0 | AX489: =SUM(AV489,AT489,AR489,AP489,AN489,AL489,AJ489,AH489,AF489,AD489,AB489,Z489,X489,V489,T489,R489,P489,N489,L489,J489) -> 0 | AY489: =SUM(AW489,AU489,AS489,AQ489,AO489,AM489,AK489,AI489,AG489,AE489,AC489,AA489,Y489,W489,U489,S489,Q489,O489,M489,K489) -> 0 | AZ489: =(F489+G489)-AX489 -> 0 | BA489: =I489-AY489 -> 0
B490: 5500000004 | C490: =IFERROR(IF(B490,VLOOKUP((AEO!$B$13&AEO!$C$13&B490&E490),MSRV5!A:F,6,0),""),"N/A") -> 4470 | D490: MONT. COLUNA DE CONCRETO, DE 20 A 25 M, | E490: =IF(B490,VLOOKUP(B490,MSRV5!B:D,3,0),"") -> UN | H490: =IFERROR(IF(B490,VLOOKUP((AEO!$B$13&AEO!$C$13&B490&E490),MSRV5!A:E,5,0),""),0) -> 8522.93 | I490: =(F490+G490)*H490 -> 0 | K490: =J490*$H490 -> 0 | M490: =L490*$H490 -> 0 | O490: =N490*$H490 -> 0 | Q490: =P490*$H490 -> 0 | S490: =R490*$H490 -> 0 | U490: =T490*$H490 -> 0 | W490: =V490*$H490 -> 0 | Y490: =X490*$H490 -> 0 | AA490: =Z490*$H490 -> 0 | AC490: =AB490*$H490 -> 0 | AE490: =AD490*$H490 -> 0 | AG490: =AF490*$H490 -> 0 | AI490: =AH490*$H490 -> 0 | AK490: =AJ490*$H490 -> 0 | AM490: =AL490*$H490 -> 0 | AO490: =AN490*$H490 -> 0 | AQ490: =AP490*$H490 -> 0 | AS490: =AR490*$H490 -> 0 | AU490: =AT490*$H490 -> 0 | AW490: =AV490*$H490 -> 0 | AX490: =SUM(AV490,AT490,AR490,AP490,AN490,AL490,AJ490,AH490,AF490,AD490,AB490,Z490,X490,V490,T490,R490,P490,N490,L490,J490) -> 0 | AY490: =SUM(AW490,AU490,AS490,AQ490,AO490,AM490,AK490,AI490,AG490,AE490,AC490,AA490,Y490,W490,U490,S490,Q490,O490,M490,K490) -> 0 | AZ490: =(F490+G490)-AX490 -> 0 | BA490: =I490-AY490 -> 0
B491: 5021000002 | C491: =IFERROR(IF(B491,VLOOKUP((AEO!$B$13&AEO!$C$13&B491&E491),MSRV5!A:F,6,0),""),"N/A") -> 4480 | D491: INSTALAR ESTRUT PRIM CRUZETA DUPLA LM | E491: =IF(B491,VLOOKUP(B491,MSRV5!B:D,3,0),"") -> UN | H491: =IFERROR(IF(B491,VLOOKUP((AEO!$B$13&AEO!$C$13&B491&E491),MSRV5!A:E,5,0),""),0) -> 3145.16 | I491: =(F491+G491)*H491 -> 0 | K491: =J491*$H491 -> 0 | M491: =L491*$H491 -> 0 | O491: =N491*$H491 -> 0 | Q491: =P491*$H491 -> 0 | S491: =R491*$H491 -> 0 | U491: =T491*$H491 -> 0 | W491: =V491*$H491 -> 0 | Y491: =X491*$H491 -> 0 | AA491: =Z491*$H491 -> 0 | AC491: =AB491*$H491 -> 0 | AE491: =AD491*$H491 -> 0 | AG491: =AF491*$H491 -> 0 | AI491: =AH491*$H491 -> 0 | AK491: =AJ491*$H491 -> 0 | AM491: =AL491*$H491 -> 0 | AO491: =AN491*$H491 -> 0 | AQ491: =AP491*$H491 -> 0 | AS491: =AR491*$H491 -> 0 | AU491: =AT491*$H491 -> 0 | AW491: =AV491*$H491 -> 0 | AX491: =SUM(AV491,AT491,AR491,AP491,AN491,AL491,AJ491,AH491,AF491,AD491,AB491,Z491,X491,V491,T491,R491,P491,N491,L491,J491) -> 0 | AY491: =SUM(AW491,AU491,AS491,AQ491,AO491,AM491,AK491,AI491,AG491,AE491,AC491,AA491,Y491,W491,U491,S491,Q491,O491,M491,K491) -> 0 | AZ491: =(F491+G491)-AX491 -> 0 | BA491: =I491-AY491 -> 0
B492: 5021000003 | C492: =IFERROR(IF(B492,VLOOKUP((AEO!$B$13&AEO!$C$13&B492&E492),MSRV5!A:F,6,0),""),"N/A") -> 4490 | D492: INSTALAR ESTRUT PRI CRUZETA SIMPLES LM | E492: =IF(B492,VLOOKUP(B492,MSRV5!B:D,3,0),"") -> UN | H492: =IFERROR(IF(B492,VLOOKUP((AEO!$B$13&AEO!$C$13&B492&E492),MSRV5!A:E,5,0),""),0) -> 2669.71 | I492: =(F492+G492)*H492 -> 0 | K492: =J492*$H492 -> 0 | M492: =L492*$H492 -> 0 | O492: =N492*$H492 -> 0 | Q492: =P492*$H492 -> 0 | S492: =R492*$H492 -> 0 | U492: =T492*$H492 -> 0 | W492: =V492*$H492 -> 0 | Y492: =X492*$H492 -> 0 | AA492: =Z492*$H492 -> 0 | AC492: =AB492*$H492 -> 0 | AE492: =AD492*$H492 -> 0 | AG492: =AF492*$H492 -> 0 | AI492: =AH492*$H492 -> 0 | AK492: =AJ492*$H492 -> 0 | AM492: =AL492*$H492 -> 0 | AO492: =AN492*$H492 -> 0 | AQ492: =AP492*$H492 -> 0 | AS492: =AR492*$H492 -> 0 | AU492: =AT492*$H492 -> 0 | AW492: =AV492*$H492 -> 0 | AX492: =SUM(AV492,AT492,AR492,AP492,AN492,AL492,AJ492,AH492,AF492,AD492,AB492,Z492,X492,V492,T492,R492,P492,N492,L492,J492) -> 0 | AY492: =SUM(AW492,AU492,AS492,AQ492,AO492,AM492,AK492,AI492,AG492,AE492,AC492,AA492,Y492,W492,U492,S492,Q492,O492,M492,K492) -> 0 | AZ492: =(F492+G492)-AX492 -> 0 | BA492: =I492-AY492 -> 0
B493: 5041100025 | C493: =IFERROR(IF(B493,VLOOKUP((AEO!$B$13&AEO!$C$13&B493&E493),MSRV5!A:F,6,0),""),"N/A") -> 4500 | D493: IMPLANTAÇÃO DE ESTRUTURA - URBANO | E493: =IF(B493,VLOOKUP(B493,MSRV5!B:D,3,0),"") -> UN | H493: =IFERROR(IF(B493,VLOOKUP((AEO!$B$13&AEO!$C$13&B493&E493),MSRV5!A:E,5,0),""),0) -> 2118.88 | I493: =(F493+G493)*H493 -> 0 | K493: =J493*$H493 -> 0 | M493: =L493*$H493 -> 0 | O493: =N493*$H493 -> 0 | Q493: =P493*$H493 -> 0 | S493: =R493*$H493 -> 0 | U493: =T493*$H493 -> 0 | W493: =V493*$H493 -> 0 | Y493: =X493*$H493 -> 0 | AA493: =Z493*$H493 -> 0 | AC493: =AB493*$H493 -> 0 | AE493: =AD493*$H493 -> 0 | AG493: =AF493*$H493 -> 0 | AI493: =AH493*$H493 -> 0 | AK493: =AJ493*$H493 -> 0 | AM493: =AL493*$H493 -> 0 | AO493: =AN493*$H493 -> 0 | AQ493: =AP493*$H493 -> 0 | AS493: =AR493*$H493 -> 0 | AU493: =AT493*$H493 -> 0 | AW493: =AV493*$H493 -> 0 | AX493: =SUM(AV493,AT493,AR493,AP493,AN493,AL493,AJ493,AH493,AF493,AD493,AB493,Z493,X493,V493,T493,R493,P493,N493,L493,J493) -> 0 | AY493: =SUM(AW493,AU493,AS493,AQ493,AO493,AM493,AK493,AI493,AG493,AE493,AC493,AA493,Y493,W493,U493,S493,Q493,O493,M493,K493) -> 0 | AZ493: =(F493+G493)-AX493 -> 0 | BA493: =I493-AY493 -> 0
B494: 5041100026 | C494: =IFERROR(IF(B494,VLOOKUP((AEO!$B$13&AEO!$C$13&B494&E494),MSRV5!A:F,6,0),""),"N/A") -> 4510 | D494: IMPLANTAÇÃO DE ESTRUTURA - RURAL | E494: =IF(B494,VLOOKUP(B494,MSRV5!B:D,3,0),"") -> UN | H494: =IFERROR(IF(B494,VLOOKUP((AEO!$B$13&AEO!$C$13&B494&E494),MSRV5!A:E,5,0),""),0) -> 2118.88 | I494: =(F494+G494)*H494 -> 0 | K494: =J494*$H494 -> 0 | M494: =L494*$H494 -> 0 | O494: =N494*$H494 -> 0 | Q494: =P494*$H494 -> 0 | S494: =R494*$H494 -> 0 | U494: =T494*$H494 -> 0 | W494: =V494*$H494 -> 0 | Y494: =X494*$H494 -> 0 | AA494: =Z494*$H494 -> 0 | AC494: =AB494*$H494 -> 0 | AE494: =AD494*$H494 -> 0 | AG494: =AF494*$H494 -> 0 | AI494: =AH494*$H494 -> 0 | AK494: =AJ494*$H494 -> 0 | AM494: =AL494*$H494 -> 0 | AO494: =AN494*$H494 -> 0 | AQ494: =AP494*$H494 -> 0 | AS494: =AR494*$H494 -> 0 | AU494: =AT494*$H494 -> 0 | AW494: =AV494*$H494 -> 0 | AX494: =SUM(AV494,AT494,AR494,AP494,AN494,AL494,AJ494,AH494,AF494,AD494,AB494,Z494,X494,V494,T494,R494,P494,N494,L494,J494) -> 0 | AY494: =SUM(AW494,AU494,AS494,AQ494,AO494,AM494,AK494,AI494,AG494,AE494,AC494,AA494,Y494,W494,U494,S494,Q494,O494,M494,K494) -> 0 | AZ494: =(F494+G494)-AX494 -> 0 | BA494: =I494-AY494 -> 0
B495: 5051000043 | C495: =IFERROR(IF(B495,VLOOKUP((AEO!$B$13&AEO!$C$13&B495&E495),MSRV5!A:F,6,0),""),"N/A") -> 4520 | D495: MONT. POSTE DE CONCRETO, DE 5 A 10 M, | E495: =IF(B495,VLOOKUP(B495,MSRV5!B:D,3,0),"") -> UN | H495: =IFERROR(IF(B495,VLOOKUP((AEO!$B$13&AEO!$C$13&B495&E495),MSRV5!A:E,5,0),""),0) -> 1973.61 | I495: =(F495+G495)*H495 -> 0 | K495: =J495*$H495 -> 0 | M495: =L495*$H495 -> 0 | O495: =N495*$H495 -> 0 | Q495: =P495*$H495 -> 0 | S495: =R495*$H495 -> 0 | U495: =T495*$H495 -> 0 | W495: =V495*$H495 -> 0 | Y495: =X495*$H495 -> 0 | AA495: =Z495*$H495 -> 0 | AC495: =AB495*$H495 -> 0 | AE495: =AD495*$H495 -> 0 | AG495: =AF495*$H495 -> 0 | AI495: =AH495*$H495 -> 0 | AK495: =AJ495*$H495 -> 0 | AM495: =AL495*$H495 -> 0 | AO495: =AN495*$H495 -> 0 | AQ495: =AP495*$H495 -> 0 | AS495: =AR495*$H495 -> 0 | AU495: =AT495*$H495 -> 0 | AW495: =AV495*$H495 -> 0 | AX495: =SUM(AV495,AT495,AR495,AP495,AN495,AL495,AJ495,AH495,AF495,AD495,AB495,Z495,X495,V495,T495,R495,P495,N495,L495,J495) -> 0 | AY495: =SUM(AW495,AU495,AS495,AQ495,AO495,AM495,AK495,AI495,AG495,AE495,AC495,AA495,Y495,W495,U495,S495,Q495,O495,M495,K495) -> 0 | AZ495: =(F495+G495)-AX495 -> 0 | BA495: =I495-AY495 -> 0
... B627: 5500100908 | C627: =IFERROR(IF(B627,VLOOKUP((AEO!$B$13&AEO!$C$13&B627&E627),MSRV5!A:F,6,0),""),"N/A") -> 5860 | D627: DMONT. POSTE CIRCULAR METÁLICO, | E627: =IF(B627,VLOOKUP(B627,MSRV5!B:D,3,0),"") -> UN | H627: =IFERROR(IF(B627,VLOOKUP((AEO!$B$13&AEO!$C$13&B627&E627),MSRV5!A:E,5,0),""),0) -> 81.05 | I627: =(F627+G627)*H627 -> 0 | K627: =J627*$H627 -> 0 | M627: =L627*$H627 -> 0 | O627: =N627*$H627 -> 0 | Q627: =P627*$H627 -> 0 | S627: =R627*$H627 -> 0 | U627: =T627*$H627 -> 0 | W627: =V627*$H627 -> 0 | Y627: =X627*$H627 -> 0 | AA627: =Z627*$H627 -> 0 | AC627: =AB627*$H627 -> 0 | AE627: =AD627*$H627 -> 0 | AG627: =AF627*$H627 -> 0 | AI627: =AH627*$H627 -> 0 | AK627: =AJ627*$H627 -> 0 | AM627: =AL627*$H627 -> 0 | AO627: =AN627*$H627 -> 0 | AQ627: =AP627*$H627 -> 0 | AS627: =AR627*$H627 -> 0 | AU627: =AT627*$H627 -> 0 | AW627: =AV627*$H627 -> 0 | AX627: =SUM(AV627,AT627,AR627,AP627,AN627,AL627,AJ627,AH627,AF627,AD627,AB627,Z627,X627,V627,T627,R627,P627,N627,L627,J627) -> 0 | AY627: =SUM(AW627,AU627,AS627,AQ627,AO627,AM627,AK627,AI627,AG627,AE627,AC627,AA627,Y627,W627,U627,S627,Q627,O627,M627,K627) -> 0 | AZ627: =(F627+G627)-AX627 -> 0 | BA627: =I627-AY627 -> 0
C628: =IFERROR(IF(B628,VLOOKUP((AEO!$B$13&AEO!$C$13&B628&E628),MSRV5!A:F,6,0),""),"N/A") | D628: SERVIÇOS ELÉTRICOS (FATOR "EL") | E628: =IF(B628,VLOOKUP(B628,MSRV5!B:D,3,0),"") | H628: =IFERROR(IF(B628,VLOOKUP((AEO!$B$13&AEO!$C$13&B628&E628),MSRV5!A:E,5,0),""),0) | I628: =SUBTOTAL(9,I629:I700) -> 0 | K628: =SUBTOTAL(9,K629:K700) -> 0 | M628: =SUBTOTAL(9,M629:M700) -> 0 | O628: =SUBTOTAL(9,O629:O700) -> 0 | Q628: =SUBTOTAL(9,Q629:Q700) -> 0 | S628: =SUBTOTAL(9,S629:S700) -> 0 | U628: =SUBTOTAL(9,U629:U700) -> 0 | W628: =SUBTOTAL(9,W629:W700) -> 0 | Y628: =SUBTOTAL(9,Y629:Y700) -> 0 | AA628: =SUBTOTAL(9,AA629:AA700) -> 0 | AC628: =SUBTOTAL(9,AC629:AC700) -> 0 | AE628: =SUBTOTAL(9,AE629:AE700) -> 0 | AG628: =SUBTOTAL(9,AG629:AG700) -> 0 | AI628: =SUBTOTAL(9,AI629:AI700) -> 0 | AK628: =SUBTOTAL(9,AK629:AK700) -> 0 | AM628: =SUBTOTAL(9,AM629:AM700) -> 0 | AO628: =SUBTOTAL(9,AO629:AO700) -> 0 | AQ628: =SUBTOTAL(9,AQ629:AQ700) -> 0 | AS628: =SUBTOTAL(9,AS629:AS700) -> 0 | AU628: =SUBTOTAL(9,AU629:AU700) -> 0 | AW628: =SUBTOTAL(9,AW629:AW700) -> 0 | AY628: =SUBTOTAL(9,AY629:AY700) -> 0 | BA628: =SUBTOTAL(9,BA629:BA700) -> 0
B629: 5050300049 | C629: =IFERROR(IF(B629,VLOOKUP((AEO!$B$13&AEO!$C$13&B629&E629),MSRV5!A:F,6,0),""),"N/A") -> N/A | D629: EXECUTAR INTERLIGAÇÃO VÃO BC ATÉ 34,5 KV | E629: =IF(B629,VLOOKUP(B629,MSRV5!B:D,3,0),"") -> #N/A | H629: =IFERROR(IF(B629,VLOOKUP((AEO!$B$13&AEO!$C$13&B629&E629),MSRV5!A:E,5,0),""),0) -> 0 | I629: =(F629+G629)*H629 -> 0 | K629: =J629*$H629 -> 0 | M629: =L629*$H629 -> 0 | O629: =N629*$H629 -> 0 | Q629: =P629*$H629 -> 0 | S629: =R629*$H629 -> 0 | U629: =T629*$H629 -> 0 | W629: =V629*$H629 -> 0 | Y629: =X629*$H629 -> 0 | AA629: =Z629*$H629 -> 0 | AC629: =AB629*$H629 -> 0 | AE629: =AD629*$H629 -> 0 | AG629: =AF629*$H629 -> 0 | AI629: =AH629*$H629 -> 0 | AK629: =AJ629*$H629 -> 0 | AM629: =AL629*$H629 -> 0 | AO629: =AN629*$H629 -> 0 | AQ629: =AP629*$H629 -> 0 | AS629: =AR629*$H629 -> 0 | AU629: =AT629*$H629 -> 0 | AW629: =AV629*$H629 -> 0 | AX629: =SUM(AV629,AT629,AR629,AP629,AN629,AL629,AJ629,AH629,AF629,AD629,AB629,Z629,X629,V629,T629,R629,P629,N629,L629,J629) -> 0 | AY629: =SUM(AW629,AU629,AS629,AQ629,AO629,AM629,AK629,AI629,AG629,AE629,AC629,AA629,Y629,W629,U629,S629,Q629,O629,M629,K629) -> 0 | AZ629: =(F629+G629)-AX629 -> 0 | BA629: =I629-AY629 -> 0
B630: 5054000004 | C630: =IFERROR(IF(B630,VLOOKUP((AEO!$B$13&AEO!$C$13&B630&E630),MSRV5!A:F,6,0),""),"N/A") -> 5880 | D630: EXECUTAR INTERLIG VÃO BC 69 KV OU 138 KV | E630: =IF(B630,VLOOKUP(B630,MSRV5!B:D,3,0),"") -> UN | H630: =IFERROR(IF(B630,VLOOKUP((AEO!$B$13&AEO!$C$13&B630&E630),MSRV5!A:E,5,0),""),0) -> 2499.67 | I630: =(F630+G630)*H630 -> 0 | K630: =J630*$H630 -> 0 | M630: =L630*$H630 -> 0 | O630: =N630*$H630 -> 0 | Q630: =P630*$H630 -> 0 | S630: =R630*$H630 -> 0 | U630: =T630*$H630 -> 0 | W630: =V630*$H630 -> 0 | Y630: =X630*$H630 -> 0 | AA630: =Z630*$H630 -> 0 | AC630: =AB630*$H630 -> 0 | AE630: =AD630*$H630 -> 0 | AG630: =AF630*$H630 -> 0 | AI630: =AH630*$H630 -> 0 | AK630: =AJ630*$H630 -> 0 | AM630: =AL630*$H630 -> 0 | AO630: =AN630*$H630 -> 0 | AQ630: =AP630*$H630 -> 0 | AS630: =AR630*$H630 -> 0 | AU630: =AT630*$H630 -> 0 | AW630: =AV630*$H630 -> 0 | AX630: =SUM(AV630,AT630,AR630,AP630,AN630,AL630,AJ630,AH630,AF630,AD630,AB630,Z630,X630,V630,T630,R630,P630,N630,L630,J630) -> 0 | AY630: =SUM(AW630,AU630,AS630,AQ630,AO630,AM630,AK630,AI630,AG630,AE630,AC630,AA630,Y630,W630,U630,S630,Q630,O630,M630,K630) -> 0 | AZ630: =(F630+G630)-AX630 -> 0 | BA630: =I630-AY630 -> 0
B631: 5054000005 | C631: =IFERROR(IF(B631,VLOOKUP((AEO!$B$13&AEO!$C$13&B631&E631),MSRV5!A:F,6,0),""),"N/A") -> 5870 | D631: EXEC INTERLIG BANC REGULADOR ATÉ 34,5 KV | E631: =IF(B631,VLOOKUP(B631,MSRV5!B:D,3,0),"") -> UN | H631: =IFERROR(IF(B631,VLOOKUP((AEO!$B$13&AEO!$C$13&B631&E631),MSRV5!A:E,5,0),""),0) -> 1381.4 | I631: =(F631+G631)*H631 -> 0 | K631: =J631*$H631 -> 0 | M631: =L631*$H631 -> 0 | O631: =N631*$H631 -> 0 | Q631: =P631*$H631 -> 0 | S631: =R631*$H631 -> 0 | U631: =T631*$H631 -> 0 | W631: =V631*$H631 -> 0 | Y631: =X631*$H631 -> 0 | AA631: =Z631*$H631 -> 0 | AC631: =AB631*$H631 -> 0 | AE631: =AD631*$H631 -> 0 | AG631: =AF631*$H631 -> 0 | AI631: =AH631*$H631 -> 0 | AK631: =AJ631*$H631 -> 0 | AM631: =AL631*$H631 -> 0 | AO631: =AN631*$H631 -> 0 | AQ631: =AP631*$H631 -> 0 | AS631: =AR631*$H631 -> 0 | AU631: =AT631*$H631 -> 0 | AW631: =AV631*$H631 -> 0 | AX631: =SUM(AV631,AT631,AR631,AP631,AN631,AL631,AJ631,AH631,AF631,AD631,AB631,Z631,X631,V631,T631,R631,P631,N631,L631,J631) -> 0 | AY631: =SUM(AW631,AU631,AS631,AQ631,AO631,AM631,AK631,AI631,AG631,AE631,AC631,AA631,Y631,W631,U631,S631,Q631,O631,M631,K631) -> 0 | AZ631: =(F631+G631)-AX631 -> 0 | BA631: =I631-AY631 -> 0
B632: 5054000006 | C632: =IFERROR(IF(B632,VLOOKUP((AEO!$B$13&AEO!$C$13&B632&E632),MSRV5!A:F,6,0),""),"N/A") -> 5900 | D632: EXECUTAR INTERLIGAÇÃO DE CHAVE SEC MAN | E632: =IF(B632,VLOOKUP(B632,MSRV5!B:D,3,0),"") -> UN | H632: =IFERROR(IF(B632,VLOOKUP((AEO!$B$13&AEO!$C$13&B632&E632),MSRV5!A:E,5,0),""),0) -> 612.48 | I632: =(F632+G632)*H632 -> 0 | K632: =J632*$H632 -> 0 | M632: =L632*$H632 -> 0 | O632: =N632*$H632 -> 0 | Q632: =P632*$H632 -> 0 | S632: =R632*$H632 -> 0 | U632: =T632*$H632 -> 0 | W632: =V632*$H632 -> 0 | Y632: =X632*$H632 -> 0 | AA632: =Z632*$H632 -> 0 | AC632: =AB632*$H632 -> 0 | AE632: =AD632*$H632 -> 0 | AG632: =AF632*$H632 -> 0 | AI632: =AH632*$H632 -> 0 | AK632: =AJ632*$H632 -> 0 | AM632: =AL632*$H632 -> 0 | AO632: =AN632*$H632 -> 0 | AQ632: =AP632*$H632 -> 0 | AS632: =AR632*$H632 -> 0 | AU632: =AT632*$H632 -> 0 | AW632: =AV632*$H632 -> 0 | AX632: =SUM(AV632,AT632,AR632,AP632,AN632,AL632,AJ632,AH632,AF632,AD632,AB632,Z632,X632,V632,T632,R632,P632,N632,L632,J632) -> 0 | AY632: =SUM(AW632,AU632,AS632,AQ632,AO632,AM632,AK632,AI632,AG632,AE632,AC632,AA632,Y632,W632,U632,S632,Q632,O632,M632,K632) -> 0 | AZ632: =(F632+G632)-AX632 -> 0 | BA632: =I632-AY632 -> 0
B633: 5054000007 | C633: =IFERROR(IF(B633,VLOOKUP((AEO!$B$13&AEO!$C$13&B633&E633),MSRV5!A:F,6,0),""),"N/A") -> 5910 | D633: EXECUTAR INTERLIGAÇÃO DE CHAVE SEC MOT | E633: =IF(B633,VLOOKUP(B633,MSRV5!B:D,3,0),"") -> UN | H633: =IFERROR(IF(B633,VLOOKUP((AEO!$B$13&AEO!$C$13&B633&E633),MSRV5!A:E,5,0),""),0) -> 1901.2 | I633: =(F633+G633)*H633 -> 0 | K633: =J633*$H633 -> 0 | M633: =L633*$H633 -> 0 | O633: =N633*$H633 -> 0 | Q633: =P633*$H633 -> 0 | S633: =R633*$H633 -> 0 | U633: =T633*$H633 -> 0 | W633: =V633*$H633 -> 0 | Y633: =X633*$H633 -> 0 | AA633: =Z633*$H633 -> 0 | AC633: =AB633*$H633 -> 0 | AE633: =AD633*$H633 -> 0 | AG633: =AF633*$H633 -> 0 | AI633: =AH633*$H633 -> 0 | AK633: =AJ633*$H633 -> 0 | AM633: =AL633*$H633 -> 0 | AO633: =AN633*$H633 -> 0 | AQ633: =AP633*$H633 -> 0 | AS633: =AR633*$H633 -> 0 | AU633: =AT633*$H633 -> 0 | AW633: =AV633*$H633 -> 0 | AX633: =SUM(AV633,AT633,AR633,AP633,AN633,AL633,AJ633,AH633,AF633,AD633,AB633,Z633,X633,V633,T633,R633,P633,N633,L633,J633) -> 0 | AY633: =SUM(AW633,AU633,AS633,AQ633,AO633,AM633,AK633,AI633,AG633,AE633,AC633,AA633,Y633,W633,U633,S633,Q633,O633,M633,K633) -> 0 | AZ633: =(F633+G633)-AX633 -> 0 | BA633: =I633-AY633 -> 0
B634: 5054000011 | C634: =IFERROR(IF(B634,VLOOKUP((AEO!$B$13&AEO!$C$13&B634&E634),MSRV5!A:F,6,0),""),"N/A") -> 5920 | D634: EXECUTAR INTERLIGAÇÃO DE TSA | E634: =IF(B634,VLOOKUP(B634,MSRV5!B:D,3,0),"") -> UN | H634: =IFERROR(IF(B634,VLOOKUP((AEO!$B$13&AEO!$C$13&B634&E634),MSRV5!A:E,5,0),""),0) -> 1071.69 | I634: =(F634+G634)*H634 -> 0 | K634: =J634*$H634 -> 0 | M634: =L634*$H634 -> 0 | O634: =N634*$H634 -> 0 | Q634: =P634*$H634 -> 0 | S634: =R634*$H634 -> 0 | U634: =T634*$H634 -> 0 | W634: =V634*$H634 -> 0 | Y634: =X634*$H634 -> 0 | AA634: =Z634*$H634 -> 0 | AC634: =AB634*$H634 -> 0 | AE634: =AD634*$H634 -> 0 | AG634: =AF634*$H634 -> 0 | AI634: =AH634*$H634 -> 0 | AK634: =AJ634*$H634 -> 0 | AM634: =AL634*$H634 -> 0 | AO634: =AN634*$H634 -> 0 | AQ634: =AP634*$H634 -> 0 | AS634: =AR634*$H634 -> 0 | AU634: =AT634*$H634 -> 0 | AW634: =AV634*$H634 -> 0 | AX634: =SUM(AV634,AT634,AR634,AP634,AN634,AL634,AJ634,AH634,AF634,AD634,AB634,Z634,X634,V634,T634,R634,P634,N634,L634,J634) -> 0 | AY634: =SUM(AW634,AU634,AS634,AQ634,AO634,AM634,AK634,AI634,AG634,AE634,AC634,AA634,Y634,W634,U634,S634,Q634,O634,M634,K634) -> 0 | AZ634: =(F634+G634)-AX634 -> 0 | BA634: =I634-AY634 -> 0
B635: 5054000008 | C635: =IFERROR(IF(B635,VLOOKUP((AEO!$B$13&AEO!$C$13&B635&E635),MSRV5!A:F,6,0),""),"N/A") -> 5930 | D635: EXECUTAR INTERLIGAÇÃO DE DISJUNTOR | E635: =IF(B635,VLOOKUP(B635,MSRV5!B:D,3,0),"") -> UN | H635: =IFERROR(IF(B635,VLOOKUP((AEO!$B$13&AEO!$C$13&B635&E635),MSRV5!A:E,5,0),""),0) -> 2105.12 | I635: =(F635+G635)*H635 -> 0 | K635: =J635*$H635 -> 0 | M635: =L635*$H635 -> 0 | O635: =N635*$H635 -> 0 | Q635: =P635*$H635 -> 0 | S635: =R635*$H635 -> 0 | U635: =T635*$H635 -> 0 | W635: =V635*$H635 -> 0 | Y635: =X635*$H635 -> 0 | AA635: =Z635*$H635 -> 0 | AC635: =AB635*$H635 -> 0 | AE635: =AD635*$H635 -> 0 | AG635: =AF635*$H635 -> 0 | AI635: =AH635*$H635 -> 0 | AK635: =AJ635*$H635 -> 0 | AM635: =AL635*$H635 -> 0 | AO635: =AN635*$H635 -> 0 | AQ635: =AP635*$H635 -> 0 | AS635: =AR635*$H635 -> 0 | AU635: =AT635*$H635 -> 0 | AW635: =AV635*$H635 -> 0 | AX635: =SUM(AV635,AT635,AR635,AP635,AN635,AL635,AJ635,AH635,AF635,AD635,AB635,Z635,X635,V635,T635,R635,P635,N635,L635,J635) -> 0 | AY635: =SUM(AW635,AU635,AS635,AQ635,AO635,AM635,AK635,AI635,AG635,AE635,AC635,AA635,Y635,W635,U635,S635,Q635,O635,M635,K635) -> 0 | AZ635: =(F635+G635)-AX635 -> 0 | BA635: =I635-AY635 -> 0
B636: 5054000037 | C636: =IFERROR(IF(B636,VLOOKUP((AEO!$B$13&AEO!$C$13&B636&E636),MSRV5!A:F,6,0),""),"N/A") -> 5940 | D636: EXECUTAR INTERLIGAÇÃO REATOR TRIFÁSICO | E636: =IF(B636,VLOOKUP(B636,MSRV5!B:D,3,0),"") -> UN | H636: =IFERROR(IF(B636,VLOOKUP((AEO!$B$13&AEO!$C$13&B636&E636),MSRV5!A:E,5,0),""),0) -> 1704.15 | I636: =(F636+G636)*H636 -> 0 | K636: =J636*$H636 -> 0 | M636: =L636*$H636 -> 0 | O636: =N636*$H636 -> 0 | Q636: =P636*$H636 -> 0 | S636: =R636*$H636 -> 0 | U636: =T636*$H636 -> 0 | W636: =V636*$H636 -> 0 | Y636: =X636*$H636 -> 0 | AA636: =Z636*$H636 -> 0 | AC636: =AB636*$H636 -> 0 | AE636: =AD636*$H636 -> 0 | AG636: =AF636*$H636 -> 0 | AI636: =AH636*$H636 -> 0 | AK636: =AJ636*$H636 -> 0 | AM636: =AL636*$H636 -> 0 | AO636: =AN636*$H636 -> 0 | AQ636: =AP636*$H636 -> 0 | AS636: =AR636*$H636 -> 0 | AU636: =AT636*$H636 -> 0 | AW636: =AV636*$H636 -> 0 | AX636: =SUM(AV636,AT636,AR636,AP636,AN636,AL636,AJ636,AH636,AF636,AD636,AB636,Z636,X636,V636,T636,R636,P636,N636,L636,J636) -> 0 | AY636: =SUM(AW636,AU636,AS636,AQ636,AO636,AM636,AK636,AI636,AG636,AE636,AC636,AA636,Y636,W636,U636,S636,Q636,O636,M636,K636) -> 0 | AZ636: =(F636+G636)-AX636 -> 0 | BA636: =I636-AY636 -> 0
B637: 5054000014 | C637: =IFERROR(IF(B637,VLOOKUP((AEO!$B$13&AEO!$C$13&B637&E637),MSRV5!A:F,6,0),""),"N/A") -> 5950 | D637: EXECUTAR INTERLIGAÇÃO DE RELIGADOR | E637: =IF(B637,VLOOKUP(B637,MSRV5!B:D,3,0),"") -> UN | H637: =IFERROR(IF(B637,VLOOKUP((AEO!$B$13&AEO!$C$13&B637&E637),MSRV5!A:E,5,0),""),0) -> 1806.12 | I637: =(F637+G637)*H637 -> 0 | K637: =J637*$H637 -> 0 | M637: =L637*$H637 -> 0 | O637: =N637*$H637 -> 0 | Q637: =P637*$H637 -> 0 | S637: =R637*$H637 -> 0 | U637: =T637*$H637 -> 0 | W637: =V637*$H637 -> 0 | Y637: =X637*$H637 -> 0 | AA637: =Z637*$H637 -> 0 | AC637: =AB637*$H637 -> 0 | AE637: =AD637*$H637 -> 0 | AG637: =AF637*$H637 -> 0 | AI637: =AH637*$H637 -> 0 | AK637: =AJ637*$H637 -> 0 | AM637: =AL637*$H637 -> 0 | AO637: =AN637*$H637 -> 0 | AQ637: =AP637*$H637 -> 0 | AS637: =AR637*$H637 -> 0 | AU637: =AT637*$H637 -> 0 | AW637: =AV637*$H637 -> 0 | AX637: =SUM(AV637,AT637,AR637,AP637,AN637,AL637,AJ637,AH637,AF637,AD637,AB637,Z637,X637,V637,T637,R637,P637,N637,L637,J637) -> 0 | AY637: =SUM(AW637,AU637,AS637,AQ637,AO637,AM637,AK637,AI637,AG637,AE637,AC637,AA637,Y637,W637,U637,S637,Q637,O637,M637,K637) -> 0 | AZ637: =(F637+G637)-AX637 -> 0 | BA637: =I637-AY637 -> 0
B638: 5054000032 | C638: =IFERROR(IF(B638,VLOOKUP((AEO!$B$13&AEO!$C$13&B638&E638),MSRV5!A:F,6,0),""),"N/A") -> 5960 | D638: EXECUTAR INSTALAÇÃO ELÉTRICA CAIXA TC | E638: =IF(B638,VLOOKUP(B638,MSRV5!B:D,3,0),"") -> UN | H638: =IFERROR(IF(B638,VLOOKUP((AEO!$B$13&AEO!$C$13&B638&E638),MSRV5!A:E,5,0),""),0) -> 977.88 | I638: =(F638+G638)*H638 -> 0 | K638: =J638*$H638 -> 0 | M638: =L638*$H638 -> 0 | O638: =N638*$H638 -> 0 | Q638: =P638*$H638 -> 0 | S638: =R638*$H638 -> 0 | U638: =T638*$H638 -> 0 | W638: =V638*$H638 -> 0 | Y638: =X638*$H638 -> 0 | AA638: =Z638*$H638 -> 0 | AC638: =AB638*$H638 -> 0 | AE638: =AD638*$H638 -> 0 | AG638: =AF638*$H638 -> 0 | AI638: =AH638*$H638 -> 0 | AK638: =AJ638*$H638 -> 0 | AM638: =AL638*$H638 -> 0 | AO638: =AN638*$H638 -> 0 | AQ638: =AP638*$H638 -> 0 | AS638: =AR638*$H638 -> 0 | AU638: =AT638*$H638 -> 0 | AW638: =AV638*$H638 -> 0 | AX638: =SUM(AV638,AT638,AR638,AP638,AN638,AL638,AJ638,AH638,AF638,AD638,AB638,Z638,X638,V638,T638,R638,P638,N638,L638,J638) -> 0 | AY638: =SUM(AW638,AU638,AS638,AQ638,AO638,AM638,AK638,AI638,AG638,AE638,AC638,AA638,Y638,W638,U638,S638,Q638,O638,M638,K638) -> 0 | AZ638: =(F638+G638)-AX638 -> 0 | BA638: =I638-AY638 -> 0
B639: 5054000009 | C639: =IFERROR(IF(B639,VLOOKUP((AEO!$B$13&AEO!$C$13&B639&E639),MSRV5!A:F,6,0),""),"N/A") -> 5970 | D639: EXECUTAR INTERLIGAÇÃO DE TC | E639: =IF(B639,VLOOKUP(B639,MSRV5!B:D,3,0),"") -> UN | H639: =IFERROR(IF(B639,VLOOKUP((AEO!$B$13&AEO!$C$13&B639&E639),MSRV5!A:E,5,0),""),0) -> 753.31 | I639: =(F639+G639)*H639 -> 0 | K639: =J639*$H639 -> 0 | M639: =L639*$H639 -> 0 | O639: =N639*$H639 -> 0 | Q639: =P639*$H639 -> 0 | S639: =R639*$H639 -> 0 | U639: =T639*$H639 -> 0 | W639: =V639*$H639 -> 0 | Y639: =X639*$H639 -> 0 | AA639: =Z639*$H639 -> 0 | AC639: =AB639*$H639 -> 0 | AE639: =AD639*$H639 -> 0 | AG639: =AF639*$H639 -> 0 | AI639: =AH639*$H639 -> 0 | AK639: =AJ639*$H639 -> 0 | AM639: =AL639*$H639 -> 0 | AO639: =AN639*$H639 -> 0 | AQ639: =AP639*$H639 -> 0 | AS639: =AR639*$H639 -> 0 | AU639: =AT639*$H639 -> 0 | AW639: =AV639*$H639 -> 0 | AX639: =SUM(AV639,AT639,AR639,AP639,AN639,AL639,AJ639,AH639,AF639,AD639,AB639,Z639,X639,V639,T639,R639,P639,N639,L639,J639) -> 0 | AY639: =SUM(AW639,AU639,AS639,AQ639,AO639,AM639,AK639,AI639,AG639,AE639,AC639,AA639,Y639,W639,U639,S639,Q639,O639,M639,K639) -> 0 | AZ639: =(F639+G639)-AX639 -> 0 | BA639: =I639-AY639 -> 0
B640: 5054000033 | C640: =IFERROR(IF(B640,VLOOKUP((AEO!$B$13&AEO!$C$13&B640&E640),MSRV5!A:F,6,0),""),"N/A") -> 5980 | D640: EXECUTAR INSTALAÇÃO ELÉTRICA CAIXA TP | E640: =IF(B640,VLOOKUP(B640,MSRV5!B:D,3,0),"") -> UN | H640: =IFERROR(IF(B640,VLOOKUP((AEO!$B$13&AEO!$C$13&B640&E640),MSRV5!A:E,5,0),""),0) -> 915.37 | I640: =(F640+G640)*H640 -> 0 | K640: =J640*$H640 -> 0 | M640: =L640*$H640 -> 0 | O640: =N640*$H640 -> 0 | Q640: =P640*$H640 -> 0 | S640: =R640*$H640 -> 0 | U640: =T640*$H640 -> 0 | W640: =V640*$H640 -> 0 | Y640: =X640*$H640 -> 0 | AA640: =Z640*$H640 -> 0 | AC640: =AB640*$H640 -> 0 | AE640: =AD640*$H640 -> 0 | AG640: =AF640*$H640 -> 0 | AI640: =AH640*$H640 -> 0 | AK640: =AJ640*$H640 -> 0 | AM640: =AL640*$H640 -> 0 | AO640: =AN640*$H640 -> 0 | AQ640: =AP640*$H640 -> 0 | AS640: =AR640*$H640 -> 0 | AU640: =AT640*$H640 -> 0 | AW640: =AV640*$H640 -> 0 | AX640: =SUM(AV640,AT640,AR640,AP640,AN640,AL640,AJ640,AH640,AF640,AD640,AB640,Z640,X640,V640,T640,R640,P640,N640,L640,J640) -> 0 | AY640: =SUM(AW640,AU640,AS640,AQ640,AO640,AM640,AK640,AI640,AG640,AE640,AC640,AA640,Y640,W640,U640,S640,Q640,O640,M640,K640) -> 0 | AZ640: =(F640+G640)-AX640 -> 0 | BA640: =I640-AY640 -> 0
... B674: 5054100001 | C674: =IFERROR(IF(B674,VLOOKUP((AEO!$B$13&AEO!$C$13&B674&E674),MSRV5!A:F,6,0),""),"N/A") -> 6320 | D674: INSTAL E INTERLIG EQUIP DE COMUNICAÇÃO | E674: =IF(B674,VLOOKUP(B674,MSRV5!B:D,3,0),"") -> UN | H674: =IFERROR(IF(B674,VLOOKUP((AEO!$B$13&AEO!$C$13&B674&E674),MSRV5!A:E,5,0),""),0) -> 1062.63 | I674: =(F674+G674)*H674 -> 0 | K674: =J674*$H674 -> 0 | M674: =L674*$H674 -> 0 | O674: =N674*$H674 -> 0 | Q674: =P674*$H674 -> 0 | S674: =R674*$H674 -> 0 | U674: =T674*$H674 -> 0 | W674: =V674*$H674 -> 0 | Y674: =X674*$H674 -> 0 | AA674: =Z674*$H674 -> 0 | AC674: =AB674*$H674 -> 0 | AE674: =AD674*$H674 -> 0 | AG674: =AF674*$H674 -> 0 | AI674: =AH674*$H674 -> 0 | AK674: =AJ674*$H674 -> 0 | AM674: =AL674*$H674 -> 0 | AO674: =AN674*$H674 -> 0 | AQ674: =AP674*$H674 -> 0 | AS674: =AR674*$H674 -> 0 | AU674: =AT674*$H674 -> 0 | AW674: =AV674*$H674 -> 0 | AX674: =SUM(AV674,AT674,AR674,AP674,AN674,AL674,AJ674,AH674,AF674,AD674,AB674,Z674,X674,V674,T674,R674,P674,N674,L674,J674) -> 0 | AY674: =SUM(AW674,AU674,AS674,AQ674,AO674,AM674,AK674,AI674,AG674,AE674,AC674,AA674,Y674,W674,U674,S674,Q674,O674,M674,K674) -> 0 | AZ674: =(F674+G674)-AX674 -> 0 | BA674: =I674-AY674 -> 0
B675: 5054000050 | C675: =IFERROR(IF(B675,VLOOKUP((AEO!$B$13&AEO!$C$13&B675&E675),MSRV5!A:F,6,0),""),"N/A") -> 6330 | D675: INTERLIGAR RELÉ MONTADO EM PAINEL | E675: =IF(B675,VLOOKUP(B675,MSRV5!B:D,3,0),"") -> UN | F675: 0 | H675: =IFERROR(IF(B675,VLOOKUP((AEO!$B$13&AEO!$C$13&B675&E675),MSRV5!A:E,5,0),""),0) -> 913.44 | I675: =(F675+G675)*H675 -> 0 | K675: =J675*$H675 -> 0 | M675: =L675*$H675 -> 0 | O675: =N675*$H675 -> 0 | Q675: =P675*$H675 -> 0 | S675: =R675*$H675 -> 0 | U675: =T675*$H675 -> 0 | W675: =V675*$H675 -> 0 | Y675: =X675*$H675 -> 0 | AA675: =Z675*$H675 -> 0 | AC675: =AB675*$H675 -> 0 | AE675: =AD675*$H675 -> 0 | AG675: =AF675*$H675 -> 0 | AI675: =AH675*$H675 -> 0 | AK675: =AJ675*$H675 -> 0 | AM675: =AL675*$H675 -> 0 | AO675: =AN675*$H675 -> 0 | AQ675: =AP675*$H675 -> 0 | AS675: =AR675*$H675 -> 0 | AU675: =AT675*$H675 -> 0 | AW675: =AV675*$H675 -> 0 | AX675: =SUM(AV675,AT675,AR675,AP675,AN675,AL675,AJ675,AH675,AF675,AD675,AB675,Z675,X675,V675,T675,R675,P675,N675,L675,J675) -> 0 | AY675: =SUM(AW675,AU675,AS675,AQ675,AO675,AM675,AK675,AI675,AG675,AE675,AC675,AA675,Y675,W675,U675,S675,Q675,O675,M675,K675) -> 0 | AZ675: =(F675+G675)-AX675 -> 0 | BA675: =I675-AY675 -> 0
B676: 5054000021 | C676: =IFERROR(IF(B676,VLOOKUP((AEO!$B$13&AEO!$C$13&B676&E676),MSRV5!A:F,6,0),""),"N/A") -> 6340 | D676: INSTAL E INTERLIG RELÉ EM PNL EXISTENTE | E676: =IF(B676,VLOOKUP(B676,MSRV5!B:D,3,0),"") -> UN | H676: =IFERROR(IF(B676,VLOOKUP((AEO!$B$13&AEO!$C$13&B676&E676),MSRV5!A:E,5,0),""),0) -> 3722.02 | I676: =(F676+G676)*H676 -> 0 | K676: =J676*$H676 -> 0 | M676: =L676*$H676 -> 0 | O676: =N676*$H676 -> 0 | Q676: =P676*$H676 -> 0 | S676: =R676*$H676 -> 0 | U676: =T676*$H676 -> 0 | W676: =V676*$H676 -> 0 | Y676: =X676*$H676 -> 0 | AA676: =Z676*$H676 -> 0 | AC676: =AB676*$H676 -> 0 | AE676: =AD676*$H676 -> 0 | AG676: =AF676*$H676 -> 0 | AI676: =AH676*$H676 -> 0 | AK676: =AJ676*$H676 -> 0 | AM676: =AL676*$H676 -> 0 | AO676: =AN676*$H676 -> 0 | AQ676: =AP676*$H676 -> 0 | AS676: =AR676*$H676 -> 0 | AU676: =AT676*$H676 -> 0 | AW676: =AV676*$H676 -> 0 | AX676: =SUM(AV676,AT676,AR676,AP676,AN676,AL676,AJ676,AH676,AF676,AD676,AB676,Z676,X676,V676,T676,R676,P676,N676,L676,J676) -> 0 | AY676: =SUM(AW676,AU676,AS676,AQ676,AO676,AM676,AK676,AI676,AG676,AE676,AC676,AA676,Y676,W676,U676,S676,Q676,O676,M676,K676) -> 0 | AZ676: =(F676+G676)-AX676 -> 0 | BA676: =I676-AY676 -> 0
B677: 5054000022 | C677: =IFERROR(IF(B677,VLOOKUP((AEO!$B$13&AEO!$C$13&B677&E677),MSRV5!A:F,6,0),""),"N/A") -> 6350 | D677: INSTALAR E INTERLIG RELÉ EM PAINEL NOVO | E677: =IF(B677,VLOOKUP(B677,MSRV5!B:D,3,0),"") -> UN | H677: =IFERROR(IF(B677,VLOOKUP((AEO!$B$13&AEO!$C$13&B677&E677),MSRV5!A:E,5,0),""),0) -> 4021.76 | I677: =(F677+G677)*H677 -> 0 | K677: =J677*$H677 -> 0 | M677: =L677*$H677 -> 0 | O677: =N677*$H677 -> 0 | Q677: =P677*$H677 -> 0 | S677: =R677*$H677 -> 0 | U677: =T677*$H677 -> 0 | W677: =V677*$H677 -> 0 | Y677: =X677*$H677 -> 0 | AA677: =Z677*$H677 -> 0 | AC677: =AB677*$H677 -> 0 | AE677: =AD677*$H677 -> 0 | AG677: =AF677*$H677 -> 0 | AI677: =AH677*$H677 -> 0 | AK677: =AJ677*$H677 -> 0 | AM677: =AL677*$H677 -> 0 | AO677: =AN677*$H677 -> 0 | AQ677: =AP677*$H677 -> 0 | AS677: =AR677*$H677 -> 0 | AU677: =AT677*$H677 -> 0 | AW677: =AV677*$H677 -> 0 | AX677: =SUM(AV677,AT677,AR677,AP677,AN677,AL677,AJ677,AH677,AF677,AD677,AB677,Z677,X677,V677,T677,R677,P677,N677,L677,J677) -> 0 | AY677: =SUM(AW677,AU677,AS677,AQ677,AO677,AM677,AK677,AI677,AG677,AE677,AC677,AA677,Y677,W677,U677,S677,Q677,O677,M677,K677) -> 0 | AZ677: =(F677+G677)-AX677 -> 0 | BA677: =I677-AY677 -> 0
...

Sheet Relatório de Evidências
D2: RELATÓRIO DE EVIDÊNCIAS DOS SERVIÇOS EXECUTADOS | N2: PERÍODO DE MEDIÇÃO
N3: 01/06/25 a 30/06/2025
B4: RESPONSÁVEL: | D4: =[27]AEO!I34 -> GIOVANNI CENDES FINOTTI | J4: CONTATO | L4: =VLOOKUP(D4,[27]Contratos!L:N,3,0) -> +55 62 98102-0756 | N4: SI / AES | P4: =[27]AEO!L3 -> 03396-26
B5: EMPRESA | D5: =[27]AEO!D13 -> ENERGY SYSTEN CONSTRUCOES E MANUTEN | J5: CONTRATO | L5: =[27]AEO!B13 -> 4600027637 | N5: RC
B7: OBJETIVO | J7: REGISTRO FOTOGRÁFICO
B8: Comprovar a execuçãdo dos serviços prestados, bem como subsdiar a validação pela empresa contratante da medição (atividade/quantidade) e a qualidade dos referidos serviços. | J8: Fazer o registro de forma à se obter as comprovações devidas de acordo com as medições apresentadas tendo nas fotos o registro de data, coordenada da foto e nome da obra
B10: A | C10: ...Passo para inserir a foto | F10: B | G10: ...Passo para selecionar a foto | J10: C | K10: ...Passo para iniciar formatar | N10: D | O10: ...Passo para conf. tamanho
B11: Clique no campo onde deseja colar a foto, após |1| clique na Aba [Inserir] e em seguida |2| clique em Imagem... | F11: |3| Localize a pasta na qual está a foto, |4| selecione a foto desejada e |5| clique em [Inserir]... | J11: |6| Clique na foto inserida, em seguida |7|clique na Aba [Ferramentas de Imagem] e após |8| clique no icone |Tamanho|... | N11: ...tela aberta na parte |Tamanho e rotação| desmarque as |9| opções Fixar taxa... |10| e Relativo ao.., em seguida configura a |11| altura=9,6 e |12| largura=12,8...
B13: EVIDÊNCIAS FOTOGRÁFICAS
B14: 1 | C14: 5056000059 | D14: MOBIL. SER. PEQ. PORTE, DUR. MÁX. DE 30D | J14: OBS:
B16: ENQUADRAR A FOTO À ESSE ESPAÇO, OBEDECENDO AS DIMENSÕES. Para inserir e configurar a foto, siga as orientações que se encontram no campo passo-a-passo, caso esteja oculto, clique no [2] ao lado da coluna A do cabeçalho para reexibir.
B36: 2 | C36: 5054000014 | D36: EXECUTAR INTERLIGAÇÃO DE RELIGADOR | J36: OBS: | K36: 4124R
B38: ENQUADRAR A FOTO À ESSE ESPAÇO, OBEDECENDO AS DIMENSÕES. Para inserir e configurar a foto, siga as orientações que se encontram no campo passo-a-passo, caso esteja oculto, clique no [2] ao lado da coluna A do cabeçalho para reexibir.
B59: 3 | C59: 5054000015 | D59: EXECUTAR INTERLIGAÇÃO TR COM AUTOMAÇÃO | J59: OBS: | K59: TR2
B61: ENQUADRAR A FOTO À ESSE ESPAÇO, OBEDECENDO AS DIMENSÕES. Para inserir e configurar a foto, siga as orientações que se encontram no campo passo-a-passo, caso esteja oculto, clique no [2] ao lado da coluna A do cabeçalho para reexibir.
B81: 4 | C81: 5054000050 | D81: INTERLIGAR RELÉ MONTADO EM PAINEL | J81: OBS: | K81: RF4
B103: 5 | C103: 5054200003 | D103: EXEC INSTALAÇÃO COMPONENTES AUXILIARES | J103: OBS: | K103: RF4
B126: 6 | C126: 5054000029 | D126: ADEQUAÇÃO FIAÇÃO RELÉ PAINEL PROTEÇÃO | J126: OBS:
B128: ENQUADRAR A FOTO À ESSE ESPAÇO, OBEDECENDO AS DIMENSÕES. Para inserir e configurar a foto, siga as orientações que se encontram no campo passo-a-passo, caso esteja oculto, clique no [2] ao lado da coluna A do cabeçalho para reexibir.
B148: 7 | C148: 5054000023 | D148: LANÇAR CABOS ATÉ 10 CONDUTORES | J148: OBS:
B170: 8 | C170: 5054100005 | D170: LANÇAR CABO DE FIBRA ÓPTICA | J170: OBS:
B172: ENQUADRAR A FOTO À ESSE ESPAÇO, OBEDECENDO AS DIMENSÕES. Para inserir e configurar a foto, siga as orientações que se encontram no campo passo-a-passo, caso esteja oculto, clique no [2] ao lado da coluna A do cabeçalho para reexibir.
B193: 9 | C193: 5054100006 | D193: LANÇAMENTO DE CORDÃO DE FIBRA ÓPTICA | J193: OBS:
B195: ENQUADRAR A FOTO À ESSE ESPAÇO, OBEDECENDO AS DIMENSÕES. Para inserir e configurar a foto, siga as orientações que se encontram no campo passo-a-passo, caso esteja oculto, clique no [2] ao lado da coluna A do cabeçalho para reexibir.
B216: 10 | C216: 5500200926 | D216: IMPLANTAÇÃO DE AJUSTES E LÓGICAS EM RELÉS EXCETO 21 E 87 E 67 | J216: OBS: | K216: 2214, NOJA POWER 4124
B218: ENQUADRAR A FOTO À ESSE ESPAÇO, OBEDECENDO AS DIMENSÕES. Para inserir e configurar a foto, siga as orientações que se encontram no campo passo-a-passo, caso esteja oculto, clique no [2] ao lado da coluna A do cabeçalho para reexibir.
B239: 11 | C239: 5500300189 | D239: MANUTENÇÃO E TESTE EM RELE DISTÂNCIA (21), DIFERENCIAL (87), DIRECIONAL (67) | J239: OBS: | K239: 2214, NOJA POWER 4124
B241: ENQUADRAR A FOTO À ESSE ESPAÇO, OBEDECENDO AS DIMENSÕES. Para inserir e configurar a foto, siga as orientações que se encontram no campo passo-a-passo, caso esteja oculto, clique no [2] ao lado da coluna A do cabeçalho para reexibir.
B262: 12 | J262: OBS:
B264: ENQUADRAR A FOTO À ESSE ESPAÇO, OBEDECENDO AS DIMENSÕES. Para inserir e configurar a foto, siga as orientações que se encontram no campo passo-a-passo, caso esteja oculto, clique no [2] ao lado da coluna A do cabeçalho para reexibir.
B285: 13 | J285: OBS:
B287: ENQUADRAR A FOTO À ESSE ESPAÇO, OBEDECENDO AS DIMENSÕES. Para inserir e configurar a foto, siga as orientações que se encontram no campo passo-a-passo, caso esteja oculto, clique no [2] ao lado da coluna A do cabeçalho para reexibir. | J287: ENQUADRAR A FOTO À ESSE ESPAÇO, OBEDECENDO AS DIMENSÕES. Para inserir e configurar a foto, siga as orientações que se encontram no campo passo-a-passo, caso esteja oculto, clique no [2] ao lado da coluna A do cabeçalho para reexibir.
B308: 14 | J308: OBS:
B310: ENQUADRAR A FOTO À ESSE ESPAÇO, OBEDECENDO AS DIMENSÕES. Para inserir e configurar a foto, siga as orientações que se encontram no campo passo-a-passo, caso esteja oculto, clique no [2] ao lado da coluna A do cabeçalho para reexibir.
B331: 15 | J331: OBS:
B333: ENQUADRAR A FOTO À ESSE ESPAÇO, OBEDECENDO AS DIMENSÕES. Para inserir e configurar a foto, siga as orientações que se encontram no campo passo-a-passo, caso esteja oculto, clique no [2] ao lado da coluna A do cabeçalho para reexibir.
B354: 16 | J354: OBS:
B356: ENQUADRAR A FOTO À ESSE ESPAÇO, OBEDECENDO AS DIMENSÕES. Para inserir e configurar a foto, siga as orientações que se encontram no campo passo-a-passo, caso esteja oculto, clique no [2] ao lado da coluna A do cabeçalho para reexibir.
B377: 17 | J377: OBS:
B379: ENQUADRAR A FOTO À ESSE ESPAÇO, OBEDECENDO AS DIMENSÕES. Para inserir e configurar a foto, siga as orientações que se encontram no campo passo-a-passo, caso esteja oculto, clique no [2] ao lado da coluna A do cabeçalho para reexibir.
B400: 18 | J400: OBS:
B402: ENQUADRAR A FOTO À ESSE ESPAÇO, OBEDECENDO AS DIMENSÕES. Para inserir e configurar a foto, siga as orientações que se encontram no campo passo-a-passo, caso esteja oculto, clique no [2] ao lado da coluna A do cabeçalho para reexibir.
B423: 19 | J423: OBS:
B425: ENQUADRAR A FOTO À ESSE ESPAÇO, OBEDECENDO AS DIMENSÕES. Para inserir e configurar a foto, siga as orientações que se encontram no campo passo-a-passo, caso esteja oculto, clique no [2] ao lado da coluna A do cabeçalho para reexibir.
B446: 20 | J446: OBS:
B448: ENQUADRAR A FOTO À ESSE ESPAÇO, OBEDECENDO AS DIMENSÕES. Para inserir e configurar a foto, siga as orientações que se encontram no campo passo-a-passo, caso esteja oculto, clique no [2] ao lado da coluna A do cabeçalho para reexibir.
B469: 21 | J469: OBS:
B471: ENQUADRAR A FOTO À ESSE ESPAÇO, OBEDECENDO AS DIMENSÕES. Para inserir e configurar a foto, siga as orientações que se encontram no campo passo-a-passo, caso esteja oculto, clique no [2] ao lado da coluna A do cabeçalho para reexibir.
B492: 22 | J492: OBS:
B494: ENQUADRAR A FOTO À ESSE ESPAÇO, OBEDECENDO AS DIMENSÕES. Para inserir e configurar a foto, siga as orientações que se encontram no campo passo-a-passo, caso esteja oculto, clique no [2] ao lado da coluna A do cabeçalho para reexibir.
B515: 23 | J515: OBS:
B517: ENQUADRAR A FOTO À ESSE ESPAÇO, OBEDECENDO AS DIMENSÕES. Para inserir e configurar a foto, siga as orientações que se encontram no campo passo-a-passo, caso esteja oculto, clique no [2] ao lado da coluna A do cabeçalho para reexibir.
B538: 24 | J538: OBS:
B540: ENQUADRAR A FOTO À ESSE ESPAÇO, OBEDECENDO AS DIMENSÕES. Para inserir e configurar a foto, siga as orientações que se encontram no campo passo-a-passo, caso esteja oculto, clique no [2] ao lado da coluna A do cabeçalho para reexibir.
B561: 25 | J561: OBS:
B563: ENQUADRAR A FOTO À ESSE ESPAÇO, OBEDECENDO AS DIMENSÕES. Para inserir e configurar a foto, siga as orientações que se encontram no campo passo-a-passo, caso esteja oculto, clique no [2] ao lado da coluna A do cabeçalho para reexibir.
B584: 26 | J584: OBS:
B586: ENQUADRAR A FOTO À ESSE ESPAÇO, OBEDECENDO AS DIMENSÕES. Para inserir e configurar a foto, siga as orientações que se encontram no campo passo-a-passo, caso esteja oculto, clique no [2] ao lado da coluna A do cabeçalho para reexibir.
B607: 27 | J607: OBS:
B609: ENQUADRAR A FOTO À ESSE ESPAÇO, OBEDECENDO AS DIMENSÕES. Para inserir e configurar a foto, siga as orientações que se encontram no campo passo-a-passo, caso esteja oculto, clique no [2] ao lado da coluna A do cabeçalho para reexibir.
B630: 28 | J630: OBS:
B632: ENQUADRAR A FOTO À ESSE ESPAÇO, OBEDECENDO AS DIMENSÕES. Para inserir e configurar a foto, siga as orientações que se encontram no campo passo-a-passo, caso esteja oculto, clique no [2] ao lado da coluna A do cabeçalho para reexibir.
B653: 29 | J653: OBS:
B655: ENQUADRAR A FOTO À ESSE ESPAÇO, OBEDECENDO AS DIMENSÕES. Para inserir e configurar a foto, siga as orientações que se encontram no campo passo-a-passo, caso esteja oculto, clique no [2] ao lado da coluna A do cabeçalho para reexibir.
B676: 30 | J676: OBS:
B678: ENQUADRAR A FOTO À ESSE ESPAÇO, OBEDECENDO AS DIMENSÕES. Para inserir e configurar a foto, siga as orientações que se encontram no campo passo-a-passo, caso esteja oculto, clique no [2] ao lado da coluna A do cabeçalho para reexibir.
B699: 31 | J699: OBS:
B701: ENQUADRAR A FOTO À ESSE ESPAÇO, OBEDECENDO AS DIMENSÕES. Para inserir e configurar a foto, siga as orientações que se encontram no campo passo-a-passo, caso esteja oculto, clique no [2] ao lado da coluna A do cabeçalho para reexibir.
B722: 32 | J722: OBS:
B724: ENQUADRAR A FOTO À ESSE ESPAÇO, OBEDECENDO AS DIMENSÕES. Para inserir e configurar a foto, siga as orientações que se encontram no campo passo-a-passo, caso esteja oculto, clique no [2] ao lado da coluna A do cabeçalho para reexibir.
B745: 33 | J745: OBS:
B747: ENQUADRAR A FOTO À ESSE ESPAÇO, OBEDECENDO AS DIMENSÕES. Para inserir e configurar a foto, siga as orientações que se encontram no campo passo-a-passo, caso esteja oculto, clique no [2] ao lado da coluna A do cabeçalho para reexibir.
B768: 34 | J768: OBS:
B770: ENQUADRAR A FOTO À ESSE ESPAÇO, OBEDECENDO AS DIMENSÕES. Para inserir e configurar a foto, siga as orientações que se encontram no campo passo-a-passo, caso esteja oculto, clique no [2] ao lado da coluna A do cabeçalho para reexibir.
C791: NOTAS/OBSERVAÇÕES:
J796: Responsável pelo relatório

Sheet MSRV5
A1: Chave | B1: Nº de serviço | C1: Texto breve | D1: UM básica | E1: Preço bruto | F1: Nº linha | G1: Nº de documento | H1: Item | I1: Código de eliminação
A2: =G2&H2&B2&D2 -> 4600027637305045500016KM | B2: 5045500016 | C2: MOB/DESMOBIL LD DE 201 A 400KM LD LM PDE | D2: KM | E2: 383.96 | F2: 40 | G2: 4600027637 | H2: 30
A3: =G3&H3&B3&D3 -> 4600027637305045500013KM | B3: 5045500013 | C3: MOB/DESMOBILIZ LD DE 0 A 50KM LD LM PDE | D3: KM | E3: 615.33 | F3: 10 | G3: 4600027637 | H3: 30
A4: =G4&H4&B4&D4 -> 4600027637305045500014KM | B4: 5045500014 | C4: MOB/DESMOBIL LD DE 51 A 200KM LD LM PDE | D4: KM | E4: 672.31 | F4: 20 | G4: 4600027637 | H4: 30
A5: =G5&H5&B5&D5 -> 4600027637305045500015KM | B5: 5045500015 | C5: MOB/DESMOBIL LD ACIMA DE 600KM LD LM PDE | D5: KM | E5: 216.59 | F5: 30 | G5: 4600027637 | H5: 30
A6: =G6&H6&B6&D6 -> 4600027637305045500019CDA | B6: 5045500019 | C6: DESMOBIL 0 A 200KM EQP 5H RESIT OHM LD | D6: CDA | E6: 135.37 | F6: 50 | G6: 4600027637 | H6: 30
A7: =G7&H7&B7&D7 -> 4600027637305045500020CDA | B7: 5045500020 | C7: DESMOBIL 0 A 200KM EQP 5H SERV TEC LD | D7: CDA | E7: 172.29 | F7: 60 | G7: 4600027637 | H7: 30
A8: =G8&H8&B8&D8 -> 4600027637305045500021CDA | B8: 5045500021 | C8: DESMOBIL 201 A 400KM EQP 5H RESIT OHM LD | D8: CDA | E8: 209.23 | F8: 70 | G8: 4600027637 | H8: 30
A9: =G9&H9&B9&D9 -> 4600027637305045500022CDA | B9: 5045500022 | C9: DESMOBIL 201 A 400KM EQP 5H SERV TEC LD | D9: CDA | E9: 19.7 | F9: 80 | G9: 4600027637 | H9: 30
A10: =G10&H10&B10&D10 -> 4600027637305045500023CDA | B10: 5045500023 | C10: DESMOBIL 401 A 600KM EQP 5H RESIT OHM LD | D10: CDA | E10: 295.35 | F10: 90 | G10: 4600027637 | H10: 30
A11: =G11&H11&B11&D11 -> 4600027637305045500024CDA | B11: 5045500024 | C11: DESMOBIL 401 A 600KM EQP 5H SERV TEC LD | D11: CDA | E11: 295.35 | F11: 100 | G11: 4600027637 | H11: 30
A12: =G12&H12&B12&D12 -> 4600027637305045500030CDA | B12: 5045500030 | C12: DESMOBILIZAR 201 A 400KM EQP 5H SOND LD | D12: CDA | E12: 315.04 | F12: 110 | G12: 4600027637 | H12: 30
A13: =G13&H13&B13&D13 -> 4600027637305045500031CDA | B13: 5045500031 | C13: DESMOBILIZAR 201 A 400KM EQP 5H TOPOG LD | D13: CDA | E13: 2707.41 | F13: 120 | G13: 4600027637 | H13: 30
... A30: =G30&H30&B30&D30 -> 4600027637305045500050CDA | B30: 5045500050 | C30: MOBILIZAR 401 A 600KM EQP 5H SERV TEC LD | D30: CDA | E30: 1722.9 | F30: 280 | G30: 4600027637 | H30: 30
A31: =G31&H31&B31&D31 -> 4600027637305045500051CDA | B31: 5045500051 | C31: MOBILIZAR 401 A 600KM EQP 5H SOND LD | D31: CDA | E31: 11937.23 | F31: 290 | G31: 4600027637 | H31: 30 | I31: L
A32: =G32&H32&B32&D32 -> 4600027637305045500053CDA | B32: 5045500053 | C32: MOBILIZAR ACIMA 600KM EQ5H RESIT OHM LD | D32: CDA | E32: 4922.57 | F32: 310 | G32: 4600027637 | H32: 30
A33: =G33&H33&B33&D33 -> 4600027637305045500054CDA | B33: 5045500054 | C33: MOBILIZAR ACIMA 600KM EQP 5H SERV TEC LD | D33: CDA | E33: 3691.93 | F33: 320 | G33: 4600027637 | H33: 30
A34: =G34&H34&B34&D34 -> 4600027637305045500056CDA | B34: 5045500056 | C34: MOBILIZAR ACIMA 600KM EQP 5H TOPOG LD | D34: CDA | E34: 1230.64 | F34: 330 | G34: 4600027637 | H34: 30
A35: =G35&H35&B35&D35 -> 4600027637305045500057CDA | B35: 5045500057 | C35: MOBILIZAR REG ISOL EQP 5H RESIT OHM LD | D35: CDA | E35: 2707.41 | F35: 340 | G35: 4600027637 | H35: 30
A36: =G36&H36&B36&D36 -> 4600027637305050200037UN | B36: 5050200037 | C36: INSTALAR PLACA DE IDENTIFICACAO DA SE | D36: UN | E36: 1378.32 | F36: 350 | G36: 4600027637 | H36: 30
A37: =G37&H37&B37&D37 -> 4600027637305056000040KM | B37: 5056000040 | C37: DESMOB EQUIPE E MAQ. ATE 200KM | D37: KM | E37: 19.15 | F37: 360 | G37: 4600027637 | H37: 30
A38: =G38&H38&B38&D38 -> 4600027637305056000041KM | B38: 5056000041 | C38: Desmob equipe e maq. De 201km a 400km | D38: KM | E38: 16.2 | F38: 370 | G38: 4600027637 | H38: 30
A39: =G39&H39&B39&D39 -> 4600027637305056000046UA | B39: 5056000046 | C39: DESMOBILIZAR OBRA DE PEQUENO PORTE | D39: UA | E39: 2561.67 | F39: 380 | G39: 4600027637 | H39: 30
A40: =G40&H40&B40&D40 -> 4600027637305056000044UA | B40: 5056000044 | C40: Desmobilizar Obra de Grande Porte | D40: UA | E40: 11859.55 | F40: 390 | G40: 4600027637 | H40: 30
A41: =G41&H41&B41&D41 -> 4600027637305056000045UA | B41: 5056000045 | C41: DESMOBILIZAR OBRA DE MEDIO PORTE | D41: UA | E41: 6085.41 | F41: 400 | G41: 4600027637 | H41: 30
A42: =G42&H42&B42&D42 -> 4600027637305056000061UA | B42: 5056000061 | C42: MOB/DES EQUIP OBRA MEDIO PORTE LD LM PDE | D42: UA | E42: 17041.68 | F42: 440 | G42: 4600027637 | H42: 30
A43: =G43&H43&B43&D43 -> 4600027637305056000043UA | B43: 5056000043 | C43: DESMOB EQUIPE E MAQ. NA CAPITAL | D43: UA | E43: 3120.52 | F43: 410 | G43: 4600027637 | H43: 30
... A914: =G914&H914&B914&D914 -> 4600027637305022000251un | B914: 5022000251 | C914: RET FLY TAP /CRUZAM AEREO LM | D914: un | E914: 222.01 | F914: 9180 | G914: 4600027637 | H914: 30

Sheet CN43N
A1: Level | B1: Definição do projeto | C1: WBS element | D1: Name | E1: Status
A2: 2 | B2: AL-2361108GTA0 | C2: AL-2361108GTA0.A | D2: EQTL-AL>SE GTA>69KV>NOVA SE | E2: LBPA DISP // ABER
A3: 2 | B3: AL-2361108GTA0 | C3: AL-2361108GTA0.D | D3: EQTL-AL>SE SRR>69KV>AMP SE | E3: LBPA DISP // ABER
A4: 2 | B4: AL-2361208ARQ0 | C4: AL-2361208ARQ0.B | D4: EQTL-AL>SE ARQ>69KV>NOVA SE | E4: LBPA DISP // ABER
A5: 2 | B5: AL-2361208ARQ0 | C5: AL-2361208ARQ0.C | D5: EQTL-AL>SE ARD>69KV>AMP | E5: LBPA DISP // ABER
A6: 2 | B6: AL-2430208AMP0 | C6: AL-2430208AMP0.C | D6: EQTL-AL>SE SRR>AMP POT | E6: LBPA DISP // ABER
A7: 2 | B7: AL-2430208AMP0 | C7: AL-2430208AMP0.B | D7: EQTL-AL>SE CDU>AMP POT | E7: LBPA DISP // ABER
A8: 2 | B8: AL-2430608PND0 | C8: AL-2430608PND0.B | D8: EQTL-AL>SE PEN>69KV>EL | E8: LBPA DISP // ABER
A9: 2 | B9: AL-2430808CAT0 | C9: AL-2430808CAT0.B | D9: EQTL-AL>SE PCA>69KV>NOVA EL | E9: LBPA DISP // ABER
A10: 2 | B10: AL-2430808CAT0 | C10: AL-2430808CAT0.D | D10: EQTL-AL>SE JDH>13,8KV>NOVA EL | E10: LBPA DISP // ABER
A11: 2 | B11: AL-2430808CAT0 | C11: AL-2430808CAT0.E | D11: EQTL-AL>SE PIL>13,8KV>NOVA EL | E11: LBPA DISP // ABER
A12: 2 | B12: AL-2431308MOP0 | C12: AL-2431308MOP0.A | D12: EQTL-AL>SE VIS>69KV>AMP | E12: LBPA DISP // ABER
... A902: 2 | B902: RS-2562408CH30 | C902: RS-2562408CH30.C | D902: EQTL-RS>2025>SMF SE CHAR3 | E902: LBPA DISP // ABER

Sheet Portifólio
A1: EMPRESA | B1: TIPO DE OBRA | C1: DEMANDANTE | D1: PI | E1: DESCRIÇÃO PI | F1: PEP | G1: DESCRIÇÃO RESUMIDA DA OBRA | H1: SEGMENTO | I1: INSTALAÇÃO | J1: ESCOPO MODULAR | K1: COMPLEMENTO ESCOPO | L1: EXPECTATIVA ENERGIZAÇÃO DEMANDANTE | M1: EXPECTATIVA ENERGIZAÇÃO CRONOGRAMA | N1: ORÇAMENTO APROVADO 2025 | O1: ORÇAMENTO NECESSIDADE GLOBAL | P1: ORÇAMENTO NECESSIDADE < 2025 | Q1: ORÇAMENTO NECESSIDADE 2025 | R1: ORÇAMENTO NECESSIDADE > 2025 | S1: ESCOPO 2023 | T1: ESCOPO 2024 | U1: ESCOPO 2025 | V1: ESCOPO 2026 | W1: REGIONAL | X1: MUNICÍPIO | Y1: UF | Z1: LATITUDE | AA1: LONGITUDE | AB1: FASE | AC1: ESTRATÉGIA DE CONTRATAÇÃO | AD1: ID CAPEX
A2: EQTL AL | B2: AMPLIAÇÃO DE POTÊNCIA | C2: Planejamento | D2: 804.110.0302 | E2: AMPLIAÇÃO DE SUBESTAÇÕES | F2: AL-2430208AMP0.B | G2: PLANEJAMENTO - AMPLIAÇÃO DE POTÊNCIA - SE CIDADE UNIVERSITÁRIA - 2025 | H2: SE | I2: SE CIDADE UNIVERSITÁRIA | J2: 2,00 x CONEXÃO DE TRAFO 69kV c/ DJ + 1,00 x CONEXÃO DE TRAFO 13,8kV c/ DJ + 1,00 x BARRAMENTO SIMPLES 69kV + 4,00 x BARRAMENTO DUPLO OU BPT 13,8kV + 1,00 x INSTALAÇÃO DE TRANSFORMADOR DE FORÇA ATÉ 40MVA + 1,00 x BARRAMENTO SIMPLES 13,8kV + 1,00 x TRANSFORMADOR DE FORÇA 69/13,8kV 20,0/26,6MVA - DYN1 | L2: 45697.125 | M2: 45811 | N2: 5679942.4 | O2: 5889838.8 | P2: 209896.36 | Q2: 5679942.4 | R2: 0 | S2: - | T2: EXECUÇÃO | U2: FINALIZAÇÃO | V2: - | W2: LESTE - AL | Y2: AL | Z2: -9.67 | AA2: -35.74 | AB2: Mobilização | AC2: -
A3: EQTL AL | B3: AMPLIAÇÃO DE POTÊNCIA | C3: Planejamento | D3: 804.110.0302 | E3: AMPLIAÇÃO DE SUBESTAÇÕES | F3: AL-2430208AMP0.C | G3: PLANEJAMENTO - AMPLIAÇÃO DE POTÊNCIA - SE SERRARIA - 2025 | H3: SE | I3: SE SERRARIA | J3: 1,00 x TRANSFORMADOR DE FORÇA 69/13,8kV 20,0/26,6MVA - DYN1 | K3: O TRF atualmente utilizado na SE SERRARIA veio da EQTL Goiás para atender a uma demanda emergencial de carga originada da SE PINHEIRO. Inicialmente, esse equipamento seria destinado a compor a reserva técnica de manutenção, porém, foi alocado de forma emergencial para suprir essa necessidade específica. Este projeto tem como objetivo repor a reserva técnica da manutenção. | L3: 46022 | M3: 46355 | N3: 0 | O3: 2957441.6 | P3: 71426.06 | Q3: 0 | R3: 2886015.5 | S3: - | T3: - | U3: EXECUÇÃO | V3: FINALIZAÇÃO | W3: LESTE - AL | Y3: AL | Z3: -9.67 | AA3: -35.74 | AB3: Preliminar | AC3: -
A4: EQTL AL | B4: AQUISIÇÃO DE TRAFO | C4: Manutenção | D4: 804.110.0316 | E4: AQUISIÇÃO DE TRANSFORMADOR DE FORÇA | F4: AL-2431608ATF0.A | G4: MANUTENÇÃO - AQUISIÇÃO DE TRAFO - SE PAJUÇARA - 2025 | H4: SE | I4: SE PAJUÇARA | J4: 2,00 x SUBST. DE CONJUNTO TCs 13,8kV + 2,00 x TRANSFORMADOR DE FORÇA 69/13,8kV 15,0/20MVA - DYN1 + 2,00 x INSTALAÇÃO DE TRANSFORMADOR DE FORÇA ATÉ 40MVA | K4: Incluso a construção de uma parede corta-fogo entre os TRF's, além da regularização das bases e da construção de suas respectivas CSO's. | L4: 45919 | M4: 45990 | N4: 617824.32 | O4: 5253002.1 | P4: 4635177.8 | Q4: 617824.32 | R4: 0 | S4: - | T4: EXECUÇÃO | U4: FINALIZAÇÃO | V4: - | W4: LESTE - AL | Y4: AL | Z4: -9.67 | AA4: -35.74 | AB4: Mobilização | AC4: -
A5: EQTL AL | B5: BANCO DE CAPACITORES | C5: Planejamento | D5: 804.110.0301 | E5: EQUIPAMENTOS DE COMPENSAÇÃO DE REATIVOS | F5: AL-2530108BCA0.A | G5: PLANEJAMENTO - BANCO DE CAPACITORES - SE CIDADE UNIVERSITÁRIA - 2025 | H5: SE | I5: SE CIDADE UNIVERSITÁRIA | J5: 1,00 x BANCO DE CAPACITOR 3,6MVAr - 13,8kV + 1,00 x BARRAMENTO SIMPLES 13,8kV + 1,00 x CONEXÃO DE BANCO DE CAPACITOR 13,8kV c/ DJ | K5: ADIÇÃO BC 3,6 MVAR | L5: 45992 | M5: 45897 | N5: 700000 | O5: 719328.46 | P5: 19328.46 | Q5: 700000 | R5: 0 | S5: - | T5: - | U5: EXECUÇÃO | V5: - | W5: LESTE - AL | Y5: AL | Z5: -9.67 | AA5: -35.74 | AB5: Mobilização | AC5: -
A6: EQTL AL | B6: BANCO DE CAPACITORES | C6: Planejamento | D6: 804.110.0301 | E6: EQUIPAMENTOS DE COMPENSAÇÃO DE REATIVOS | F6: AL-2530108BCA0.B | G6: PLANEJAMENTO - BANCO DE CAPACITORES - SE PAJUÇARA - 2025 | H6: SE | I6: SE PAJUÇARA | J6: 1,00 x BANCO DE CAPACITOR 3,6MVAr - 13,8kV + 1,00 x BARRAMENTO SIMPLES 13,8kV + 1,00 x CONEXÃO DE BANCO DE CAPACITOR 13,8kV c/ DJ | K6: ADIÇÃO BC 3,6 MVAR | L6: 45992 | M6: 45941 | N6: 1000000 | O6: 1019328.5 | P6: 19328.46 | Q6: 1000000 | R6: 0 | S6: - | T6: - | U6: EXECUÇÃO | V6: - | W6: LESTE - AL | Y6: AL | Z6: -9.67 | AA6: -35.74 | AB6: Projeto Básico | AC6: -
A7: EQTL AL | B7: BAY | C7: Planejamento | D7: 804.110.0300 | E7: IMPLANTAÇÃO DE BAYS DE ALIMENTADORES | F7: AL-2530008BAY0.A | G7: PLANEJAMENTO - BAY - SE CORURIPE - 2025 | H7: SE | I7: SE CORURIPE | J7: 1,00 x BARRAMENTO SIMPLES 13,8kV + 1,00 x ENTRADA DE LINHA 13,8kV c/ DJ | L7: 46020.125 | M7: 45924 | N7: 590559.48 | O7: 590559.48 | P7: 0 | Q7: 590559.48 | R7: 0 | S7: - | T7: - | U7: EXECUÇÃO | V7: - | W7: OESTE - AL | Y7: AL | Z7: -10.13 | AA7: -36.18 | AB7: Projeto Básico | AC7: Pacote SE - Oeste
A8: EQTL AL | B8: BAY | C8: Planejamento | D8: 804.110.0300 | E8: IMPLANTAÇÃO DE BAYS DE ALIMENTADORES | F8: AL-2530008BAY0.B | G8: PLANEJAMENTO - BAY - SE DELMIRO GOUVEIA - 2025 | H8: SE | I8: SE DELMIRO GOUVEIA | J8: 1,00 x BARRAMENTO SIMPLES 13,8kV + 1,00 x ENTRADA DE LINHA 13,8kV c/ DJ | L8: 46020.125 | M8: 46014 | N8: 523297.12 | O8: 523297.12 | P8: 0 | Q8: 523297.12 | R8: 0 | S8: - | T8: - | U8: EXECUÇÃO | V8: - | W8: OESTE - AL | Y8: AL | Z8: -9.38 | AA8: -37.99 | AB8: Projeto Básico | AC8: Pacote SE - Oeste
A9: EQTL AL | B9: BAY | C9: Planejamento | D9: 804.110.0300 | E9: IMPLANTAÇÃO DE BAYS DE ALIMENTADORES | F9: AL-2530008BAY0.D | G9: PLANEJAMENTO - BAY - SE SÃO MIGUEL DOS CAMPOS - 2025 | H9: SE | I9: SE SÃO MIGUEL DOS CAMPOS | J9: 1,00 x BARRAMENTO SIMPLES 13,8kV + 1,00 x ENTRADA DE LINHA 13,8kV c/ DJ | L9: 46020.125 | M9: 45961 | N9: 590559.48 | O9: 590559.48 | P9: 0 | Q9: 590559.48 | R9: 0 | S9: - | T9: - | U9: EXECUÇÃO | V9: - | W9: LESTE - AL | Y9: AL | Z9: -9.77 | AA9: -36.09 | AB9: Projeto Básico | AC9: Pacote SE - Oeste
A10: EQTL AL | B10: BAY | C10: Planejamento | D10: 804.110.0300 | E10: IMPLANTAÇÃO DE BAYS DE ALIMENTADORES | F10: AL-2530008BAY0.E | G10: PLANEJAMENTO - BAY - SE SERRARIA - 2025 | H10: SE | I10: SE SERRARIA | J10: 1,00 x ENTRADA DE LINHA 13,8kV CUBÍCULO BS | L10: 46020.125 | M10: 46097 | N10: 146508.1 | O10: 590559.48 | P10: 0 | Q10: 146508.1 | R10: 444051.38 | S10: - | T10: - | U10: EXECUÇÃO | V10: - | W10: LESTE - AL | Y10: AL | Z10: -9.67 | AA10: -35.74 | AB10: Projeto Básico | AC10: Pacote SE - Oeste
A11: EQTL AL | B11: BAY | C11: Planejamento | D11: 804.110.0300 | E11: IMPLANTAÇÃO DE BAYS DE ALIMENTADORES | F11: AL-2530008BAY0.F | G11: PLANEJAMENTO - BAY - SE UNIÃO DOS PALMARES - 2025 | H11: SE | I11: SE UNIÃO DOS PALMARES | J11: 1,00 x BARRAMENTO SIMPLES 13,8kV + 1,00 x ENTRADA DE LINHA 13,8kV c/ DJ | L11: 45992.125 | M11: 46027 | N11: 1014150.2 | O11: 1114464.9 | P11: 0 | Q11: 1014150.2 | R11: 100314.71 | S11: - | T11: - | U11: EXECUÇÃO | V11: - | W11: LESTE - AL | Y11: AL | Z11: -9.16 | AA11: -36.03 | AB11: Projeto Básico | AC11: Pacote SE - Oeste
A12: EQTL AL | B12: ENTRADA DE LINHA | C12: Manutenção | D12: 804.110.0306 | E12: IMPLANTAÇÃO DE NOVAS LDs | F12: AL-2430608PND0.B | G12: MANUTENÇÃO - ENTRADA DE LINHA - SE MARITUBA - 2025 | H12: SE | I12: SE MARITUBA | J12: 1,00 x ENTRADA DE LINHA 69kV c/ DJ | L12: 46022 | M12: 45999 | N12: 855547 | O12: 855547 | P12: 0 | Q12: 855547 | R12: 0 | S12: - | T12: - | U12: EXECUÇÃO | V12: - | W12: OESTE - AL | Y12: AL | Z12: -10.28 | AA12: -36.4 | AB12: Módulo
A13: EQTL AL | B13: ENTRADA DE LINHA | C13: Manutenção | D13: 804.110.0311 | E13: Implantação de Novas LDs | F13: AL-2531108MCH0.B | G13: MANUTENÇÃO - ENTRADA DE LINHA - SE MARECHAL DEODORO - 2025 | H13: SE | I13: SE MARECHAL DEODORO | J13: 1,00 x BARRAMENTO SIMPLES 69kV + 1,00 x ENTRADA DE LINHA 69kV c/ DJ | L13: 46022.125 | M13: 45993 | N13: 865893.37 | O13: 962103.75 | P13: 0 | Q13: 865893.37 | R13: 96210.38 | S13: - | T13: - | U13: EXECUÇÃO | V13: - | W13: OESTE - AL | Y13: AL | Z13: -9.71 | AA13: -35.9 | AB13: Projeto Básico | AC13: PACOTE SE - LESTE
A14: EQTL AL | B14: ENTRADA DE LINHA | C14: Manutenção | D14: 804.110.0313 | E14: Melhorias Operacionais | F14: AL-2431308MOP0.A | G14: MANUTENÇÃO - ENTRADA DE LINHA - SE VIÇOSA - 2025 | H14: SE | I14: SE VIÇOSA | J14: 1,00 x ENTRADA DE LINHA 69kV c/ DJ | K14: INSTALAÇÃO DE BAY DE ENTRADA DE LINHA - TENSÃO 69KV | L14: 45868 | M14: 45723 | N14: 1320000.7 | O14: 1661419.3 | P14: 341418.61 | Q14: 1320000.7 | R14: 0 | S14: - | T14: EXECUÇÃO | U14: FINALIZAÇÃO | V14: - | W14: OESTE - AL | Y14: AL | Z14: -9.37 | AA14: -36.24 | AB14: Execução | AC14: -
A15: EQTL AL | B15: MELHORIA SE | C15: Manutenção | D15: 804.110.0313 | E15: Melhorias Operacionais | F15: AL-2531308MOP0.A | G15: MANUTENÇÃO - MELHORIA SE - SE ARAPIRACA I - 2025 | H15: SE | I15: SE ARAPIRACA I | J15: 1,00 x BARRAMENTO DUPLO OU BPT 69kV + 2,00 x CONEXÃO DE TRAFO 69kV c/ DJ + 4,00 x ENTRADA DE LINHA 69kV c/ DJ + 1,00 x INTERLIGAÇÃO DE BARRAS 69kV c/ DJ + 0,50 x MIG 69/34,5kV e MIG 69/13,8kV PEQUENO | K15: 12J5, 12J2, 12J4, 12J3, 12T1, 12T2 | L15: 46022.125 | M15: 46137 | N15: 5019967.9 | O15: 9168327.5 | P15: 0 | Q15: 5019967.9 | R15: 4148359.6 | S15: - | T15: - | U15: EXECUÇÃO | V15: FINALIZAÇÃO | W15: OESTE - AL | Y15: AL | Z15: -9.75 | AA15: -36.65 | AB15: Projeto Básico | AC15: Pacote Oeste Nova SE 25/26
A16: EQTL AL | B16: RETROFIT | C16: Automação | D16: 804.110.0317 | E16: OBRAS AUTOMAÇÃO SE | F16: AL-2531708ASE0.A | G16: AUTOMAÇÃO - RETROFIT - SE CAPELA - 2025 | H16: AUT | I16: SE CAPELA | J16: 1,00 x CONSTRUÇÃO DE CASA DE COMANDO + 1,00 x RETROFIT BANCO CAPACITOR <= 34,5KV + 4,00 x RETROFIT BAY ALIMENTADOR + 1,00 x RETROFIT BAY CONEXÃO ALTA TRAFO + 2,00 x RETROFIT BAY CONEXÃO BAIXA TRAFO + 1,00 x RETROFIT BAY CONEXÃO BANCO CAPACITOR >= 69kV - 751A + 4,00 x RETROFIT BAY ENTRADA DE LINHA - 751.4 + 1,00 x RETROFIT BAY TRANSFERÊNCIA >= 69kV - 311C + 1,00 x RETROFIT INFRA. SE GRANDE PORTE + 2,00 x RETROFIT TRANSFORMADOR FORÇA | K16: 02T1, 02T2, 11H2, 11T1, 11T2, 12D2, 12J4, 12J5, 12T1, 12V1, 12V3, 21Y2, 21Y3, 21Y4, 21Y5, 51H1 | L16: 46020.125 | M16: 45992 | N16: 2834712.4 | O16: 2834712.4 | P16: 0 | Q16: 2834712.4 | R16: 0 | S16: - | T16: - | U16: EXECUÇÃO | V16: - | W16: LESTE - AL | Y16: AL | Z16: -9.71 | AA16: -36.07 | AB16: Módulo | AC16: -
A17: EQTL AL | B17: RETROFIT | C17: Automação | D17: 804.110.0317 | E17: OBRAS AUTOMAÇÃO SE | F17: AL-2531708ASE0.B | G17: AUTOMAÇÃO - RETROFIT - SE MATRIZ DE CAMARAGIBE - 2025 | H17: AUT | I17: SE MATRIZ DE CAMARAGIBE | J17: 2,00 x RETROFIT BANCO CAPACITOR <= 34,5KV + 4,00 x RETROFIT BAY ALIMENTADOR + 1,00 x RETROFIT BAY CONEXÃO ALTA TRAFO + 1,00 x RETROFIT BAY CONEXÃO BAIXA TRAFO + 1,00 x RETROFIT BAY TRANSFERÊNCIA >= 69kV - 311C + 1,00 x RETROFIT INFRA. SE GRANDE PORTE + 1,00 x RETROFIT TRANSFORMADOR FORÇA + 5,00 x RETROFIT BAY ENTRADA DE LINHA - 311C + 1,00 x RETROFIT BAY CONEXÃO BANCO CAPACITOR <= 34,5kV | K17: 12V2, 12L3,12L4, 12V3, 12V4, 12D1,12T1, 02T1, 11T1, 51H1, 11H2, 51H2, 21Y4, 21Y3, 21Y2, 21Y1. | L17: 46020.125 | M17: 45992 | N17: 2461847.4 | O17: 2461847.4 | P17: 0 | Q17: 2461847.4 | R17: 0 | S17: - | T17: - | U17: EXECUÇÃO | V17: - | W17: LESTE - AL | Y17: AL | Z17: -9.18 | AA17: -35.52 | AB17: Módulo | AC17: -
A18: EQTL AL | B18: RETROFIT | C18: Automação | D18: 804.110.0317 | E18: OBRAS AUTOMAÇÃO SE | F18: AL-2531708ASE0.C | G18: AUTOMAÇÃO - RETROFIT - SE PORTO CALVO - 2025 | H18: AUT | I18: SE PORTO CALVO | J18: 1,00 x RETROFIT - 2414 + 1,00 x RETROFIT BANCO CAPACITOR <= 34,5KV + 1,00 x RETROFIT BAY CONEXÃO ALTA TRAFO + 2,00 x RETROFIT BAY ENTRADA DE LINHA - 311C + 2,00 x RETROFIT BAY ENTRADA DE LINHA - 751.4 + 1,00 x RETROFIT INFRA. SE GRANDE PORTE + 2,00 x RETROFIT TRANSFORMADOR FORÇA | K18: 02T1-2, 12V5, 12V4, 12L4, 12V3, 12T1, 02T1-1, 02T1-2, 51H1 | L18: 46020.125 | M18: 45962 | N18: 1442280.3 | O18: 1442280.3 | P18: 0 | Q18: 1442280.3 | R18: 0 | S18: - | T18: - | U18: EXECUÇÃO | V18: - | W18: LESTE - AL | Y18: AL | Z18: -9.05 | AA18: -35.4 | AB18: Módulo | AC18: -
A19: EQTL AL | B19: RETROFIT | C19: Automação | D19: 804.110.0317 | E19: OBRAS AUTOMAÇÃO SE | F19: AL-2531708ASE0.D | G19: AUTOMAÇÃO - RETROFIT - SE SÃO MIGUEL DOS CAMPOS - 2025 | H19: AUT | I19: SE SÃO MIGUEL DOS CAMPOS | J19: 2,00 x RETROFIT - 2414 | K19: 02T1 e 02T2 | L19: 46020.125 | M19: 45902 | N19: 108229.09 | O19: 108229.09 | P19: 0 | Q19: 108229.09 | R19: 0 | S19: - | T19: - | U19: EXECUÇÃO | V19: - | W19: LESTE - AL | Y19: AL | Z19: -9.77 | AA19: -36.09 | AB19: Módulo | AC19: -
A20: EQTL AL | B20: RETROFIT | C20: Automação | D20: 804.110.0317 | E20: OBRAS AUTOMAÇÃO SE | F20: AL-2531708ASE0.F | G20: AUTOMAÇÃO - RETROFIT - SE UNIÃO DOS PALMARES - 2025 | H20: AUT | I20: SE UNIÃO DOS PALMARES | J20: 1,00 x RETROFIT - 2414 + 1,00 x RETROFIT TRANSFORMADOR FORÇA | K20: 02T1-1 | L20: 46020.125 | M20: 45951 | N20: 54114.54 | O20: 54114.54 | P20: 0 | Q20: 54114.54 | R20: 0 | S20: - | T20: - | U20: EXECUÇÃO | V20: - | W20: LESTE - AL | Y20: AL | Z20: -9.16 | AA20: -36.03 | AB20: Módulo | AC20: -
A21: EQTL AL | B21: AMPLIAÇÃO DE SUBESTAÇÃO | C21: Planejamento | D21: 804.120.0611 | E21: PROJETO GRUTA SE 69 Kv | F21: AL-2361108GTA0.D | G21: PLANEJAMENTO - AMPLIAÇÃO DE SUBESTAÇÃO - SE SERRARIA - 2025 | H21: SE | I21: SE SERRARIA | J21: 1,00 x CONEXÃO DE TRAFO 69kV c/ DJ + 1,00 x CONEXÃO DE TRAFO 13,8kV CUBÍCULO BS + 1,00 x CONEXÃO DE BANCO DE CAPACITOR 13,8kV CUBÍCULO BS + 2,00 x ENTRADA DE LINHA 13,8kV CUBÍCULO BS | L21: 45745.125 | M21: 45945 | N21: 4509050.8 | O21: 4546333.7 | P21: 37282.98 | Q21: 4509050.8 | R21: 0 | S21: - | T21: ETAPA PRELIMINAR | U21: EXECUÇÃO | V21: - | W21: LESTE - AL | Y21: AL | Z21: -9.67 | AA21: -35.74 | AB21: Preliminar | AC21: -
A22: EQTL AL | B22: NOVA SE | C22: Planejamento | D22: 804.120.0611 | E22: PROJETO GRUTA SE 69 Kv | F22: AL-2361108GTA0.A | G22: PLANEJAMENTO - NOVA SE - SE GRUTA - 2025 | H22: SE | I22: SE GRUTA | J22: 2,00 x BANCO DE CAPACITOR 3,6MVAr - 13,8kV + 4,00 x BARRAMENTO DUPLO OU BPT 13,8kV + 2,00 x BARRAMENTO DUPLO OU BPT 69kV + 1,00 x BARRAMENTO SIMPLES 69kV - SE MÓVEL + 2,00 x CONEXÃO DE BANCO DE CAPACITOR 13,8kV c/ DJ + 2,00 x CONEXÃO DE TRAFO 13,8kV c/ DJ + 2,00 x CONEXÃO DE TRAFO 69kV c/ DJ + 8,00 x ENTRADA DE LINHA 13,8kV c/ DJ + 3,00 x ENTRADA DE LINHA 69kV c/ DJ + 2,00 x INSTALAÇÃO DE TRANSFORMADOR DE FORÇA ATÉ 40MVA + 1,00 x INTERLIGAÇÃO DE BARRAS BPT 13,8kV c/ DJ + 1,00 x INTERLIGAÇÃO DE BARRAS 69kV c/ DJ + 1,00 x MIG 69/34,5kV e MIG 69/13,8kV GRANDE + 1,00 x TRANSFORMADOR DE FORÇA 69/13,8kV 20,0/26,6MVA - DYN1 | K22: REUTILIZAR OS 1X15/20MVA DA SE PNO; 2X3.6MVAR; 3XEL69KV (2XTBM;1CTO); 8XEL13.8KV (8XAL; 2XBC); 2XCT 69KV; 2XCT 13,8KV | L22: 45777 | M22: 46094 | N22: 23843489 | O22: 32693480 | P22: 3659537.1 | Q22: 23843489 | R22: 5190453.2 | S22: - | T22: ETAPA PRELIMINAR | U22: EXECUÇÃO | V22: - | W22: LESTE - AL | Y22: AL | Z22: -9.67 | AA22: -35.74 | AB22: Preliminar | AC22: -
A23: EQTL AL | B23: NOVA SE | C23: Planejamento | D23: 804.120.0608 | E23: Projeto Nova SE Cânions 69/13,8 kV | F23: AL-2560808CNO0.A | G23: PLANEJAMENTO - NOVA SE - SE CÂNIONS - 2026 | H23: SE | I23: SE CÂNIONS | J23: 1,00 x BANCO DE CAPACITOR 3,6MVAr - 13,8kV + 3,00 x BARRAMENTO SIMPLES 13,8kV + 1,00 x BARRAMENTO SIMPLES 69kV + 1,00 x BARRAMENTO SIMPLES 69kV - SE MÓVEL + 1,00 x CONEXÃO DE BANCO DE CAPACITOR 13,8kV c/ DJ + 1,00 x CONEXÃO DE TRAFO 13,8kV c/ DJ + 1,00 x CONEXÃO DE TRAFO 69kV c/ DJ + 3,00 x ENTRADA DE LINHA 13,8kV c/ DJ + 2,00 x ENTRADA DE LINHA 69kV c/ DJ + 1,00 x INSTALAÇÃO DE TRANSFORMADOR DE FORÇA ATÉ 15MVA + 1,00 x MIG 69/34,5kV e MIG 69/13,8kV MÉDIA + 1,00 x TRANSFORMADOR DE FORÇA 69/13,8kV 10/12,5MVA - DYN1 | L23: 46385.125 | M23: 46283 | N23: 331999.43 | O23: 14809411 | P23: 0 | Q23: 331999.43 | R23: 14477411 | S23: - | T23: - | U23: EXECUÇÃO | V23: - | W23: OESTE - AL | Y23: AL | Z23: -9.62 | AA23: -37.75 | AB23: Preliminar | AC23: Pacote SE - Oeste
A24: EQTL AL | B24: ENTRADA DE LINHA | C24: Planejamento | D24: 804.120.0612 | E24: PROJETO SE ARAPIRACA IV 69KV | F24: AL-2361208ARQ0.C | G24: PLANEJAMENTO - ENTRADA DE LINHA - SE ARAPIRACA II - 2025 | H24: SE | I24: SE ARAPIRACA II | J24: 1,00 x BARRAMENTO DUPLO OU BPT 69kV + 1,00 x ENTRADA DE LINHA 69kV c/ DJ | K24: 1 EL DE ARAPIRACA IV | L24: 45717 | M24: 45806 | N24: 514285.4 | O24: 572717.43 | P24: 58432.03 | Q24: 514285.4 | R24: 0 | S24: ETAPA PRELIMINAR | T24: EXECUÇÃO | U24: FINALIZAÇÃO | V24: - | W24: OESTE - AL | Y24: AL | Z24: -9.75 | AA24: -36.65 | AB24: Mobilização | AC24: -
A25: EQTL AL | B25: NOVA SE | C25: Planejamento | D25: 804.120.0612 | E25: PROJETO SE ARAPIRACA IV 69KV | F25: AL-2361208ARQ0.B | G25: PLANEJAMENTO - NOVA SE - SE ARAPIRACA IV - 2025 | H25: SE | I25: SE ARAPIRACA IV | J25: 1,00 x BANCO DE CAPACITOR 3,6MVAr - 13,8kV + 5,00 x BARRAMENTO DUPLO OU BPT 13,8kV + 1,00 x BARRAMENTO SIMPLES 69kV + 1,00 x BARRAMENTO SIMPLES 69kV - SE MÓVEL + 1,00 x CONEXÃO DE BANCO DE CAPACITOR 13,8kV c/ DJ + 1,00 x CONEXÃO DE TRAFO 13,8kV c/ DJ + 1,00 x CONEXÃO DE TRAFO 69kV s/ DJ + 6,00 x ENTRADA DE LINHA 13,8kV c/ DJ + 1,00 x ENTRADA DE LINHA 69kV c/ DJ + 1,00 x INTERLIGAÇÃO DE BARRAS BPT 13,8kV c/ DJ + 1,00 x MIG 69/34,5kV e MIG 69/13,8kV MÉDIA + 1,00 x TRANSFORMADOR DE FORÇA 69/13,8kV 20,0/26,6MVA - DYN1 + 1,00 x INSTALAÇÃO DE TRANSFORMADOR DE FORÇA ATÉ 40MVA | K25: 1X25/26,66MVA 1X3.6MVAR 1XEL69KV (1XARD) 6XEL13.8KV (6XAL) | L25: 45717 | M25: 46116 | N25: 11772966 | O25: 12932421 | P25: 1112154.2 | Q25: 11772966 | R25: 47300.99 | S25: ETAPA PRELIMINAR | T25: EXECUÇÃO | U25: FINALIZAÇÃO | V25: - | W25: OESTE - AL | Y25: AL | Z25: -9.75 | AA25: -36.65 | AB25: Mobilização | AC25: -
A26: EQTL AL | B26: AMPLIAÇÃO DE SUBESTAÇÃO | C26: Cliente | D26: 804.110.0308 | E26: PROJETOS DE CLIENTES AT | F26: AL-2430808CAT0.D | G26: CLIENTE - AMPLIAÇÃO DE SUBESTAÇÃO - SE JACARÉ DOS HOMENS - 2024 | H26: SE | I26: SE JACARÉ DOS HOMENS | J26: 1,00 x ENTRADA DE LINHA 13,8kV c/ DJ + 1,00 x BARRAMENTO SIMPLES 13,8kV | K26: 1002519328 - FSP PARTICIPACOES LTDA | L26: 45638 | M26: 45638 | N26: 208759.64 | O26: 548904.14 | P26: 340144.5 | Q26: 208759.64 | R26: 0 | S26: - | T26: EXECUÇÃO | U26: FINALIZAÇÃO | V26: - | W26: OESTE - AL | Y26: AL | Z26: -9.64 | AA26: -37.21 | AB26: Execução | AC26: -
A27: EQTL AL | B27: AMPLIAÇÃO DE SUBESTAÇÃO | C27: Cliente | D27: 804.110.0308 | E27: PROJETOS DE CLIENTES AT | F27: AL-2430808CAT0.E | G27: CLIENTE - AMPLIAÇÃO DE SUBESTAÇÃO - SE PILAR - 2024 | H27: SE | I27: SE PILAR | J27: 1,00 x ENTRADA DE LINHA 13,8kV c/ DJ | K27: 1004116126 - HOSPITAL NOSSA SRA DE LOURDES E MATERN DR ARMANDO LAGES | L27: 45638 | M27: 45638 | N27: 0 | O27: 252844.07 | P27: 252844.07 | Q27: 0 | R27: 0 | S27: - | T27: EXECUÇÃO | U27: FINALIZAÇÃO | V27: - | W27: OESTE - AL | Y27: AL | Z27: -9.6 | AA27: -35.96 | AB27: Execução | AC27: -
A28: EQTL AL | B28: AMPLIAÇÃO DE SUBESTAÇÃO | C28: Cliente | D28: 804.110.0308 | E28: PROJETOS DE CLIENTES AT | F28: AL-2530808CAT0.D | G28: CLIENTE - AMPLIAÇÃO DE SUBESTAÇÃO - SE INHAPI - 2025 | H28: SE | I28: SE INHAPI | J28: 1,00 x ENTRADA DE LINHA 13,8kV c/ DJ | K28: Contrato nº 1002397633/2023. | L28: 45726 | M28: 46057 | N28: 469552.01 | O28: 586940.01 | P28: 0 | Q28: 469552.01 | R28: 117388 | S28: - | T28: - | U28: - | V28: - | W28: OESTE - AL | Y28: AL | Z28: 0 | AA28: 0 | AB28: Módulo
A29: EQTL AL | B29: AMPLIAÇÃO DE SUBESTAÇÃO | C29: Cliente | D29: 804.110.0308 | E29: PROJETOS DE CLIENTES AT | F29: AL-2530808CAT0.F | G29: CLIENTE - AMPLIAÇÃO DE SUBESTAÇÃO - SE CIDADE UNIVERSITÁRIA - 2027 | H29: SE | I29: SE CIDADE UNIVERSITÁRIA | J29: 1,00 x ENTRADA DE LINHA 13,8kV c/ DJ + 1,00 x BARRAMENTO DUPLO OU BPT 13,8kV | K29: Atendimento para os empreendimentos Cidade Jardim I (CC nº 1000002605 / Contrato nº 1016014002) e Cidade Jardim III (CC nº 1000004058 / Contrato nº 1016014106) | L29: 46411 | M29: 46406 | N29: 0 | O29: 624851.2 | P29: 0 | Q29: 0 | R29: 624851.2 | S29: - | T29: - | U29: - | V29: - | W29: LESTE - AL | Y29: AL | Z29: -9.67 | AA29: -35.74 | AB29: Conceitual
A30: EQTL AL | B30: BAY | C30: Cliente | D30: 804.110.0308 | E30: PROJETOS DE CLIENTES AT | F30: AL-2530808CAT0.B | G30: CLIENTE - BAY - SE CORURIPE - 2025 | H30: SE | I30: SE CORURIPE | J30: 1,00 x ENTRADA DE LINHA 13,8kV c/ DJ | K30: Contrato do cliente COOP DE COLONIZACAO AGROPECUARIA E INDUSTRIAL PINDORAMA LTDA nº 1008602988/2024. | L30: 46015 | M30: 46013 | N30: 586940.01 | O30: 586940.01 | P30: 0 | Q30: 586940.01 | R30: 0 | S30: - | T30: - | U30: EXECUÇÃO | V30: - | W30: OESTE - AL | Y30: AL | Z30: -10.13 | AA30: -36.18 | AB30: Conceitual | AC30: -
A31: EQTL AL | B31: ENTRADA DE LINHA | C31: Cliente | D31: 804.110.0308 | E31: PROJETOS DE CLIENTES AT | F31: AL-2430808CAT0.B | G31: CLIENTE - ENTRADA DE LINHA - SE POLO CLOROQUÍMICO - 2025 | H31: SE | I31: SE POLO CLOROQUÍMICO | J31: 1,00 x ENTRADA DE LINHA 69kV c/ DJ + 1,00 x BARRAMENTO DUPLO OU BPT 69kV | K31: 1006079416/2024 - INTERLÂNDIA LTDA | L31: 46022.125 | M31: 46107 | N31: 1359452.3 | O31: 1393753.7 | P31: 34301.32 | Q31: 1359452.3 | R31: 0 | S31: - | T31: - | U31: EXECUÇÃO | V31: - | W31: LESTE - AL | Y31: AL | Z31: -9.71 | AA31: -35.9 | AB31: Preliminar | AC31: -
A32: EQTL AL | B32: ENTRADA DE LINHA | C32: Cliente | D32: 804.110.0308 | E32: PROJETOS DE CLIENTES AT | F32: AL-2530808CAT0.A | G32: CLIENTE - ENTRADA DE LINHA - SE BARRA DE SÃO MIGUEL - 2025 | H32: SE | I32: SE BARRA DE SÃO MIGUEL | J32: 1,00 x ENTRADA DE LINHA 13,8kV c/ DJ | K32: 1003369455-2023 NEW FIELD CONSÓRCIO DE ENERGIA 3 | L32: 45777 | M32: 45977 | N32: 590559.49 | O32: 590559.49 | P32: 0 | Q32: 590559.49 | R32: 0 | S32: - | T32: - | U32: EXECUÇÃO | V32: - | W32: LESTE - AL | Y32: AL | Z32: -9.83 | AA32: -35.91 | AB32: Módulo | AC32: -
A33: EQTL AL | B33: ENTRADA DE LINHA | C33: Cliente | D33: 804.110.0308 | E33: PROJETOS DE CLIENTES AT | F33: AL-2530808CAT0.E | G33: CLIENTE - ENTRADA DE LINHA - SE INHAPI - 2026 | H33: SE | I33: SE INHAPI | J33: 1,00 x ENTRADA DE LINHA 13,8kV c/ DJ | K33: Contratos nº 1011491404;1011491440 1011491496;1011491553;1011491601. | L33: 46111 | M33: 46112 | N33: 0 | O33: 586940 | P33: 0 | Q33: 0 | R33: 586940 | S33: - | T33: - | U33: - | V33: - | W33: OESTE - AL | Y33: AL | Z33: 0 | AA33: 0 | AB33: Módulo
A34: EQTL AL | B34: RENOVAÇÃO SE | C34: Manutenção | D34: 804.110.0314 | E34: RENOVAÇÃO SE/LD | F34: AL-2431408RNV0.M | G34: MANUTENÇÃO - RENOVAÇÃO SE - SE MURICI - 2025 | H34: SE | I34: SE MURICI | J34: 3,00 x SUBSTITUIÇÃO RELIGADOR 13,8kV POR DISJUNTOR + 1,00 x SUBSTITUIÇÃO DISJUNTOR 13,8kV + 1,00 x SUBSTITUIÇÃO DISJUNTOR 69kV + 1,00 x SUBST. DE CONJUNTO CHAVE FUSÍVEL 13,8kV (TSA) + 1,00 x SUBST. DE CONJUNTO TCs 13,8kV + 1,00 x SUBST. DE CONJUNTO TPs 13,8kV + 1,00 x SUBST. DE CONJUNTO TPs 69kV + 4,00 x SUBSTITUIÇÃO PARA-RAIOS 13,8kV + 6,00 x SUBST. DE CONJUNTO CHAVES TFF 13,8kV 1600A MONOPOLAR + 3,00 x SUBST. DE CONJUNTO CHAVES TFF 13,8kV 630A MONOPOLAR + 1,00 x DESAT. BANCO DE CAPACITOR ATÉ 34,5kV | L34: 45926 | M34: 46007 | N34: 0 | O34: 1338184.9 | P34: 0 | Q34: 1338184.9 | R34: 0 | S34: - | T34: - | U34: - | V34: - | W34: LESTE - AL | X34: MURICI | Y34: AL | Z34: -9.31 | AA34: -35.61 | AB34: Indefinido
A35: EQTL AL | B35: SUBSTITUIÇÃO DE EQUIPAMENTO | C35: Manutenção | D35: 804.110.0314 | E35: RENOVAÇÃO SE/LD | F35: AL-2431408RNV0.A | G35: MANUTENÇÃO - SUBSTITUIÇÃO DE EQUIPAMENTO - SE BENEDITO BENTES - 2025 | H35: SE | I35: SE BENEDITO BENTES | J35: 2,00 x CONEXÃO DE BANCO DE CAPACITOR 13,8kV c/ DJ + 2,00 x SUBST. BANCO DE CAPACITOR 2,4MVAr - 13,8kV | K35: SUBSTITUIÇÃO DE BAY DE BANCO DE CAPACITORES EM FIM DE VIDA ÚTIL - 51H1 + 01H1 e 51H2 + 01H2 ; SUBSTITUIÇÃO DO RELIGADOR 21Y1, 21Y2, 21Y3 e 21Y4 EM FIM DE VIDA ÚTIL - TENSÃO DE 13,8KV | L35: 45868 | M35: 45783 | N35: 1678774.6 | O35: 2188875.4 | P35: 510100.78 | Q35: 1678774.6 | R35: 0 | S35: - | T35: EXECUÇÃO | U35: FINALIZAÇÃO | V35: - | W35: LESTE - AL | Y35: AL | Z35: -9.67 | AA35: -35.74 | AB35: Preliminar | AC35: -
A36: EQTL AL | B36: SUBSTITUIÇÃO DE EQUIPAMENTO | C36: Manutenção | D36: 804.110.0314 | E36: RENOVAÇÃO SE/LD | F36: AL-2431408RNV0.B | G36: MANUTENÇÃO - SUBSTITUIÇÃO DE EQUIPAMENTO - SE CRUZ DAS ALMAS - 2025 | H36: SE | I36: SE CRUZ DAS ALMAS | J36: 2,00 x SUBST. DE CONJUNTO TCs 13,8kV + 4,00 x SUBST. DE CONJUNTO TCs 69kV + 2,00 x SUBSTITUIÇÃO DISJUNTOR 13,8kV + 2,00 x SUBSTITUIÇÃO DISJUNTOR 69kV | K36: Equipamentos: TC's 69kV - 72T1, 72T2, 72J7 e 72N4 TC's 13,8kV - 71T1 e 71T2 Disjuntores 69kV - 12T1, 12T2 e 12J7 Disjuntores 13,8kV - 11T1 e 11T2 | L36: 45868 | M36: 45854 | N36: 695829.94 | O36: 1384992.4 | P36: 689162.47 | Q36: 695829.94 | R36: 0 | S36: - | T36: EXECUÇÃO | U36: FINALIZAÇÃO | V36: - | W36: LESTE - AL | Y36: AL | Z36: -9.67 | AA36: -35.74 | AB36: Preliminar | AC36: -
A37: EQTL AL | B37: SUBSTITUIÇÃO DE EQUIPAMENTO | C37: Manutenção | D37: 804.110.0314 | E37: RENOVAÇÃO SE/LD | F37: AL-2431408RNV0.C | G37: MANUTENÇÃO - SUBSTITUIÇÃO DE EQUIPAMENTO - SE OLHO D´ÁGUA DAS FLORES - 2025 | H37: SE | I37: SE OLHO D´ÁGUA DAS FLORES | J37: 1,00 x CONEXÃO DE BANCO DE CAPACITOR 13,8kV c/ DJ + 1,00 x SUBST. BANCO DE CAPACITOR 2,4MVAr - 13,8kV + 2,00 x SUBST. DE CONJUNTO TCs 69kV + 2,00 x SUBSTITUIÇÃO DISJUNTOR 69kV | K37: SUBSTITUIÇÃO DE TC´S DE 69KV EM FIM DE VIDA ÚTIL - 72J3 E 72J7; SUBSTITUIÇÃO DE BAY DE BANCO DE CAPACITORES EM FIM DE VIDA ÚTIL - 51H0 + 01H0 E 01H0 + 01H1; SUBSTITUIÇÃO DE DISJUNTOR DE 69KV EM FIM DE VIDA ÚTIL - 12J3 E 12J7 | L37: 45868 | M37: 46058 | N37: 1176164.8 | O37: 1325442.4 | P37: 149277.63 | Q37: 1176164.8 | R37: 0 | S37: - | T37: EXECUÇÃO | U37: FINALIZAÇÃO | V37: - | W37: OESTE - AL | Y37: AL | Z37: -9.54 | AA37: -37.29 | AB37: Preliminar | AC37: Pacote SE - Oeste
A38: EQTL AL | B38: SUBSTITUIÇÃO DE EQUIPAMENTO | C38: Manutenção | D38: 804.110.0314 | E38: RENOVAÇÃO SE/LD | F38: AL-2431408RNV0.D | G38: MANUTENÇÃO - SUBSTITUIÇÃO DE EQUIPAMENTO - SE PERI PERI - 2025 | H38: SE | I38: SE PERI PERI | J38: 2,00 x CONEXÃO DE BANCO DE CAPACITOR 13,8kV c/ DJ + 2,00 x SUBST. BANCO DE CAPACITOR 2,4MVAr - 13,8kV | K38: SUBSTITUIÇÃO DE BAY DE BANCO DE CAPACITORES EM FIM DE VIDA ÚTIL - 51H2 + 01H2 e 51H3 + 01H3 | L38: 45868 | M38: 45986 | N38: 1205345.7 | O38: 1338759 | P38: 133413.29 | Q38: 1205345.7 | R38: 0 | S38: - | T38: EXECUÇÃO | U38: FINALIZAÇÃO | V38: FINALIZAÇÃO | W38: OESTE - AL | Y38: AL | Z38: -9.93 | AA38: -36.55 | AB38: Preliminar | AC38: Pacote SE - Oeste
A39: EQTL AL | B39: SUBSTITUIÇÃO DE EQUIPAMENTO | C39: Manutenção | D39: 804.110.0314 | E39: RENOVAÇÃO SE/LD | F39: AL-2431408RNV0.E | G39: MANUTENÇÃO - SUBSTITUIÇÃO DE EQUIPAMENTO - SE SANTANA DO IPANEMA - 2025 | H39: SE | I39: SE SANTANA DO IPANEMA | J39: 1,00 x CONEXÃO DE BANCO DE CAPACITOR 13,8kV c/ DJ + 1,00 x SUBST. BANCO DE CAPACITOR 2,4MVAr - 13,8kV + 3,00 x SUBSTITUIÇÃO RELIGADOR 13,8kV POR DISJUNTOR | K39: SUBSTITUIÇÃO DE BAY DE BANCO DE CAPACITORES EM FIM DE VIDA ÚTIL - 51H1 + 01H1; SUBSTITUIÇÃO DO RELIGADOR 21Y1, 21Y2, e 21Y3 EM FIM DE VIDA ÚTIL - TENSÃO DE 13,8KV | L39: 45868 | M39: 46108 | N39: 1105818.3 | O39: 1270828.6 | P39: 165010.33 | Q39: 1105818.3 | R39: 0 | S39: - | T39: EXECUÇÃO | U39: FINALIZAÇÃO | V39: - | W39: OESTE - AL | Y39: AL | Z39: -9.38 | AA39: -37.25 | AB39: Preliminar | AC39: Pacote SE - Oeste
A40: EQTL AL | B40: SUBSTITUIÇÃO DE EQUIPAMENTO | C40: Manutenção | D40: 804.110.0314 | E40: RENOVAÇÃO SE/LD | F40: AL-2431408RNV0.F | G40: MANUTENÇÃO - SUBSTITUIÇÃO DE EQUIPAMENTO - SE JACARÉ DOS HOMENS - 2025 | H40: SE | I40: SE JACARÉ DOS HOMENS | J40: 2,00 x CONEXÃO DE BANCO DE CAPACITOR 13,8kV c/ DJ + 2,00 x SUBST. BANCO DE CAPACITOR 2,4MVAr - 13,8kV | K40: SUBSTITUIÇÃO DE BAY DE BANCO DE CAPACITORES EM FIM DE VIDA ÚTIL - 51H1 + 01H1 E 51H2 + 01H2 | L40: 45868 | M40: 46016 | N40: 1185093.3 | O40: 1268237.9 | P40: 83144.58 | Q40: 1185093.3 | R40: 0 | S40: - | T40: EXECUÇÃO | U40: FINALIZAÇÃO | V40: - | W40: OESTE - AL | Y40: AL | Z40: -9.64 | AA40: -37.21 | AB40: Preliminar | AC40: Pacote SE - Oeste
A41: EQTL AL | B41: SUBSTITUIÇÃO DE EQUIPAMENTO | C41: Manutenção | D41: 804.110.0314 | E41: RENOVAÇÃO SE/LD | F41: AL-2431408RNV0.G | G41: MANUTENÇÃO - SUBSTITUIÇÃO DE EQUIPAMENTO - SE PILAR - 2025 | H41: SE | I41: SE PILAR | J41: 1,00 x CONEXÃO DE BANCO DE CAPACITOR 13,8kV c/ DJ + 1,00 x SUBST. DE CONJUNTO TCs 69kV + 1,00 x SUBSTITUIÇÃO DISJUNTOR 69kV + 1,00 x SUBST. BANCO DE CAPACITOR 3,6MVAr - 13,8kV | K41: SUBSTITUIÇÃO DE TC´S DE 13,8KV - 71T1 - EM FIM DE VIDA ÚTIL; SUBSTITUIÇÃO DO DISJUNTOR 11T1 EM FIM DE VIDA ÚTIL - TENSÃO DE 13,8KV; SUBSTITUIÇÃO DE DISJUNTOR DE 69KV EM FIM DE VIDA ÚTIL - 12T1, 12P2 E 12V7; SUBSTITUIÇÃO DE TC´S DE 69KV EM FIM DE VIDA ÚTIL - 12T1, 12P2 E 12V7; SUBSTITUIÇÃO DE BAY DE BANCO DE CAPACITORES EM FIM DE VIDA ÚTIL - 51H0 + 01H1 | L41: 45868 | M41: 45990 | N41: 652212.21 | O41: 932555.36 | P41: 228555.36 | Q41: 704000 | R41: 0 | S41: - | T41: EXECUÇÃO | U41: FINALIZAÇÃO | V41: - | W41: OESTE - AL | X41: PILAR | Y41: AL | Z41: -9.6 | AA41: -35.96 | AB41: Preliminar | AC41: -
A42: EQTL AL | B42: SUBSTITUIÇÃO DE EQUIPAMENTO | C42: Manutenção | D42: 804.110.0314 | E42: RENOVAÇÃO SE/LD | F42: AL-2431408RNV0.H | G42: MANUTENÇÃO - SUBSTITUIÇÃO DE EQUIPAMENTO - SE TABULEIRO DOS MARTINS - 2025 | H42: SE | I42: SE TABULEIRO DOS MARTINS | J42: 3,00 x CONEXÃO DE BANCO DE CAPACITOR 13,8kV c/ DJ + 3,00 x SUBST. BANCO DE CAPACITOR 2,4MVAr - 13,8kV | K42: SUBSTITUIÇÃO DE BAY DE BANCO DE CAPACITORES EM FIM DE VIDA ÚTIL - 51H1 + 01H1, 51H3+ 01H3 e 51H4 + 01H4 | L42: 45868 | M42: 45955 | N42: 1267471.5 | O42: 1426032 | P42: 158560.43 | Q42: 1267471.5 | R42: 0 | S42: - | T42: EXECUÇÃO | U42: FINALIZAÇÃO | V42: - | W42: LESTE - AL | Y42: AL | Z42: -9.67 | AA42: -35.74 | AB42: Preliminar | AC42: PACOTE SE - LESTE
A43: EQTL AL | B43: SUBSTITUIÇÃO DE EQUIPAMENTO | C43: Manutenção | D43: 804.110.0314 | E43: RENOVAÇÃO SE/LD | F43: AL-2431408RNV0.I | G43: MANUTENÇÃO - SUBSTITUIÇÃO DE EQUIPAMENTO - SE TRAPICHE DA BARRA - 2025 | H43: SE | I43: SE TRAPICHE DA BARRA | J43: 1,00 x SUBSTITUIÇÃO RELIGADOR 13,8kV POR DISJUNTOR + 1,00 x SUBST. DE CONJUNTO TCs 69kV + 1,00 x SUBST. DE CONJUNTO TCs 13,8kV | K43: SUBSTITUIÇÃO DO RELIGADOR 21Y1 EM FIM DE VIDA ÚTIL - TENSÃO DE 13,8KV | L43: 45868 | M43: 45938 | N43: 279136.97 | O43: 381210.29 | P43: 102073.32 | Q43: 279136.97 | R43: 0 | S43: - | T43: EXECUÇÃO | U43: FINALIZAÇÃO | V43: - | W43: LESTE - AL | Y43: AL | Z43: -9.67 | AA43: -35.74 | AB43: Preliminar | AC43: -
A44: EQTL AL | B44: SUBSTITUIÇÃO DE EQUIPAMENTO | C44: Manutenção | D44: 804.110.0314 | E44: RENOVAÇÃO SE/LD | F44: AL-2431408RNV0.J | G44: MANUTENÇÃO - SUBSTITUIÇÃO DE EQUIPAMENTO - SE UNIÃO DOS PALMARES - 2025 | H44: SE | I44: SE UNIÃO DOS PALMARES | J44: 1,00 x CONEXÃO DE BANCO DE CAPACITOR 13,8kV c/ DJ + 1,00 x SUBST. DE CONJUNTO TCs 13,8kV + 1,00 x SUBSTITUIÇÃO DISJUNTOR 69kV + 1,00 x SUBSTITUIÇÃO DISJUNTOR 13,8kV + 1,00 x SUBST. BANCO DE CAPACITOR 3,6MVAr - 13,8kV + 1,00 x SUBST. DE CONJUNTO TCs 69kV + 1,00 x SUBSTITUIÇÃO DE TSA 13,8kV + 1,00 x SUBST. DE CONJUNTO CHAVE FUSÍVEL 13,8kV (TSA) + 1,00 x DESAT. DE CHAVE TRIPOLAR 69/138kV + 1,00 x SUBSTITUIÇÃO DE ESTRUTURA EM SE – CONCRETO + 1,00 x INSTALAÇÃO DE CHAVES 69kV TRIPOLAR | K44: Conjuntos de TC's de 13,8kV: 71T1 Religadores 13,8kV: 21Y2, 21Y4 e 21Y5 Disjuntor 13,8kV: 11T1 Banco + Conexão de banco: 51H0 + 01H0 (Substituir 2xBC-1,8MVAr por 1XBC-3,6MVAr) Disjuntores 69kV: 12T1 | L44: 45868 | M44: 46043 | N44: 1520932.2 | O44: 1471223.8 | P44: 255540.09 | Q44: 1215683.7 | R44: 0 | S44: - | T44: EXECUÇÃO | U44: FINALIZAÇÃO | V44: - | W44: LESTE - AL | X44: UNIÃO DOS PALMARES | Y44: AL | Z44: -9.16 | AA44: -36.03 | AB44: Preliminar | AC44: PACOTE SE - LESTE
A45: EQTL AL | B45: SUBSTITUIÇÃO DE EQUIPAMENTO | C45: Manutenção | D45: 804.110.0314 | E45: RENOVAÇÃO SE/LD | F45: AL-2431408RNV0.L | G45: MANUTENÇÃO - SUBSTITUIÇÃO DE EQUIPAMENTO - SE SECC. SÃO MIGUEL DOS CAMPOS - 2025 | H45: SE | I45: SE SECC. SÃO MIGUEL DOS CAMPOS | J45: 4,00 x SUBST. DE CONJUNTO TCs 69kV + 4,00 x SUBSTITUIÇÃO DISJUNTOR 69kV | K45: SUBSTITUIÇÃO DE TC´S DE 69KV EM FIM DE VIDA ÚTIL - 72D1, 72V4, 72J6, 72V9; SUBSTITUIÇÃO DE DISJUNTOR DE 69KV EM FIM DE VIDA ÚTIL - 12D1, 12V4, 12V5; 12V9 | L45: 45868 | M45: 45675 | N45: 200088.42 | O45: 2250581.5 | P45: 2050493.1 | Q45: 200088.42 | R45: 0 | S45: - | T45: EXECUÇÃO | U45: FINALIZAÇÃO | V45: - | W45: LESTE - AL | Y45: AL | Z45: -9.78 | AA45: -36.09 | AB45: Preliminar | AC45: -
A46: EQTL AL | B46: SUBSTITUIÇÃO DE EQUIPAMENTO | C46: Manutenção | D46: 804.110.0314 | E46: RENOVAÇÃO SE/LD | F46: AL-2531408RNV0.A | G46: MANUTENÇÃO - SUBSTITUIÇÃO DE EQUIPAMENTO - SE DELMIRO GOUVEIA - 2025 | H46: SE | I46: SE DELMIRO GOUVEIA | J46: 3,00 x SUBSTITUIÇÃO RELIGADOR 13,8kV POR DISJUNTOR | K46: 21Y5, 21Y3, 21Y2 | L46: 46022.125 | M46: 46044 | N46: 583643.64 | O46: 648492.93 | P46: 0 | Q46: 583643.64 | R46: 64849.29 | S46: - | T46: - | U46: EXECUÇÃO | V46: - | W46: OESTE - AL | Y46: AL | Z46: -9.38 | AA46: -37.99 | AB46: Projeto Básico | AC46: Pacote SE - Oeste
A47: EQTL AL | B47: SUBSTITUIÇÃO DE EQUIPAMENTO | C47: Manutenção | D47: 804.110.0314 | E47: RENOVAÇÃO SE/LD | F47: AL-2531408RNV0.B | G47: MANUTENÇÃO - SUBSTITUIÇÃO DE EQUIPAMENTO - SE JACARÉ DOS HOMENS - 2025 | H47: SE | I47: SE JACARÉ DOS HOMENS | J47: 2,00 x SUBSTITUIÇÃO RELIGADOR 13,8kV POR DISJUNTOR | K47: 21Y3, 21Y2 | L47: 46022.125 | M47: 45979 | N47: 389095.77 | O47: 432328.63 | P47: 0 | Q47: 389095.77 | R47: 43232.86 | S47: - | T47: - | U47: EXECUÇÃO | V47: - | W47: OESTE - AL | Y47: AL | Z47: -9.64 | AA47: -37.21 | AB47: Projeto Básico | AC47: Pacote SE - Oeste
A48: EQTL AP | B48: AMPLIAÇÃO DE POTÊNCIA | C48: Planejamento | D48: 806.110.0302 | E48: AMPLIAÇÃO DE SUBESTAÇÕES | F48: AP-2530208AMP0.A | G48: PLANEJAMENTO - AMPLIAÇÃO DE POTÊNCIA - SE CENTRAL - 2025 | H48: SE | I48: SE CENTRAL | J48: 1,00 x BARRAMENTO SIMPLES 13,8kV + 1,00 x CONEXÃO DE TRAFO 13,8kV c/ DJ + 1,00 x CONEXÃO DE TRAFO 34,5kV c/ DJ + 2,00 x ENTRADA DE LINHA 34,5kV c/ DJ + 1,00 x INSTALAÇÃO DE TRANSFORMADOR DE FORÇA ATÉ 15MVA | K48: Inclui implantação de disjuntor para 09F1 | L48: 45931.125 | M48: 46071 | N48: 1244357.8 | O48: 2113614.7 | P48: 0 | Q48: 1244357.8 | R48: 869256.85 | S48: - | T48: - | U48: EXECUÇÃO | V48: - | W48: INTERIOR - AP | Y48: AP | Z48: 0.86 | AA48: -51.18 | AB48: Conceitual | AC48: Pacote SE 01 - Amapá
A49: EQTL AP | B49: AMPLIAÇÃO DE POTÊNCIA | C49: Planejamento | D49: 806.110.0302 | E49: AMPLIAÇÃO DE SUBESTAÇÕES | F49: AP-2530208AMP0.B | G49: PLANEJAMENTO - AMPLIAÇÃO DE POTÊNCIA - SE INAJÁ - 2025 | H49: SE | I49: SE INAJÁ | J49: 2,00 x INSTALAÇÃO DE TRANSFORMADOR DE FORÇA ATÉ 15MVA + 2,00 x TRANSFORMADOR DE FORÇA 34,5/13,8kV 5,0/6,3MVA - YNYN0D1 + 0,25 x RETROFIT INFRA. SE MÉDIO/PEQUENO PORTE | K49: Retrofit referente a realocação do banco de baterias da SE Central para a SE Inajá | L49: 45931.125 | M49: 45853 | N49: 3425467.7 | O49: 3425467.7 | P49: 0 | Q49: 3425467.7 | R49: 0 | S49: - | T49: - | U49: EXECUÇÃO | V49: - | W49: METROPOLITANA - AP | Y49: AP | Z49: 0.71 | AA49: -50.85 | AB49: Conceitual | AC49: Pacote SE 02 - Amapá
A50: EQTL AP | B50: AMPLIAÇÃO DE POTÊNCIA | C50: Planejamento | D50: 806.110.0302 | E50: AMPLIAÇÃO DE SUBESTAÇÕES | F50: AP-2630208AMP0.A | G50: PLANEJAMENTO - AMPLIAÇÃO DE POTÊNCIA - SE EQUATORIAL - 2026 | H50: SE | I50: SE EQUATORIAL | J50: 1,00 x TRANSFORMADOR DE FORÇA 69/13,8kV 20,0/26,6MVA - DYN1 + 1,00 x INSTALAÇÃO DE TRANSFORMADOR DE FORÇA ATÉ 40MVA + 1,00 x CONEXÃO DE TRAFO 69kV c/ DJ + 1,00 x CONEXÃO DE TRAFO 13,8kV c/ DJ + 3,00 x ENTRADA DE LINHA 13,8kV c/ DJ + 2,00 x BARRAMENTO SIMPLES 13,8kV + 1,00 x CABO SUBTERRÂNEO + 1,20 x DESAT. INFRAESTRUTURA GERAL PEQUENA + 0,05 x MIG 69/34,5kV e MIG 69/13,8kV PEQUENO + 1,00 x INTERLIGAÇÃO DE BARRAS BPT 13,8kV c/ DJ | K50: Cabo subterrâneo para interligação do novo trafo T4 ao novo barramento 01B4 + interligação 01B4 a 01B2; Realizar desativação de cubículos. | L50: 46175 | M50: 46203 | N50: 0 | O50: 8698832.2 | P50: 0 | Q50: 0 | R50: 8698832.2 | S50: - | T50: - | U50: - | V50: - | W50: METROPOLITANA - AP | X50: MACAPÁ | Y50: AP | Z50: 0.15 | AA50: -51.07 | AB50: Conceitual
A51: EQTL AP | B51: BANCO DE CAPACITORES | C51: Planejamento | D51: 806.110.0301 | E51: Equipamento de Compensação de Reativos | F51: AP-2530108BCA0.A | G51: PLANEJAMENTO - BANCO DE CAPACITORES - SE DERIVAÇÃO - 2025 | H51: SE | I51: SE DERIVAÇÃO | J51: 1,00 x BANCO DE CAPACITOR 5,0MVAr - 69kV + 1,00 x CONEXÃO DE BANCO DE CAPACITOR 69kV c/ DJ | L51: 45931.125 | M51: 45961 | N51: 0 | O51: 1231111.4 | P51: 0 | Q51: 1231111.4 | R51: 0 | S51: - | T51: - | U51: EXECUÇÃO | V51: - | W51: INTERIOR - AP | Y51: AP | Z51: 0.89 | AA51: -52 | AB51: Conceitual | AC51: Pacote SE 02 - Amapá
A52: EQTL AP | B52: MEDIÇÃO OPERACIONAL | C52: Automação | D52: 806.110.0318 | E52: MEDIÇÃO OPERACIONAL SE | F52: AP-2531808MOP0.B | G52: AUTOMAÇÃO - MEDIÇÃO OPERACIONAL - SE OIAPOQUE - 2025 | H52: AUT | I52: SE OIAPOQUE | J52: 4,00 x MEDIÇÃO OPERACIONAL 13,8KV - C/ TI's | K52: 21Y1, 21Y2, 21Y3, 21Y4 | L52: 46020.125 | M52: 46007 | N52: 587961.68 | O52: 587961.68 | P52: 0 | Q52: 587961.68 | R52: 0 | S52: - | T52: - | U52: EXECUÇÃO | V52: - | W52: INTERIOR - AP | Y52: AP | Z52: 3.85 | AA52: -51.81 | AB52: Módulo | AC52: -
A53: EQTL AP | B53: MEDIÇÃO OPERACIONAL | C53: Automação | D53: 806.110.0318 | E53: MEDIÇÃO OPERACIONAL SE | F53: AP-2531808MOP0.C | G53: AUTOMAÇÃO - MEDIÇÃO OPERACIONAL - SE SERRA DO NAVIO - 2025 | H53: AUT | I53: SE SERRA DO NAVIO | J53: 4,00 x MEDIÇÃO OPERACIONAL 13,8KV - C/ TI's | K53: 21N1, 21N2, 21N3 e 21B1 | L53: 46020.125 | M53: 46009 | N53: 587961.68 | O53: 587961.68 | P53: 0 | Q53: 587961.68 | R53: 0 | S53: - | T53: - | U53: EXECUÇÃO | V53: - | W53: INTERIOR - AP | Y53: AP | Z53: 0.9 | AA53: -52.36 | AB53: Módulo | AC53: -
A54: EQTL AP | B54: MEDIÇÃO OPERACIONAL | C54: Automação | D54: 806.110.0318 | E54: MEDIÇÃO OPERACIONAL SE | F54: AP-2531808MOP0.D | G54: AUTOMAÇÃO - MEDIÇÃO OPERACIONAL - SE TARTARUGALZINHO - 2025 | H54: AUT | I54: SE TARTARUGALZINHO | J54: 3,00 x MEDIÇÃO OPERACIONAL 13,8KV - C/ TI's | K54: 21Y1, 21Y2 e 21B1 | L54: 46020.125 | M54: 45922 | N54: 440971.26 | O54: 440971.26 | P54: 0 | Q54: 440971.26 | R54: 0 | S54: - | T54: - | U54: EXECUÇÃO | V54: - | W54: INTERIOR - AP | Y54: AP | Z54: 1.51 | AA54: -50.91 | AB54: Módulo | AC54: -
A55: EQTL AP | B55: MEDIÇÃO OPERACIONAL | C55: Automação | D55: 806.110.0318 | E55: MEDIÇÃO OPERACIONAL SE | F55: AP-2631808MOP0.A | G55: AUTOMAÇÃO - MEDIÇÃO OPERACIONAL - SE APOREMA - 2026 | H55: AUT | I55: SE APOREMA | J55: 2,00 x MEDIÇÃO OPERACIONAL 34,5KV - C/ TI's | K55: 09B1, 09P1 | L55: 46102 | M55: 46142 | N55: 0 | O55: 357294.48 | P55: 0 | Q55: 0 | R55: 357294.48 | S55: - | T55: - | U55: - | V55: - | W55: INTERIOR - AP | Y55: AP | Z55: 1.51 | AA55: -50.91 | AB55: Conceitual
A56: EQTL AP | B56: MEDIÇÃO OPERACIONAL | C56: Automação | D56: 806.110.0318 | E56: MEDIÇÃO OPERACIONAL SE | F56: AP-2631808MOP0.B | G56: AUTOMAÇÃO - MEDIÇÃO OPERACIONAL - SE RIO PRETO (AP) - 2026 | H56: AUT | I56: SE RIO PRETO (AP) | J56: 2,00 x MEDIÇÃO OPERACIONAL 34,5KV - C/ TI's | K56: 09B1, 09P1 | L56: 46163 | M56: 46169 | N56: 0 | O56: 357294.48 | P56: 0 | Q56: 0 | R56: 357294.48 | S56: - | T56: - | U56: - | V56: - | W56: INTERIOR - AP | Y56: AP | Z56: -0.15 | AA56: -51.37 | AB56: Conceitual
A57: EQTL AP | B57: MEDIÇÃO OPERACIONAL | C57: Automação | D57: 806.110.0318 | E57: MEDIÇÃO OPERACIONAL SE | F57: AP-2631808MOP0.C | G57: AUTOMAÇÃO - MEDIÇÃO OPERACIONAL - SE TREVO - 2026 | H57: AUT | I57: SE TREVO | J57: 2,00 x MEDIÇÃO OPERACIONAL 34,5KV - C/ TI's | K57: 09B1, 09L1 | L57: 46133 | M57: 46197 | N57: 0 | O57: 357294.48 | P57: 0 | Q57: 0 | R57: 357294.48 | S57: - | T57: - | U57: - | V57: - | W57: INTERIOR - AP | Y57: AP | Z57: 2.49 | AA57: -50.99 | AB57: Conceitual
A58: EQTL AP | B58: ENTRADA DE LINHA | C58: Manutenção | D58: 806.110.0313 | E58: Melhorias Operacionais | F58: AP-2431308MOP0.A | G58: MANUTENÇÃO - ENTRADA DE LINHA - SE CUPIXI - 2024 | H58: SE | I58: SE CUPIXI | J58: 1,00 x ENTRADA DE LINHA 69kV c/ DJ | K58: Seccionar a LD em frente a SE Cupixi e transformar em duas LDs (Central - Cupixi e Cupixi - Serra do Navio) | L58: 45657 | M58: 45717 | N58: 853654.57 | O58: 1518462.9 | P58: 664808.31 | Q58: 853654.57 | R58: 0 | S58: - | T58: EXECUÇÃO | U58: FINALIZAÇÃO | V58: - | W58: INTERIOR - AP | Y58: AP | Z58: 0.71 | AA58: -51.41 | AB58: Execução | AC58: -
A59: EQTL AP | B59: MELHORIA SE | C59: Manutenção | D59: 806.110.0313 | E59: Melhorias Operacionais | F59: AP-2431308MOP0.C | G59: MANUTENÇÃO - MELHORIA SE - SE AMAPÁ - 2024 | H59: SE | I59: SE AMAPÁ | J59: 1,00 x BARRAMENTO SIMPLES 69kV - SE MÓVEL | L59: 45657 | M59: 45573 | N59: 92912.81 | O59: 170057.89 | P59: 77145.08 | Q59: 92912.81 | R59: 0 | S59: - | T59: EXECUÇÃO | U59: FINALIZAÇÃO | V59: - | W59: INTERIOR - AP | Y59: AP | Z59: 0.03 | AA59: -51.07 | AB59: Execução | AC59: -
A60: EQTL AP | B60: MELHORIA SE | C60: Manutenção | D60: 806.110.0313 | E60: Melhorias Operacionais | F60: AP-2431308MOP0.E | G60: MANUTENÇÃO - MELHORIA SE - SE EQUATORIAL - 2024 | H60: SE | I60: SE EQUATORIAL | J60: 1,00 x BARRAMENTO SIMPLES 69kV - SE MÓVEL | L60: 45657 | M60: 45695 | N60: 150400.4 | O60: 227024.53 | P60: 76624.13 | Q60: 150400.4 | R60: 0 | S60: - | T60: EXECUÇÃO | U60: FINALIZAÇÃO | V60: - | W60: METROPOLITANA - AP | Y60: AP | Z60: 0.15 | AA60: -51.07 | AB60: Execução | AC60: -
A61: EQTL AP | B61: MELHORIA SE | C61: Manutenção | D61: 806.110.0313 | E61: Melhorias Operacionais | F61: AP-2531308MOP0.A | G61: MANUTENÇÃO - MELHORIA SE - SE CALÇOENE - 2025 | H61: SE | I61: SE CALÇOENE | J61: 1,00 x BARRAMENTO SIMPLES 69kV - SE MÓVEL | L61: 46022.125 | M61: 45999 | N61: 79815.45 | O61: 104742.34 | P61: 0 | Q61: 79815.45 | R61: 24926.89 | S61: - | T61: - | U61: EXECUÇÃO | V61: - | W61: INTERIOR - AP | Y61: AP | Z61: 2.5 | AA61: -50.95 | AB61: Conceitual | AC61: Pacote SE 02 - Amapá
A62: EQTL AP | B62: MELHORIA SE | C62: Manutenção | D62: 806.110.0313 | E62: Melhorias Operacionais | F62: AP-2531308MOP0.B | G62: MANUTENÇÃO - MELHORIA SE - SE EQUATORIAL - 2025 | H62: SE | I62: SE EQUATORIAL | J62: 1,00 x BARRAMENTO SIMPLES 13,8kV + 1,00 x CONEXÃO DE BANCO DE CAPACITOR 13,8kV c/ DJ + 1,00 x CONEXÃO DE TRAFO 13,8kV c/ DJ + 5,00 x ENTRADA DE LINHA 13,8kV c/ DJ + 1,00 x INTERLIGAÇÃO DE BARRAS BPT 13,8kV c/ DJ + 0,43 x MIG 34,5/13,8kV PEQUENO + 1,00 x INSTALAÇÃO DE CONJUNTO TP's 13,8kV + 2,00 x CONJUNTO CHAVE FUSÍVEL 13,8kV (TSA) + 1,00 x INSTALAÇÃO DE TSA 13,8kV + 1,00 x RETROFIT BANCO CAPACITOR <= 34,5KV | K62: Substituição de barra 2 de cubículos por pátio aéreo - Entrada de linha: 01C6, 01C7, 01C8, 01C9 e 01Y1 - Conexão de transformadores: 11B2 - Conexão de Banco e Retrofit: 11H2; - Realizar implantação de TP e TSA aéreo. | L62: 46022.125 | M62: 46051 | N62: 1764651.9 | O62: 4591142.7 | P62: 0 | Q62: 1764651.9 | R62: 2826490.7 | S62: - | T62: - | U62: EXECUÇÃO | V62: - | W62: METROPOLITANA - AP | Y62: AP | Z62: 0.15 | AA62: -51.07 | AB62: Conceitual | AC62: Pacote SE 02 - Amapá
A63: EQTL AP | B63: MELHORIA SE | C63: Manutenção | D63: 806.110.0313 | E63: Melhorias Operacionais | F63: AP-2531308MOP0.C | G63: MANUTENÇÃO - MELHORIA SE - SE SANTA RITA (AP) - 2025 | H63: SE | I63: SE SANTA RITA (AP) | J63: 1,00 x BARRAMENTO DUPLO OU BPT 69kV + 3,00 x BARRAMENTO SIMPLES 13,8kV + 3,00 x CONEXÃO DE BANCO DE CAPACITOR 13,8kV c/ DJ + 3,00 x CONEXÃO DE TRAFO 13,8kV c/ DJ + 12,00 x ENTRADA DE LINHA 13,8kV c/ DJ + 2,00 x INTERLIGAÇÃO DE BARRAS BPT 13,8kV c/ DJ + 5,00 x CONJUNTO CHAVE FUSÍVEL 13,8kV (TSA) + 2,00 x INSTALAÇÃO DE TSA 13,8kV + 3,00 x INSTALAÇÃO DE CONJUNTO TP's 13,8kV + 0,04 x MIG 34,5/13,8kV MÉDIA | K63: Realizar implantação de barramento aéreo nas barras 1, 2 e 3 Códigos operacionais: - EL: 11P1 a 11P9, 11F1, 11F2, 11F5; - Interligação de barra: 11I1 e 11I2; - CT: 11B1, 11B2 e 11B3 - Conexão de banco: 11H1, 11H2 e 11H3 - Realizar a implantação de TP's para supervisão de barra e TSA's; - Interligação da malha de aterramento. | L63: 46022.125 | M63: 46162 | N63: 3357363.4 | O63: 9449740.9 | P63: 0 | Q63: 3357363.4 | R63: 6092377.6 | S63: - | T63: - | U63: EXECUÇÃO | V63: - | W63: METROPOLITANA - AP | Y63: AP | Z63: 0.15 | AA63: -51.07 | AB63: Conceitual | AC63: Pacote SE 01 - Amapá
A64: EQTL AP | B64: MELHORIA SE | C64: Manutenção | D64: 806.110.0313 | E64: Melhorias Operacionais | F64: AP-2531308MOP0.D | G64: MANUTENÇÃO - MELHORIA SE - SE SANTANA - 2025 | H64: SE | I64: SE SANTANA | J64: 1,00 x BARRAMENTO SIMPLES 13,8kV + 1,00 x CONEXÃO DE BANCO DE CAPACITOR 13,8kV c/ DJ + 1,00 x CONEXÃO DE TRAFO 13,8kV c/ DJ + 4,00 x ENTRADA DE LINHA 13,8kV c/ DJ + 1,00 x INSTALAÇÃO DE CONJUNTO TP's 13,8kV + 1,00 x INSTALAÇÃO DE TSA 13,8kV + 2,00 x CONJUNTO CHAVE FUSÍVEL 13,8kV (TSA) | K64: - Realizar a implantação de pátio aéreo da barra 1 - EL - 11S1 a 11S4; - CT - 11B1; - Conexão de Banco - 11H1 - Necessário instalação de TP's e TSA | L64: 46022.125 | M64: 46093 | N64: 1465423.1 | O64: 2774556.4 | P64: 0 | Q64: 1465423.1 | R64: 1309133.4 | S64: - | T64: - | U64: EXECUÇÃO | V64: - | W64: METROPOLITANA - AP | Y64: AP | Z64: 0 | AA64: -51.38 | AB64: Conceitual | AC64: Pacote SE 01 - Amapá
A65: EQTL AP | B65: MELHORIA SE | C65: Manutenção | D65: 806.110.0313 | E65: Melhorias Operacionais | F65: AP-2531308MOP0.E | G65: MANUTENÇÃO - MELHORIA SE - SE PORTO GRANDE - 2025 | H65: SE | I65: SE PORTO GRANDE | J65: 0,04 x MIG 34,5/13,8kV MÉDIA | K65: Realizar reforço da interligação da malha de aterramento antiga a nova malha da subestação | L65: 46022 | M65: 46035 | N65: 114078.53 | O65: 114078.53 | P65: 0 | Q65: 114078.53 | R65: 0 | S65: - | T65: - | U65: EXECUÇÃO | V65: - | W65: METROPOLITANA - AP | Y65: AP | Z65: 0.7 | AA65: -51.4 | AB65: Módulo
A66: EQTL AP | B66: MELHORIA SE | C66: Manutenção | D66: 806.110.0313 | E66: Melhorias Operacionais | F66: AP-2631308MOP0.A | G66: MANUTENÇÃO - MELHORIA SE - SE AMAPÁ - 2026 | H66: SE | I66: SE AMAPÁ | J66: 1,00 x BARRAMENTO SIMPLES 13,8kV + 0,14 x MIG 34,5/13,8kV PEQUENO + 1,00 x CONEXÃO DE TRAFO 13,8kV c/ DJ + 1,00 x ENTRADA DE LINHA 13,8kV c/ DJ + 0,20 x DESAT. INFRAESTRUTURA GERAL PEQUENA | K66: Substituição de cubículos por pátio aéreo: - Entrada de linha: 01Y1; - Conexão de transformador: 01B1; - Realizar implantação de TP e TSA aéreo; - Realizar desativação de cubículo. | L66: 46202 | M66: 46200 | N66: 0 | O66: 1566369.7 | P66: 0 | Q66: 0 | R66: 1566369.7 | S66: - | T66: - | U66: - | V66: - | W66: INTERIOR - AP | X66: AMAPÁ | Y66: AP | Z66: 0.03 | AA66: -51.07 | AB66: Conceitual
A67: EQTL AP | B67: MELHORIA SE | C67: Manutenção | D67: 806.110.0313 | E67: Melhorias Operacionais | F67: AP-2631308MOP0.B | G67: MANUTENÇÃO - MELHORIA SE - SE CALÇOENE - 2026 | H67: SE | I67: SE CALÇOENE | J67: 1,00 x BARRAMENTO SIMPLES 13,8kV + 1,00 x CONEXÃO DE TRAFO 13,8kV c/ DJ + 2,00 x ENTRADA DE LINHA 13,8kV c/ DJ + 0,14 x MIG 34,5/13,8kV PEQUENO + 0,20 x DESAT. INFRAESTRUTURA GERAL PEQUENA | K67: Substituição de cubículos por pátio aéreo: - Entrada de linha: 01C1, 01C2; - Conexão de transformador: 01B1; - Realizar implantação de TP e TSA aéreo; - Realizar desativação de cubículo. | L67: 46202 | N67: 0 | O67: 2056131.1 | P67: 0 | Q67: 0 | R67: 2056131.1 | S67: - | T67: - | U67: - | V67: - | W67: INTERIOR - AP | X67: CALÇOENE | Y67: AP | Z67: 2.5 | AA67: -50.95 | AB67: Conceitual
A68: EQTL AP | B68: RETROFIT | C68: Automação | D68: 806.110.0317 | E68: OBRAS AUTOMAÇÃO SE | F68: AP-2431708ASE0.A | G68: AUTOMAÇÃO - RETROFIT - SE CALÇOENE - 2024 | H68: AUT | I68: SE CALÇOENE | J68: 2,00 x RETROFIT BAY ALIMENTADOR + 1,00 x RETROFIT BAY CONEXÃO ALTA TRAFO + 1,00 x RETROFIT BAY CONEXÃO BAIXA TRAFO + 1,00 x RETROFIT INFRA. SE GRANDE PORTE + 1,00 x RETROFIT TRANSFORMADOR FORÇA | K68: 12Y3 + 11B1 + 11C1+ 11C2 + 02T1 | L68: 45656 | M68: 45688 | N68: 18549.82 | O68: 1107853.6 | P68: 1089303.7 | Q68: 18549.82 | R68: 0 | S68: - | T68: EXECUÇÃO | U68: FINALIZAÇÃO | V68: - | W68: INTERIOR - AP | Y68: AP | Z68: 2.5 | AA68: -50.95 | AB68: Execução | AC68: -
A69: EQTL AP | B69: RETROFIT | C69: Automação | D69: 806.110.0317 | E69: OBRAS AUTOMAÇÃO SE | F69: AP-2531708ASE0.A | G69: AUTOMAÇÃO - RETROFIT - SE OIAPOQUE - 2025 | H69: AUT | I69: SE OIAPOQUE | J69: 1,00 x RETROFIT INFRA. SE MÉDIO/PEQUENO PORTE | K69: INSTALAÇÃO DE PAINEL OUTDOOR DE COMUNICAÇÃO (RTAC E SWITCH) | L69: 46020.125 | M69: 45972 | N69: 166981.56 | O69: 166981.56 | P69: 0 | Q69: 166981.56 | R69: 0 | S69: - | T69: - | U69: EXECUÇÃO | V69: - | W69: INTERIOR - AP | Y69: AP | Z69: 3.85 | AA69: -51.81 | AB69: Módulo | AC69: -
A70: EQTL AP | B70: RETROFIT | C70: Automação | D70: 806.110.0317 | E70: OBRAS AUTOMAÇÃO SE | F70: AP-2531708ASE0.B | G70: AUTOMAÇÃO - RETROFIT - SE APOREMA - 2025 | H70: AUT | I70: SE APOREMA | J70: 1,00 x RETROFIT INFRA. SE MÉDIO/PEQUENO PORTE | K70: INSTALAÇÃO DE PAINEL OUTDOOR DE COMUNICAÇÃO (RTAC E SWITCH) | L70: 46020.125 | M70: 45947 | N70: 166981.56 | O70: 166981.56 | P70: 0 | Q70: 166981.56 | R70: 0 | S70: - | T70: - | U70: EXECUÇÃO | V70: - | W70: INTERIOR - AP | Y70: AP | Z70: 1.51 | AA70: -50.91 | AB70: Módulo | AC70: -
A71: EQTL AP | B71: RETROFIT | C71: Automação | D71: 806.110.0317 | E71: OBRAS AUTOMAÇÃO SE | F71: AP-2531708ASE0.C | G71: AUTOMAÇÃO - RETROFIT - SE TARTARUGALZINHO - 2025 | H71: AUT | I71: SE TARTARUGALZINHO | J71: 1,00 x RETROFIT BAY ENTRADA DE LINHA - 311C + 1,00 x RETROFIT INFRA. SE MÉDIO/PEQUENO PORTE | K71: 13Y1, 13T2, 13T1, 03T2, 03T1, 12T1, 12T2, 12Y3, 11B2, 11Y1, 11Y2, 21B1, 21Y1, 21Y2, 11J1 | L71: 46020.125 | M71: 45891 | N71: 340951.8 | O71: 340951.8 | P71: 0 | Q71: 340951.8 | R71: 0 | S71: - | T71: - | U71: EXECUÇÃO | V71: - | W71: INTERIOR - AP | Y71: AP | Z71: 1.51 | AA71: -50.91 | AB71: Módulo | AC71: -
A72: EQTL AP | B72: RETROFIT | C72: Automação | D72: 806.110.0317 | E72: OBRAS AUTOMAÇÃO SE | F72: AP-2531708ASE0.D | G72: AUTOMAÇÃO - RETROFIT - SE EQUATORIAL - 2025 | H72: AUT | I72: SE EQUATORIAL | J72: 2,00 x RETROFIT BAY CONEXÃO ALTA TRAFO + 2,00 x RETROFIT BAY CONEXÃO BAIXA TRAFO + 2,00 x RETROFIT BAY ENTRADA DE LINHA - 311C + 1,00 x RETROFIT BAY ENTRADA DE LINHA - 751.4 + 1,00 x RETROFIT INFRA. SE GRANDE PORTE + 1,00 x RETROFIT RTAC/UTR + 2,00 x RETROFIT TRANSFORMADOR FORÇA + 2,00 x RETROFIT - 2414 | K72: Códigos: 12D1 (transferência - utilizado módulo de entrada linha visto que não havia módulo para disjuntor de transferência 69kV com 751.4), 12Q1, 12Q2 (retrofit entrada de linha 311), 02T2 e 02T3 (conexão de alta e baixa dos transformadores) e dos transformadores 02T2 e 02T3. | L72: 46020.125 | M72: 45922 | N72: 3014561.3 | O72: 3840394 | P72: 0 | Q72: 3014561.3 | R72: 825832.72 | S72: - | T72: - | U72: EXECUÇÃO | V72: - | W72: METROPOLITANA - AP | Y72: AP | Z72: 0.15 | AA72: -51.07 | AB72: Preliminar | AC72: -
A73: EQTL AP | B73: RETROFIT | C73: Automação | D73: 806.110.0317 | E73: OBRAS AUTOMAÇÃO SE | F73: AP-2531708ASE0.E | G73: AUTOMAÇÃO - RETROFIT - SE PORTUÁRIA - 2025 | H73: AUT | I73: SE PORTUÁRIA | J73: 3,00 x RETROFIT BAY ALIMENTADOR + 1,00 x RETROFIT BAY CONEXÃO BAIXA TRAFO + 1,00 x RETROFIT BAY ENTRADA DE LINHA - 751.4 + 1,00 x RETROFIT INFRA. SE MÉDIO/PEQUENO PORTE + 1,00 x RETROFIT TRANSFORMADOR FORÇA | K73: 13P1, 11B1,01T1, 21V1, 11V2, 11V3 | L73: 46020.125 | M73: 45972 | N73: 612748.15 | O73: 612748.15 | P73: 0 | Q73: 612748.15 | R73: 0 | S73: - | T73: - | U73: EXECUÇÃO | V73: - | W73: METROPOLITANA - AP | Y73: AP | Z73: 0 | AA73: -51.38 | AB73: Módulo | AC73: -
A74: EQTL AP | B74: RETROFIT | C74: Automação | D74: 806.110.0317 | E74: OBRAS AUTOMAÇÃO SE | F74: AP-2531708ASE0.F | G74: AUTOMAÇÃO - RETROFIT - SE CENTRAL - 2025 | H74: AUT | I74: SE CENTRAL | J74: 2,00 x RETROFIT TRANSFORMADOR FORÇA + 2,00 x RETROFIT - 2414 + 1,00 x RETROFIT RTAC/UTR + 1,00 x RETROFIT BAY ALIMENTADOR + 1,00 x RETROFIT BAY CONEXÃO ALTA TRAFO | K74:  2 x RETROFIT TRANSFORMADOR FORÇA ( 03T2, 09T4);  2 x RETROFIT - 2414 (03T2, 09T4);  1 x RETROFIT RTAC/UTR;  1 x RETROFIT BAY ALIMENTADOR (11C2);  1 x RETROFIT BAY CONEXÃO ALTA TRAFO (13T2); | L74: 46022 | M74: 46037 | N74: 1413509.9 | O74: 1413509.9 | P74: 0 | Q74: 1413509.9 | R74: 0 | S74: - | T74: - | U74: EXECUÇÃO | V74: - | W74: INTERIOR - AP | Y74: AP | Z74: 0.86 | AA74: -51.18 | AB74: Conceitual
A75: EQTL AP | B75: NOVA SE | C75: Planejamento | D75: 806.120.0603 | E75: PROJETO AMAZONAS 69kV | F75: AP-2560308AMA0.B | G75: PLANEJAMENTO - NOVA SE - SE AMAZONAS - 2027 | H75: SE | I75: SE AMAZONAS | J75: 3,00 x BARRAMENTO SIMPLES 13,8kV + 1,00 x BARRAMENTO SIMPLES 69kV + 1,00 x BARRAMENTO SIMPLES 69kV - SE MÓVEL + 1,00 x CONEXÃO DE TRAFO 13,8kV c/ DJ + 5,00 x ENTRADA DE LINHA 13,8kV c/ DJ + 2,00 x ENTRADA DE LINHA 69kV c/ DJ + 1,00 x INSTALAÇÃO DE TRANSFORMADOR DE FORÇA ATÉ 15MVA + 1,00 x MIG 69/34,5kV e MIG 69/13,8kV PEQUENO + 1,00 x TRANSFORMADOR DE FORÇA 69/13,8kV 20,0/26,6MVA - DYN1 + 1,00 x CONEXÃO DE TRAFO 69kV c/ DJ | L75: 46598 | M75: 46166 | N75: 1999512 | O75: 12402272 | P75: 0 | Q75: 1999512 | R75: 10402760 | S75: - | T75: - | U75: ETAPA PRELIMINAR | V75: EXECUÇÃO | W75: METROPOLITANA - AP | Y75: AP | Z75: 0.15 | AA75: -51.07 | AB75: Conceitual | AC75: Pacote SE 01 - Amapá
A76: EQTL AP | B76: ENTRADA DE LINHA | C76: Planejamento | D76: 806.120.0604 | E76: PROJETO FAZENDINHA 69 KV | F76: AP-2360408FZD0.D | G76: PLANEJAMENTO - ENTRADA DE LINHA - SE SANTANA - 2025 | H76: SE | I76: SE SANTANA | J76: 1,00 x ENTRADA DE LINHA 69kV c/ DJ | L76: 45916 | M76: 45768 | N76: 625111.57 | O76: 1218812.6 | P76: 593701.03 | Q76: 625111.57 | R76: 0 | S76: - | T76: - | U76: FINALIZAÇÃO | V76: - | W76: METROPOLITANA - AP | Y76: AP | Z76: 0 | AA76: -51.38 | AB76: Execução | AC76: -
A77: EQTL AP | B77: NOVA SE | C77: Planejamento | D77: 806.120.0604 | E77: PROJETO FAZENDINHA 69 KV | F77: AP-2360408FZD0.B | G77: PLANEJAMENTO - NOVA SE - SE FORTE CUMAÚ - 2025 | H77: SE | I77: SE FORTE CUMAÚ | J77: 4,00 x BARRAMENTO SIMPLES 13,8kV + 1,00 x BARRAMENTO SIMPLES 69kV + 1,00 x BARRAMENTO SIMPLES 69kV - SE MÓVEL + 2,00 x CONEXÃO DE TRAFO 13,8kV c/ DJ + 2,00 x CONEXÃO DE TRAFO 69kV c/ DJ + 5,00 x ENTRADA DE LINHA 13,8kV c/ DJ + 1,00 x ENTRADA DE LINHA 69kV c/ DJ + 2,00 x INSTALAÇÃO DE TRANSFORMADOR DE FORÇA ATÉ 15MVA + 1,00 x MIG 69/34,5kV e MIG 69/13,8kV MÉDIA + 2,00 x TRANSFORMADOR DE FORÇA 69/13,8kV 20,0/26,6MVA - DYN1 | L77: 45916 | M77: 45769 | N77: 12584396 | O77: 17175020 | P77: 4590624.6 | Q77: 12584396 | R77: 0 | S77: - | T77: EXECUÇÃO | U77: FINALIZAÇÃO | V77: - | W77: METROPOLITANA - AP | X77: SANTANA | Y77: AP | Z77: -0.05 | AA77: -51.17 | AB77: Execução | AC77: -
A78: EQTL AP | B78: ENTRADA DE LINHA | C78: Planejamento | D78: 806.120.0600 | E78: Projeto São José 69 / 13,8 kV – 53,2 M | F78: AP-2560008MSJ0.B | G78: PLANEJAMENTO - ENTRADA DE LINHA - SE MACAPÁ II - 2025 | H78: SE | I78: SE MACAPÁ II | J78: 1,00 x ENTRADA DE LINHA 69kV c/ DJ + 1,00 x SUBST. DE CHAVES 69kV C/ LÂMINA DE TERRA | L78: 45931.125 | M78: 45976 | N78: 0 | O78: 868013.58 | P78: 0 | Q78: 0 | R78: 868013.58 | S78: - | T78: - | U78: EXECUÇÃO | V78: - | W78: METROPOLITANA - AP | Y78: AP | Z78: 0.08 | AA78: -51.07 | AB78: Conceitual | AC78: Pacote SE 02 - Amapá
A79: EQTL AP | B79: ENTRADA DE LINHA | C79: Planejamento | D79: 806.120.0600 | E79: Projeto São José 69 / 13,8 kV – 53,2 M | F79: AP-2560008MSJ0.C | G79: PLANEJAMENTO - ENTRADA DE LINHA - SE SÃO JOSÉ - 2025 | H79: SE | I79: SE SÃO JOSÉ | J79: 1,00 x ENTRADA DE LINHA 69kV c/ DJ | L79: 45931.125 | M79: 45976 | N79: 0 | O79: 868013.58 | P79: 0 | Q79: 0 | R79: 868013.58 | S79: - | T79: - | U79: EXECUÇÃO | V79: - | W79: METROPOLITANA - AP | Y79: AP | Z79: 0.04 | AA79: -51.06 | AB79: Conceitual | AC79: Pacote SE 02 - Amapá
A80: EQTL AP | B80: RENOVAÇÃO SE | C80: Manutenção | D80: 806.110.0314 | E80: RENOVAÇÃO SE/LD | F80: AP-2331408RNV0.A | G80: MANUTENÇÃO - RENOVAÇÃO SE - SE CENTRAL - 2023 | H80: SE | I80: SE CENTRAL | J80: 1,00 x SUBST. DE CONJUNTO TCs 69kV + 1,00 x SUBST. DE CONJUNTO TPs 138kV + 4,00 x SUBSTITUIÇÃO DISJUNTOR 138kV + 1,00 x SUBSTITUIÇÃO PARA-RAIOS 69kV + 2,00 x RETROFIT BAY ENTRADA DE LINHA - 311C + 1,00 x RETROFIT BAY CONEXÃO ALTA TRAFO + 1,00 x RETROFIT BAY ENTRADA DE LINHA - 751.4 | K80: Disjuntores ELM: 13Y1, 13L2, 13T1 e 13D1 Disjuntores retrofit: 13L2, 13Y1, 13T1 e 13D1 | L80: 45291 | M80: 45829 | N80: 706570.63 | O80: 1878237.9 | P80: 1171667.2 | Q80: 706570.63 | R80: 0 | S80: - | T80: FINALIZAÇÃO | U80: FINALIZAÇÃO | V80: - | W80: INTERIOR - AP | Y80: AP | Z80: 0.86 | AA80: -51.18 | AB80: Execução | AC80: -
A81: EQTL AP | B81: RENOVAÇÃO SE | C81: Manutenção | D81: 806.110.0314 | E81: RENOVAÇÃO SE/LD | F81: AP-2331408RNV0.H | G81: MANUTENÇÃO - RENOVAÇÃO SE - SE CENTRAL - 2024 | H81: SE | I81: SE CENTRAL | J81: 1,00 x SUBSTITUIÇÃO DISJUNTOR 69kV + 1,00 x RETROFIT BAY ENTRADA DE LINHA - 311C | K81: 12V1 | L81: 45657 | M81: 45765 | N81: 145138.44 | O81: 161574.01 | P81: 16435.57 | Q81: 145138.44 | R81: 0 | S81: EXECUÇÃO | T81: FINALIZAÇÃO | U81: FINALIZAÇÃO | V81: - | W81: INTERIOR - AP | Y81: AP | Z81: 0.86 | AA81: -51.18 | AB81: Execução | AC81: -
A82: EQTL AP | B82: RENOVAÇÃO SE | C82: Manutenção | D82: 806.110.0314 | E82: RENOVAÇÃO SE/LD | F82: AP-2431408RNV0.A | G82: MANUTENÇÃO - RENOVAÇÃO SE - SE SANTANA - 2025 | H82: SE | I82: SE SANTANA | J82: 3,00 x SUBST. BANCO DE CAPACITOR 3,6MVAr - 13,8kV + 2,00 x SUBST. BANCO DE CAPACITOR 5,0MVAr - 69kV2 | K82: 13L1, 13P1 e 13T1 (LD C1, LD Portuária e ATF5-01 respectivamente) | L82: 45838 | M82: 45868 | N82: 1384786.2 | O82: 1915021.5 | P82: 530235.23 | Q82: 1384786.2 | R82: 0 | S82: - | T82: EXECUÇÃO | U82: FINALIZAÇÃO | V82: - | W82: METROPOLITANA - AP | Y82: AP | Z82: 0 | AA82: -51.38 | AB82: Execução | AC82: -
A83: EQTL AP | B83: RENOVAÇÃO SE | C83: Manutenção | D83: 806.110.0314 | E83: RENOVAÇÃO SE/LD | F83: AP-2531408RNV0.A | G83: MANUTENÇÃO - RENOVAÇÃO SE - SE LARANJAL DO JARI - 2025 | H83: SE | I83: SE LARANJAL DO JARI | J83: 0,10 x MIG 34,5/13,8kV PEQUENO + 4,00 x SUBSTITUIÇÃO RELIGADOR 13,8kV POR DISJUNTOR + 0,25 x RETROFIT INFRA. SE MÉDIO/PEQUENO PORTE + 4,00 x SUBST. DE CONJUNTO CHAVES FACA 13,8kV 630A MONOPOLAR + 4,00 x SUBST. DE CONJUNTO CHAVES TFF 13,8kV 630A MONOPOLAR | K83: 21F1, 21F2, 21F3 e 21F4 Retrofit referente a realocação do retificador da SE Central para a SE Laranjal do Jari | L83: 46022.125 | M83: 46085 | N83: 547461.45 | O83: 1105579.2 | P83: 0 | Q83: 547461.45 | R83: 558117.75 | S83: - | T83: - | U83: EXECUÇÃO | V83: - | W83: INTERIOR - AP | Y83: AP | Z83: -0.82 | AA83: -52.5 | AB83: Conceitual | AC83: Pacote SE 02 - Amapá
A84: EQTL AP | B84: RENOVAÇÃO SE | C84: Manutenção | D84: 806.110.0314 | E84: RENOVAÇÃO SE/LD | F84: AP-2531408RNV0.B | G84: MANUTENÇÃO - RENOVAÇÃO SE - SE EQUATORIAL - 2025 | H84: SE | I84: SE EQUATORIAL | J84: 10,00 x SUBST. DE CONJUNTO TCs 13,8kV + 10,00 x SUBSTITUIÇÃO DISJUNTOR 13,8kV + 10,00 x RETROFIT BAY ALIMENTADOR | K84: Códigos Operacionais (substituição e retrofit): 11C1, 11C2, 11C3, 11C4, 11C5, 11Y2, 11Y3, 11Y4, 11Y5 e 11Y6 | L84: 46022.125 | M84: 46000 | N84: 103052.22 | O84: 626883.76 | P84: 0 | Q84: 103052.22 | R84: 523831.54 | S84: - | T84: - | U84: EXECUÇÃO | V84: - | W84: METROPOLITANA - AP | Y84: AP | Z84: 0.15 | AA84: -51.07 | AB84: Conceitual | AC84: Pacote SE 02 - Amapá
A85: EQTL AP | B85: RENOVAÇÃO SE | C85: Manutenção | D85: 806.110.0314 | E85: RENOVAÇÃO SE/LD | F85: AP-2531408RNV0.C | G85: MANUTENÇÃO - RENOVAÇÃO SE - SE CENTRAL - 2025 | H85: SE | I85: SE CENTRAL | J85: 1,00 x RETROFIT BAY CONEXÃO BAIXA TRAFO + 1,00 x RETROFIT BAY ENTRADA DE LINHA - 311C + 1,00 x SUBST. DE CONJUNTO TPs 138kV + 1,00 x SUBSTITUIÇÃO DISJUNTOR 138kV + 2,00 x SUBSTITUIÇÃO PARA-RAIOS 138kV + 1,00 x SUBST. DE CONJUNTO TCs 138kV + 1,00 x SUBSTITUIÇÃO DISJUNTOR 13,8kV + 1,00 x SUBST. DE CONJUNTO TCs 13,8kV + 1,00 x SUBST. DE CONJUNTO CHAVES FACA 13,8kV 1600A MONOPOLAR + 1,00 x SUBST. DE CONJUNTO CHAVES TFF 13,8kV 1600A MONOPOLAR + 2,00 x SUBSTITUIÇÃO PARA-RAIOS 13,8kV + 0,22 x MIG 34,5/13,8kV MÉDIA | K85:  1x SUBST. DE CONJUNTO TP's 138kV (83L1);  1x SUBSTITUIÇÃO DISJUNTOR 138kV (13L1);  2x SUBSTITUIÇÃO PARA-RAIOS 138kV (93L1 e 93L2);  1x SUBST. DE CONJUNTO TC's 138kV (73T2);  1xSUBSTITUIÇÃO DISJUNTOR 13,8kV (11B2);  1xSUBST. DE CONJUNTO TC's 13,8kV (71B2);  1xSUBST. DE CONJUNTO CHAVES FACA 13,8kV 1600A MONOPOLAR (31B2-5);  1xSUBST. DE CONJUNTO CHAVES TFF 13,8kV 1600A MONOPOLAR;  2xSUBSTITUIÇÃO PARA-RAIOS 13,8kV (91C1 e 91C2);  0,22xMIG 34,5/13,8kV MÉDIA (intervenção civil e reforço da malha do aterramento);  1x RETROFIT BAY ENTRADA DE LINHA - 311C (13L1);  1 x RETROFIT BAY CONEXÃO BAIXA TRAFO (11B2); | L85: 46022 | M85: 46032 | N85: 889268.2 | O85: 1014360.3 | P85: 0 | Q85: 889268.2 | R85: 125092.1 | S85: - | T85: - | U85: EXECUÇÃO | V85: - | W85: INTERIOR - AP | Y85: AP | Z85: 0.86 | AA85: -51.18 | AB85: Módulo
A86: EQTL GO | B86: AMPLIAÇÃO DE POTÊNCIA | C86: Planejamento | D86: 807.110.0302 | E86: AMPLIAÇÃO DE SUBESTAÇÕES | F86: GO-2430208AMP0.A | G86: PLANEJAMENTO - AMPLIAÇÃO DE POTÊNCIA - SE CEPAIGO - 2025 | H86: SE | I86: SE CEPAIGO | J86: 1,00 x ENTRADA DE LINHA 69kV c/ DJ + 1,00 x RETROFIT BAY CONEXÃO ALTA TRAFO + 1,00 x INTERLIGAÇÃO DE BARRAS BPT 34,5kV c/ DJ + 1,00 x RETROFIT TRANSFORMADOR FORÇA + 1,00 x MIG 34,5/13,8kV PEQUENO + 1,00 x RETROFIT BAY ALIMENTADOR + 1,00 x BARRAMENTO DUPLO OU BPT 69kV + 1,00 x ENTRADA DE LINHA 34,5kV c/ DJ + 1,00 x CONEXÃO DE TRAFO 34,5kV c/ DJ + 1,00 x TRANSFORMADOR DE FORÇA 69/34,5kV 15/20MVA - DYN1 + 1,00 x RETROFIT BAY CONEXÃO BAIXA TRAFO + 1,00 x RETROFIT BAY TRANSFERÊNCIA <= 34,5KV - 751.1 + 1,00 x CONEXÃO DE TRAFO 69kV c/ DJ + 1,00 x INSTALAÇÃO DE TRANSFORMADOR DE FORÇA ATÉ 15MVA | L86: 45960.125 | M86: 45745 | N86: 657686.78 | O86: 3142053.9 | P86: 2484367.1 | Q86: 657686.78 | R86: 0 | S86: - | T86: - | U86: FINALIZAÇÃO | V86: - | W86: METROPOLITANA - GO | Y86: GO | Z86: -16.82 | AA86: -49.25 | AB86: Indefinido
A87: EQTL GO | B87: AMPLIAÇÃO DE POTÊNCIA | C87: Planejamento | D87: 807.110.0302 | E87: AMPLIAÇÃO DE SUBESTAÇÕES | F87: GO-2430208AMP0.B | G87: PLANEJAMENTO - AMPLIAÇÃO DE POTÊNCIA - SE GOIÁ - 2025 | H87: SE | I87: SE GOIÁ | J87: 1,00 x CONEXÃO DE TRAFO 138kV c/ DJ + 1,00 x TRANSFORMADOR DE FORÇA 138/13,8kV 25/33,3MVA - DYN1 + 1,00 x INSTALAÇÃO DE TRANSFORMADOR DE FORÇA ATÉ 40MVA + 1,00 x CONEXÃO DE TRAFO 13,8kV c/ DJ + 1,00 x BARRAMENTO DUPLO OU BPT 138kV + 5,00 x BARRAMENTO DUPLO OU BPT 13,8kV + 1,00 x ENTRADA DE LINHA 13,8kV c/ DJ + 3,00 x INTERLIGAÇÃO DE BARRAS BPT 13,8kV c/ DJ + 1,00 x MIG 138/34,5/13,8kV e MIG 138/13,8/34,5kV MÉDIA | K87: SS 183527464 - BIG BULL | L87: 45960.125 | M87: 45761 | N87: 1727746.2 | O87: 7195298.7 | P87: 5467552.5 | Q87: 1727746.2 | R87: 0 | S87: - | T87: - | U87: FINALIZAÇÃO | V87: - | W87: GOIÂNIA - GO | X87: GOIÂNIA | Y87: GO | Z87: -16.68 | AA87: -49.26 | AB87: Indefinido
A88: EQTL GO | B88: AMPLIAÇÃO DE POTÊNCIA | C88: Planejamento | D88: 807.110.0302 | E88: AMPLIAÇÃO DE SUBESTAÇÕES | F88: GO-2430208AMP0.C | G88: PLANEJAMENTO - AMPLIAÇÃO DE POTÊNCIA - SE INDEPENDÊNCIA - 2025 | H88: SE | I88: SE INDEPENDÊNCIA | J88: 1,00 x TRANSFORMADOR DE FORÇA 138/13,8kV 30/40MVA - DYN1 + 1,00 x SUBST. DE TRANSFORMADOR DE FORÇA + 1,00 x MIG 138/34,5kV e MIG 138/13,8kV PEQUENO | L88: 45960.125 | M88: 45730 | N88: 431539.11 | O88: 2769675.6 | P88: 2338136.5 | Q88: 431539.11 | R88: 0 | S88: - | T88: - | U88: FINALIZAÇÃO | V88: - | W88: METROPOLITANA - GO | Y88: GO | Z88: -16.82 | AA88: -49.25 | AB88: Indefinido
A89: EQTL GO | B89: AMPLIAÇÃO DE POTÊNCIA | C89: Planejamento | D89: 807.110.0302 | E89: AMPLIAÇÃO DE SUBESTAÇÕES | F89: GO-2430208AMP0.D | G89: PLANEJAMENTO - AMPLIAÇÃO DE POTÊNCIA - SE BOM JESUS DE GOIÁS - 2024 | H89: SE | I89: SE BOM JESUS DE GOIÁS | J89: 1,00 x TRANSFORMADOR DE FORÇA 69/34,5kV 15/20MVA - DYN1 + 1,00 x SUBST. DE TRANSFORMADOR DE FORÇA + 1,00 x RETROFIT TRANSFORMADOR FORÇA | L89: 45656 | M89: 45647 | N89: 875671.35 | O89: 3078218.2 | P89: 2202546.8 | Q89: 875671.35 | R89: 0 | S89: - | T89: EXECUÇÃO | U89: EXECUÇÃO | V89: - | W89: MORRINHOS - GO | Y89: GO | Z89: -18.22 | AA89: -49.74 | AB89: Revisão
A90: EQTL GO | B90: AMPLIAÇÃO DE POTÊNCIA | C90: Planejamento | D90: 807.110.0302 | E90: AMPLIAÇÃO DE SUBESTAÇÕES | F90: GO-2530208AMP0.1 | G90: PLANEJAMENTO - AMPLIAÇÃO DE POTÊNCIA - SE PLANALTINA - 2025 | H90: SE | I90: SE PLANALTINA | J90: 1,00 x CONEXÃO DE TRAFO 138kV c/ DJ + 1,00 x INSTALAÇÃO DE TRANSFORMADOR DE FORÇA ATÉ 40MVA + 1,00 x CONEXÃO DE TRAFO 13,8kV c/ DJ + 1,00 x BARRAMENTO DUPLO OU BPT 138kV + 6,00 x BARRAMENTO DUPLO OU BPT 13,8kV + 3,00 x ENTRADA DE LINHA 13,8kV c/ DJ + 1,00 x INTERLIGAÇÃO DE BARRAS BPT 13,8kV c/ DJ + 1,00 x CONEXÃO DE BANCO DE CAPACITOR 13,8kV c/ DJ + 2,00 x BANCO DE CAPACITOR 1,8MVAr - 13,8kV + 1,00 x MIG 138/34,5/13,8kV e MIG 138/13,8/34,5kV MÉDIA + 1,00 x TRANSFORMADOR DE FORÇA 138/13,8kV 30/40MVA - DYN1 | L90: 45960.125 | M90: 46231 | N90: 122604.9 | O90: 16000936 | P90: 0 | Q90: 122604.9 | R90: 15878331 | S90: - | T90: - | U90: ETAPA PRELIMINAR | V90: EXECUÇÃO | W90: CENTRO - GO | Y90: GO | Z90: -16.68 | AA90: -49.26 | AB90: Conceitual
A91: EQTL GO | B91: AMPLIAÇÃO DE POTÊNCIA | C91: Planejamento | D91: 807.110.0302 | E91: AMPLIAÇÃO DE SUBESTAÇÕES | F91: GO-2530208AMP0.2 | G91: PLANEJAMENTO - AMPLIAÇÃO DE POTÊNCIA - SE AEROPORTO - 2025 | H91: SE | I91: SE AEROPORTO | J91: 1,00 x CONEXÃO DE TRAFO 138kV c/ DJ + 1,00 x INSTALAÇÃO DE TRANSFORMADOR DE FORÇA ATÉ 40MVA + 1,00 x CONEXÃO DE TRAFO 13,8kV c/ DJ + 1,00 x BARRAMENTO DUPLO OU BPT 138kV + 6,00 x BARRAMENTO DUPLO OU BPT 13,8kV + 4,00 x ENTRADA DE LINHA 13,8kV c/ DJ + 1,00 x INTERLIGAÇÃO DE BARRAS BPT 13,8kV c/ DJ + 1,00 x MIG 138/34,5/13,8kV e MIG 138/13,8/34,5kV MÉDIA + 1,00 x TRANSFORMADOR DE FORÇA 138/13,8kV 30/40MVA - DYN1 | K91: 15 x Cubículos 13,8kV + 2 x ENTRADA DE LINHA 13,8KV C/DJ Obra associada à cliente - Contrato 184669528 - COOPERATIVA HABITACIONAL IMPERADOR | L91: 45960.125 | M91: 46008 | N91: 14993341 | O91: 15033566 | P91: 40224.95 | Q91: 14993341 | R91: 0 | S91: - | T91: - | U91: EXECUÇÃO | V91: - | W91: GOIÂNIA - GO | X91: GOIÂNIA | Y91: GO | Z91: -16.68 | AA91: -49.26 | AB91: Indefinido
A92: EQTL GO | B92: AMPLIAÇÃO DE POTÊNCIA | C92: Planejamento | D92: 807.110.0302 | E92: AMPLIAÇÃO DE SUBESTAÇÕES | F92: GO-2530208AMP0.3 | G92: PLANEJAMENTO - AMPLIAÇÃO DE POTÊNCIA - SE ÁGUAS LINDAS - 2025 | H92: SE | I92: SE ÁGUAS LINDAS | J92: 1,00 x TRANSFORMADOR DE FORÇA 69/13,8KV 30/40MVA - DYN1 + 1,00 x SUBST. DE TRANSFORMADOR DE FORÇA + 1,00 x MIG 69/34,5/13,8kV e MIG 69/13,8/34,5kV PEQUENO | L92: 45960.125 | M92: 46069 | N92: 5305543 | O92: 6165504.6 | P92: 9123.24 | Q92: 5305543 | R92: 850838.4 | S92: - | T92: - | U92: EXECUÇÃO | V92: FINALIZAÇÃO | W92: LUZIÂNIA - GO | Y92: GO | Z92: -15.76 | AA92: -48.28 | AB92: Indefinido
A93: EQTL GO | B93: AMPLIAÇÃO DE POTÊNCIA | C93: Planejamento | D93: 807.110.0302 | E93: AMPLIAÇÃO DE SUBESTAÇÕES | F93: GO-2530208AMP0.4 | G93: PLANEJAMENTO - AMPLIAÇÃO DE POTÊNCIA - SE CARAJÁS - 2025 | H93: SE | I93: SE CARAJÁS | J93: 1,00 x SUBST. DE TRANSFORMADOR DE FORÇA + 1,00 x TRANSFORMADOR DE FORÇA 138/69KV 24/32/40MVA – DYN1 + 1,00 x MIG 138/34,5/13,8kV e MIG 138/13,8/34,5kV PEQUENO | L93: 45960.125 | M93: 45853 | N93: 3237011.5 | O93: 3248990.4 | P93: 11978.92 | Q93: 3237011.5 | R93: 0 | S93: - | T93: - | U93: EXECUÇÃO | V93: - | W93: GOIÂNIA - GO | Y93: GO | Z93: -15.87 | AA93: -50.87 | AB93: Indefinido
A94: EQTL GO | B94: AMPLIAÇÃO DE POTÊNCIA | C94: Planejamento | D94: 807.110.0302 | E94: AMPLIAÇÃO DE SUBESTAÇÕES | F94: GO-2530208AMP0.5 | G94: PLANEJAMENTO - AMPLIAÇÃO DE POTÊNCIA - SE ITABERAÍ - 2025 | H94: SE | I94: SE ITABERAÍ | J94: 2,00 x BARRAMENTO DUPLO OU BPT 138kV + 1,00 x CONEXÃO DE TRAFO 138kV c/ DJ + 1,00 x INSTALAÇÃO DE TRANSFORMADOR DE FORÇA ATÉ 40MVA + 1,00 x TRANSFORMADOR DE FORÇA 138/34,5kV 30/40MVA - DYN1 + 1,00 x CONEXÃO DE TRAFO 34,5kV c/ DJ + 1,00 x BARRAMENTO DUPLO OU BPT 34,5kV + 2,00 x INTERLIGAÇÃO DE BARRAS 34,5kV c/ DJ + 1,00 x MIG 138/34,5kV e MIG 138/13,8kV PEQUENO | L94: 45960.125 | M94: 46057 | N94: 12361496 | O94: 12387948 | P94: 26452.73 | Q94: 12361496 | R94: 0 | S94: - | T94: - | U94: EXECUÇÃO | V94: - | W94: MONTES BELOS - GO | Y94: GO | Z94: -16.02 | AA94: -49.81 | AB94: Indefinido
A95: EQTL GO | B95: AMPLIAÇÃO DE POTÊNCIA | C95: Planejamento | D95: 807.110.0302 | E95: AMPLIAÇÃO DE SUBESTAÇÕES | F95: GO-2530208AMP0.6 | G95: PLANEJAMENTO - AMPLIAÇÃO DE POTÊNCIA - SE ITABERAÍ - 2025 | H95: SE | I95: SE ITABERAÍ | J95: 1,00 x CONEXÃO DE TRAFO 138kV c/ DJ + 1,00 x INSTALAÇÃO DE TRANSFORMADOR DE FORÇA ATÉ 40MVA + 1,00 x CONEXÃO DE TRAFO 13,8kV c/ DJ + 2,00 x ENTRADA DE LINHA 13,8kV c/ DJ + 4,00 x BARRAMENTO DUPLO OU BPT 13,8kV + 2,00 x INTERLIGAÇÃO DE BARRAS 13,8kV c/ DJ + 1,00 x MIG 138/34,5kV e MIG 138/13,8kV PEQUENO + 1,00 x TRANSFORMADOR DE FORÇA 138/13,8kV 30/40MVA - DYN1 | L95: 45960.125 | M95: 46202 | N95: 0 | O95: 17682843 | P95: 212330.9 | Q95: 0 | R95: 17470512 | S95: - | T95: - | U95: EXECUÇÃO | V95: FINALIZAÇÃO | W95: MONTES BELOS - GO | Y95: GO | Z95: -16.02 | AA95: -49.81 | AB95: Conceitual
A96: EQTL GO | B96: AMPLIAÇÃO DE POTÊNCIA | C96: Planejamento | D96: 807.110.0302 | E96: AMPLIAÇÃO DE SUBESTAÇÕES | F96: GO-2530208AMP0.8 | G96: PLANEJAMENTO - AMPLIAÇÃO DE POTÊNCIA - SE ITAPIRAPUA - 2024 | H96: SE | I96: SE ITAPIRAPUA | J96: 1,00 x SUBST. DE TRANSFORMADOR DE FORÇA + 1,00 x TRANSFORMADOR DE FORÇA 34,5/13,8kV 10/12,5MVA - DYN1 | L96: 45638.125 | M96: 45639 | N96: 346613.08 | O96: 852158.49 | P96: 505545.41 | Q96: 346613.08 | R96: 0 | S96: - | T96: EXECUÇÃO | U96: - | V96: - | W96: MONTES BELOS - GO | Y96: GO | Z96: -15.83 | AA96: -50.25 | AB96: Indefinido
A97: EQTL GO | B97: AMPLIAÇÃO DE POTÊNCIA | C97: Planejamento | D97: 807.110.0302 | E97: AMPLIAÇÃO DE SUBESTAÇÕES | F97: GO-2530208AMP0.9 | G97: PLANEJAMENTO - AMPLIAÇÃO DE POTÊNCIA - SE PORANGATU - 2025 | H97: SE | I97: SE PORANGATU | J97: 1,00 x TRANSFORMADOR DE FORÇA 138/13,8kV 25/33,3MVA - DYN1 + 1,00 x INSTALAÇÃO DE TRANSFORMADOR DE FORÇA ATÉ 40MVA + 1,00 x CONEXÃO DE TRAFO 138kV c/ DJ + 1,00 x BARRAMENTO DUPLO OU BPT 138kV + 1,00 x MIG 138/69/34,5/13,8kV GRANDE | L97: 45960.125 | M97: 45715 | N97: 1102979.1 | O97: 4462663.1 | P97: 3359684 | Q97: 1102979.1 | R97: 0 | S97: - | T97: - | U97: FINALIZAÇÃO | V97: - | W97: URUAÇU - GO | Y97: GO | Z97: -13.43 | AA97: -49.15 | AB97: Indefinido
A98: EQTL GO | B98: AMPLIAÇÃO DE POTÊNCIA | C98: Planejamento | D98: 807.110.0302 | E98: AMPLIAÇÃO DE SUBESTAÇÕES | F98: GO-2530208AMP0.A | G98: PLANEJAMENTO - AMPLIAÇÃO DE POTÊNCIA - SE ANHANGUERA - 2025 | H98: SE | I98: SE ANHANGUERA | J98: 1,00 x TRANSFORMADOR DE FORÇA 69/13,8KV 30/40MVA - DYN1 + 1,00 x SUBST. DE TRANSFORMADOR DE FORÇA + 2,00 x BARRAMENTO DUPLO OU BPT 13,8kV + 2,00 x ENTRADA DE LINHA 13,8kV c/ DJ + 1,00 x CONEXÃO DE TRAFO 69kV c/ DJ + 1,00 x CONEXÃO DE TRAFO 13,8kV c/ DJ + 1,00 x INTERLIGAÇÃO DE BARRAS BPT 13,8kV c/ DJ + 1,00 x DESATIVAÇÃO DISJUNTOR OU RELIGADOR ATÉ 34,5kV + 1,00 x MIG 69/34,5kV e MIG 69/13,8kV MÉDIA | L98: 45960.125 | M98: 46125 | N98: 3518845.3 | O98: 12602860 | P98: 0 | Q98: 3518845.3 | R98: 9084014.5 | S98: - | T98: - | U98: EXECUÇÃO | V98: FINALIZAÇÃO | W98: METROPOLITANA - GO | Y98: GO | Z98: -16.82 | AA98: -49.25 | AB98: Indefinido
A99: EQTL GO | B99: AMPLIAÇÃO DE POTÊNCIA | C99: Planejamento | D99: 807.110.0302 | E99: AMPLIAÇÃO DE SUBESTAÇÕES | F99: GO-2530208AMP0.B | G99: PLANEJAMENTO - AMPLIAÇÃO DE POTÊNCIA - SE IACIARA - 2025 | H99: SE | I99: SE IACIARA | J99: 1,00 x TRANSFORMADOR DE FORÇA 69/34,5kV 20/26,6MVA - DYN1 + 1,00 x SUBST. DE TRANSFORMADOR DE FORÇA + 1,00 x BANCO DE CAPACITOR 5,0MVAr - 69kV + 1,00 x CONEXÃO DE BANCO DE CAPACITOR 69kV c/ DJ + 1,00 x MIG 69/34,5kV e MIG 69/13,8kV PEQUENO + 1,00 x BARRAMENTO DUPLO OU BPT 13,8kV + 1,00 x ENTRADA DE LINHA 13,8kV c/ DJ | L99: 45960.125 | M99: 46160 | N99: 4843540.4 | O99: 9448156 | P99: 0 | Q99: 4843540.4 | R99: 4604615.6 | S99: - | T99: - | U99: EXECUÇÃO | V99: FINALIZAÇÃO | W99: NORDESTE - GO | Y99: GO | Z99: -14.1 | AA99: -46.63 | AB99: Conceitual
A100: EQTL GO | B100: AMPLIAÇÃO DE POTÊNCIA | C100: Planejamento | D100: 807.110.0302 | E100: AMPLIAÇÃO DE SUBESTAÇÕES | F100: GO-2530208AMP0.C | G100: PLANEJAMENTO - AMPLIAÇÃO DE POTÊNCIA - SE INDIARA - 2025 | H100: SE | I100: SE INDIARA | J100: 1,00 x SUBST. DE TRANSFORMADOR DE FORÇA + 1,00 x REGULADOR DE TENSÃO 3F - 12 MVA 34,5KV + 1,00 x TRANSFORMADOR DE FORÇA 34,5/13,8kV 10/12,5MVA - DYN1 | K100: Substituição do BRT 34,5 kV de 6 MVA por outro de 12 MVA | L100: 45960.125 | M100: 46144 | N100: 910757 | O100: 2894422.1 | P100: 0 | Q100: 910757 | R100: 1983665.1 | S100: - | T100: - | U100: ETAPA PRELIMINAR | V100: EXECUÇÃO | X100: INDIARA | Y100: GO | Z100: -16 | AA100: -48 | AB100: Indefinido
...

Sheet Contratos
A3: ID | B3: EMPRESA | C3: TIPO | D3: CONTRATO JURÍDICO | E3: CONTRATO | F3: COD. FORNECEDOR | G3: FORNECEDOR | H3: ITEM | I3: LINHAS | J3: RESPONSÁVEL EQTL | K3: MATRICULA RESPONSÁVEL EQTL | L3: RESPONSÁVEL FORNECEDOR | M3: CPF RESPONSÁVEL FORNECEDOR | N3: CONTATO FORNECEDOR
A4: 1 | B4: EQUATORIAL GOIÁS | C4: EXECUÇÃO | D4: 5000000741 | E4: 4600027637 | F4: 4017934 | G4: ENERGY SYSTEN CONSTRUCOES E MANUTEN | H4: {=MAX(IF(MSRV5!G:G=Contratos!E4,MSRV5!H:H))} -> 30 | I4: =COUNTIFS(MSRV5!G:G,E4,MSRV5!H:H,H4) -> 913 | J4: FELIPPE GEORGE DE LIMA WALBON | K4: U21057705 | L4: GIOVANNI CENDES FINOTTI | M4: 027.157.771-16 | N4: +55 62 98102-0756
A5: 1 | B5: EQUATORIAL GOIÁS | C5: EXECUÇÃO | D5: 5000000741 | E5: 4600027637 | F5: 4017934 | G5: ENERGY SYSTEN CONSTRUCOES E MANUTEN | H5: {=MAX(IF(MSRV5!G:G=Contratos!E5,MSRV5!H:H))} -> 30 | I5: =COUNTIFS(MSRV5!G:G,E5,MSRV5!H:H,H5) -> 913 | J5: GUSTAVO DE JESUS OLIVEIRA | K5: G52901707 | L5: GIOVANNI CENDES FINOTTI | M5: 027.157.771-16 | N5: +55 62 98102-0756
A6: 1 | B6: EQUATORIAL GOIÁS | C6: EXECUÇÃO | D6: 5000000741 | E6: 4600027637 | F6: 4017934 | G6: ENERGY SYSTEN CONSTRUCOES E MANUTEN | H6: {=MAX(IF(MSRV5!G:G=Contratos!E6,MSRV5!H:H))} -> 30 | I6: =COUNTIFS(MSRV5!G:G,E6,MSRV5!H:H,H6) -> 913 | J6: JONATAS SIQUEIRA COSTA | K6: U21024073 | L6: GIOVANNI CENDES FINOTTI | M6: 027.157.771-16 | N6: +55 62 98102-0756
A7: 1 | B7: EQUATORIAL GOIÁS | C7: EXECUÇÃO | D7: 5000000741 | E7: 4600027637 | F7: 4017934 | G7: ENERGY SYSTEN CONSTRUCOES E MANUTEN | H7: {=MAX(IF(MSRV5!G:G=Contratos!E7,MSRV5!H:H))} -> 30 | I7: =COUNTIFS(MSRV5!G:G,E7,MSRV5!H:H,H7) -> 913 | J7: LEANDRO SANTOS DIAS | K7: U21057706 | L7: GIOVANNI CENDES FINOTTI | M7: 027.157.771-16 | N7: +55 62 98102-0756
