Workbook

Sheet LPU
A2: LPU - LISTA DE PREÇOS UNITÁRIOS | J2: Revisão 4
A4: ITEM | B4: CÓD. | C4: DESCRIÇÃO SIMPLES | D4: UN. | E4: QUANT. | F4: PREÇO UNIT. BASE | G4: PREÇO TOTAL BASE | H4: PREÇO UNIT. AJUSTADO | I4: PREÇO TOTAL AJUSTADO | J4: INFORMAÇÕES ADICIONAIS
A5: I | C5: OBRAS DIVERSAS | F5: TOTAL | G5: =SUBTOTAL(9,G6:G1007) -> 655458.06 | H5: TOTAL | I5: =SUBTOTAL(9,I6:I1007) -> 1114692.4
A6: 1.0 | C6: SERVIÇOS PRELIMINARES - MOBILIZAÇÃO & DESMOBILIZAÇÃO (FATOR "M") | F6: SUB. TOTAL | G6: =SUBTOTAL(9,G7:G80) -> 124497.88 | H6: SUB. TOTAL | I6: =SUBTOTAL(9,I7:I80) -> 106323.68
A7: 1.1 | B7: 5000011080 | C7: MOB / DESMOBILIZACAO LD DE 0 A 50KM LD | D7: KM | F7: 420.83 | G7: =ROUND(E7*F7,2) -> 0 | H7: =ROUND('[1]RESUMO DA PROPOSTA'!$C$16*F7,2) -> 589.16 | I7: =ROUND(E7*H7,2) -> 0
A8: 1.2 | B8: 5000011081 | C8: MOB / DESMOBILIZACAO LD DE 51 A 200KM LD | D8: KM | F8: 459.8 | G8: =ROUND(E8*F8,2) -> 0 | H8: =ROUND('[1]RESUMO DA PROPOSTA'!$C$16*F8,2) -> 643.72 | I8: =ROUND(E8*H8,2) -> 0
A9: 1.3 | B9: 5000011082 | C9: MOB/ DESMOBILIZACAO LD ACIMA DE 600KM LD | D9: KM | F9: 148.13 | G9: =ROUND(E9*F9,2) -> 0 | H9: =ROUND('[1]RESUMO DA PROPOSTA'!$C$16*F9,2) -> 207.38 | I9: =ROUND(E9*H9,2) -> 0
A10: 1.4 | B10: 5000011083 | C10: MOB/ DESMOBILIZACAO LD DE 201 A 400KM LD | D10: KM | F10: 262.59 | G10: =ROUND(E10*F10,2) -> 0 | H10: =ROUND('[1]RESUMO DA PROPOSTA'!$C$16*F10,2) -> 367.63 | I10: =ROUND(E10*H10,2) -> 0
A11: 1.5 | B11: 5000011084 | C11: DESMOBIL 0 A 200KM EQP 5H RESIT OHM LD | D11: UN | F11: 92.58 | G11: =ROUND(E11*F11,2) -> 0 | H11: =ROUND('[1]RESUMO DA PROPOSTA'!$C$16*F11,2) -> 129.61 | I11: =ROUND(E11*H11,2) -> 0
A12: 1.6 | B12: 5000011085 | C12: DESMOBIL 0 A 200KM EQP 5H SERV TEC LD | D12: UN | F12: 117.83 | G12: =ROUND(E12*F12,2) -> 0 | H12: =ROUND('[1]RESUMO DA PROPOSTA'!$C$16*F12,2) -> 164.96 | I12: =ROUND(E12*H12,2) -> 0
A13: 1.7 | B13: 5000011086 | C13: DESMOBIL 201 A 400KM EQP 5H RESIT OHM LD | D13: UN | F13: 143.09 | G13: =ROUND(E13*F13,2) -> 0 | H13: =ROUND('[1]RESUMO DA PROPOSTA'!$C$16*F13,2) -> 200.33 | I13: =ROUND(E13*H13,2) -> 0
A14: 1.8 | B14: 5000011087 | C14: DESMOBIL 201 A 400KM EQP 5H SERV TEC LD | D14: UN | F14: 13.47 | G14: =ROUND(E14*F14,2) -> 0 | H14: =ROUND('[1]RESUMO DA PROPOSTA'!$C$16*F14,2) -> 18.86 | I14: =ROUND(E14*H14,2) -> 0
A15: 1.9 | B15: 5000011088 | C15: DESMOBIL 401 A 600KM EQP 5H RESIT OHM LD | D15: UN | F15: 201.99 | G15: =ROUND(E15*F15,2) -> 0 | H15: =ROUND('[1]RESUMO DA PROPOSTA'!$C$16*F15,2) -> 282.79 | I15: =ROUND(E15*H15,2) -> 0
A16: 1.10 | B16: 5000011089 | C16: DESMOBIL 401 A 600KM EQP 5H SERV TEC LD | D16: UN | F16: 201.99 | G16: =ROUND(E16*F16,2) -> 0 | H16: =ROUND('[1]RESUMO DA PROPOSTA'!$C$16*F16,2) -> 282.79 | I16: =ROUND(E16*H16,2) -> 0
A17: 1.11 | B17: 5000011090 | C17: DESMOBILIZAR 201 A 400KM EQP 5H SOND LD | D17: UN | F17: 215.46 | G17: =ROUND(E17*F17,2) -> 0 | H17: =ROUND('[1]RESUMO DA PROPOSTA'!$C$16*F17,2) -> 301.64 | I17: =ROUND(E17*H17,2) -> 0
A18: 1.12 | B18: 5000011091 | C18: DESMOBILIZAR 201 A 400KM EQP 5H TOPOG LD | D18: UN | F18: 1851.63 | G18: =ROUND(E18*F18,2) -> 0 | H18: =ROUND('[1]RESUMO DA PROPOSTA'!$C$16*F18,2) -> 2592.28 | I18: =ROUND(E18*H18,2) -> 0
... A48: 1.42 | B48: 5000011122 | C48: MOBIL. SER. PEQ. PORTE, DUR. MÁX. DE 30D | D48: VB | F48: 5961.81 | G48: =ROUND(E48*F48,2) -> 0 | H48: =ROUND('[1]RESUMO DA PROPOSTA'!$C$16*F48,2) -> 8346.53 | I48: =ROUND(E48*H48,2) -> 0
A49: 1.43 | B49: 5000011123 | C49: MOBILIZAR SERV. GRANDE PORTE DUR. >120 D | D49: VB | E49: 1 | F49: 20295.38 | G49: =ROUND(E49*F49,2) -> 20295.38 | H49: =ROUND('[1]RESUMO DA PROPOSTA'!$C$16*F49,2) -> 28413.53 | I49: =ROUND(E49*H49,2) -> 28413.53
A50: 1.44 | B50: 5000011124 | C50: MOBIL. SERV. MÉD. PORTE DUR. >60 E <120D | D50: VB | F50: 11654.99 | G50: =ROUND(E50*F50,2) -> 0 | H50: =ROUND('[1]RESUMO DA PROPOSTA'!$C$16*F50,2) -> 16316.99 | I50: =ROUND(E50*H50,2) -> 0
A51: 1.45 | B51: 5000011125 | C51: MOBILIZ. SER. PEQ. PORTE, DUR. MÁX. 60D | D51: VB | F51: 7357.5 | G51: =ROUND(E51*F51,2) -> 0 | H51: =ROUND('[1]RESUMO DA PROPOSTA'!$C$16*F51,2) -> 10300.5 | I51: =ROUND(E51*H51,2) -> 0
A52: 1.46 | B52: 5000011385 | C52: LOCAÇÃO, MARCAÇÃO E ACOMPANHAM. DA OBRA | D52: UN | E52: 1 | F52: 9759.24 | G52: =ROUND(E52*F52,2) -> 9759.24 | H52: =ROUND('[1]RESUMO DA PROPOSTA'!$C$16*F52,2) -> 13662.94 | I52: =ROUND(E52*H52,2) -> 13662.94
A53: 1.47 | B53: 5000011126 | C53: LIGAÇÃO PROVISÓRIA DE LUZ E FORÇA P/ SE | D53: UN | E53: 1 | F53: 3543.65 | G53: =ROUND(E53*F53,2) -> 3543.65 | H53: =ROUND('[1]RESUMO DA PROPOSTA'!$C$16*F53,2) -> 4961.11 | I53: =ROUND(E53*H53,2) -> 4961.11
A54: 1.48 | B54: 5000011386 | C54: INSTALAÇÕES PROVIS. DE ENERGIA ELÉTRICA | D54: MÊS | E54: 1 | F54: 4365.87 | G54: =ROUND(E54*F54,2) -> 4365.87 | H54: =ROUND('[1]RESUMO DA PROPOSTA'!$C$16*F54,2) -> 6112.22 | I54: =ROUND(E54*H54,2) -> 6112.22
A55: 1.49 | B55: 5000011387 | C55: TELA TAPUME (ISOLAMENTO/SINALIZAÇÃO) | D55: M | E55: 17.5 | F55: 13.74 | G55: =ROUND(E55*F55,2) -> 240.45 | H55: =ROUND('[1]RESUMO DA PROPOSTA'!$C$16*F55,2) -> 19.24 | I55: =ROUND(E55*H55,2) -> 336.7
A56: 1.50 | B56: 5000011127 | C56: LIMPEZA GERAL DA OBRA (CIVIL) | D56: UN | F56: 927.5 | G56: =ROUND(E56*F56,2) -> 0 | H56: =ROUND('[1]RESUMO DA PROPOSTA'!$C$16*F56,2) -> 1298.5 | I56: =ROUND(E56*H56,2) -> 0
A57: 1.51 | B57: 5000011388 | C57: LIMPEZA INICIAL | D57: UN | E57: 1 | F57: 2277.86 | G57: =ROUND(E57*F57,2) -> 2277.86 | H57: =ROUND('[1]RESUMO DA PROPOSTA'!$C$16*F57,2) -> 3189 | I57: =ROUND(E57*H57,2) -> 3189
A58: 1.52 | B58: 5000011389 | C58: INSTALAÇÕES PROVISÓRIAS DE ÁGUA E ESGOTO | D58: MÊS | E58: 1 | F58: 3500 | G58: =ROUND(E58*F58,2) -> 3500 | H58: =ROUND('[1]RESUMO DA PROPOSTA'!$C$16*F58,2) -> 4900 | I58: =ROUND(E58*H58,2) -> 4900
A59: 1.53 | B59: 5000011128 | C59: CONSTRUIR BARRACÃO DE OBRAS | D59: M2 | F59: 545.46 | G59: =ROUND(E59*F59,2) -> 0 | H59: =ROUND('[1]RESUMO DA PROPOSTA'!$C$16*F59,2) -> 763.64 | I59: =ROUND(E59*H59,2) -> 0
A60: 1.54 | B60: 5000011129 | C60: EMITIR ART E DOCUMENTAÇÃO DE AMPLI SE'S | D60: UN | E60: 2 | F60: 2742.75 | G60: =ROUND(E60*F60,2) -> 5485.5 | H60: =ROUND('[1]RESUMO DA PROPOSTA'!$C$16*F60,2) -> 3839.85 | I60: =ROUND(E60*H60,2) -> 7679.7
A61: 1.55 | B61: 5000011130 | C61: EMITIR ART E DOCUMENTAÇÃO DE NOVAS SE'S | D61: UN | F61: 5611 | G61: =ROUND(E61*F61,2) -> 0 | H61: =ROUND('[1]RESUMO DA PROPOSTA'!$C$16*F61,2) -> 7855.4 | I61: =ROUND(E61*H61,2) -> 0
A62: 1.56 | B62: 5000011131 | C62: INSTALAR PLACA DE IDENTIFICAÇÃO DE OBRAS | D62: M2 | E62: 3 | F62: 694.12 | G62: =ROUND(E62*F62,2) -> 2082.36 | H62: =ROUND('[1]RESUMO DA PROPOSTA'!$C$16*F62,2) -> 971.77 | I62: =ROUND(E62*H62,2) -> 2915.31
A63: 1.57 | B63: 5000011132 | C63: SERVIÇO INSTALAR TAPUME P/ ISOLAM. OBRAS | D63: M2 | F63: 137.73 | G63: =ROUND(E63*F63,2) -> 0 | H63: =ROUND('[1]RESUMO DA PROPOSTA'!$C$16*F63,2) -> 192.82 | I63: =ROUND(E63*H63,2) -> 0
A64: 1.58 | B64: 5000011133 | C64: FORNEC. E INSTAL. ESCRIT. CONTAINER OBRA | D64: MÊS | E64: 1 | F64: 1555.45 | G64: =ROUND(E64*F64,2) -> 1555.45 | H64: =ROUND('[1]RESUMO DA PROPOSTA'!$C$16*F64,2) -> 2177.63 | I64: =ROUND(E64*H64,2) -> 2177.63
A65: 1.59 | B65: 5000011134 | C65: FORNEC. E INSTAL. DEPOSI. CONTAINER OBRA | D65: MÊS | F65: 1184.24 | G65: =ROUND(E65*F65,2) -> 0 | H65: =ROUND('[1]RESUMO DA PROPOSTA'!$C$16*F65,2) -> 1657.94 | I65: =ROUND(E65*H65,2) -> 0
A66: 1.60 | B66: 5000011135 | C66: DISPONIBILIZAR VEICULOS PARA SERVIÇO | D66: KM | F66: 61.17 | G66: =ROUND(E66*F66,2) -> 0 | H66: =ROUND('[1]RESUMO DA PROPOSTA'!$C$16*F66,2) -> 85.64 | I66: =ROUND(E66*H66,2) -> 0
A67: 1.61 | B67: 5000011136 | C67: GUARDA FISICA DIURNA/NOTURNA DA SE | D67: DIA | F67: 482.55 | G67: =ROUND(E67*F67,2) -> 0 | H67: =ROUND('[1]RESUMO DA PROPOSTA'!$C$16*F67,2) -> 675.57 | I67: =ROUND(E67*H67,2) -> 0
A68: 1.62 | B68: 3000018187 | C68: ALUGUEL DE CONTAINER P/ BANHEIROS | D68: MÊS | E68: 1 | F68: 1085.04 | G68: =ROUND(E68*F68,2) -> 1085.04 | H68: =ROUND('[1]RESUMO DA PROPOSTA'!$C$16*F68,2) -> 1519.06 | I68: =ROUND(E68*H68,2) -> 1519.06
A69: 1.64 | B69: 3000018189 | C69: ALUGUEL DE CONTAINER PARA REFEITÓRIO | D69: MÊS | F69: 400 | G69: =ROUND(E69*F69,2) -> 0 | H69: =ROUND('[1]RESUMO DA PROPOSTA'!$C$16*F69,2) -> 560 | I69: =ROUND(E69*H69,2) -> 0
A70: 1.65 | B70: 5000011390 | C70: BANHEIRO QUÍMICO | D70: MÊS | F70: 1972.8 | G70: =ROUND(E70*F70,2) -> 0 | H70: =ROUND('[1]RESUMO DA PROPOSTA'!$C$16*F70,2) -> 2761.92 | I70: =ROUND(E70*H70,2) -> 0
A71: 1.66 | B71: 5000011391 | C71: ALUGUEL DE CONTAINER P/ ALMOXARIFADO | D71: MÊS | E71: 1 | F71: 678.16 | G71: =ROUND(E71*F71,2) -> 678.16 | H71: =ROUND('[1]RESUMO DA PROPOSTA'!$C$16*F71,2) -> 949.42 | I71: =ROUND(E71*H71,2) -> 949.42
A72: 1.67 | B72: 5000011392 | C72: ALUGUEL DE 2 APARELHOS DE AR CONDIC. | D72: MÊS | F72: 394.56 | G72: =ROUND(E72*F72,2) -> 0 | H72: =ROUND('[1]RESUMO DA PROPOSTA'!$C$16*F72,2) -> 552.38 | I72: =ROUND(E72*H72,2) -> 0
A73: 1.68 | B73: 5000011393 | C73: CONS. DE ENERGIA (150 KW +IMPOSTOS) | D73: MÊS | F73: 219.02 | G73: =ROUND(E73*F73,2) -> 0 | H73: =ROUND('[1]RESUMO DA PROPOSTA'!$C$16*F73,2) -> 306.63 | I73: =ROUND(E73*H73,2) -> 0
A74: 1.69 | B74: 5000011394 | C74: CONSUMO DE ÁGUA 20 M³ | D74: MÊS | F74: 207.01 | G74: =ROUND(E74*F74,2) -> 0 | H74: =ROUND('[1]RESUMO DA PROPOSTA'!$C$16*F74,2) -> 289.81 | I74: =ROUND(E74*H74,2) -> 0
A75: 1.70 | B75: 5000011395 | C75: TRANSPORTE DOS CONTAINER | D75: UN | E75: 2 | F75: 2367.36 | G75: =ROUND(E75*F75,2) -> 4734.72 | H75: =ROUND('[1]RESUMO DA PROPOSTA'!$C$16*F75,2) -> 3314.3 | I75: =ROUND(E75*H75,2) -> 6628.6
A76: 1.71 | B76: 5000011396 | C76: AÇÕES DE SEGURANÇA | D76: VB | E76: 1 | F76: 6148.56 | G76: =ROUND(E76*F76,2) -> 6148.56 | H76: =ROUND('[1]RESUMO DA PROPOSTA'!$C$16*F76,2) -> 8607.98 | I76: =ROUND(E76*H76,2) -> 8607.98
A77: 1.72 | B77: 5000011397 | C77: AÇÕES AMBIENTAIS | D77: VB | E77: 1 | F77: 5260.8 | G77: =ROUND(E77*F77,2) -> 5260.8 | H77: =ROUND('[1]RESUMO DA PROPOSTA'!$C$16*F77,2) -> 7365.12 | I77: =ROUND(E77*H77,2) -> 7365.12
A78: 1.73 | B78: 5000011398 | C78: BARRAÇÃO REFEITÓRIO 6X6m | D78: UN | E78: 1 | F78: 4932.39 | G78: =ROUND(E78*F78,2) -> 4932.39 | H78: =ROUND('[1]RESUMO DA PROPOSTA'!$C$16*F78,2) -> 6905.35 | I78: =ROUND(E78*H78,2) -> 6905.35
A79: 1.74 | B79: 5000011399 | C79: LIMPEZA DURANTE E NO FINAL DA OBRA | D79: MÊS | F79: 1678.72 | G79: =ROUND(E79*F79,2) -> 0 | H79: =ROUND('[1]RESUMO DA PROPOSTA'!$C$16*F79,2) -> 2350.21 | I79: =ROUND(E79*H79,2) -> 0
A80: 1.75 | B80: 5000011400 | C80: MÃO DE OBRA DE ADMINISTRAÇÃO LOCAL | D80: % | E80: 8 | F80: =SUBTOTAL(9,(G7:G79),(G82:G1005)) -> 606905.61 | G80: =ROUND(E80%*F80,2) -> 48552.45 | H80: 0.08 | I80: =ROUND(E80%*H80,2) -> 0.01
A81: 2.0 | C81: SERVIÇOS PRELIMINARES - TRANSPORTE (FATOR "T") | F81: SUB. TOTAL | G81: =SUBTOTAL(9,G82:G94) -> 1138.94 | H81: SUB. TOTAL | I81: =SUBTOTAL(9,I82:I94) -> 1708.41
A82: 2.1 | B82: 3000001041 | C82: TRANSPORTE E ESPALHAMENTO | D82: M3 | F82: 10.95 | G82: =ROUND(E82*F82,2) -> 0 | H82: =ROUND('[1]RESUMO DA PROPOSTA'!$C$17*F82,2) -> 16.43 | I82: =ROUND(E82*H82,2) -> 0
A83: 2.2 | B83: 5000007398 | C83: TRANSPORTE DAS ESCAVAÇÕES PARA LOCAL ADEQUADO | D83: KM | F83: 27 | G83: =ROUND(E83*F83,2) -> 0 | H83: =ROUND('[1]RESUMO DA PROPOSTA'!$C$17*F83,2) -> 40.5 | I83: =ROUND(E83*H83,2) -> 0
A84: 2.3 | B84: 5000007476 | C84: TRANSPORTE/REMOÇÃO DO MATERIAL PROVENIENTE DAS ESCAVAÇÕES PARA FORA DO PÁTIO | D84: M3 | F84: 66.53 | G84: =ROUND(E84*F84,2) -> 0 | H84: =ROUND('[1]RESUMO DA PROPOSTA'!$C$17*F84,2) -> 99.8 | I84: =ROUND(E84*H84,2) -> 0
A85: 2.4 | B85: 5000007567 | C85: TRANSPORTE E ESPALHAMENTO ATÉ 200 M | D85: M3 | F85: 2.05 | G85: =ROUND(E85*F85,2) -> 0 | H85: =ROUND('[1]RESUMO DA PROPOSTA'!$C$17*F85,2) -> 3.08 | I85: =ROUND(E85*H85,2) -> 0
A86: 2.5 | B86: 5000007569 | C86: TRANSPORTE DE POSTE DE AT EM DISTÂNCIA ATÉ 70KM | D86: Km RODADO | E86: 47 | F86: 18 | G86: =ROUND(E86*F86,2) -> 846 | H86: =ROUND('[1]RESUMO DA PROPOSTA'!$C$17*F86,2) -> 27 | I86: =ROUND(E86*H86,2) -> 1269
A87: 2.6 | B87: 5000007570 | C87: TRANSPORTE DE POSTE DE AT EM DISTÂNCIA SUPERIOR A 70KM | D87: Km RODADO | F87: 13 | G87: =ROUND(E87*F87,2) -> 0 | H87: =ROUND('[1]RESUMO DA PROPOSTA'!$C$17*F87,2) -> 19.5 | I87: =ROUND(E87*H87,2) -> 0
A88: 2.7 | B88: 5000007722 | C88: TRANSPORTE DE EQUIPAMENTOS MENORES - LT | D88: KM | F88: 2 | G88: =ROUND(E88*F88,2) -> 0 | H88: =ROUND('[1]RESUMO DA PROPOSTA'!$C$17*F88,2) -> 3 | I88: =ROUND(E88*H88,2) -> 0
A89: 2.8 | B89: 5000011137 | C89: S. FRETE/TRANSP. EQUIP./MAT. DMT>800KM. | D89: KM | F89: 7.61 | G89: =ROUND(E89*F89,2) -> 0 | H89: =ROUND('[1]RESUMO DA PROPOSTA'!$C$17*F89,2) -> 11.42 | I89: =ROUND(E89*H89,2) -> 0
A90: 2.9 | B90: 5000011138 | C90: S. FRETE/TRANS. EQ./MAT. 401<DMT<800KM. | D90: KM | F90: 9.98 | G90: =ROUND(E90*F90,2) -> 0 | H90: =ROUND('[1]RESUMO DA PROPOSTA'!$C$17*F90,2) -> 14.97 | I90: =ROUND(E90*H90,2) -> 0
A91: 2.10 | B91: 5000011139 | C91: S. FRETE/TRAN. EQ. /MAT. 201<DMT<400KM. | D91: KM | F91: 7.74 | G91: =ROUND(E91*F91,2) -> 0 | H91: =ROUND('[1]RESUMO DA PROPOSTA'!$C$17*F91,2) -> 11.61 | I91: =ROUND(E91*H91,2) -> 0
A92: 2.11 | B92: 5000011140 | C92: S. FRET./TRA. EQUIP./MAT. P/ OBR. CAPIT. | D92: UN | F92: 1510.48 | G92: =ROUND(E92*F92,2) -> 0 | H92: =ROUND('[1]RESUMO DA PROPOSTA'!$C$17*F92,2) -> 2265.72 | I92: =ROUND(E92*H92,2) -> 0
A93: 2.12 | B93: 5000011141 | C93: S. FRETE/TRANSP. EQUIP./MAT. DMT<200KM. | D93: UN | F93: 19.63 | G93: =ROUND(E93*F93,2) -> 0 | H93: =ROUND('[1]RESUMO DA PROPOSTA'!$C$17*F93,2) -> 29.45 | I93: =ROUND(E93*H93,2) -> 0
A94: 2.13 | B94: 5000011401 | C94: TRANSP. DE EQUIPAM. E/OU MATERIAIS - SE | D94: KM | E94: 48.5 | F94: 6.04 | G94: =ROUND(E94*F94,2) -> 292.94 | H94: =ROUND('[1]RESUMO DA PROPOSTA'!$C$17*F94,2) -> 9.06 | I94: =ROUND(E94*H94,2) -> 439.41
A95: 3.0 | C95: CENTRO MODULAR DE INFRA-ESTRUTURA GERAL - OBRAS CIVIS (FATOR "C") | F95: SUB. TOTAL | G95: =SUBTOTAL(9,G96:G489) -> 529821.24 | H95: SUB. TOTAL | I95: =SUBTOTAL(9,I96:I489) -> 1006660.3
A96: 3.1 | C96: REGULARIZAÇÃO / NIVELAMENTO DA ÁREA | F96: SUB. TOTAL | G96: =SUBTOTAL(9,G97:G115) -> 254.28 | H96: SUB. TOTAL | I96: =SUBTOTAL(9,I97:I115) -> 483.18
A97: 3.1.1 | B97: 5000011142 | C97: EXECUTAR LEVANTAMENTO PLANIALTIMETRICO | D97: M2 | F97: 1.59 | G97: =ROUND(E97*F97,2) -> 0 | H97: =ROUND('[1]RESUMO DA PROPOSTA'!$C$18*F97,2) -> 3.02 | I97: =ROUND(E97*H97,2) -> 0
A98: 3.1.2 | B98: 5000011402 | C98: LIMPEZA DO TERRENO / REMOÇÃO | D98: M3 | F98: 82.49 | G98: =ROUND(E98*F98,2) -> 0 | H98: =ROUND('[1]RESUMO DA PROPOSTA'!$C$18*F98,2) -> 156.73 | I98: =ROUND(E98*H98,2) -> 0
A99: 3.1.3 | B99: 5000011143 | C99: EXECUTAR LIMPEZA MANUAL DE TERRENO | D99: M2 | E99: 17.5 | F99: 3.24 | G99: =ROUND(E99*F99,2) -> 56.7 | H99: =ROUND('[1]RESUMO DA PROPOSTA'!$C$18*F99,2) -> 6.16 | I99: =ROUND(E99*H99,2) -> 107.8
A100: 3.1.4 | B100: 5000011144 | C100: EXECUTAR LIMPEZA MECANIZADA DE TERRENO | D100: M2 | F100: 4.25 | G100: =ROUND(E100*F100,2) -> 0 | H100: =ROUND('[1]RESUMO DA PROPOSTA'!$C$18*F100,2) -> 8.08 | I100: =ROUND(E100*H100,2) -> 0
A101: 3.1.5 | B101: 5000011145 | C101: EXECUTAR LOCAÇÃO DE OBRA DE SUBESTAÇÃO | D101: M2 | E101: 17.5 | F101: 11.29 | G101: =ROUND(E101*F101,2) -> 197.58 | H101: =ROUND('[1]RESUMO DA PROPOSTA'!$C$18*F101,2) -> 21.45 | I101: =ROUND(E101*H101,2) -> 375.38
A102: 3.1.6 | B102: 5000011403 | C102: ESCAV. C/ MARTELETE ROMPEDOR EM ROCHA | D102: M3 | F102: 286.62 | G102: =ROUND(E102*F102,2) -> 0 | H102: =ROUND('[1]RESUMO DA PROPOSTA'!$C$18*F102,2) -> 544.58 | I102: =ROUND(E102*H102,2) -> 0
A103: 3.1.7 | B103: 5000007396 | C103: AQUISIÇÃO DE CASCALHO PARA ATERRO | D103: M3 | F103: 107.7 | G103: =ROUND(E103*F103,2) -> 0 | H103: =ROUND('[1]RESUMO DA PROPOSTA'!$C$18*F103,2) -> 204.63 | I103: =ROUND(E103*H103,2) -> 0
A104: 3.1.8 | B104: 5000007631 | C104: ESCAVAÇÃO DE MATERIAL DE 1ª CATEGORIA | D104: M3 | F104: 5.5 | G104: =ROUND(E104*F104,2) -> 0 | H104: =ROUND('[1]RESUMO DA PROPOSTA'!$C$18*F104,2) -> 10.45 | I104: =ROUND(E104*H104,2) -> 0
A105: 3.1.9 | B105: 5000011146 | C105: EXECUTAR CORTE MECANIZADO (1ª CATEGORIA) | D105: M3 | F105: 71.45 | G105: =ROUND(E105*F105,2) -> 0 | H105: =ROUND('[1]RESUMO DA PROPOSTA'!$C$18*F105,2) -> 135.76 | I105: =ROUND(E105*H105,2) -> 0
A106: 3.1.10 | B106: 5000007397 | C106: ESCAVAÇÃO DE MATERIAL DE 2ª CATEGORIA | D106: M3 | F106: 9.17 | G106: =ROUND(E106*F106,2) -> 0 | H106: =ROUND('[1]RESUMO DA PROPOSTA'!$C$18*F106,2) -> 17.42 | I106: =ROUND(E106*H106,2) -> 0
A107: 3.1.11 | B107: 5000011147 | C107: EXECUTAR CORTE MECANIZADO (3ª CATEGORIA) | D107: M3 | F107: 39.11 | G107: =ROUND(E107*F107,2) -> 0 | H107: =ROUND('[1]RESUMO DA PROPOSTA'!$C$18*F107,2) -> 74.31 | I107: =ROUND(E107*H107,2) -> 0
A108: 3.1.12 | B108: 5000011148 | C108: EXECUTAR ATERRO MECANIZADO (JAZIDA) | D108: M3 | F108: 125.06 | G108: =ROUND(E108*F108,2) -> 0 | H108: =ROUND('[1]RESUMO DA PROPOSTA'!$C$18*F108,2) -> 237.61 | I108: =ROUND(E108*H108,2) -> 0
A109: 3.1.13 | B109: 5000011149 | C109: EXECUTAR ATERRO MECANIZADO (MAT LOCAL) | D109: M3 | F109: 54.28 | G109: =ROUND(E109*F109,2) -> 0 | H109: =ROUND('[1]RESUMO DA PROPOSTA'!$C$18*F109,2) -> 103.13 | I109: =ROUND(E109*H109,2) -> 0
A110: 3.1.14 | B110: 5000007632 | C110: COMPACTAÇÃO ATÉ 95% DO PROCTOR NORMAL (ATERRO) (SINAPI INSUMO 00006081 E COMPOSIÇÃO 96385) | D110: M3 | F110: 11.27 | G110: =ROUND(E110*F110,2) -> 0 | H110: =ROUND('[1]RESUMO DA PROPOSTA'!$C$18*F110,2) -> 21.41 | I110: =ROUND(E110*H110,2) -> 0
A111: 3.1.15 | B111: 5000011150 | C111: EXECUTAR REVESTIMENTO EM PÓ DE BRITA | D111: M2 | F111: 33.2 | G111: =ROUND(E111*F111,2) -> 0 | H111: =ROUND('[1]RESUMO DA PROPOSTA'!$C$18*F111,2) -> 63.08 | I111: =ROUND(E111*H111,2) -> 0
A112: 3.1.16 | B112: 5000011404 | C112: AQUIS. ARG/BARRO ATERRO/REATER C/ TRANSP | D112: M3 | F112: 51.12 | G112: =ROUND(E112*F112,2) -> 0 | H112: =ROUND('[1]RESUMO DA PROPOSTA'!$C$18*F112,2) -> 97.13 | I112: =ROUND(E112*H112,2) -> 0
A113: 3.1.17 | B113: 5000011405 | C113: AQUIS. ARG/BARRO ATERRO/REATER S/ TRANSP | D113: M3 | F113: 36.51 | G113: =ROUND(E113*F113,2) -> 0 | H113: =ROUND('[1]RESUMO DA PROPOSTA'!$C$18*F113,2) -> 69.37 | I113: =ROUND(E113*H113,2) -> 0
... A115: 3.1.19 | B115: 5000011407 | C115: REGULARIZ. E COMPAC. DE SUBLEITO DE SOLO | D115: M2 | F115: 2.47 | G115: =ROUND(E115*F115,2) -> 0 | H115: =ROUND('[1]RESUMO DA PROPOSTA'!$C$18*F115,2) -> 4.69 | I115: =ROUND(E115*H115,2) -> 0
A116: 3.2 | C116: BASES PARA EQUIPAMENTOS E ESTRUTURAS DE BARRAMENTO 13,8 kV | F116: SUB. TOTAL | G116: =SUBTOTAL(9,G117:G147) -> 5752.64 | H116: SUB. TOTAL | I116: =SUBTOTAL(9,I117:I147) -> 10930.02
A117: 3.2.1 | B117: 5000007682 | C117: BASE POSTE ALIMENTADOR | D117: M3 | F117: 3033.09 | G117: =ROUND(E117*F117,2) -> 0 | H117: =ROUND('[1]RESUMO DA PROPOSTA'!$C$18*F117,2) -> 5762.87 | I117: =ROUND(E117*H117,2) -> 0
A118: 3.2.2 | B118: 5000007682 | C118: BASE PARA MUFLA DO TRAFO | D118: M3 | F118: 3033.09 | G118: =ROUND(E118*F118,2) -> 0 | H118: =ROUND('[1]RESUMO DA PROPOSTA'!$C$18*F118,2) -> 5762.87 | I118: =ROUND(E118*H118,2) -> 0
A119: 3.2.3 | B119: 5000011408 | C119: BASE ELETROCENTRO | D119: CJ | F119: 50004.76 | G119: =ROUND(E119*F119,2) -> 0 | H119: =ROUND('[1]RESUMO DA PROPOSTA'!$C$18*F119,2) -> 95009.04 | I119: =ROUND(E119*H119,2) -> 0
A120: 3.2.4 | B120: 5000011409 | C120: BASE PARA CONTENIER | D120: CJ | F120: 35860.6 | G120: =ROUND(E120*F120,2) -> 0 | H120: =ROUND('[1]RESUMO DA PROPOSTA'!$C$18*F120,2) -> 68135.14 | I120: =ROUND(E120*H120,2) -> 0
A121: 3.2.5 | B121: 3000018249 | C121: BASE POSTE 7/1000 - G-0-0-PJ-PP-37 | D121: UN | E121: 2 | F121: 2876.32 | G121: =ROUND(E121*F121,2) -> 5752.64 | H121: =ROUND('[1]RESUMO DA PROPOSTA'!$C$18*F121,2) -> 5465.01 | I121: =ROUND(E121*H121,2) -> 10930.02
A122: 3.2.6 | B122: 5000009008 | C122: BASE POSTE 8/1000 - G-0-0-PJ-PP-38 | D122: UN | F122: 2887.15 | G122: =ROUND(E122*F122,2) -> 0 | H122: =ROUND('[1]RESUMO DA PROPOSTA'!$C$18*F122,2) -> 5485.59 | I122: =ROUND(E122*H122,2) -> 0
A123: 3.2.7 | B123: 3000018815 | C123: BASE POSTE 8/1650 - G-0-0-PJ-PP-38 | D123: UN | F123: 3690.17 | G123: =ROUND(E123*F123,2) -> 0 | H123: =ROUND('[1]RESUMO DA PROPOSTA'!$C$18*F123,2) -> 7011.32 | I123: =ROUND(E123*H123,2) -> 0
A124: 3.2.8 | B124: 3000018709 | C124: BASE POSTE 10/1000 - SOLO-CIMENTO | D124: UN | F124: 652.86 | G124: =ROUND(E124*F124,2) -> 0 | H124: =ROUND('[1]RESUMO DA PROPOSTA'!$C$18*F124,2) -> 1240.43 | I124: =ROUND(E124*H124,2) -> 0
A125: 3.2.9 | B125: 5000006788 | C125: BASE POSTE 11/1000 - G-0-0-PJ-PP-42 | D125: UN | F125: 1668.95 | G125: =ROUND(E125*F125,2) -> 0 | H125: =ROUND('[1]RESUMO DA PROPOSTA'!$C$18*F125,2) -> 3171.01 | I125: =ROUND(E125*H125,2) -> 0
A126: 3.2.10 | B126: 5000011410 | C126: BASE POSTE 11/1650 - G-0-0-PJ-PP-42 | D126: UN | F126: 4713.59 | G126: =ROUND(E126*F126,2) -> 0 | H126: =ROUND('[1]RESUMO DA PROPOSTA'!$C$18*F126,2) -> 8955.82 | I126: =ROUND(E126*H126,2) -> 0
A127: 3.2.11 | B127: 3000015803 | C127: BASE POSTE 12/1000 - G-0-0-PJ-PP-39 | D127: UN | F127: 3702.34 | G127: =ROUND(E127*F127,2) -> 0 | H127: =ROUND('[1]RESUMO DA PROPOSTA'!$C$18*F127,2) -> 7034.45 | I127: =ROUND(E127*H127,2) -> 0
A128: 3.2.12 | B128: 3000018810 | C128: BASE POSTE 12/1650 - G-0-0-PJ-PP-39 | D128: UN | F128: 4688.35 | G128: =ROUND(E128*F128,2) -> 0 | H128: =ROUND('[1]RESUMO DA PROPOSTA'!$C$18*F128,2) -> 8907.87 | I128: =ROUND(E128*H128,2) -> 0
A129: 3.2.13 | B129: 5000011411 | C129: BASE POSTE 13-1000 - G-0-0-PJ-PP-43 | D129: UN | F129: 4122.5 | G129: =ROUND(E129*F129,2) -> 0 | H129: =ROUND('[1]RESUMO DA PROPOSTA'!$C$18*F129,2) -> 7832.75 | I129: =ROUND(E129*H129,2) -> 0
A130: 3.2.14 | B130: 5000011412 | C130: BASE POSTE 15-1350 - G-0-0-PJ-PP-40 | D130: UN | F130: 6897.52 | G130: =ROUND(E130*F130,2) -> 0 | H130: =ROUND('[1]RESUMO DA PROPOSTA'!$C$18*F130,2) -> 13105.29 | I130: =ROUND(E130*H130,2) -> 0
A131: 3.2.15 | B131: 5000011151 | C131: EXECUTAR BASE PARA CHAVE SEC 15 KV | D131: UN | F131: 3506.31 | G131: =ROUND(E131*F131,2) -> 0 | H131: =ROUND('[1]RESUMO DA PROPOSTA'!$C$18*F131,2) -> 6661.99 | I131: =ROUND(E131*H131,2) -> 0
A132: 3.2.16 | B132: 5000011413 | C132: SUPORTE ACION. DE CHAVE SECCIONADORA | D132: UN | F132: 265 | G132: =ROUND(E132*F132,2) -> 0 | H132: =ROUND('[1]RESUMO DA PROPOSTA'!$C$18*F132,2) -> 503.5 | I132: =ROUND(E132*H132,2) -> 0
...

Sheet MEDIÇÕES
B1: SDAT CORUMBÁ | G1: MED 01 | I1: MED 02 | K1: MED 03 | M1: MED 04 | O1: MED 05 | Q1: MED 06 | S1: MED 07 | U1: MED 08 | W1: MED 09 | Y1: ACUMULADO | AA1: SALDO
A2: RESUMO DA AEO - PEP/ GO2530108BCA0.K | F2: =SUM(F5:F60) -> 344416.82 | G2: 46053 | I2: 46112 | K2: 46142
A3: CÓD. | B3: DESCRIÇÃO SIMPLES | C3: UN. | D3: PREÇO UNIT. | E3: QTD | F3: PREÇO TOTAL | H3: =SUM(H5:H47) -> 116842.19 | J3: =TRUNC(SUM(J5:J50),2) -> 56491.57 | L3: =TRUNC(SUM(L5:L50),2) -> 79594.93 | N3: =TRUNC(SUM(N5:N64),2) -> 93231.39 | P3: =TRUNC(SUM(P5:P46),2) -> 0 | R3: =TRUNC(SUM(R5:R60),2) -> 0 | T3: =TRUNC(SUM(T5:T46),2) -> 0 | V3: =TRUNC(SUM(V5:V46),2) -> 0 | X3: =TRUNC(SUM(X5:X46),2) -> 0 | Z3: =TRUNC(SUM(Z5:Z46),2) -> 0 | AB3: =TRUNC(SUM(AB5:AB46),2) -> 0
B4: SETORES 138/34,5/13,8kV
A5: 5000011120 | B5: =IFERROR(VLOOKUP(A5,LPU!$B$7:$H$1007,2,FALSE),"") -> DESMOB. SER. MÉD. PORTE DUR. >60 E <120D | C5: =IFERROR(VLOOKUP(A5,LPU!$B$7:H1007,3,FALSE),"") -> VB | D5: =IFERROR(VLOOKUP(A5,LPU!B7:$H$1007,7,FALSE),"") -> 5826.63 | E5: 1 | F5: =IFERROR(E5*D5,"") -> 5826.63 | H5: =IF(G5>0,G5*D5,"") | J5: =IF(I5>0,I5*$D5,"") | L5: =IF(K5>0,K5*$D5,"") | N5: =IF(M5>0,M5*$D5,"") | P5: =IF(O5>0,O5*$D5,"") | R5: =IF(Q5>0,Q5*$D5,"") | T5: =IF(S5>0,S5*$D5,"") | V5: =IF(U5>0,U5*$D5,"") | X5: =IF(W5>0,W5*$D5,"") | Y5: =SUM(G5,I5,K5,M5,O5,Q5,S5,U5,W5) -> 0
A6: 5000011124 | B6: =IFERROR(VLOOKUP(A6,LPU!$B$7:$H$1007,2,FALSE),"") -> MOBIL. SERV. MÉD. PORTE DUR. >60 E <120D | C6: =IFERROR(VLOOKUP(A6,LPU!$B$7:H1008,3,FALSE),"") -> VB | D6: =IFERROR(VLOOKUP(A6,LPU!B8:$H$1007,7,FALSE),"") -> 16316.99 | E6: 1 | F6: =IFERROR(E6*D6,"") -> 16316.99 | G6: 1 | H6: =IF(G6>0,G6*D6,"") -> 16316.99 | J6: =IF(I6>0,I6*D6,"") | L6: =IF(K6>0,K6*$D6,"") | N6: =IF(M6>0,M6*$D6,"") | T6: =IF(S6>0,S6*$D6,"") | V6: =IF(U6>0,U6*$D6,"") | X6: =IF(W6>0,W6*$D6,"") | Y6: =SUM(G6,I6,K6,M6,O6,Q6,S6,U6,W6) -> 1
A7: 5000011388 | B7: =IFERROR(VLOOKUP(A7,LPU!$B$7:$H$1007,2,FALSE),"") -> LIMPEZA INICIAL | C7: =IFERROR(VLOOKUP(A7,LPU!$B$7:H1011,3,FALSE),"") -> UN | D7: =IFERROR(VLOOKUP(A7,LPU!B11:$H$1007,7,FALSE),"") -> 3189 | E7: 1 | F7: =IFERROR(E7*D7,"") -> 3189 | G7: 1 | H7: =IF(G7>0,G7*D7,"") -> 3189 | J7: =IF(I7>0,I7*D7,"") | L7: =IF(K7>0,K7*$D7,"") | N7: =IF(M7>0,M7*$D7,"") | T7: =IF(S7>0,S7*$D7,"") | V7: =IF(U7>0,U7*$D7,"") | X7: =IF(W7>0,W7*$D7,"") | Y7: =SUM(G7,I7,K7,M7,O7,Q7,S7,U7,W7) -> 1
A8: 5000011389 | B8: =IFERROR(VLOOKUP(A8,LPU!$B$7:$H$1007,2,FALSE),"") -> INSTALAÇÕES PROVISÓRIAS DE ÁGUA E ESGOTO | C8: =IFERROR(VLOOKUP(A8,LPU!$B$7:H1012,3,FALSE),"") -> MÊS | D8: =IFERROR(VLOOKUP(A8,LPU!B12:$H$1007,7,FALSE),"") -> 4900 | E8: 1 | F8: =IFERROR(E8*D8,"") -> 4900 | G8: 1 | H8: =IF(G8>0,G8*D8,"") -> 4900 | J8: =IF(I8>0,I8*D8,"") | L8: =IF(K8>0,K8*$D8,"") | N8: =IF(M8>0,M8*$D8,"") | T8: =IF(S8>0,S8*$D8,"") | V8: =IF(U8>0,U8*$D8,"") | X8: =IF(W8>0,W8*$D8,"") | Y8: =SUM(G8,I8,K8,M8,O8,Q8,S8,U8,W8) -> 1
A9: 5000011129 | B9: =IFERROR(VLOOKUP(A9,LPU!$B$7:$H$1007,2,FALSE),"") -> EMITIR ART E DOCUMENTAÇÃO DE AMPLI SE'S | C9: =IFERROR(VLOOKUP(A9,LPU!$B$7:H1013,3,FALSE),"") -> UN | D9: =IFERROR(VLOOKUP(A9,LPU!B13:$H$1007,7,FALSE),"") -> 3839.85 | E9: 1 | F9: =IFERROR(E9*D9,"") -> 3839.85 | H9: =IF(G9>0,G9*D9,"") | J9: =IF(I9>0,I9*D9,"") | L9: =IF(K9>0,K9*$D9,"") | N9: =IF(M9>0,M9*$D9,"") | T9: =IF(S9>0,S9*$D9,"") | V9: =IF(U9>0,U9*$D9,"") | X9: =IF(W9>0,W9*$D9,"") | Y9: =SUM(G9,I9,K9,M9,O9,Q9,S9,U9,W9) -> 0
A10: 5000011131 | B10: =IFERROR(VLOOKUP(A10,LPU!$B$7:$H$1007,2,FALSE),"") -> INSTALAR PLACA DE IDENTIFICAÇÃO DE OBRAS | C10: =IFERROR(VLOOKUP(A10,LPU!$B$7:H1014,3,FALSE),"") -> M2 | D10: =IFERROR(VLOOKUP(A10,LPU!B14:$H$1007,7,FALSE),"") -> 971.77 | E10: 6 | F10: =IFERROR(E10*D10,"") -> 5830.62 | H10: =IF(G10>0,G10*D10,"") | J10: =IF(I10>0,I10*D10,"") | L10: =IF(K10>0,K10*$D10,"") | N10: =IF(M10>0,M10*$D10,"") | T10: =IF(S10>0,S10*$D10,"") | V10: =IF(U10>0,U10*$D10,"") | X10: =IF(W10>0,W10*$D10,"") | Y10: =SUM(G10,I10,K10,M10,O10,Q10,S10,U10,W10) -> 0
A11: 5000011133 | B11: =IFERROR(VLOOKUP(A11,LPU!$B$7:$H$1007,2,FALSE),"") -> FORNEC. E INSTAL. ESCRIT. CONTAINER OBRA | C11: =IFERROR(VLOOKUP(A11,LPU!$B$7:H1015,3,FALSE),"") -> MÊS | D11: 2274.35 | E11: 3 | F11: =IFERROR(E11*D11,"") -> 6823.05 | G11: 1 | H11: =IF(G11>0,G11*D11,"") -> 2274.35 | I11: 2 | J11: =IF(I11>0,I11*D11,"") -> 4548.7 | K11: 1 | L11: =IF(K11>0,K11*$D11,"") -> 2274.35 | M11: 1 | N11: =IF(M11>0,M11*$D11,"") -> 2274.35 | T11: =IF(S11>0,S11*$D11,"") | V11: =IF(U11>0,U11*$D11,"") | X11: =IF(W11>0,W11*$D11,"") | Y11: =SUM(G11,I11,K11,M11,O11,Q11,S11,U11,W11) -> 5
A12: 3000018187 | B12: =IFERROR(VLOOKUP(A12,LPU!$B$7:$H$1007,2,FALSE),"") -> ALUGUEL DE CONTAINER P/ BANHEIROS | C12: =IFERROR(VLOOKUP(A12,LPU!$B$7:H1016,3,FALSE),"") -> MÊS | D12: 1586.53 | E12: 3 | F12: =IFERROR(E12*D12,"") -> 4759.59 | G12: 1 | H12: =IF(G12>0,G12*D12,"") -> 1586.53 | I12: 2 | J12: =IF(I12>0,I12*D12,"") -> 3173.06 | K12: 1 | L12: =IF(K12>0,K12*$D12,"") -> 1586.53 | M12: 1 | N12: =IF(M12>0,M12*$D12,"") -> 1586.53 | T12: =IF(S12>0,S12*$D12,"") | V12: =IF(U12>0,U12*$D12,"") | X12: =IF(W12>0,W12*$D12,"") | Y12: =SUM(G12,I12,K12,M12,O12,Q12,S12,U12,W12) -> 5
A13: 5000011391 | B13: =IFERROR(VLOOKUP(A13,LPU!$B$7:$H$1007,2,FALSE),"") -> ALUGUEL DE CONTAINER P/ ALMOXARIFADO | C13: =IFERROR(VLOOKUP(A13,LPU!$B$7:H1017,3,FALSE),"") -> MÊS | D13: 991.59 | E13: 3 | F13: =IFERROR(E13*D13,"") -> 2974.77 | G13: 2 | H13: =IF(G13>0,G13*D13,"") -> 1983.18 | I13: 4 | J13: =IF(I13>0,I13*D13,"") -> 3966.36 | K13: 2 | L13: =IF(K13>0,K13*$D13,"") -> 1983.18 | M13: 1 | N13: =IF(M13>0,M13*$D13,"") -> 991.59 | T13: =IF(S13>0,S13*$D13,"") | V13: =IF(U13>0,U13*$D13,"") | X13: =IF(W13>0,W13*$D13,"") | Y13: =SUM(G13,I13,K13,M13,O13,Q13,S13,U13,W13) -> 9
A14: 5000011395 | B14: =IFERROR(VLOOKUP(A14,LPU!$B$7:$H$1007,2,FALSE),"") -> TRANSPORTE DOS CONTAINER | C14: =IFERROR(VLOOKUP(A14,LPU!$B$7:H1019,3,FALSE),"") -> UN | D14: =IFERROR(VLOOKUP(A14,LPU!B19:$H$1007,7,FALSE),"") -> 3314.3 | E14: 3 | F14: =IFERROR(E14*D14,"") -> 9942.9 | G14: 3 | H14: =IF(G14>0,G14*D14,"") -> 9942.9 | J14: =IF(I14>0,I14*D14,"") | L14: =IF(K14>0,K14*$D14,"") | N14: =IF(M14>0,M14*$D14,"") | T14: =IF(S14>0,S14*$D14,"") | V14: =IF(U14>0,U14*$D14,"") | X14: =IF(W14>0,W14*$D14,"") | Y14: =SUM(G14,I14,K14,M14,O14,Q14,S14,U14,W14) -> 3
A15: 5000011398 | B15: =IFERROR(VLOOKUP(A15,LPU!$B$7:$H$1007,2,FALSE),"") -> BARRAÇÃO REFEITÓRIO 6X6m | C15: =IFERROR(VLOOKUP(A15,LPU!$B$7:H1022,3,FALSE),"") -> UN | D15: =IFERROR(VLOOKUP(A15,LPU!B22:$H$1007,7,FALSE),"") -> 6905.35 | E15: 1 | F15: =IFERROR(E15*D15,"") -> 6905.35 | G15: 1 | H15: =IF(G15>0,G15*D15,"") -> 6905.35 | J15: =IF(I15>0,I15*D15,"") | L15: =IF(K15>0,K15*$D15,"") | N15: =IF(M15>0,M15*$D15,"") | T15: =IF(S15>0,S15*$D15,"") | V15: =IF(U15>0,U15*$D15,"") | X15: =IF(W15>0,W15*$D15,"") | Y15: =SUM(G15,I15,K15,M15,O15,Q15,S15,U15,W15) -> 1
A16: 5000011399 | B16: =IFERROR(VLOOKUP(A16,LPU!$B$7:$H$1007,2,FALSE),"") -> LIMPEZA DURANTE E NO FINAL DA OBRA | C16: =IFERROR(VLOOKUP(A16,LPU!$B$7:H1023,3,FALSE),"") -> MÊS | D16: 2454.59 | E16: 3 | F16: =IFERROR(E16*D16,"") -> 7363.77 | G16: 1 | H16: =IF(G16>0,G16*D16,"") -> 2454.59 | I16: 1 | J16: =IF(I16>0,I16*D16,"") -> 2454.59 | K16: 1 | L16: =IF(K16>0,K16*$D16,"") -> 2454.59 | M16: 1 | N16: =IF(M16>0,M16*$D16,"") -> 2454.59 | T16: =IF(S16>0,S16*$D16,"") | V16: =IF(U16>0,U16*$D16,"") | X16: =IF(W16>0,W16*$D16,"") | Y16: =SUM(G16,I16,K16,M16,O16,Q16,S16,U16,W16) -> 4
A17: 5000011401 | B17: =IFERROR(VLOOKUP(A17,LPU!$B$7:$H$1007,2,FALSE),"") -> TRANSP. DE EQUIPAM. E/OU MATERIAIS - SE | C17: =IFERROR(VLOOKUP(A17,LPU!$B$7:H1024,3,FALSE),"") -> KM | D17: 9.46 | E17: 900 | F17: =IFERROR(E17*D17,"") -> 8514 | G17: 942 | H17: =IF(G17>0,G17*D17,"") -> 8911.32 | I17: 1608 | J17: =IF(I17>0,I17*D17,"") -> 15211.68 | K17: 832 | L17: =IF(K17>0,K17*$D17,"") -> 7870.72 | M17: 494 | N17: =IF(M17>0,M17*$D17,"") -> 4673.24 | T17: =IF(S17>0,S17*$D17,"") | V17: =IF(U17>0,U17*$D17,"") | X17: =IF(W17>0,W17*$D17,"") | Y17: =SUM(G17,I17,K17,M17,O17,Q17,S17,U17,W17) -> 3876
A18: 5000007476 | B18: =IFERROR(VLOOKUP(A18,LPU!$B$7:$H$1007,2,FALSE),"") -> TRANSPORTE/REMOÇÃO DO MATERIAL PROVENIENTE DAS ESCAVAÇÕES PARA FORA DO PÁTIO | C18: =IFERROR(VLOOKUP(A18,LPU!$B$7:H1026,3,FALSE),"") -> M3 | D18: 104.23 | E18: 100 | F18: =IFERROR(E18*D18,"") -> 10423 | G18: 5 | H18: =IF(G18>0,G18*D18,"") -> 521.15 | I18: 2 | J18: =IF(I18>0,I18*D18,"") -> 208.46 | K18: 3 | L18: =IF(K18>0,K18*$D18,"") -> 312.69 | N18: =IF(M18>0,M18*$D18,"") | T18: =IF(S18>0,S18*$D18,"") | V18: =IF(U18>0,U18*$D18,"") | X18: =IF(W18>0,W18*$D18,"") | Y18: =SUM(G18,I18,K18,M18,O18,Q18,S18,U18,W18) -> 10
A19: 5000011387 | B19: =IFERROR(VLOOKUP(A19,LPU!$B$7:$H$1007,2,FALSE),"") -> TELA TAPUME (ISOLAMENTO/SINALIZAÇÃO) | C19: =IFERROR(VLOOKUP(A19,LPU!$B$7:H1027,3,FALSE),"") -> M | D19: =IFERROR(VLOOKUP(A19,LPU!B27:$H$1007,7,FALSE),"") -> 19.24 | E19: 150 | F19: =IFERROR(E19*D19,"") -> 2886 | G19: 100 | H19: =IF(G19>0,G19*D19,"") -> 1924 | J19: =IF(I19>0,I19*D19,"") | L19: =IF(K19>0,K19*$D19,"") | N19: =IF(M19>0,M19*$D19,"") | T19: =IF(S19>0,S19*$D19,"") | V19: =IF(U19>0,U19*$D19,"") | X19: =IF(W19>0,W19*$D19,"") | Y19: =SUM(G19,I19,K19,M19,O19,Q19,S19,U19,W19) -> 100
A20: 5000011386 | B20: =IFERROR(VLOOKUP(A20,LPU!$B$7:$H$1007,2,FALSE),"") -> INSTALAÇÕES PROVIS. DE ENERGIA ELÉTRICA | C20: =IFERROR(VLOOKUP(A20,LPU!$B$7:H1028,3,FALSE),"") -> MÊS | D20: =IFERROR(VLOOKUP(A20,LPU!B28:$H$1007,7,FALSE),"") -> 6112.22 | E20: 1 | F20: =IFERROR(E20*D20,"") -> 6112.22 | G20: 1 | H20: =IF(G20>0,G20*D20,"") -> 6112.22 | J20: =IF(I20>0,I20*D20,"") | L20: =IF(K20>0,K20*$D20,"") | N20: =IF(M20>0,M20*$D20,"") | T20: =IF(S20>0,S20*$D20,"") | V20: =IF(U20>0,U20*$D20,"") | X20: =IF(W20>0,W20*$D20,"") | Y20: =SUM(G20,I20,K20,M20,O20,Q20,S20,U20,W20) -> 1
A21: 5000011400 | B21: =IFERROR(VLOOKUP(A21,LPU!$B$7:$H$1007,2,FALSE),"") -> MÃO DE OBRA DE ADMINISTRAÇÃO LOCAL | C21: =IFERROR(VLOOKUP(A21,LPU!$B$7:H1030,3,FALSE),"") -> % | D21: 269552.72 | E21: 0.08 | F21: =IFERROR(E21*D21,"") -> 21564.218 | G21: 0.08 | H21: =106833.76*0.08 -> 8546.7008 | I21: 0.08 | J21: =52307.01*0.08 -> 4184.5608 | K21: 0.08 | L21: =73699.01*0.08 -> 5895.9208 | M21: 0.08 | N21: =86325.36*0.08 -> 6906.0288 | T21: =IF(S21>0,S21*$D21,"") | V21: =IF(U21>0,U21*$D21,"") | X21: =IF(W21>0,W21*$D21,"") | Y21: =SUM(G21,I21,K21,M21,O21,Q21,S21,U21,W21) -> 0.32
A22: 5000011145 | B22: =IFERROR(VLOOKUP(A22,LPU!$B$7:$H$1007,2,FALSE),"") -> EXECUTAR LOCAÇÃO DE OBRA DE SUBESTAÇÃO | C22: =IFERROR(VLOOKUP(A22,LPU!$B$7:H1031,3,FALSE),"") -> M2 | D22: 21.45 | E22: 300 | F22: =IFERROR(E22*D22,"") -> 6435 | G22: 126 | H22: =IF(G22>0,G22*D22,"") -> 2702.7 | J22: =IF(I22>0,I22*D22,"") | L22: =IF(K22>0,K22*$D22,"") | N22: =IF(M22>0,M22*$D22,"") | T22: =IF(S22>0,S22*$D22,"") | V22: =IF(U22>0,U22*$D22,"") | X22: =IF(W22>0,W22*$D22,"") | Y22: =SUM(G22,I22,K22,M22,O22,Q22,S22,U22,W22) -> 126
A23: 3000018810 | B23: =IFERROR(VLOOKUP(A23,LPU!$B$7:$H$1007,2,FALSE),"") -> BASE POSTE 12/1650 - G-0-0-PJ-PP-39 | C23: =IFERROR(VLOOKUP(A23,LPU!$B$7:H1032,3,FALSE),"") -> UN | D23: =IFERROR(VLOOKUP(A23,LPU!B32:$H$1007,7,FALSE),"") -> 8907.87 | E23: 4 | F23: =IFERROR(E23*D23,"") -> 35631.48 | G23: 2 | H23: =IF(G23>0,G23*D23,"") -> 17815.74 | J23: =IF(I23>0,I23*D23,"") | L23: =IF(K23>0,K23*$D23,"") | N23: =IF(M23>0,M23*$D23,"") | T23: =IF(S23>0,S23*$D23,"") | V23: =IF(U23>0,U23*$D23,"") | X23: =IF(W23>0,W23*$D23,"") | Y23: =SUM(G23,I23,K23,M23,O23,Q23,S23,U23,W23) -> 2
A24: 5000011416 | B24: =IFERROR(VLOOKUP(A24,LPU!$B$7:$H$1007,2,FALSE),"") -> BANCO CAPAC. 2,25MVAR - G-0-0-PJ-PB-88 | C24: =IFERROR(VLOOKUP(A24,LPU!$B$7:H1033,3,FALSE),"") -> UN | D24: 5369.19 | E24: 2 | F24: =IFERROR(E24*D24,"") -> 10738.38 | G24: 2 | H24: =IF(G24>0,G24*D24,"") -> 10738.38 | I24: 1 | J24: =IF(I24>0,I24*D24,"") -> 5369.19 | L24: =IF(K24>0,K24*$D24,"") | N24: =IF(M24>0,M24*$D24,"") | T24: =IF(S24>0,S24*$D24,"") | V24: =IF(U24>0,U24*$D24,"") | X24: =IF(W24>0,W24*$D24,"") | Y24: =SUM(G24,I24,K24,M24,O24,Q24,S24,U24,W24) -> 3
A25: 3000018724 | B25: =IFERROR(VLOOKUP(A25,LPU!$B$7:$H$1007,2,FALSE),"") -> FUNDAÇÃO DISJUNTOR 13,8/34,5KV - G-0-0-PJ-PB-123 | C25: =IFERROR(VLOOKUP(A25,LPU!$B$7:H1034,3,FALSE),"") -> UN | D25: 8923.56 | E25: 1 | F25: =IFERROR(E25*D25,"") -> 8923.56 | G25: 0.5 | H25: =IF(G25>0,G25*D25,"") -> 4461.78 | J25: =IF(I25>0,I25*D25,"") | L25: =IF(K25>0,K25*$D25,"") | M25: 0.5 | N25: =IF(M25>0,M25*$D25,"") -> 4461.78 | T25: =IF(S25>0,S25*$D25,"") | V25: =IF(U25>0,U25*$D25,"") | X25: =IF(W25>0,W25*$D25,"") | Y25: =SUM(G25,I25,K25,M25,O25,Q25,S25,U25,W25) -> 1
A26: 5000011253 | B26: =IFERROR(VLOOKUP(A26,LPU!$B$7:$H$1007,2,FALSE),"") -> REALOCAR E ESPALHAR BRITA NO PÁTIO DE SE | C26: =IFERROR(VLOOKUP(A26,LPU!$B$7:H1035,3,FALSE),"") -> M2 | D26: 29.83 | E26: 8.5 | F26: =IFERROR(E26*D26,"") -> 253.555 | G26: 50 | H26: =IF(G26>0,G26*D26,"") -> 1491.5 | I26: 46.865 | J26: =IF(I26>0,I26*D26,"") -> 1397.983 | K26: 30 | L26: =IF(K26>0,K26*$D26,"") -> 894.9 | M26: 6 | N26: =IF(M26>0,M26*$D26,"") -> 178.98 | T26: =IF(S26>0,S26*$D26,"") | V26: =IF(U26>0,U26*$D26,"") | X26: =IF(W26>0,W26*$D26,"") | Y26: =SUM(G26,I26,K26,M26,O26,Q26,S26,U26,W26) -> 132.865
A27: 3000016144 | B27: =IFERROR(VLOOKUP(A27,LPU!$B$7:$H$1007,2,FALSE),"") -> DEMOLIÇÃO DE CONCRETO ARMADO E BASES DE POSTES, TRAFO, ESTRUTURAS E SIMILARES, VIGA TRILHO | C27: =IFERROR(VLOOKUP(A27,LPU!$B$7:H1036,3,FALSE),"") -> M3 | D27: =IFERROR(VLOOKUP(A27,LPU!B36:$H$1007,7,FALSE),"") -> 893.3 | E27: 0.44 | F27: =IFERROR(E27*D27,"") -> 393.052 | G27: 0.5 | H27: =IF(G27>0,G27*D27,"") -> 446.65 | J27: =IF(I27>0,I27*D27,"") | L27: =IF(K27>0,K27*$D27,"") | N27: =IF(M27>0,M27*$D27,"") | T27: =IF(S27>0,S27*$D27,"") | V27: =IF(U27>0,U27*$D27,"") | X27: =IF(W27>0,W27*$D27,"") | Y27: =SUM(G27,I27,K27,M27,O27,Q27,S27,U27,W27) -> 0.5
A28: 3000016130 | B28: =IFERROR(VLOOKUP(A28,LPU!$B$7:$H$1007,2,FALSE),"") -> CONEXÃO DE EQUIPAMENTOS OU ESTRUTURAS A MALHA DE TERRA | C28: =IFERROR(VLOOKUP(A28,LPU!$B$7:H1037,3,FALSE),"") -> UN | D28: 670.19 | E28: 18 | F28: =IFERROR(E28*D28,"") -> 12063.42 | H28: =IF(G28>0,G28*D28,"") | I28: 2 | J28: =IF(I28>0,I28*D28,"") -> 1340.38 | K28: 2 | L28: =IF(K28>0,K28*$D28,"") -> 1340.38 | M28: 29 | N28: =IF(M28>0,M28*$D28,"") -> 19435.51 | T28: =IF(S28>0,S28*$D28,"") | V28: =IF(U28>0,U28*$D28,"") | X28: =IF(W28>0,W28*$D28,"") | Y28: =SUM(G28,I28,K28,M28,O28,Q28,S28,U28,W28) -> 33
A29: 3000017670 | B29: =IFERROR(VLOOKUP(A29,LPU!$B$7:$H$1007,2,FALSE),"") -> MONT. HASTE DE COBRE, COM DIÂMETRO ATÉ 3/4" | C29: =IFERROR(VLOOKUP(A29,LPU!$B$7:H1040,3,FALSE),"") -> UN | D29: =IFERROR(VLOOKUP(A29,LPU!B39:$H$1007,7,FALSE),"") -> 190 | E29: 2 | F29: =IFERROR(E29*D29,"") -> 380 | H29: =IF(G29>0,G29*D29,"") | J29: =IF(I29>0,I29*D29,"") | L29: =IF(K29>0,K29*$D29,"") | N29: =IF(M29>0,M29*$D29,"") | T29: =IF(S29>0,S29*$D29,"") | V29: =IF(U29>0,U29*$D29,"") | X29: =IF(W29>0,W29*$D29,"") | Y29: =SUM(G29,I29,K29,M29,O29,Q29,S29,U29,W29) -> 0
A30: 5000007387 | B30: =IFERROR(VLOOKUP(A30,LPU!$B$7:$H$1007,2,FALSE),"") -> LANC. CABO DE ALUMÍNIO, ATÉ 1000 MCM, | C30: =IFERROR(VLOOKUP(A30,LPU!$B$7:H1041,3,FALSE),"") -> M | D30: 23.18 | E30: 111 | F30: =IFERROR(E30*D30,"") -> 2572.98 | H30: =IF(G30>0,G30*D30,"") | J30: =IF(I30>0,I30*D30,"") | K30: 111 | L30: =IF(K30>0,K30*$D30,"") -> 2572.98 | N30: =IF(M30>0,M30*$D30,"") | T30: =IF(S30>0,S30*$D30,"") | V30: =IF(U30>0,U30*$D30,"") | X30: =IF(W30>0,W30*$D30,"") | Y30: =SUM(G30,I30,K30,M30,O30,Q30,S30,U30,W30) -> 111
A31: 5000007573 | B31: =IFERROR(VLOOKUP(A31,LPU!$B$7:$H$1007,2,FALSE),"") -> MONT. CADEIA DE ISOLADORES 34,5kV E 69kV | C31: =IFERROR(VLOOKUP(A31,LPU!$B$7:H1042,3,FALSE),"") -> UN | D31: 526.44 | E31: 6 | F31: =IFERROR(E31*D31,"") -> 3158.64 | H31: =IF(G31>0,G31*D31,"") | J31: =IF(I31>0,I31*D31,"") | K31: 6 | L31: =IF(K31>0,K31*$D31,"") -> 3158.64 | N31: =IF(M31>0,M31*$D31,"") | T31: =IF(S31>0,S31*$D31,"") | V31: =IF(U31>0,U31*$D31,"") | X31: =IF(W31>0,W31*$D31,"") | Y31: =SUM(G31,I31,K31,M31,O31,Q31,S31,U31,W31) -> 6
A32: 3000016113 | B32: =IFERROR(VLOOKUP(A32,LPU!$B$7:$H$1007,2,FALSE),"") -> MONT. ISOLADOR DE PEDESTAL 13,8 KV E 34,5KV | C32: =IFERROR(VLOOKUP(A32,LPU!$B$7:H1043,3,FALSE),"") -> UN | D32: 222.01 | E32: 3 | F32: =IFERROR(E32*D32,"") -> 666.03 | H32: =IF(G32>0,G32*D32,"") | J32: =IF(I32>0,I32*D32,"") | L32: =IF(K32>0,K32*$D32,"") | M32: 3 | N32: =IF(M32>0,M32*$D32,"") -> 666.03 | T32: =IF(S32>0,S32*$D32,"") | V32: =IF(U32>0,U32*$D32,"") | X32: =IF(W32>0,W32*$D32,"") | Y32: =SUM(G32,I32,K32,M32,O32,Q32,S32,U32,W32) -> 3
A33: 5000011279 | B33: =IFERROR(VLOOKUP(A33,LPU!$B$7:$H$1007,2,FALSE),"") -> INSTALAR PLACA NUMERO COMPONENTE | C33: =IFERROR(VLOOKUP(A33,LPU!$B$7:H1043,3,FALSE),"") -> UN | D33: 58.06 | E33: 9 | F33: =IFERROR(E33*D33,"") -> 522.54 | H33: =IF(G33>0,G33*D33,"") | J33: =IF(I33>0,I33*D33,"") | L33: =IF(K33>0,K33*$D33,"") | N33: =IF(M33>0,M33*$D33,"") | T33: =IF(S33>0,S33*$D33,"") | V33: =IF(U33>0,U33*$D33,"") | X33: =IF(W33>0,W33*$D33,"") | Y33: =SUM(G33,I33,K33,M33,O33,Q33,S33,U33,W33) -> 0
A34: 5000011284 | B34: =IFERROR(VLOOKUP(A34,LPU!$B$7:$H$1007,2,FALSE),"") -> SERV INST/CONFEC PLACA OPERAC EQUIP SE | C34: =IFERROR(VLOOKUP(A34,LPU!$B$7:H1044,3,FALSE),"") -> UN | D34: 24.01 | E34: 9 | F34: =IFERROR(E34*D34,"") -> 216.09 | H34: =IF(G34>0,G34*D34,"") | J34: =IF(I34>0,I34*D34,"") | L34: =IF(K34>0,K34*$D34,"") | M34: 21 | N34: =IF(M34>0,M34*$D34,"") -> 504.21 | T34: =IF(S34>0,S34*$D34,"") | V34: =IF(U34>0,U34*$D34,"") | X34: =IF(W34>0,W34*$D34,"") | Y34: =SUM(G34,I34,K34,M34,O34,Q34,S34,U34,W34) -> 21
A35: 5000011285 | B35: =IFERROR(VLOOKUP(A35,LPU!$B$7:$H$1007,2,FALSE),"") -> INSTALAR CAIXA DE DERIVAÇÃO PARA TC/TP | C35: =IFERROR(VLOOKUP(A35,LPU!$B$7:H1045,3,FALSE),"") -> UN | D35: 3336.5 | E35: 1 | F35: =IFERROR(E35*D35,"") -> 3336.5 | H35: =IF(G35>0,G35*D35,"") | J35: =IF(I35>0,I35*D35,"") | L35: =IF(K35>0,K35*$D35,"") | M35: 1 | N35: =IF(M35>0,M35*$D35,"") -> 3336.5 | T35: =IF(S35>0,S35*$D35,"") | V35: =IF(U35>0,U35*$D35,"") | X35: =IF(W35>0,W35*$D35,"") | Y35: =SUM(G35,I35,K35,M35,O35,Q35,S35,U35,W35) -> 1
A36: 5000011288 | B36: =IFERROR(VLOOKUP(A36,LPU!$B$7:$H$1007,2,FALSE),"") -> INSTALAR ELETRODUTO DE 1 1/2" ATÉ 2" | C36: =IFERROR(VLOOKUP(A36,LPU!$B$7:H1046,3,FALSE),"") -> M | D36: 133.33 | E36: 70 | F36: =IFERROR(E36*D36,"") -> 9333.1 | H36: =IF(G36>0,G36*D36,"") | I36: 40 | J36: =IF(I36>0,I36*D36,"") -> 5333.2 | L36: =IF(K36>0,K36*$D36,"") | M36: 62.6 | N36: =IF(M36>0,M36*$D36,"") -> 8346.458 | T36: =IF(S36>0,S36*$D36,"") | V36: =IF(U36>0,U36*$D36,"") | X36: =IF(W36>0,W36*$D36,"") | Y36: =SUM(G36,I36,K36,M36,O36,Q36,S36,U36,W36) -> 102.6
A37: 3000016219 | B37: =IFERROR(VLOOKUP(A37,LPU!$B$7:$H$1007,2,FALSE),"") -> MONT. CHAVE SECCIONADORA MONOFÁSICA 13,8 KV E 34,5KV | C37: =IFERROR(VLOOKUP(A37,LPU!$B$7:H1047,3,FALSE),"") -> UN | D37: 479.76 | E37: 6 | F37: =IFERROR(E37*D37,"") -> 2878.56 | H37: =IF(G37>0,G37*D37,"") | J37: =IF(I37>0,I37*D37,"") | L37: =IF(K37>0,K37*$D37,"") | M37: 3 | N37: =IF(M37>0,M37*$D37,"") -> 1439.28 | T37: =IF(S37>0,S37*$D37,"") | V37: =IF(U37>0,U37*$D37,"") | X37: =IF(W37>0,W37*$D37,"") | Y37: =SUM(G37,I37,K37,M37,O37,Q37,S37,U37,W37) -> 3
A38: 3000016244 | B38: =IFERROR(VLOOKUP(A38,LPU!$B$7:$H$1007,2,FALSE),"") -> MONT. CHAVE FUSÍVEL UNIPOLAR 13,8 KV E 34,5 KV | C38: =IFERROR(VLOOKUP(A38,LPU!$B$7:H1048,3,FALSE),"") -> UN | D38: 3878.26 | E38: 1 | F38: =IFERROR(E38*D38,"") -> 3878.26 | H38: =IF(G38>0,G38*D38,"") | J38: =IF(I38>0,I38*D38,"") | L38: =IF(K38>0,K38*$D38,"") | M38: 1 | N38: =IF(M38>0,M38*$D38,"") -> 3878.26 | T38: =IF(S38>0,S38*$D38,"") | V38: =IF(U38>0,U38*$D38,"") | X38: =IF(W38>0,W38*$D38,"") | Y38: =SUM(G38,I38,K38,M38,O38,Q38,S38,U38,W38) -> 1
A39: 5000007613 | B39: =IFERROR(VLOOKUP(A39,LPU!$B$7:$H$1007,2,FALSE),"") -> DEMOLIÇÃO DE MURO COM RETIRADA DA CONCERTINA | C39: =IFERROR(VLOOKUP(A39,LPU!$B$7:H1049,3,FALSE),"") -> M3 | D39: =IFERROR(VLOOKUP(A39,LPU!B49:$H$1007,7,FALSE),"") -> 893.3 | E39: 2 | F39: =IFERROR(E39*D39,"") -> 1786.6 | H39: =IF(G39>0,G39*D39,"") | J39: =IF(I39>0,I39*D39,"") | L39: =IF(K39>0,K39*$D39,"") | N39: =IF(M39>0,M39*$D39,"") | T39: =IF(S39>0,S39*$D39,"") | V39: =IF(U39>0,U39*$D39,"") | X39: =IF(W39>0,W39*$D39,"") | Y39: =SUM(G39,I39,K39,M39,O39,Q39,S39,U39,W39) -> 0
B40: SERVIÇOS EXECUTADOS FORA DA AEO | C40: =IFERROR(VLOOKUP(A40,LPU!$B$7:H1063,3,FALSE),"") | D40: =IFERROR(VLOOKUP(A40,LPU!B63:$H$1007,7,FALSE),"") | F40: =IFERROR(E40*D40,"")
A41: 5000007630 | B41: =IFERROR(VLOOKUP(A41,LPU!$B$7:$H$1007,2,FALSE),"") -> MONT. POSTE DE CONCRETO, DE 10 A 14 M, | C41: =IFERROR(VLOOKUP(A41,LPU!$B$7:H1064,3,FALSE),"") -> UN | D41: 3501.19 | E41: 3 | F41: =IFERROR(E41*D41,"") -> 10503.57 | H41: =IF(G41>0,G41*D41,"") | I41: 2 | J41: =IF(I41>0,I41*D41,"") -> 7002.38 | L41: =IF(K41>0,K41*$D41,"") | N41: =IF(M41>0,M41*$D41,"") | T41: =IF(S41>0,S41*$D41,"") | V41: =IF(U41>0,U41*$D41,"") | X41: =IF(W41>0,W41*$D41,"") | Y41: =SUM(G41,I41,K41,M41,O41,Q41,S41,U41,W41) -> 2
A42: 5000007652 | B42: =IFERROR(VLOOKUP(A42,LPU!$B$7:$H$1007,2,FALSE),"") -> MONT. COLUNA E VIGA METÁLICA TRELIÇADA, | C42: =IFERROR(VLOOKUP(A42,LPU!$B$7:H1065,3,FALSE),"") -> KG | D42: 8.65 | E42: 670.68 | F42: =IFERROR(E42*D42,"") -> 5801.382 | H42: =IF(G42>0,G42*D42,"") | J42: =IF(I42>0,I42*D42,"") | K42: 670.68 | L42: =IF(K42>0,K42*$D42,"") -> 5801.382 | N42: =IF(M42>0,M42*$D42,"") | T42: =IF(S42>0,S42*$D42,"") | V42: =IF(U42>0,U42*$D42,"") | X42: =IF(W42>0,W42*$D42,"") | Y42: =SUM(G42,I42,K42,M42,O42,Q42,S42,U42,W42) -> 670.68
A43: 3000018693 | B43: =IFERROR(VLOOKUP(A43,LPU!$B$7:$H$1007,2,FALSE),"") -> BASE TRAFO SERVIÇO AUXILIAR - G-0-0-PJ-PB-79 | C43: =IFERROR(VLOOKUP(A43,LPU!$B$7:H1066,3,FALSE),"") -> UN | D43: 3617.16 | E43: 1 | F43: =IFERROR(E43*D43,"") -> 3617.16 | G43: 1 | H43: =IF(G43>0,G43*D43,"") -> 3617.16 | J43: =IF(I43>0,I43*D43,"") | L43: =IF(K43>0,K43*$D43,"") | N43: =IF(M43>0,M43*$D43,"") | T43: =IF(S43>0,S43*$D43,"") | V43: =IF(U43>0,U43*$D43,"") | X43: =IF(W43>0,W43*$D43,"") | Y43: =SUM(G43,I43,K43,M43,O43,Q43,S43,U43,W43) -> 1
A44: 5000011231 | B44: =IFERROR(VLOOKUP(A44,LPU!$B$7:$H$1007,2,FALSE),"") -> EXECUTAR CAIXA DE PASSAGEM 600MM X 600MM | C44: =IFERROR(VLOOKUP(A44,LPU!$B$7:H1067,3,FALSE),"") -> UN | D44: 2301.03 | E44: 2 | F44: =IFERROR(E44*D44,"") -> 4602.06 | H44: =IF(G44>0,G44*D44,"") | I44: 1 | J44: =IF(I44>0,I44*D44,"") -> 2301.03 | K44: 2 | L44: =IF(K44>0,K44*$D44,"") -> 4602.06 | N44: =IF(M44>0,M44*$D44,"") | T44: =IF(S44>0,S44*$D44,"") | V44: =IF(U44>0,U44*$D44,"") | X44: =IF(W44>0,W44*$D44,"") | Y44: =SUM(G44,I44,K44,M44,O44,Q44,S44,U44,W44) -> 3
A45: 3000016312 | B45: =IFERROR(VLOOKUP(A45,LPU!$B$7:$H$1007,2,FALSE),"") -> FORNECIM. DE MATERIAIS MENORES ELETRICOS | C45: =IFERROR(VLOOKUP(A45,LPU!$B$7:H1068,3,FALSE),"") -> CJ | D45: =IFERROR(VLOOKUP(A45,LPU!B68:$H$1007,7,FALSE),"") -> 1.6 | E45: 5000 | F45: =IFERROR(E45*D45,"") -> 8000 | H45: =IF(G45>0,G45*D45,"") | J45: =IF(I45>0,I45*D45,"") | K45: 1897.69 | L45: =IF(K45>0,K45*$D45,"") -> 3036.304 | N45: =IF(M45>0,M45*$D45,"") | T45: =IF(S45>0,S45*$D45,"") | V45: =IF(U45>0,U45*$D45,"") | X45: =IF(W45>0,W45*$D45,"") | Y45: =SUM(G45,I45,K45,M45,O45,Q45,S45,U45,W45) -> 1897.69
A46: 5000007406 | B46: =IFERROR(VLOOKUP(A46,LPU!$B$7:$H$1007,2,FALSE),"") -> 4 DUTOS Ø 110MM - G-0-0-PJ-AJ-29 | C46: =IFERROR(VLOOKUP(A46,LPU!$B$7:H1069,3,FALSE),"") -> M | D46: 926.15 | E46: 50 | F46: =IFERROR(E46*D46,"") -> 46307.5 | H46: =IF(G46>0,G46*D46,"") | K46: 30 | L46: =IF(K46>0,K46*$D46,"") -> 27784.5 | N46: =IF(M46>0,M46*$D46,"") | T46: =IF(S46>0,S46*$D46,"") | V46: =IF(U46>0,U46*$D46,"") | X46: =IF(W46>0,W46*$D46,"") | Y46: =SUM(G46,I46,K46,M46,O46,Q46,S46,U46,W46) -> 30
A47: 5000007594 | B47: =IFERROR(VLOOKUP(A47,LPU!$B$7:$H$1007,2,FALSE),"") -> MONT. TRAFO DE SERVIÇO AUXILIAR EM 13,8 KV E 34,5 KV, | C47: =IFERROR(VLOOKUP(A47,LPU!$B$7:H1070,3,FALSE),"") -> UN | D47: 5583.15 | E47: 1 | F47: =IFERROR(E47*D47,"") -> 5583.15 | H47: =IF(G47>0,G47*D47,"") | K47: 1 | L47: =IF(K47>0,K47*$D47,"") -> 5583.15 | N47: =IF(M47>0,M47*$D47,"") | T47: =IF(S47>0,S47*$D47,"") | V47: =IF(U47>0,U47*$D47,"") | X47: =IF(W47>0,W47*$D47,"") | Y47: =SUM(G47,I47,K47,M47,O47,Q47,S47,U47,W47) -> 1
A48: 5000011286 | B48: =IFERROR(VLOOKUP(A48,LPU!$B$7:$H$1007,2,FALSE),"") -> INSTALAR ELETRODUTO ACIMA DE 2" | C48: =IFERROR(VLOOKUP(A48,LPU!$B$7:H1071,3,FALSE),"") -> M | D48: 156.35 | E48: 3 | F48: =IFERROR(E48*D48,"") -> 469.05 | H48: =IF(G48>0,G48*D48,"") | K48: 3 | L48: =IF(K48>0,K48*$D48,"") -> 469.05 | N48: =IF(M48>0,M48*$D48,"") | T48: =IF(S48>0,S48*$D48,"") | V48: =IF(U48>0,U48*$D48,"") | X48: =IF(W48>0,W48*$D48,"") | Y48: =SUM(G48,I48,K48,M48,O48,Q48,S48,U48,W48) -> 3
A49: 5000011270 | B49: =IFERROR(VLOOKUP(A49,LPU!$B$7:$H$1007,2,FALSE),"") -> MONT. POSTE DE CONCRETO, DE 5 A 10 M, | C49: =IFERROR(VLOOKUP(A49,LPU!$B$7:H1072,3,FALSE),"") -> UN | D49: 1973.61 | E49: 1 | F49: =IFERROR(E49*D49,"") -> 1973.61 | H49: =IF(G49>0,G49*D49,"") | K49: 1 | L49: =IF(K49>0,K49*$D49,"") -> 1973.61 | N49: =IF(M49>0,M49*$D49,"") | T49: =IF(S49>0,S49*$D49,"") | V49: =IF(U49>0,U49*$D49,"") | X49: =IF(W49>0,W49*$D49,"") | Y49: =SUM(G49,I49,K49,M49,O49,Q49,S49,U49,W49) -> 1
A50: 5000006701 | B50: =IFERROR(VLOOKUP(A50,LPU!$B$7:$H$1007,2,FALSE),"") -> DMONT. CABO ISOLADO 1 KV, ATÉ 240 MM², | C50: =IFERROR(VLOOKUP(A50,LPU!$B$7:H1073,3,FALSE),"") -> M | D50: 12.59 | E50: 60 | F50: =IFERROR(E50*D50,"") -> 755.4 | H50: =IF(G50>0,G50*D50,"") | L50: =IF(K50>0,K50*$D50,"") | M50: 60 | N50: =IF(M50>0,M50*$D50,"") -> 755.4 | T50: =IF(S50>0,S50*$D50,"") | V50: =IF(U50>0,U50*$D50,"") | X50: =IF(W50>0,W50*$D50,"") | Y50: =SUM(G50,I50,K50,M50,O50,Q50,S50,U50,W50) -> 60
A51: 3000017839 | B51: =IFERROR(VLOOKUP(A51,LPU!$B$7:$H$1007,2,FALSE),"") -> LANC. CABO ISOLADO 1KV, ATÉ 240 MM², | C51: =IFERROR(VLOOKUP(A51,LPU!$B$7:H1074,3,FALSE),"") -> M | D51: 27.62 | E51: 20 | F51: =IFERROR(E51*D51,"") -> 552.4 | H51: =IF(G51>0,G51*D51,"") | L51: =IF(K51>0,K51*$D51,"") | M51: 20 | N51: =IF(M51>0,M51*$D51,"") -> 552.4 | T51: =IF(S51>0,S51*$D51,"") | V51: =IF(U51>0,U51*$D51,"") | X51: =IF(W51>0,W51*$D51,"") | Y51: =SUM(G51,I51,K51,M51,O51,Q51,S51,U51,W51) -> 20
A52: 3000016133 | B52: =IFERROR(VLOOKUP(A52,LPU!$B$7:$H$1007,2,FALSE),"") -> DMONT. ISOLADOR DE PEDESTAL 34,5KV | C52: =IFERROR(VLOOKUP(A52,LPU!$B$7:H1075,3,FALSE),"") -> UN | D52: 175.86 | E52: 3 | F52: =IFERROR(E52*D52,"") -> 527.58 | H52: =IF(G52>0,G52*D52,"") | N52: =IF(M52>0,M52*$D52,"") | T52: =IF(S52>0,S52*$D52,"") | V52: =IF(U52>0,U52*$D52,"") | X52: =IF(W52>0,W52*$D52,"") | Y52: =SUM(G52,I52,K52,M52,O52,Q52,S52,U52,W52) -> 0
A53: 3000016249 | B53: =IFERROR(VLOOKUP(A53,LPU!$B$7:$H$1007,2,FALSE),"") -> DMONT. CHAVE FUSÍVEL UNIPOLAR, 13,8 KV E 34,5 KV, | C53: =IFERROR(VLOOKUP(A53,LPU!$B$7:H1076,3,FALSE),"") -> UN | D53: 2185.49 | E53: 1 | F53: =IFERROR(E53*D53,"") -> 2185.49 | H53: =IF(G53>0,G53*D53,"") | M53: 1 | N53: =IF(M53>0,M53*$D53,"") -> 2185.49 | T53: =IF(S53>0,S53*$D53,"") | V53: =IF(U53>0,U53*$D53,"") | X53: =IF(W53>0,W53*$D53,"") | Y53: =SUM(G53,I53,K53,M53,O53,Q53,S53,U53,W53) -> 1
A54: 5000011306 | B54: =IFERROR(VLOOKUP(A54,LPU!$B$7:$H$1007,2,FALSE),"") -> DMONT. TRAFO DE SERV. AUX. ATÉ 34,5 KV, | C54: =IFERROR(VLOOKUP(A54,LPU!$B$7:H1077,3,FALSE),"") -> UN | D54: 2885.89 | E54: 1 | F54: =IFERROR(E54*D54,"") -> 2885.89 | H54: =IF(G54>0,G54*D54,"") | M54: 1 | N54: =IF(M54>0,M54*$D54,"") -> 2885.89 | T54: =IF(S54>0,S54*$D54,"") | V54: =IF(U54>0,U54*$D54,"") | X54: =IF(W54>0,W54*$D54,"") | Y54: =SUM(G54,I54,K54,M54,O54,Q54,S54,U54,W54) -> 1
A55: 3000016275 | B55: =IFERROR(VLOOKUP(A55,LPU!$B$7:$H$1007,2,FALSE),"") -> MONT. DISJUNTOR TRIPOLAR 13,8 KV E 34,5KV | C55: =IFERROR(VLOOKUP(A55,LPU!$B$7:H1078,3,FALSE),"") -> UN | D55: 7506.02 | E55: 1 | F55: =IFERROR(E55*D55,"") -> 7506.02 | H55: =IF(G55>0,G55*D55,"") | M55: 2 | N55: =IF(M55>0,M55*$D55,"") -> 15012.04 | T55: =IF(S55>0,S55*$D55,"") | V55: =IF(U55>0,U55*$D55,"") | X55: =IF(W55>0,W55*$D55,"") | Y55: =SUM(G55,I55,K55,M55,O55,Q55,S55,U55,W55) -> 2
A56: 5000007385 | B56: =IFERROR(VLOOKUP(A56,LPU!$B$7:$H$1007,2,FALSE),"") -> MONT. SUPORTE METÁLICO PARA TC | C56: =IFERROR(VLOOKUP(A56,LPU!$B$7:H1079,3,FALSE),"") -> UN | D56: 1100.01 | E56: 1 | F56: =IFERROR(E56*D56,"") -> 1100.01 | H56: =IF(G56>0,G56*D56,"") | N56: =IF(M56>0,M56*$D56,"") | T56: =IF(S56>0,S56*$D56,"") | V56: =IF(U56>0,U56*$D56,"") | X56: =IF(W56>0,W56*$D56,"") | Y56: =SUM(G56,I56,K56,M56,O56,Q56,S56,U56,W56) -> 0
A57: 5000011536 | B57: =IFERROR(VLOOKUP(A57,LPU!$B$7:$H$1007,2,FALSE),"") -> INSTALAÇÃO DE PROTEÇÃO ANTI-FAUNA | C57: =IFERROR(VLOOKUP(A57,LPU!$B$7:H1080,3,FALSE),"") -> UN | D57: 444.86 | E57: 3 | F57: =IFERROR(E57*D57,"") -> 1334.58 | H57: =IF(G57>0,G57*D57,"") | M57: 3 | N57: =IF(M57>0,M57*$D57,"") -> 1334.58 | T57: =IF(S57>0,S57*$D57,"") | V57: =IF(U57>0,U57*$D57,"") | X57: =IF(W57>0,W57*$D57,"") | Y57: =SUM(G57,I57,K57,M57,O57,Q57,S57,U57,W57) -> 3
A58: 3000016361 | B58: =IFERROR(VLOOKUP(A58,LPU!$B$7:$H$1007,2,FALSE),"") -> DMONT. DISJUNTOR TRIPOLAR 13,8 KV E 34,5KV | C58: =IFERROR(VLOOKUP(A58,LPU!$B$7:H1081,3,FALSE),"") -> UN | D58: 5361.45 | E58: 1 | F58: =IFERROR(E58*D58,"") -> 5361.45 | H58: =IF(G58>0,G58*D58,"") | M58: 1 | N58: =IF(M58>0,M58*$D58,"") -> 5361.45 | T58: =IF(S58>0,S58*$D58,"") | V58: =IF(U58>0,U58*$D58,"") | X58: =IF(W58>0,W58*$D58,"") | Y58: =SUM(G58,I58,K58,M58,O58,Q58,S58,U58,W58) -> 1
A59: 3000016294 | B59: =IFERROR(VLOOKUP(A59,LPU!$B$7:$H$1007,2,FALSE),"") -> MONT. TRANSFORMADOR DE MEDIDAS 13,8 KV E 34,5KV | C59: =IFERROR(VLOOKUP(A59,LPU!$B$7:H1082,3,FALSE),"") -> UN | D59: 3077.84 | E59: 1 | F59: =IFERROR(E59*D59,"") -> 3077.84 | H59: =IF(G59>0,G59*D59,"") | M59: 1 | N59: =IF(M59>0,M59*$D59,"") -> 3077.84 | T59: =IF(S59>0,S59*$D59,"") | V59: =IF(U59>0,U59*$D59,"") | X59: =IF(W59>0,W59*$D59,"") | Y59: =SUM(G59,I59,K59,M59,O59,Q59,S59,U59,W59) -> 1
A60: 3000016144 | B60: =IFERROR(VLOOKUP(A60,LPU!$B$7:$H$1007,2,FALSE),"") -> DEMOLIÇÃO DE CONCRETO ARMADO E BASES DE POSTES, TRAFO, ESTRUTURAS E SIMILARES, VIGA TRILHO | C60: =IFERROR(VLOOKUP(A60,LPU!$B$7:H1078,3,FALSE),"") -> M3 | D60: 932.97 | E60: 1 | F60: =IFERROR(E60*D60,"") -> 932.97 | H60: =IF(G60>0,G60*D60,"") | M60: 1 | N60: =IF(M60>0,M60*$D60,"") -> 932.97 | T60: =IF(S60>0,S60*$D60,"") | V60: =IF(U60>0,U60*$D60,"") | X60: =IF(W60>0,W60*$D60,"") | Y60: =SUM(G60,I60,K60,M60,O60,Q60,S60,U60,W60) -> 1
